Workbook

Sheet Instructions 
B2: Instructions to be followed to complete the Data Collection Template
B3: This form is intended to be filled out by each farmer involved in the Test Case (TC) and aims at collecting information that will be used for assessing the impacts of Digital agriculture technology solutions (DATSs). Please read carefully the following instructions. - We kindly ask you to be as accurate as possible in providing the data and monitor them periodically as these will be the input for performance assessment. - Please ensure you keep track of the data requested and regularly check its availability. It's crucial that these values align for both user and non-user parcels. If they differ, kindly notify us promptly via email at the provided contact details. - The data included in the template have been carefully chosen based on their link with the DATSs used in your TC and they were further customised following your feedback. If some of the data cannot be applicable/available to your TC, please enter ‘n.a.’ in the corresponding cell and provide a comment explaining why they are not applicable. Additionally, in case some of the data cannot be collected due to some problems you may encounter during the season, please inform us promptly by writing an e-mail to the contact details provided below. - In order to obtain the assessment of the impacts of DATS, it is necessary to provide data for the farm(s) using DATS and for the one without. According to the QuantiFarm project proposal, each parcel using DATSs is associated with a comparable non-DATs parcel (in terms of size, geographical area, production, etc.). - Recall that: - the term DATS refers to the combinations or set of technological solutions implemented within the TC; For any doubts or clarifications, please do not hesitate to contact us at the following email address: francesco.parigi@polimi.it and andrea.bianchi@polimi.it (cc: dmoniz@consulai.com) This form is intended to be filled out by each farmer involved in the Test Case (TC) and aims at collecting information that will be used for assessing the impacts of Digital agriculture technology solutions (DATSs).
B5: Table of abbreviations
B6: - | C6: number (1, 2, 3, …)
B7: € | C7: euro
B8: cm3 | C8: cubic centimetre
B9: dm3 | C9: cubic decimetre
B10: g | C10: grams
B11: h | C11: hour
B12: ha | C12: hectare
B13: K | C13: potassium
B14: k€ | C14: kiloeuro (€ 1,000)
B15: kg | C15: kilograms
B16: kWh | C16: kilowatt-hour
B17: l | C17: litre
... B27: y | C27: year

Sheet General Information
B2: Question | C2: Unit of measure | D2: Value
A3: parcelInformation | B3: TC Number | C3: n | D3: 6 | E3: testcaseNumber | N3: D3 | O3: =CONCATENATE("""",N3,"""",":","""",LOWER(A3),"_",LOWER(E3),"""") -> "D3":"parcelinformation_testcasenumber"
A4: parcelInformation | B4: TC Leader | C4: - | E4: testcaseLeader | N4: D4 | O4: =CONCATENATE("""",N4,"""",":","""",LOWER(A4),"_",LOWER(E4),"""") -> "D4":"parcelinformation_testcaseleader"
B5: FARM DATA | N5: D5 | O5: =CONCATENATE("""",N5,"""",":","""",LOWER(A5),"_",LOWER(E5),"""") -> "D5":"_"
A6: parcelInformation | B6: Type of output/product | C6: - | D6: Crop | E6: cultivationType | N6: D6 | O6: =CONCATENATE("""",N6,"""",":","""",LOWER(A6),"_",LOWER(E6),"""") -> "D6":"parcelinformation_cultivationtype"
A7: parcelInformation | B7: Crop | C7: - | D7: Onion | E7: productType | N7: D7 | O7: =CONCATENATE("""",N7,"""",":","""",LOWER(A7),"_",LOWER(E7),"""") -> "D7":"parcelinformation_producttype"
A8: parcelInformation | B8: Animal | E8: productType | N8: D8 | O8: =CONCATENATE("""",N8,"""",":","""",LOWER(A8),"_",LOWER(E8),"""") -> "D8":"parcelinformation_producttype"
A9: parcelInformation | B9: Start of the growing/production season | C9: (gg/mm/yyyy) | E9: startMonth | N9: D9 | O9: =CONCATENATE("""",N9,"""",":","""",LOWER(A9),"_",LOWER(E9),"""") -> "D9":"parcelinformation_startmonth"
A10: parcelInformation | B10: End of the growing/production season | C10: (gg/mm/yyyy) | E10: endMonth | N10: D10 | O10: =CONCATENATE("""",N10,"""",":","""",LOWER(A10),"_",LOWER(E10),"""") -> "D10":"parcelinformation_endmonth"
A11: parcelInformation | B11: Biogeographical region | C11: - | E11: biogeographicalRegion | N11: D11 | O11: =CONCATENATE("""",N11,"""",":","""",LOWER(A11),"_",LOWER(E11),"""") -> "D11":"parcelinformation_biogeographicalregion"
A12: parcelInformation | B12: Total farm size | C12: ha | E12: totalFarmSize | N12: D12 | O12: =CONCATENATE("""",N12,"""",":","""",LOWER(A12),"_",LOWER(E12),"""") -> "D12":"parcelinformation_totalfarmsize"
A13: parcelInformation | B13: Number of comparison(s) | C13: n | E13: numberOfComparisons | N13: D13 | O13: =CONCATENATE("""",N13,"""",":","""",LOWER(A13),"_",LOWER(E13),"""") -> "D13":"parcelinformation_numberofcomparisons"
A14: parcelInformation | B14: Number of employees | C14: n | E14: numberOfEmployees | N14: D14 | O14: =CONCATENATE("""",N14,"""",":","""",LOWER(A14),"_",LOWER(E14),"""") -> "D14":"parcelinformation_numberofemployees"
A15: parcelInformation | B15: Number of full-time employees | C15: n | E15: numberofFullTimeEmployees | N15: D15 | O15: =CONCATENATE("""",N15,"""",":","""",LOWER(A15),"_",LOWER(E15),"""") -> "D15":"parcelinformation_numberoffulltimeemployees"
A16: parcelInformation | B16: Number of seasonal employees | C16: n | E16: numberOfSeasonalEmployees | N16: D16 | O16: =CONCATENATE("""",N16,"""",":","""",LOWER(A16),"_",LOWER(E16),"""") -> "D16":"parcelinformation_numberofseasonalemployees"
N17: D17 | O17: =CONCATENATE("""",N17,"""",":","""",LOWER(A17),"_",LOWER(E17),"""") -> "D17":"_"
B18: DATSs 1 DATA | G18: DATSs 2 DATA | K18: DATSs n DATA | N18: D18 | O18: =CONCATENATE("""",N18,"""",":","""",LOWER(A18),"_",LOWER(E18),"""") -> "D18":"_"
B19: Question | C19: Unit of measure | D19: Value | G19: Question | H19: Unit of measure | I19: Value | K19: Question | L19: Unit of measure | M19: Value | N19: D19 | O19: =CONCATENATE("""",N19,"""",":","""",LOWER(A19),"_",LOWER(E19),"""") -> "D19":"_"
A20: datsInformation | B20: Initial investment for DATSs | C20: € | D20: 0 | E20: datsInitialInvestmentCosts | G20: Initial investment for DATSs | H20: € | K20: Initial investment for DATSs | L20: € | N20: D20 | O20: =CONCATENATE("""",N20,"""",":","""",LOWER(A20),"_",LOWER(E20),"""") -> "D20":"datsinformation_datsinitialinvestmentcosts"
A21: datsInformation | B21: Expected life span of each DATSs | C21: y | D21: 1 | E21: datsExpectedLifespan | G21: Expected life span of each DATSs | H21: y | K21: Expected life span of each DATSs | L21: y | N21: D21 | O21: =CONCATENATE("""",N21,"""",":","""",LOWER(A21),"_",LOWER(E21),"""") -> "D21":"datsinformation_datsexpectedlifespan"
A22: datsInformation | B22: Time to install and make DATSs operational | C22: h | D22: 1 | E22: datsInstallationTime | G22: Time to install and make DATSs operational | H22: h | K22: Time to install and make DATSs operational | L22: h | N22: D22 | O22: =CONCATENATE("""",N22,"""",":","""",LOWER(A22),"_",LOWER(E22),"""") -> "D22":"datsinformation_datsinstallationtime"
A23: datsInformation | B23: DATs maintenance costs | C23: €/y | D23: 0 | E23: datsMaintenanceCosts | G23: DATs maintenance costs | H23: €/y | K23: DATs maintenance costs | L23: €/y | N23: D23 | O23: =CONCATENATE("""",N23,"""",":","""",LOWER(A23),"_",LOWER(E23),"""") -> "D23":"datsinformation_datsmaintenancecosts"
A24: datsInformation | B24: DATS annual fees | C24: €/y | D24: 300 | E24: datsAnnualFees | G24: DATS annual fees | H24: €/y | K24: DATS annual fees | L24: €/y | N24: D24 | O24: =CONCATENATE("""",N24,"""",":","""",LOWER(A24),"_",LOWER(E24),"""") -> "D24":"datsinformation_datsannualfees"
A25: datsInformation | B25: Training hours for the use of the DATSs in a year | C25: h | D25: 2 | E25: datsTrainingTime | G25: Training hours for the use of the DATSs in a year | H25: h | K25: Training hours for the use of the DATSs in a year | L25: h | N25: D25 | O25: =CONCATENATE("""",N25,"""",":","""",LOWER(A25),"_",LOWER(E25),"""") -> "D25":"datsinformation_datstrainingtime"
A26: datsInformation | B26: Number of people involved in the training | C26: n | D26: 2 | E26: datsTrainers | G26: Number of people involved in the training | H26: n | K26: Number of people involved in the training | L26: n | N26: D26 | O26: =CONCATENATE("""",N26,"""",":","""",LOWER(A26),"_",LOWER(E26),"""") -> "D26":"datsinformation_datstrainers"
A27: datsInformation | B27: Cost of training service by external people (advisor, DATS providers, ...) | C27: €/y | D27: 0 | E27: datsTrainingCosts | G27: Cost of training service by external people (advisor, DATS providers, ...) | H27: €/y | K27: Cost of training service by external people (advisor, DATS providers, ...) | L27: €/y | N27: D27 | O27: =CONCATENATE("""",N27,"""",":","""",LOWER(A27),"_",LOWER(E27),"""") -> "D27":"datsinformation_datstrainingcosts"
A28: datsInformation | B28: DATSs name | C28: - | D28: QMS Water Software | E28: datsName | G28: DATSs name | H28: - | K28: DATSs name | L28: - | N28: D28 | O28: =CONCATENATE("""",N28,"""",":","""",LOWER(A28),"_",LOWER(E28),"""") -> "D28":"datsinformation_datsname"
N29: D29 | O29: =CONCATENATE("""",N29,"""",":","""",LOWER(A29),"_",LOWER(E29),"""") -> "D29":"_"
B30: MARKET DATA FOR DATSs USER | G30: MARKET DATA FOR NON-DATSs USER | N30: D30 | O30: =CONCATENATE("""",N30,"""",":","""",LOWER(A30),"_",LOWER(E30),"""") -> "D30":"_"
B31: Question | C31: Unit of measure | D31: Value | G31: Question | H31: Unit of measure | I31: Value | N31: D31 | O31: =CONCATENATE("""",N31,"""",":","""",LOWER(A31),"_",LOWER(E31),"""") -> "D31":"_"
A32: marketinformation | B32: Water price | C32: €/m3 | D32: 0 | E32: waterPrice | G32: Water price | H32: €/m3 | I32: 0 | N32: D32 | O32: =CONCATENATE("""",N32,"""",":","""",LOWER(A32),"_",LOWER(E32),"""") -> "D32":"marketinformation_waterprice"
A33: marketinformation | B33: Fuel price | C33: €/l | D33: 1.18 | E33: fuelPrice | G33: Fuel price | H33: €/l | I33: 1.18 | N33: D33 | O33: =CONCATENATE("""",N33,"""",":","""",LOWER(A33),"_",LOWER(E33),"""") -> "D33":"marketinformation_fuelprice"
A34: marketinformation | B34: Number of fuel for greehnouse temperature control price | C34: n | E34: n_fuel_for_greenhouse | G34: Number of fuel for greehnouse temperature control price | H34: n | N34: D34 | O34: =CONCATENATE("""",N34,"""",":","""",LOWER(A34),"_",LOWER(E34),"""") -> "D34":"marketinformation_n_fuel_for_greenhouse"
A35: fuelfortemperaturecontrolinformation | B35: Fuel 1 for greehnouse temperature control price | C35: €/m3 | E35: productPrice_0 | G35: Fuel 1 for greehnouse temperature control price | H35: €/m3 | N35: D35 | O35: =CONCATENATE("""",N35,"""",":","""",LOWER(A35),"_",LOWER(E35),"""") -> "D35":"fuelfortemperaturecontrolinformation_productprice_0"
A36: fuelfortemperaturecontrolinformation | B36: Fuel 2 for greehnouse temperature control price | C36: €/m3 | E36: productPrice_1 | G36: Fuel 2 for greehnouse temperature control price | H36: €/m3 | N36: D36 | O36: =CONCATENATE("""",N36,"""",":","""",LOWER(A36),"_",LOWER(E36),"""") -> "D36":"fuelfortemperaturecontrolinformation_productprice_1"
A37: fuelfortemperaturecontrolinformation | B37: Fuel 3 for greehnouse temperature control price | C37: €/m3 | E37: productPrice_2 | G37: Fuel 3 for greehnouse temperature control price | H37: €/m4 | N37: D37 | O37: =CONCATENATE("""",N37,"""",":","""",LOWER(A37),"_",LOWER(E37),"""") -> "D37":"fuelfortemperaturecontrolinformation_productprice_2"
A38: marketinformation | B38: Electricity price | C38: €/kWh | D38: 0.15 | E38: electricityPrice | G38: Electricity price | H38: €/kWh | I38: 0.15 | N38: D38 | O38: =CONCATENATE("""",N38,"""",":","""",LOWER(A38),"_",LOWER(E38),"""") -> "D38":"marketinformation_electricityprice"
A39: marketinformation | B39: Average salary (farmer and emloyees) | C39: €/h | D39: 50 | E39: averageSalary | G39: Average salary (farmer and emloyees) | H39: €/h | I39: 50 | N39: D39 | O39: =CONCATENATE("""",N39,"""",":","""",LOWER(A39),"_",LOWER(E39),"""") -> "D39":"marketinformation_averagesalary"
A40: marketinformation | B40: Average professional salary (agronomist, veterinary, ...) | C40: €/h | D40: 100 | E40: averageProfessionalSalary | G40: Average professional salary (agronomist, veterinary, ...) | H40: €/h | I40: 100 | N40: D40 | O40: =CONCATENATE("""",N40,"""",":","""",LOWER(A40),"_",LOWER(E40),"""") -> "D40":"marketinformation_averageprofessionalsalary"
A41: marketinformation | B41: Sold product market price | C41: €/t | D41: 170 | E41: productMarketPrice | G41: Sold product market price | H41: €/t | I41: 170 | N41: D41 | O41: =CONCATENATE("""",N41,"""",":","""",LOWER(A41),"_",LOWER(E41),"""") -> "D41":"marketinformation_productmarketprice"
A42: marketinformation | B42: Number of pesticide used (herbicides, fungicides, insecticides) | C42: n | E42: n_of_pesticide_used | G42: Number of pesticide used (herbicides, fungicides, insecticides) | H42: n | N42: D42 | O42: =CONCATENATE("""",N42,"""",":","""",LOWER(A42),"_",LOWER(E42),"""") -> "D42":"marketinformation_n_of_pesticide_used"
A43: pesticidesusageinformation | B43: Pesticide 1 price | C43: €/kg | E43: productPrice_0 | G43: Pesticide 1 price | H43: €/kg | N43: D43 | O43: =CONCATENATE("""",N43,"""",":","""",LOWER(A43),"_",LOWER(E43),"""") -> "D43":"pesticidesusageinformation_productprice_0"
A44: pesticidesusageinformation | B44: Pesticide 2 price | C44: €/kg | E44: productPrice_1 | G44: Pesticide 2 price | H44: €/kg | N44: D44 | O44: =CONCATENATE("""",N44,"""",":","""",LOWER(A44),"_",LOWER(E44),"""") -> "D44":"pesticidesusageinformation_productprice_1"
A45: pesticidesusageinformation | B45: Pesticide 3 price | C45: €/kg | E45: productPrice_2 | G45: Pesticide 3 price | H45: €/kg | N45: D45 | O45: =CONCATENATE("""",N45,"""",":","""",LOWER(A45),"_",LOWER(E45),"""") -> "D45":"pesticidesusageinformation_productprice_2"
A46: pesticidesusageinformation | B46: Pesticide 4 price | C46: €/kg | E46: productPrice_3 | G46: Pesticide 4 price | H46: €/kg | N46: D46 | O46: =CONCATENATE("""",N46,"""",":","""",LOWER(A46),"_",LOWER(E46),"""") -> "D46":"pesticidesusageinformation_productprice_3"
A47: pesticidesusageinformation | B47: Pesticide 5 price | C47: €/kg | E47: productPrice_4 | G47: Pesticide 5 price | H47: €/kg | N47: D47 | O47: =CONCATENATE("""",N47,"""",":","""",LOWER(A47),"_",LOWER(E47),"""") -> "D47":"pesticidesusageinformation_productprice_4"
A48: pesticidesusageinformation | B48: Pesticide 6 price | C48: €/kg | E48: productPrice_5 | G48: Pesticide 6 price | H48: €/kg | N48: D48 | O48: =CONCATENATE("""",N48,"""",":","""",LOWER(A48),"_",LOWER(E48),"""") -> "D48":"pesticidesusageinformation_productprice_5"
A49: pesticidesusageinformation | B49: Pesticide 7 price | C49: €/kg | E49: productPrice_6 | G49: Pesticide 7 price | H49: €/kg | N49: D49 | O49: =CONCATENATE("""",N49,"""",":","""",LOWER(A49),"_",LOWER(E49),"""") -> "D49":"pesticidesusageinformation_productprice_6"
A50: pesticidesusageinformation | B50: Pesticide 8 price | C50: €/kg | E50: productPrice_7 | G50: Pesticide 8 price | N50: D50 | O50: =CONCATENATE("""",N50,"""",":","""",LOWER(A50),"_",LOWER(E50),"""") -> "D50":"pesticidesusageinformation_productprice_7"
A51: pesticidesusageinformation | B51: Pesticide 9 price | C51: €/kg | E51: productPrice_8 | G51: Pesticide 9 price | N51: D51 | O51: =CONCATENATE("""",N51,"""",":","""",LOWER(A51),"_",LOWER(E51),"""") -> "D51":"pesticidesusageinformation_productprice_8"
A52: pesticidesusageinformation | B52: Pesticide 10 price | C52: €/kg | E52: productPrice_9 | G52: Pesticide 10 price | N52: D52 | O52: =CONCATENATE("""",N52,"""",":","""",LOWER(A52),"_",LOWER(E52),"""") -> "D52":"pesticidesusageinformation_productprice_9"
A53: marketinformation | B53: Number of fertilizers used | C53: n | D53: 5 | E53: n_of_fertilizers_used | G53: Number of fertilizers used | H53: n | I53: 5 | N53: D53 | O53: =CONCATENATE("""",N53,"""",":","""",LOWER(A53),"_",LOWER(E53),"""") -> "D53":"marketinformation_n_of_fertilizers_used"
A54: fertilizersusageinformation | B54: Fertiliser 1 price | C54: €/kg | D54: 0.35 | E54: productPrice_0 | G54: Fertiliser 1 price | H54: €/kg | I54: 0.35 | N54: D54 | O54: =CONCATENATE("""",N54,"""",":","""",LOWER(A54),"_",LOWER(E54),"""") -> "D54":"fertilizersusageinformation_productprice_0"
A55: fertilizersusageinformation | B55: Fertiliser 2 price | C55: €/kg | D55: 2.2 | E55: productPrice_1 | G55: Fertiliser 2 price | H55: €/kg | I55: 2.2 | N55: D55 | O55: =CONCATENATE("""",N55,"""",":","""",LOWER(A55),"_",LOWER(E55),"""") -> "D55":"fertilizersusageinformation_productprice_1"
A56: fertilizersusageinformation | B56: Fertiliser 3 price | C56: €/kg | D56: 0.68 | E56: productPrice_2 | G56: Fertiliser 3 price | H56: €/kg | I56: 0.68 | N56: D56 | O56: =CONCATENATE("""",N56,"""",":","""",LOWER(A56),"_",LOWER(E56),"""") -> "D56":"fertilizersusageinformation_productprice_2"
A57: fertilizersusageinformation | B57: Fertiliser 4 price | C57: €/kg | D57: 0.3 | E57: productPrice_3 | G57: Fertiliser 4 price | H57: €/kg | I57: 0.3 | N57: D57 | O57: =CONCATENATE("""",N57,"""",":","""",LOWER(A57),"_",LOWER(E57),"""") -> "D57":"fertilizersusageinformation_productprice_3"
A58: fertilizersusageinformation | B58: Fertiliser 5 price | C58: €/kg | D58: 1.4 | E58: productPrice_4 | G58: Fertiliser 5 price | H58: €/kg | I58: 1.4 | N58: D58 | O58: =CONCATENATE("""",N58,"""",":","""",LOWER(A58),"_",LOWER(E58),"""") -> "D58":"fertilizersusageinformation_productprice_4"
A59: fertilizersusageinformation | B59: Fertiliser 6 price | C59: €/kg | E59: productPrice_5 | G59: Fertiliser 6 price | H59: €/kg | N59: D59 | O59: =CONCATENATE("""",N59,"""",":","""",LOWER(A59),"_",LOWER(E59),"""") -> "D59":"fertilizersusageinformation_productprice_5"
A60: fertilizersusageinformation | B60: Fertiliser 7 price | E60: productPrice_6 | G60: Fertiliser 7 price | N60: D60 | O60: =CONCATENATE("""",N60,"""",":","""",LOWER(A60),"_",LOWER(E60),"""") -> "D60":"fertilizersusageinformation_productprice_6"
A61: fertilizersusageinformation | B61: Fertiliser 8 price | E61: productPrice_7 | G61: Fertiliser 8 price | N61: D61 | O61: =CONCATENATE("""",N61,"""",":","""",LOWER(A61),"_",LOWER(E61),"""") -> "D61":"fertilizersusageinformation_productprice_7"
A62: fertilizersusageinformation | B62: Fertiliser 9 price | E62: productPrice_8 | G62: Fertiliser 9 price | N62: D62 | O62: =CONCATENATE("""",N62,"""",":","""",LOWER(A62),"_",LOWER(E62),"""") -> "D62":"fertilizersusageinformation_productprice_8"
A63: fertilizersusageinformation | B63: Fertiliser 10 price | E63: productPrice_9 | G63: Fertiliser 10 price | N63: D63 | O63: =CONCATENATE("""",N63,"""",":","""",LOWER(A63),"_",LOWER(E63),"""") -> "D63":"fertilizersusageinformation_productprice_9"
A64: marketinformation | B64: Number of feed used | C64: n | E64: n_of_feed_used | G64: Number of feed used | H64: n | N64: D64 | O64: =CONCATENATE("""",N64,"""",":","""",LOWER(A64),"_",LOWER(E64),"""") -> "D64":"marketinformation_n_of_feed_used"
A65: feedusageinformation | B65: Feed 1 price | C65: €/t | E65: productPrice_0 | G65: Feed 1 price | H65: €/t | N65: D65 | O65: =CONCATENATE("""",N65,"""",":","""",LOWER(A65),"_",LOWER(E65),"""") -> "D65":"feedusageinformation_productprice_0"
A66: feedusageinformation | B66: Feed 2 price | C66: €/t | E66: productPrice_1 | G66: Feed 2 price | H66: €/t | N66: D66 | O66: =CONCATENATE("""",N66,"""",":","""",LOWER(A66),"_",LOWER(E66),"""") -> "D66":"feedusageinformation_productprice_1"
A67: feedusageinformation | B67: Feed 3 price | E67: productPrice_2 | G67: Feed 3 price | N67: D67 | O67: =CONCATENATE("""",N67,"""",":","""",LOWER(A67),"_",LOWER(E67),"""") -> "D67":"feedusageinformation_productprice_2"
A68: feedusageinformation | B68: Feed 4 price | E68: productPrice_3 | G68: Feed 4 price | N68: D68 | O68: =CONCATENATE("""",N68,"""",":","""",LOWER(A68),"_",LOWER(E68),"""") -> "D68":"feedusageinformation_productprice_3"
A69: feedusageinformation | B69: Feed 5 price | C69: €/t | E69: productPrice_4 | G69: Feed 5 price | H69: €/t | N69: D69 | O69: =CONCATENATE("""",N69,"""",":","""",LOWER(A69),"_",LOWER(E69),"""") -> "D69":"feedusageinformation_productprice_4"
A70: marketinformation | B70: Number of drugs used | C70: n | E70: n_of_drugs_used | G70: Number of drugs used | H70: n | N70: D70 | O70: =CONCATENATE("""",N70,"""",":","""",LOWER(A70),"_",LOWER(E70),"""") -> "D70":"marketinformation_n_of_drugs_used"
A71: drugsusageinformation | B71: Drug 1 price | C71: €/g | E71: productPrice_0 | G71: Drug 1 price | H71: €/g | N71: D71 | O71: =CONCATENATE("""",N71,"""",":","""",LOWER(A71),"_",LOWER(E71),"""") -> "D71":"drugsusageinformation_productprice_0"
A72: drugsusageinformation | B72: Drug 2 price | C72: €/g | E72: productPrice_1 | G72: Drug 2 price | H72: €/g | N72: D72 | O72: =CONCATENATE("""",N72,"""",":","""",LOWER(A72),"_",LOWER(E72),"""") -> "D72":"drugsusageinformation_productprice_1"
A73: drugsusageinformation | B73: Drug 3 price | C73: €/g | E73: productPrice_2 | G73: Drug 3 price | H73: €/g | N73: D73 | O73: =CONCATENATE("""",N73,"""",":","""",LOWER(A73),"_",LOWER(E73),"""") -> "D73":"drugsusageinformation_productprice_2"

Sheet Parcel 1 with DATSs
AG1: yes
G2: PARCEL WITH DATSs | AG2: no
C4: Identification | D4: Parcel Name | E4: Onions - DAT
B8: Information about the TC
B9: # | C9: data | D9: u.m. | E9: value | G9: Notes
A10: parcelInformation | B10: 1 | C10: Parcel dimension | D10: ha | E10: parcelDimension | F10: G10 | G10: 4.1 | J10: =CONCATENATE("""",F10,"""",":","""","parcelassessmentwithdats_",LOWER($A10),"_",LOWER($E10),"""") -> "G10":"parcelassessmentwithdats_parcelinformation_parceldimension"
A11: parcelInformation | B11: 2 | C11: Number of plants/trees | D11: n | E11: numberOfPlants | F11: G11 | J11: =CONCATENATE("""",F11,"""",":","""","parcelassessmentwithdats_",LOWER($A11),"_",LOWER($E11),"""") -> "G11":"parcelassessmentwithdats_parcelinformation_numberofplants"
A12: parcelInformation | B12: 3 | C12: Sand content in the soil | D12: % | E12: soilFractionSand | F12: G12 | G12: 37 | J12: =CONCATENATE("""",F12,"""",":","""","parcelassessmentwithdats_",LOWER($A12),"_",LOWER($E12),"""") -> "G12":"parcelassessmentwithdats_parcelinformation_soilfractionsand"
A13: parcelInformation | B13: 4 | C13: Clay content in the soil | D13: % | E13: soilFractionClay | F13: G13 | G13: 22 | J13: =CONCATENATE("""",F13,"""",":","""","parcelassessmentwithdats_",LOWER($A13),"_",LOWER($E13),"""") -> "G13":"parcelassessmentwithdats_parcelinformation_soilfractionclay"
A14: parcelInformation | B14: 5 | C14: Silt content in the soil | D14: % | E14: soilFractionSilt | F14: G14 | G14: 31 | J14: =CONCATENATE("""",F14,"""",":","""","parcelassessmentwithdats_",LOWER($A14),"_",LOWER($E14),"""") -> "G14":"parcelassessmentwithdats_parcelinformation_soilfractionsilt"
A15: parcelInformation | B15: 6 | C15: Soil Bulk Density | D15: g/cm3 | E15: bulkDensity | F15: G15 | J15: =CONCATENATE("""",F15,"""",":","""","parcelassessmentwithdats_",LOWER($A15),"_",LOWER($E15),"""") -> "G15":"parcelassessmentwithdats_parcelinformation_bulkdensity"
A16: parcelInformation | B16: 7 | C16: Soil Organic Carbon | D16: % | E16: soilOrganicCarbon | F16: G16 | G16: 1 | J16: =CONCATENATE("""",F16,"""",":","""","parcelassessmentwithdats_",LOWER($A16),"_",LOWER($E16),"""") -> "G16":"parcelassessmentwithdats_parcelinformation_soilorganiccarbon"
A17: parcelInformation | B17: 8 | C17: Number of animals | D17: n | E17: numberOfAnimals | F17: G17 | J17: =CONCATENATE("""",F17,"""",":","""","parcelassessmentwithdats_",LOWER($A17),"_",LOWER($E17),"""") -> "G17":"parcelassessmentwithdats_parcelinformation_numberofanimals"
A18: parcelInformation | B18: 9 | C18: Livestock units per hectare | D18: LSU/ha | E18: livestockUnits | F18: G18 | J18: =CONCATENATE("""",F18,"""",":","""","parcelassessmentwithdats_",LOWER($A18),"_",LOWER($E18),"""") -> "G18":"parcelassessmentwithdats_parcelinformation_livestockunits"
A19: parcelInformation | B19: 10 | C19: Number of beehives | D19: n | E19: numberOfBeehives | F19: G19 | J19: =CONCATENATE("""",F19,"""",":","""","parcelassessmentwithdats_",LOWER($A19),"_",LOWER($E19),"""") -> "G19":"parcelassessmentwithdats_parcelinformation_numberofbeehives"
A20: parcelInformation | B20: 11 | C20: Area under aquaculture | D20: m2 | E20: aquacultureArea | F20: G20 | J20: =CONCATENATE("""",F20,"""",":","""","parcelassessmentwithdats_",LOWER($A20),"_",LOWER($E20),"""") -> "G20":"parcelassessmentwithdats_parcelinformation_aquaculturearea"
F21: G21 | J21: =CONCATENATE("""",F21,"""",":","""","parcelassessmentwithdats_",LOWER($A21),"_",LOWER($E21),"""") -> "G21":"parcelassessmentwithdats__"
B22: WATER | F22: G22 | G22: Year 1 | J22: =CONCATENATE("""",F22,"""",":","""","parcelassessmentwithdats_",LOWER($A22),"_",LOWER($E22),"""") -> "G22":"parcelassessmentwithdats__"
B23: # | C23: data | D23: u.m. | F23: G23 | G23: With DATSs | H23: Notes | J23: =CONCATENATE("""",F23,"""",":","""","parcelassessmentwithdats_",LOWER($A23),"_",LOWER($E23),"""") -> "G23":"parcelassessmentwithdats__"
A24: waterUsageInformation | B24: 12 | C24: Irrigation | D24: m3 | E24: waterUsageForIrrigation | F24: G24 | G24: 936 | J24: =CONCATENATE("""",F24,"""",":","""","parcelassessmentwithdats_",LOWER($A24),"_",LOWER($E24),"""") -> "G24":"parcelassessmentwithdats_waterusageinformation_waterusageforirrigation"
A25: waterUsageInformation | B25: 13 | C25: Fertigation | D25: m3 | E25: waterUsageForFertigation | F25: G25 | G25: 370 | J25: =CONCATENATE("""",F25,"""",":","""","parcelassessmentwithdats_",LOWER($A25),"_",LOWER($E25),"""") -> "G25":"parcelassessmentwithdats_waterusageinformation_waterusageforfertigation"
A26: waterUsageInformation | B26: 14 | C26: Pest dilution | D26: m3 | E26: waterUsageForPestDilution | F26: G26 | J26: =CONCATENATE("""",F26,"""",":","""","parcelassessmentwithdats_",LOWER($A26),"_",LOWER($E26),"""") -> "G26":"parcelassessmentwithdats_waterusageinformation_waterusageforpestdilution"
A27: waterUsageInformation | B27: 15 | C27: Cleaning | D27: m3 | E27: waterUsageForCleaning | F27: G27 | J27: =CONCATENATE("""",F27,"""",":","""","parcelassessmentwithdats_",LOWER($A27),"_",LOWER($E27),"""") -> "G27":"parcelassessmentwithdats_waterusageinformation_waterusageforcleaning"
A28: waterUsageInformation | B28: 16 | C28: Drinking | D28: m3 | E28: waterUsageForDrinking | F28: G28 | J28: =CONCATENATE("""",F28,"""",":","""","parcelassessmentwithdats_",LOWER($A28),"_",LOWER($E28),"""") -> "G28":"parcelassessmentwithdats_waterusageinformation_waterusagefordrinking"
A29: waterUsageInformation | B29: 17 | C29: Total water used | D29: m3 | E29: totalWaterUsage | F29: G29 | G29: 1306 | J29: =CONCATENATE("""",F29,"""",":","""","parcelassessmentwithdats_",LOWER($A29),"_",LOWER($E29),"""") -> "G29":"parcelassessmentwithdats_waterusageinformation_totalwaterusage"
F30: G30 | J30: =CONCATENATE("""",F30,"""",":","""","parcelassessmentwithdats_",LOWER($A30),"_",LOWER($E30),"""") -> "G30":"parcelassessmentwithdats__"
B31: FUEL | F31: G31 | G31: Year 1 | J31: =CONCATENATE("""",F31,"""",":","""","parcelassessmentwithdats_",LOWER($A31),"_",LOWER($E31),"""") -> "G31":"parcelassessmentwithdats__"
B32: # | C32: data | D32: u.m. | F32: G32 | G32: With DATSs | H32: Notes | J32: =CONCATENATE("""",F32,"""",":","""","parcelassessmentwithdats_",LOWER($A32),"_",LOWER($E32),"""") -> "G32":"parcelassessmentwithdats__"
A33: fuelUsageInformation | B33: 18 | C33: Fertilisation | D33: l | E33: fuelUsageForFertilisation | F33: G33 | J33: =CONCATENATE("""",F33,"""",":","""","parcelassessmentwithdats_",LOWER($A33),"_",LOWER($E33),"""") -> "G33":"parcelassessmentwithdats_fuelusageinformation_fuelusageforfertilisation"
A34: fuelUsageInformation | B34: 19 | C34: Pesticides | D34: l | E34: fuelUsageForPesticides | F34: G34 | J34: =CONCATENATE("""",F34,"""",":","""","parcelassessmentwithdats_",LOWER($A34),"_",LOWER($E34),"""") -> "G34":"parcelassessmentwithdats_fuelusageinformation_fuelusageforpesticides"
A35: fuelUsageInformation | B35: 20 | C35: Irrigation | D35: l | E35: fuelUsageForIrrigation | F35: G35 | J35: =CONCATENATE("""",F35,"""",":","""","parcelassessmentwithdats_",LOWER($A35),"_",LOWER($E35),"""") -> "G35":"parcelassessmentwithdats_fuelusageinformation_fuelusageforirrigation"
A36: fuelUsageInformation | B36: 21 | C36: Sowing / Planting | D36: l | E36: fuelUsageForSowing | F36: G36 | J36: =CONCATENATE("""",F36,"""",":","""","parcelassessmentwithdats_",LOWER($A36),"_",LOWER($E36),"""") -> "G36":"parcelassessmentwithdats_fuelusageinformation_fuelusageforsowing"
A37: fuelUsageInformation | B37: 22 | C37: Temperature and Humidity Control | D37: l | E37: fuelUsageForPruning | F37: G37 | J37: =CONCATENATE("""",F37,"""",":","""","parcelassessmentwithdats_",LOWER($A37),"_",LOWER($E37),"""") -> "G37":"parcelassessmentwithdats_fuelusageinformation_fuelusageforpruning"
A38: fuelUsageInformation | B38: 23 | C38: Pruning | D38: l | E38: fuelUsageForTemperatureHumidityControl | F38: G38 | J38: =CONCATENATE("""",F38,"""",":","""","parcelassessmentwithdats_",LOWER($A38),"_",LOWER($E38),"""") -> "G38":"parcelassessmentwithdats_fuelusageinformation_fuelusagefortemperaturehumiditycontrol"
A39: fuelUsageInformation | B39: 24 | C39: Beehives visits | D39: l | E39: fuelUsageForBeehivesVisits | F39: G39 | J39: =CONCATENATE("""",F39,"""",":","""","parcelassessmentwithdats_",LOWER($A39),"_",LOWER($E39),"""") -> "G39":"parcelassessmentwithdats_fuelusageinformation_fuelusageforbeehivesvisits"
A40: fuelUsageInformation | B40: 25 | C40: Transporting oysters to the laboratory | D40: l | E40: fuelUsageForTransportingOysters | F40: G40 | J40: =CONCATENATE("""",F40,"""",":","""","parcelassessmentwithdats_",LOWER($A40),"_",LOWER($E40),"""") -> "G40":"parcelassessmentwithdats_fuelusageinformation_fuelusagefortransportingoysters"
A41: fuelUsageInformation | B41: 26 | C41: Milking | D41: l | E41: fuelUsageForMilking | F41: G41 | J41: =CONCATENATE("""",F41,"""",":","""","parcelassessmentwithdats_",LOWER($A41),"_",LOWER($E41),"""") -> "G41":"parcelassessmentwithdats_fuelusageinformation_fuelusageformilking"
A42: fuelUsageInformation | B42: 27 | C42: Feeding | D42: l | E42: fuelUsageForFeeding | F42: G42 | J42: =CONCATENATE("""",F42,"""",":","""","parcelassessmentwithdats_",LOWER($A42),"_",LOWER($E42),"""") -> "G42":"parcelassessmentwithdats_fuelusageinformation_fuelusageforfeeding"
A43: fuelUsageInformation | B43: 28 | C43: Total fuel used | D43: l | E43: totalFuelUsage | F43: G43 | G43: 0 | J43: =CONCATENATE("""",F43,"""",":","""","parcelassessmentwithdats_",LOWER($A43),"_",LOWER($E43),"""") -> "G43":"parcelassessmentwithdats_fuelusageinformation_totalfuelusage"
F44: G44 | J44: =CONCATENATE("""",F44,"""",":","""","parcelassessmentwithdats_",LOWER($A44),"_",LOWER($E44),"""") -> "G44":"parcelassessmentwithdats__"
B45: FUEL FOR GREENHOUSE TEMPERATURE CONTROL | F45: G45 | G45: Year 1 | J45: =CONCATENATE("""",F45,"""",":","""","parcelassessmentwithdats_",LOWER($A45),"_",LOWER($E45),"""") -> "G45":"parcelassessmentwithdats__"
B46: # | C46: data | F46: G46 | G46: With DATSs | H46: Notes | J46: =CONCATENATE("""",F46,"""",":","""","parcelassessmentwithdats_",LOWER($A46),"_",LOWER($E46),"""") -> "G46":"parcelassessmentwithdats__"
A47: fuelForTemperatureControlInformation | B47: 29 | C47: Fuel 1 | D47: Name fuel 1 | E47: productName_0 | F47: G47 | J47: =CONCATENATE("""",F47,"""",":","""","parcelassessmentwithdats_",LOWER($A47),"_",LOWER($E47),"""") -> "G47":"parcelassessmentwithdats_fuelfortemperaturecontrolinformation_productname_0"
A48: fuelForTemperatureControlInformation | B48: 30 | C48: Fuel 1 | D48: Quantity | E48: quantity_0 | F48: G48 | J48: =CONCATENATE("""",F48,"""",":","""","parcelassessmentwithdats_",LOWER($A48),"_",LOWER($E48),"""") -> "G48":"parcelassessmentwithdats_fuelfortemperaturecontrolinformation_quantity_0"
A49: fuelForTemperatureControlInformation | B49: 31 | C49: Fuel 2 | D49: Name fuel 2 | E49: productName_1 | F49: G49 | J49: =CONCATENATE("""",F49,"""",":","""","parcelassessmentwithdats_",LOWER($A49),"_",LOWER($E49),"""") -> "G49":"parcelassessmentwithdats_fuelfortemperaturecontrolinformation_productname_1"
A50: fuelForTemperatureControlInformation | B50: 32 | C50: Fuel 2 | D50: Quantity | E50: quantity_1 | F50: G50 | J50: =CONCATENATE("""",F50,"""",":","""","parcelassessmentwithdats_",LOWER($A50),"_",LOWER($E50),"""") -> "G50":"parcelassessmentwithdats_fuelfortemperaturecontrolinformation_quantity_1"
A51: fuelForTemperatureControlInformation | B51: 33 | C51: Fuel n | D51: Name fuel n | E51: productName_2 | F51: G51 | J51: =CONCATENATE("""",F51,"""",":","""","parcelassessmentwithdats_",LOWER($A51),"_",LOWER($E51),"""") -> "G51":"parcelassessmentwithdats_fuelfortemperaturecontrolinformation_productname_2"
A52: fuelForTemperatureControlInformation | B52: 34 | C52: Fuel n | D52: Quantity | E52: quantity_2 | F52: G52 | J52: =CONCATENATE("""",F52,"""",":","""","parcelassessmentwithdats_",LOWER($A52),"_",LOWER($E52),"""") -> "G52":"parcelassessmentwithdats_fuelfortemperaturecontrolinformation_quantity_2"
F53: G53 | J53: =CONCATENATE("""",F53,"""",":","""","parcelassessmentwithdats_",LOWER($A53),"_",LOWER($E53),"""") -> "G53":"parcelassessmentwithdats__"
B54: ELECTRICITY | F54: G54 | G54: Year 1 | J54: =CONCATENATE("""",F54,"""",":","""","parcelassessmentwithdats_",LOWER($A54),"_",LOWER($E54),"""") -> "G54":"parcelassessmentwithdats__"
B55: # | C55: data | D55: u.m. | F55: G55 | G55: With DATSs | H55: Notes | J55: =CONCATENATE("""",F55,"""",":","""","parcelassessmentwithdats_",LOWER($A55),"_",LOWER($E55),"""") -> "G55":"parcelassessmentwithdats__"
A56: electricityUsageInformation | B56: 35 | C56: Temperature and Humidity Control | D56: kWh | E56: electricityUsageForTemperatureHumidityControl | F56: G56 | J56: =CONCATENATE("""",F56,"""",":","""","parcelassessmentwithdats_",LOWER($A56),"_",LOWER($E56),"""") -> "G56":"parcelassessmentwithdats_electricityusageinformation_electricityusagefortemperaturehumiditycontrol"
A57: electricityUsageInformation | B57: 36 | C57: Irrigation | D57: kWh | E57: electricityUsageForIrrigation | F57: G57 | J57: =CONCATENATE("""",F57,"""",":","""","parcelassessmentwithdats_",LOWER($A57),"_",LOWER($E57),"""") -> "G57":"parcelassessmentwithdats_electricityusageinformation_electricityusageforirrigation"
A58: electricityUsageInformation | B58: 37 | C58: Milking | D58: kWh | E58: electricityUsageForMilking | F58: G58 | J58: =CONCATENATE("""",F58,"""",":","""","parcelassessmentwithdats_",LOWER($A58),"_",LOWER($E58),"""") -> "G58":"parcelassessmentwithdats_electricityusageinformation_electricityusageformilking"
A59: electricityUsageInformation | B59: 38 | C59: Heat detection | D59: kWh | E59: electricityUsageForHeatDetection | F59: G59 | J59: =CONCATENATE("""",F59,"""",":","""","parcelassessmentwithdats_",LOWER($A59),"_",LOWER($E59),"""") -> "G59":"parcelassessmentwithdats_electricityusageinformation_electricityusageforheatdetection"
A60: electricityUsageInformation | B60: 39 | C60: Calving detection | D60: kWh | E60: electricityUsageForCalvingDetection | F60: G60 | J60: =CONCATENATE("""",F60,"""",":","""","parcelassessmentwithdats_",LOWER($A60),"_",LOWER($E60),"""") -> "G60":"parcelassessmentwithdats_electricityusageinformation_electricityusageforcalvingdetection"
A61: electricityUsageInformation | B61: 40 | C61: Feeding | D61: kWh | E61: electricityUsageForFeeding | F61: G61 | J61: =CONCATENATE("""",F61,"""",":","""","parcelassessmentwithdats_",LOWER($A61),"_",LOWER($E61),"""") -> "G61":"parcelassessmentwithdats_electricityusageinformation_electricityusageforfeeding"
A62: electricityUsageInformation | B62: 41 | C62: Total electricity used | D62: kWh | E62: totalElectricityUsage | F62: G62 | G62: 70 | J62: =CONCATENATE("""",F62,"""",":","""","parcelassessmentwithdats_",LOWER($A62),"_",LOWER($E62),"""") -> "G62":"parcelassessmentwithdats_electricityusageinformation_totalelectricityusage"
F63: G63 | J63: =CONCATENATE("""",F63,"""",":","""","parcelassessmentwithdats_",LOWER($A63),"_",LOWER($E63),"""") -> "G63":"parcelassessmentwithdats__"
B64: PESTICIDES (HERBICIDES, FUNGICIDES, INSECTICIDES) | F64: G64 | G64: Year 1 | J64: =CONCATENATE("""",F64,"""",":","""","parcelassessmentwithdats_",LOWER($A64),"_",LOWER($E64),"""") -> "G64":"parcelassessmentwithdats__"
B65: # | C65: data | F65: G65 | G65: With DATSs | H65: Notes | J65: =CONCATENATE("""",F65,"""",":","""","parcelassessmentwithdats_",LOWER($A65),"_",LOWER($E65),"""") -> "G65":"parcelassessmentwithdats__"
A66: pesticidesUsageInformation | B66: 42 | C66: Product 1 | D66: Name product 1 | E66: productName_0 | F66: G66 | J66: =CONCATENATE("""",F66,"""",":","""","parcelassessmentwithdats_",LOWER($A66),"_",LOWER($E66),"""") -> "G66":"parcelassessmentwithdats_pesticidesusageinformation_productname_0"
A67: pesticidesUsageInformation | B67: 43 | C67: Product 1 | D67: N. of treatements | E67: numberOfTreatments_0 | F67: G67 | J67: =CONCATENATE("""",F67,"""",":","""","parcelassessmentwithdats_",LOWER($A67),"_",LOWER($E67),"""") -> "G67":"parcelassessmentwithdats_pesticidesusageinformation_numberoftreatments_0"
A68: pesticidesUsageInformation | B68: 44 | C68: Product 1 | D68: Average quantity per application | E68: averageQuantity_0 | F68: G68 | J68: =CONCATENATE("""",F68,"""",":","""","parcelassessmentwithdats_",LOWER($A68),"_",LOWER($E68),"""") -> "G68":"parcelassessmentwithdats_pesticidesusageinformation_averagequantity_0"
A69: pesticidesUsageInformation | B69: 45 | C69: Product 2 | D69: Name product 2 | E69: productName_1 | F69: G69 | J69: =CONCATENATE("""",F69,"""",":","""","parcelassessmentwithdats_",LOWER($A69),"_",LOWER($E69),"""") -> "G69":"parcelassessmentwithdats_pesticidesusageinformation_productname_1"
A70: pesticidesUsageInformation | B70: 46 | C70: Product 2 | D70: N. of treatements | E70: numberOfTreatments_1 | F70: G70 | J70: =CONCATENATE("""",F70,"""",":","""","parcelassessmentwithdats_",LOWER($A70),"_",LOWER($E70),"""") -> "G70":"parcelassessmentwithdats_pesticidesusageinformation_numberoftreatments_1"
A71: pesticidesUsageInformation | B71: 47 | C71: Product 2 | D71: Average quantity per application | E71: averageQuantity_1 | F71: G71 | J71: =CONCATENATE("""",F71,"""",":","""","parcelassessmentwithdats_",LOWER($A71),"_",LOWER($E71),"""") -> "G71":"parcelassessmentwithdats_pesticidesusageinformation_averagequantity_1"
A72: pesticidesUsageInformation | B72: 48 | C72: Product 3 | D72: Name product n | E72: productName_2 | F72: G72 | J72: =CONCATENATE("""",F72,"""",":","""","parcelassessmentwithdats_",LOWER($A72),"_",LOWER($E72),"""") -> "G72":"parcelassessmentwithdats_pesticidesusageinformation_productname_2"
A73: pesticidesUsageInformation | B73: 49 | C73: Product 3 | D73: N. of treatements | E73: numberOfTreatments_2 | F73: G73 | J73: =CONCATENATE("""",F73,"""",":","""","parcelassessmentwithdats_",LOWER($A73),"_",LOWER($E73),"""") -> "G73":"parcelassessmentwithdats_pesticidesusageinformation_numberoftreatments_2"
A74: pesticidesUsageInformation | B74: 50 | C74: Product 3 | D74: Average quantity per application | E74: averageQuantity_2 | F74: G74 | J74: =CONCATENATE("""",F74,"""",":","""","parcelassessmentwithdats_",LOWER($A74),"_",LOWER($E74),"""") -> "G74":"parcelassessmentwithdats_pesticidesusageinformation_averagequantity_2"
A75: pesticidesUsageInformation | B75: 51 | C75: Product 4 | D75: Name product n | E75: productName_3 | F75: G75 | J75: =CONCATENATE("""",F75,"""",":","""","parcelassessmentwithdats_",LOWER($A75),"_",LOWER($E75),"""") -> "G75":"parcelassessmentwithdats_pesticidesusageinformation_productname_3"
A76: pesticidesUsageInformation | B76: 52 | C76: Product 4 | D76: N. of treatements | E76: numberOfTreatments_3 | F76: G76 | J76: =CONCATENATE("""",F76,"""",":","""","parcelassessmentwithdats_",LOWER($A76),"_",LOWER($E76),"""") -> "G76":"parcelassessmentwithdats_pesticidesusageinformation_numberoftreatments_3"
A77: pesticidesUsageInformation | B77: 53 | C77: Product 4 | D77: Average quantity per application | E77: averageQuantity_3 | F77: G77 | J77: =CONCATENATE("""",F77,"""",":","""","parcelassessmentwithdats_",LOWER($A77),"_",LOWER($E77),"""") -> "G77":"parcelassessmentwithdats_pesticidesusageinformation_averagequantity_3"
... A95: pesticidesUsageInformation | B95: 71 | C95: Product 10 | D95: Average quantity per application | E95: averageQuantity_9 | F95: G95 | J95: =CONCATENATE("""",F95,"""",":","""","parcelassessmentwithdats_",LOWER($A95),"_",LOWER($E95),"""") -> "G95":"parcelassessmentwithdats_pesticidesusageinformation_averagequantity_9"
F96: G96 | J96: =CONCATENATE("""",F96,"""",":","""","parcelassessmentwithdats_",LOWER($A96),"_",LOWER($E96),"""") -> "G96":"parcelassessmentwithdats__"
B97: FERTILISER | F97: G97 | G97: Year 1 | J97: =CONCATENATE("""",F97,"""",":","""","parcelassessmentwithdats_",LOWER($A97),"_",LOWER($E97),"""") -> "G97":"parcelassessmentwithdats__"
B98: # | C98: data | F98: G98 | G98: With DATSs | H98: Notes | J98: =CONCATENATE("""",F98,"""",":","""","parcelassessmentwithdats_",LOWER($A98),"_",LOWER($E98),"""") -> "G98":"parcelassessmentwithdats__"
A99: fertilizersUsageInformation | B99: 72 | C99: Fertilizer 1 | D99: Name fertiliser 1 | E99: productName_0 | F99: G99 | G99: 26-14-0 | J99: =CONCATENATE("""",F99,"""",":","""","parcelassessmentwithdats_",LOWER($A99),"_",LOWER($E99),"""") -> "G99":"parcelassessmentwithdats_fertilizersusageinformation_productname_0"
A100: fertilizersUsageInformation | B100: 73 | C100: Fertilizer 1 | D100: Mineral/Organic | E100: productType_0 | F100: G100 | G100: Mineral | J100: =CONCATENATE("""",F100,"""",":","""","parcelassessmentwithdats_",LOWER($A100),"_",LOWER($E100),"""") -> "G100":"parcelassessmentwithdats_fertilizersusageinformation_producttype_0"
A101: fertilizersUsageInformation | B101: 74 | C101: Fertilizer 1 | D101: N. of treatements | E101: numberOfTreatments_0 | F101: G101 | G101: 1 | J101: =CONCATENATE("""",F101,"""",":","""","parcelassessmentwithdats_",LOWER($A101),"_",LOWER($E101),"""") -> "G101":"parcelassessmentwithdats_fertilizersusageinformation_numberoftreatments_0"
A102: fertilizersUsageInformation | B102: 75 | C102: Fertilizer 1 | D102: Average quantity per application | E102: averageQuantity_0 | F102: G102 | G102: 173 | J102: =CONCATENATE("""",F102,"""",":","""","parcelassessmentwithdats_",LOWER($A102),"_",LOWER($E102),"""") -> "G102":"parcelassessmentwithdats_fertilizersusageinformation_averagequantity_0"
A103: fertilizersUsageInformation | B103: 76 | C103: Fertilizer 1 | D103: N concentration | E103: averageNitrogenQuantity_0 | F103: G103 | G103: 26 | J103: =CONCATENATE("""",F103,"""",":","""","parcelassessmentwithdats_",LOWER($A103),"_",LOWER($E103),"""") -> "G103":"parcelassessmentwithdats_fertilizersusageinformation_averagenitrogenquantity_0"
A104: fertilizersUsageInformation | B104: 77 | C104: Fertilizer 1 | D104: P concentration | E104: averagePhosphorusQuantity_0 | F104: G104 | G104: 14 | J104: =CONCATENATE("""",F104,"""",":","""","parcelassessmentwithdats_",LOWER($A104),"_",LOWER($E104),"""") -> "G104":"parcelassessmentwithdats_fertilizersusageinformation_averagephosphorusquantity_0"
A105: fertilizersUsageInformation | B105: 78 | C105: Fertilizer 1 | D105: K concentration | E105: averagePotassiumQuantity_0 | F105: G105 | G105: 0 | J105: =CONCATENATE("""",F105,"""",":","""","parcelassessmentwithdats_",LOWER($A105),"_",LOWER($E105),"""") -> "G105":"parcelassessmentwithdats_fertilizersusageinformation_averagepotassiumquantity_0"
A106: fertilizersUsageInformation | B106: 79 | C106: Fertilizer 2 | D106: Name fertiliser 2 | E106: productName_1 | F106: G106 | G106: Superstart | J106: =CONCATENATE("""",F106,"""",":","""","parcelassessmentwithdats_",LOWER($A106),"_",LOWER($E106),"""") -> "G106":"parcelassessmentwithdats_fertilizersusageinformation_productname_1"
A107: fertilizersUsageInformation | B107: 80 | C107: Fertilizer 2 | D107: Mineral/Organic | E107: productType_1 | F107: G107 | G107: Mineral | J107: =CONCATENATE("""",F107,"""",":","""","parcelassessmentwithdats_",LOWER($A107),"_",LOWER($E107),"""") -> "G107":"parcelassessmentwithdats_fertilizersusageinformation_producttype_1"
A108: fertilizersUsageInformation | B108: 81 | C108: Fertilizer 2 | D108: N. of treatements | E108: numberOfTreatments_1 | F108: G108 | G108: 1 | J108: =CONCATENATE("""",F108,"""",":","""","parcelassessmentwithdats_",LOWER($A108),"_",LOWER($E108),"""") -> "G108":"parcelassessmentwithdats_fertilizersusageinformation_numberoftreatments_1"
A109: fertilizersUsageInformation | B109: 82 | C109: Fertilizer 2 | D109: Average quantity per application | E109: averageQuantity_1 | F109: G109 | G109: 45 | J109: =CONCATENATE("""",F109,"""",":","""","parcelassessmentwithdats_",LOWER($A109),"_",LOWER($E109),"""") -> "G109":"parcelassessmentwithdats_fertilizersusageinformation_averagequantity_1"
A110: fertilizersUsageInformation | B110: 83 | C110: Fertilizer 2 | D110: N concentration | E110: averageNitrogenQuantity_1 | F110: G110 | G110: 10 | J110: =CONCATENATE("""",F110,"""",":","""","parcelassessmentwithdats_",LOWER($A110),"_",LOWER($E110),"""") -> "G110":"parcelassessmentwithdats_fertilizersusageinformation_averagenitrogenquantity_1"
A111: fertilizersUsageInformation | B111: 84 | C111: Fertilizer 2 | D111: P concentration | E111: averagePhosphorusQuantity_1 | F111: G111 | G111: 35 | J111: =CONCATENATE("""",F111,"""",":","""","parcelassessmentwithdats_",LOWER($A111),"_",LOWER($E111),"""") -> "G111":"parcelassessmentwithdats_fertilizersusageinformation_averagephosphorusquantity_1"
A112: fertilizersUsageInformation | B112: 85 | C112: Fertilizer 2 | D112: K concentration | E112: averagePotassiumQuantity_1 | F112: G112 | G112: 0 | J112: =CONCATENATE("""",F112,"""",":","""","parcelassessmentwithdats_",LOWER($A112),"_",LOWER($E112),"""") -> "G112":"parcelassessmentwithdats_fertilizersusageinformation_averagepotassiumquantity_1"
A113: fertilizersUsageInformation | B113: 86 | C113: Fertilizer 3 | D113: Name fertiliser 3 | E113: productName_2 | F113: G113 | G113: Kaliumsulfaat (English potassium sulfate) | J113: =CONCATENATE("""",F113,"""",":","""","parcelassessmentwithdats_",LOWER($A113),"_",LOWER($E113),"""") -> "G113":"parcelassessmentwithdats_fertilizersusageinformation_productname_2"
A114: fertilizersUsageInformation | B114: 87 | C114: Fertilizer 3 | D114: Mineral/Organic | E114: productType_2 | F114: G114 | G114: Mineral | J114: =CONCATENATE("""",F114,"""",":","""","parcelassessmentwithdats_",LOWER($A114),"_",LOWER($E114),"""") -> "G114":"parcelassessmentwithdats_fertilizersusageinformation_producttype_2"
A115: fertilizersUsageInformation | B115: 88 | C115: Fertilizer 3 | D115: N. of treatements | E115: numberOfTreatments_2 | F115: G115 | G115: 1 | J115: =CONCATENATE("""",F115,"""",":","""","parcelassessmentwithdats_",LOWER($A115),"_",LOWER($E115),"""") -> "G115":"parcelassessmentwithdats_fertilizersusageinformation_numberoftreatments_2"
A116: fertilizersUsageInformation | B116: 89 | C116: Fertilizer 3 | D116: Average quantity per application | E116: averageQuantity_2 | F116: G116 | G116: 134 | J116: =CONCATENATE("""",F116,"""",":","""","parcelassessmentwithdats_",LOWER($A116),"_",LOWER($E116),"""") -> "G116":"parcelassessmentwithdats_fertilizersusageinformation_averagequantity_2"
A117: fertilizersUsageInformation | B117: 90 | C117: Fertilizer 3 | D117: N concentration | E117: averageNitrogenQuantity_2 | F117: G117 | G117: 0 | J117: =CONCATENATE("""",F117,"""",":","""","parcelassessmentwithdats_",LOWER($A117),"_",LOWER($E117),"""") -> "G117":"parcelassessmentwithdats_fertilizersusageinformation_averagenitrogenquantity_2"
A118: fertilizersUsageInformation | B118: 91 | C118: Fertilizer 3 | D118: P concentration | E118: averagePhosphorusQuantity_2 | F118: G118 | G118: 0 | J118: =CONCATENATE("""",F118,"""",":","""","parcelassessmentwithdats_",LOWER($A118),"_",LOWER($E118),"""") -> "G118":"parcelassessmentwithdats_fertilizersusageinformation_averagephosphorusquantity_2"
A119: fertilizersUsageInformation | B119: 92 | C119: Fertilizer 3 | D119: K concentration | E119: averagePotassiumQuantity_2 | F119: G119 | G119: 50 | J119: =CONCATENATE("""",F119,"""",":","""","parcelassessmentwithdats_",LOWER($A119),"_",LOWER($E119),"""") -> "G119":"parcelassessmentwithdats_fertilizersusageinformation_averagepotassiumquantity_2"
A120: fertilizersUsageInformation | B120: 93 | C120: Fertilizer 4 | D120: Name fertiliser 4 | E120: productName_3 | F120: G120 | G120: Urean (mixture of ammonium nitrate and urea) | J120: =CONCATENATE("""",F120,"""",":","""","parcelassessmentwithdats_",LOWER($A120),"_",LOWER($E120),"""") -> "G120":"parcelassessmentwithdats_fertilizersusageinformation_productname_3"
A121: fertilizersUsageInformation | B121: 94 | C121: Fertilizer 4 | D121: Mineral/Organic | E121: productType_3 | F121: G121 | G121: Mineral | J121: =CONCATENATE("""",F121,"""",":","""","parcelassessmentwithdats_",LOWER($A121),"_",LOWER($E121),"""") -> "G121":"parcelassessmentwithdats_fertilizersusageinformation_producttype_3"
...

Sheet Parcel 1 without DATSs
BA1: yes
H2: PARCEL WITHOUT DATSs | BA2: no
C4: Identification | D4: Parcel Name | E4: Onions - NO DAT
B8: Information about the TC
B9: # | C9: data | D9: u.m. | H9: Notes
A10: parcelInformation | B10: 1 | C10: Parcel dimension | D10: ha | E10: parcelDimension | F10: H10 | H10: 4.1 | K10: =CONCATENATE("""",F10,"""",":","""","parcelassessmentwithdats_",LOWER($A10),"_",LOWER($E10),"""") -> "H10":"parcelassessmentwithdats_parcelinformation_parceldimension"
A11: parcelInformation | B11: 2 | C11: Number of plants/trees | D11: n | E11: numberOfPlants | F11: H11 | K11: =CONCATENATE("""",F11,"""",":","""","parcelassessmentwithdats_",LOWER($A11),"_",LOWER($E11),"""") -> "H11":"parcelassessmentwithdats_parcelinformation_numberofplants"
A12: parcelInformation | B12: 3 | C12: Sand content in the soil | D12: % | E12: soilFractionSand | F12: H12 | H12: 37 | K12: =CONCATENATE("""",F12,"""",":","""","parcelassessmentwithdats_",LOWER($A12),"_",LOWER($E12),"""") -> "H12":"parcelassessmentwithdats_parcelinformation_soilfractionsand"
A13: parcelInformation | B13: 4 | C13: Clay content in the soil | D13: % | E13: soilFractionClay | F13: H13 | H13: 22 | K13: =CONCATENATE("""",F13,"""",":","""","parcelassessmentwithdats_",LOWER($A13),"_",LOWER($E13),"""") -> "H13":"parcelassessmentwithdats_parcelinformation_soilfractionclay"
A14: parcelInformation | B14: 5 | C14: Silt content in the soil | D14: % | E14: soilFractionSilt | F14: H14 | H14: 31 | K14: =CONCATENATE("""",F14,"""",":","""","parcelassessmentwithdats_",LOWER($A14),"_",LOWER($E14),"""") -> "H14":"parcelassessmentwithdats_parcelinformation_soilfractionsilt"
A15: parcelInformation | B15: 6 | C15: Soil Bulk Density | D15: g/cm3 | E15: bulkDensity | F15: H15 | K15: =CONCATENATE("""",F15,"""",":","""","parcelassessmentwithdats_",LOWER($A15),"_",LOWER($E15),"""") -> "H15":"parcelassessmentwithdats_parcelinformation_bulkdensity"
A16: parcelInformation | B16: 7 | C16: Soil Organic Carbon | D16: % | E16: soilOrganicCarbon | F16: H16 | H16: 1 | K16: =CONCATENATE("""",F16,"""",":","""","parcelassessmentwithdats_",LOWER($A16),"_",LOWER($E16),"""") -> "H16":"parcelassessmentwithdats_parcelinformation_soilorganiccarbon"
A17: parcelInformation | B17: 8 | C17: Number of animals | D17: n | E17: numberOfAnimals | F17: H17 | K17: =CONCATENATE("""",F17,"""",":","""","parcelassessmentwithdats_",LOWER($A17),"_",LOWER($E17),"""") -> "H17":"parcelassessmentwithdats_parcelinformation_numberofanimals"
A18: parcelInformation | B18: 9 | C18: Livestock units per hectare | D18: LSU/ha | E18: livestockUnits | F18: H18 | K18: =CONCATENATE("""",F18,"""",":","""","parcelassessmentwithdats_",LOWER($A18),"_",LOWER($E18),"""") -> "H18":"parcelassessmentwithdats_parcelinformation_livestockunits"
A19: parcelInformation | B19: 10 | C19: Number of beehives | D19: n | E19: numberOfBeehives | F19: H19 | K19: =CONCATENATE("""",F19,"""",":","""","parcelassessmentwithdats_",LOWER($A19),"_",LOWER($E19),"""") -> "H19":"parcelassessmentwithdats_parcelinformation_numberofbeehives"
A20: parcelInformation | B20: 11 | C20: Area under aquaculture | D20: m2 | E20: aquacultureArea | F20: H20 | K20: =CONCATENATE("""",F20,"""",":","""","parcelassessmentwithdats_",LOWER($A20),"_",LOWER($E20),"""") -> "H20":"parcelassessmentwithdats_parcelinformation_aquaculturearea"
F21: H21 | K21: =CONCATENATE("""",F21,"""",":","""","parcelassessmentwithdats_",LOWER($A21),"_",LOWER($E21),"""") -> "H21":"parcelassessmentwithdats__"
B22: WATER | F22: H22 | H22: Year 1 | K22: =CONCATENATE("""",F22,"""",":","""","parcelassessmentwithdats_",LOWER($A22),"_",LOWER($E22),"""") -> "H22":"parcelassessmentwithdats__"
B23: # | C23: data | D23: u.m. | F23: H23 | H23: Without DATSs | I23: Notes | K23: =CONCATENATE("""",F23,"""",":","""","parcelassessmentwithdats_",LOWER($A23),"_",LOWER($E23),"""") -> "H23":"parcelassessmentwithdats__"
A24: waterUsageInformation | B24: 12 | C24: Irrigation | D24: m3 | E24: waterUsageForIrrigation | F24: H24 | H24: 2619 | K24: =CONCATENATE("""",F24,"""",":","""","parcelassessmentwithdats_",LOWER($A24),"_",LOWER($E24),"""") -> "H24":"parcelassessmentwithdats_waterusageinformation_waterusageforirrigation"
A25: waterUsageInformation | B25: 13 | C25: Fertigation | D25: m3 | E25: waterUsageForFertigation | F25: H25 | H25: 1023 | K25: =CONCATENATE("""",F25,"""",":","""","parcelassessmentwithdats_",LOWER($A25),"_",LOWER($E25),"""") -> "H25":"parcelassessmentwithdats_waterusageinformation_waterusageforfertigation"
A26: waterUsageInformation | B26: 14 | C26: Pest dilution | D26: m3 | E26: waterUsageForPestDilution | F26: H26 | K26: =CONCATENATE("""",F26,"""",":","""","parcelassessmentwithdats_",LOWER($A26),"_",LOWER($E26),"""") -> "H26":"parcelassessmentwithdats_waterusageinformation_waterusageforpestdilution"
A27: waterUsageInformation | B27: 15 | C27: Cleaning | D27: m3 | E27: waterUsageForCleaning | F27: H27 | K27: =CONCATENATE("""",F27,"""",":","""","parcelassessmentwithdats_",LOWER($A27),"_",LOWER($E27),"""") -> "H27":"parcelassessmentwithdats_waterusageinformation_waterusageforcleaning"
A28: waterUsageInformation | B28: 16 | C28: Drinking | D28: m3 | E28: waterUsageForDrinking | F28: H28 | K28: =CONCATENATE("""",F28,"""",":","""","parcelassessmentwithdats_",LOWER($A28),"_",LOWER($E28),"""") -> "H28":"parcelassessmentwithdats_waterusageinformation_waterusagefordrinking"
A29: waterUsageInformation | B29: 17 | C29: or Total water used | D29: m3 | E29: totalWaterUsage | F29: H29 | H29: 3642 | K29: =CONCATENATE("""",F29,"""",":","""","parcelassessmentwithdats_",LOWER($A29),"_",LOWER($E29),"""") -> "H29":"parcelassessmentwithdats_waterusageinformation_totalwaterusage"
F30: H30 | K30: =CONCATENATE("""",F30,"""",":","""","parcelassessmentwithdats_",LOWER($A30),"_",LOWER($E30),"""") -> "H30":"parcelassessmentwithdats__"
B31: FUEL | F31: H31 | H31: Year 1 | K31: =CONCATENATE("""",F31,"""",":","""","parcelassessmentwithdats_",LOWER($A31),"_",LOWER($E31),"""") -> "H31":"parcelassessmentwithdats__"
B32: # | C32: data | D32: u.m. | F32: H32 | H32: Without DATSs | I32: Notes | K32: =CONCATENATE("""",F32,"""",":","""","parcelassessmentwithdats_",LOWER($A32),"_",LOWER($E32),"""") -> "H32":"parcelassessmentwithdats__"
A33: fuelUsageInformation | B33: 18 | C33: Fertilisation | D33: l | E33: fuelUsageForFertilisation | F33: H33 | K33: =CONCATENATE("""",F33,"""",":","""","parcelassessmentwithdats_",LOWER($A33),"_",LOWER($E33),"""") -> "H33":"parcelassessmentwithdats_fuelusageinformation_fuelusageforfertilisation"
A34: fuelUsageInformation | B34: 19 | C34: Pesticides | D34: l | E34: fuelUsageForPesticides | F34: H34 | K34: =CONCATENATE("""",F34,"""",":","""","parcelassessmentwithdats_",LOWER($A34),"_",LOWER($E34),"""") -> "H34":"parcelassessmentwithdats_fuelusageinformation_fuelusageforpesticides"
A35: fuelUsageInformation | B35: 20 | C35: Irrigation | D35: l | E35: fuelUsageForIrrigation | F35: H35 | K35: =CONCATENATE("""",F35,"""",":","""","parcelassessmentwithdats_",LOWER($A35),"_",LOWER($E35),"""") -> "H35":"parcelassessmentwithdats_fuelusageinformation_fuelusageforirrigation"
A36: fuelUsageInformation | B36: 21 | C36: Sowing / Planting | D36: l | E36: fuelUsageForSowing | F36: H36 | K36: =CONCATENATE("""",F36,"""",":","""","parcelassessmentwithdats_",LOWER($A36),"_",LOWER($E36),"""") -> "H36":"parcelassessmentwithdats_fuelusageinformation_fuelusageforsowing"
A37: fuelUsageInformation | B37: 22 | C37: Temperature and Humidity Control | D37: l | E37: fuelUsageForPruning | F37: H37 | K37: =CONCATENATE("""",F37,"""",":","""","parcelassessmentwithdats_",LOWER($A37),"_",LOWER($E37),"""") -> "H37":"parcelassessmentwithdats_fuelusageinformation_fuelusageforpruning"
A38: fuelUsageInformation | B38: 23 | C38: Pruning | D38: l | E38: fuelUsageForTemperatureHumidityControl | F38: H38 | K38: =CONCATENATE("""",F38,"""",":","""","parcelassessmentwithdats_",LOWER($A38),"_",LOWER($E38),"""") -> "H38":"parcelassessmentwithdats_fuelusageinformation_fuelusagefortemperaturehumiditycontrol"
A39: fuelUsageInformation | B39: 24 | C39: Beehives visits | D39: l | E39: fuelUsageForBeehivesVisits | F39: H39 | K39: =CONCATENATE("""",F39,"""",":","""","parcelassessmentwithdats_",LOWER($A39),"_",LOWER($E39),"""") -> "H39":"parcelassessmentwithdats_fuelusageinformation_fuelusageforbeehivesvisits"
A40: fuelUsageInformation | B40: 25 | C40: Transporting oysters to the laboratory | D40: l | E40: fuelUsageForTransportingOysters | F40: H40 | K40: =CONCATENATE("""",F40,"""",":","""","parcelassessmentwithdats_",LOWER($A40),"_",LOWER($E40),"""") -> "H40":"parcelassessmentwithdats_fuelusageinformation_fuelusagefortransportingoysters"
A41: fuelUsageInformation | B41: 26 | C41: Milking | D41: l | E41: fuelUsageForMilking | F41: H41 | K41: =CONCATENATE("""",F41,"""",":","""","parcelassessmentwithdats_",LOWER($A41),"_",LOWER($E41),"""") -> "H41":"parcelassessmentwithdats_fuelusageinformation_fuelusageformilking"
A42: fuelUsageInformation | B42: 27 | C42: Feeding | D42: l | E42: fuelUsageForFeeding | F42: H42 | K42: =CONCATENATE("""",F42,"""",":","""","parcelassessmentwithdats_",LOWER($A42),"_",LOWER($E42),"""") -> "H42":"parcelassessmentwithdats_fuelusageinformation_fuelusageforfeeding"
A43: fuelUsageInformation | B43: 28 | C43: or Total fuel used | D43: l | E43: totalFuelUsage | F43: H43 | K43: =CONCATENATE("""",F43,"""",":","""","parcelassessmentwithdats_",LOWER($A43),"_",LOWER($E43),"""") -> "H43":"parcelassessmentwithdats_fuelusageinformation_totalfuelusage"
F44: H44 | K44: =CONCATENATE("""",F44,"""",":","""","parcelassessmentwithdats_",LOWER($A44),"_",LOWER($E44),"""") -> "H44":"parcelassessmentwithdats__"
B45: FUEL FOR GREENHOUSE TEMPERATURE CONTROL | F45: H45 | H45: Year 1 | K45: =CONCATENATE("""",F45,"""",":","""","parcelassessmentwithdats_",LOWER($A45),"_",LOWER($E45),"""") -> "H45":"parcelassessmentwithdats__"
B46: # | C46: data | F46: H46 | H46: Without DATSs | I46: Notes | K46: =CONCATENATE("""",F46,"""",":","""","parcelassessmentwithdats_",LOWER($A46),"_",LOWER($E46),"""") -> "H46":"parcelassessmentwithdats__"
A47: fuelForTemperatureControlInformation | B47: 29 | C47: Fuel 1 | D47: Name fuel 1 | E47: productName_0 | F47: H47 | K47: =CONCATENATE("""",F47,"""",":","""","parcelassessmentwithdats_",LOWER($A47),"_",LOWER($E47),"""") -> "H47":"parcelassessmentwithdats_fuelfortemperaturecontrolinformation_productname_0"
A48: fuelForTemperatureControlInformation | B48: 30 | C48: Fuel 1 | D48: Quantity | E48: quantity_0 | F48: H48 | K48: =CONCATENATE("""",F48,"""",":","""","parcelassessmentwithdats_",LOWER($A48),"_",LOWER($E48),"""") -> "H48":"parcelassessmentwithdats_fuelfortemperaturecontrolinformation_quantity_0"
A49: fuelForTemperatureControlInformation | B49: 31 | C49: Fuel 2 | D49: Name fuel 2 | E49: productName_1 | F49: H49 | K49: =CONCATENATE("""",F49,"""",":","""","parcelassessmentwithdats_",LOWER($A49),"_",LOWER($E49),"""") -> "H49":"parcelassessmentwithdats_fuelfortemperaturecontrolinformation_productname_1"
A50: fuelForTemperatureControlInformation | B50: 32 | C50: Fuel 2 | D50: Quantity | E50: quantity_1 | F50: H50 | K50: =CONCATENATE("""",F50,"""",":","""","parcelassessmentwithdats_",LOWER($A50),"_",LOWER($E50),"""") -> "H50":"parcelassessmentwithdats_fuelfortemperaturecontrolinformation_quantity_1"
A51: fuelForTemperatureControlInformation | B51: 33 | C51: Fuel n | D51: Name fuel 2 | E51: productName_2 | F51: H51 | K51: =CONCATENATE("""",F51,"""",":","""","parcelassessmentwithdats_",LOWER($A51),"_",LOWER($E51),"""") -> "H51":"parcelassessmentwithdats_fuelfortemperaturecontrolinformation_productname_2"
A52: fuelForTemperatureControlInformation | B52: 34 | C52: Fuel n | D52: Quantity | E52: quantity_2 | F52: H52 | K52: =CONCATENATE("""",F52,"""",":","""","parcelassessmentwithdats_",LOWER($A52),"_",LOWER($E52),"""") -> "H52":"parcelassessmentwithdats_fuelfortemperaturecontrolinformation_quantity_2"
F53: H53 | K53: =CONCATENATE("""",F53,"""",":","""","parcelassessmentwithdats_",LOWER($A53),"_",LOWER($E53),"""") -> "H53":"parcelassessmentwithdats__"
B54: ELECTRICITY | F54: H54 | H54: Year 1 | K54: =CONCATENATE("""",F54,"""",":","""","parcelassessmentwithdats_",LOWER($A54),"_",LOWER($E54),"""") -> "H54":"parcelassessmentwithdats__"
B55: # | C55: data | D55: u.m. | F55: H55 | H55: Without DATSs | I55: Notes | K55: =CONCATENATE("""",F55,"""",":","""","parcelassessmentwithdats_",LOWER($A55),"_",LOWER($E55),"""") -> "H55":"parcelassessmentwithdats__"
A56: electricityUsageInformation | B56: 35 | C56: Temperature and Humidity Control | D56: kWh | E56: electricityUsageForTemperatureHumidityControl | F56: H56 | K56: =CONCATENATE("""",F56,"""",":","""","parcelassessmentwithdats_",LOWER($A56),"_",LOWER($E56),"""") -> "H56":"parcelassessmentwithdats_electricityusageinformation_electricityusagefortemperaturehumiditycontrol"
A57: electricityUsageInformation | B57: 36 | C57: Irrigation | D57: kWh | E57: electricityUsageForIrrigation | F57: H57 | K57: =CONCATENATE("""",F57,"""",":","""","parcelassessmentwithdats_",LOWER($A57),"_",LOWER($E57),"""") -> "H57":"parcelassessmentwithdats_electricityusageinformation_electricityusageforirrigation"
A58: electricityUsageInformation | B58: 37 | C58: Milking | D58: kWh | E58: electricityUsageForMilking | F58: H58 | K58: =CONCATENATE("""",F58,"""",":","""","parcelassessmentwithdats_",LOWER($A58),"_",LOWER($E58),"""") -> "H58":"parcelassessmentwithdats_electricityusageinformation_electricityusageformilking"
A59: electricityUsageInformation | B59: 38 | C59: Heat detection | D59: kWh | E59: electricityUsageForHeatDetection | F59: H59 | K59: =CONCATENATE("""",F59,"""",":","""","parcelassessmentwithdats_",LOWER($A59),"_",LOWER($E59),"""") -> "H59":"parcelassessmentwithdats_electricityusageinformation_electricityusageforheatdetection"
A60: electricityUsageInformation | B60: 39 | C60: Calving detection | D60: kWh | E60: electricityUsageForCalvingDetection | F60: H60 | K60: =CONCATENATE("""",F60,"""",":","""","parcelassessmentwithdats_",LOWER($A60),"_",LOWER($E60),"""") -> "H60":"parcelassessmentwithdats_electricityusageinformation_electricityusageforcalvingdetection"
A61: electricityUsageInformation | B61: 40 | C61: Feeding | D61: kWh | E61: electricityUsageForFeeding | F61: H61 | K61: =CONCATENATE("""",F61,"""",":","""","parcelassessmentwithdats_",LOWER($A61),"_",LOWER($E61),"""") -> "H61":"parcelassessmentwithdats_electricityusageinformation_electricityusageforfeeding"
A62: electricityUsageInformation | B62: 41 | C62: or Total electricity used | D62: kWh | E62: totalElectricityUsage | F62: H62 | H62: 70 | K62: =CONCATENATE("""",F62,"""",":","""","parcelassessmentwithdats_",LOWER($A62),"_",LOWER($E62),"""") -> "H62":"parcelassessmentwithdats_electricityusageinformation_totalelectricityusage"
F63: H63 | K63: =CONCATENATE("""",F63,"""",":","""","parcelassessmentwithdats_",LOWER($A63),"_",LOWER($E63),"""") -> "H63":"parcelassessmentwithdats__"
B64: PESTICIDES (HERBICIDES, FUNGICIDES, INSECTICIDES) | F64: H64 | H64: Year 1 | K64: =CONCATENATE("""",F64,"""",":","""","parcelassessmentwithdats_",LOWER($A64),"_",LOWER($E64),"""") -> "H64":"parcelassessmentwithdats__"
B65: # | C65: data | F65: H65 | H65: Without DATSs | I65: Notes | K65: =CONCATENATE("""",F65,"""",":","""","parcelassessmentwithdats_",LOWER($A65),"_",LOWER($E65),"""") -> "H65":"parcelassessmentwithdats__"
A66: pesticidesUsageInformation | B66: 42 | C66: Product 1 | D66: Name product 1 | E66: productName_0 | F66: H66 | K66: =CONCATENATE("""",F66,"""",":","""","parcelassessmentwithdats_",LOWER($A66),"_",LOWER($E66),"""") -> "H66":"parcelassessmentwithdats_pesticidesusageinformation_productname_0"
A67: pesticidesUsageInformation | B67: 43 | C67: Product 1 | D67: N. of treatements | E67: numberOfTreatments_0 | F67: H67 | K67: =CONCATENATE("""",F67,"""",":","""","parcelassessmentwithdats_",LOWER($A67),"_",LOWER($E67),"""") -> "H67":"parcelassessmentwithdats_pesticidesusageinformation_numberoftreatments_0"
A68: pesticidesUsageInformation | B68: 44 | C68: Product 1 | D68: Average quantity per application | E68: averageQuantity_0 | F68: H68 | K68: =CONCATENATE("""",F68,"""",":","""","parcelassessmentwithdats_",LOWER($A68),"_",LOWER($E68),"""") -> "H68":"parcelassessmentwithdats_pesticidesusageinformation_averagequantity_0"
A69: pesticidesUsageInformation | B69: 45 | C69: Product 2 | D69: Name product 2 | E69: productName_1 | F69: H69 | K69: =CONCATENATE("""",F69,"""",":","""","parcelassessmentwithdats_",LOWER($A69),"_",LOWER($E69),"""") -> "H69":"parcelassessmentwithdats_pesticidesusageinformation_productname_1"
A70: pesticidesUsageInformation | B70: 46 | C70: Product 2 | D70: N. of treatements | E70: numberOfTreatments_1 | F70: H70 | K70: =CONCATENATE("""",F70,"""",":","""","parcelassessmentwithdats_",LOWER($A70),"_",LOWER($E70),"""") -> "H70":"parcelassessmentwithdats_pesticidesusageinformation_numberoftreatments_1"
A71: pesticidesUsageInformation | B71: 47 | C71: Product 2 | D71: Average quantity per application | E71: averageQuantity_1 | F71: H71 | K71: =CONCATENATE("""",F71,"""",":","""","parcelassessmentwithdats_",LOWER($A71),"_",LOWER($E71),"""") -> "H71":"parcelassessmentwithdats_pesticidesusageinformation_averagequantity_1"
A72: pesticidesUsageInformation | B72: 48 | C72: Product 3 | D72: Name product n | E72: productName_2 | F72: H72 | K72: =CONCATENATE("""",F72,"""",":","""","parcelassessmentwithdats_",LOWER($A72),"_",LOWER($E72),"""") -> "H72":"parcelassessmentwithdats_pesticidesusageinformation_productname_2"
A73: pesticidesUsageInformation | B73: 49 | C73: Product 3 | D73: N. of treatements | E73: numberOfTreatments_2 | F73: H73 | K73: =CONCATENATE("""",F73,"""",":","""","parcelassessmentwithdats_",LOWER($A73),"_",LOWER($E73),"""") -> "H73":"parcelassessmentwithdats_pesticidesusageinformation_numberoftreatments_2"
A74: pesticidesUsageInformation | B74: 50 | C74: Product 3 | D74: Average quantity per application | E74: averageQuantity_2 | F74: H74 | K74: =CONCATENATE("""",F74,"""",":","""","parcelassessmentwithdats_",LOWER($A74),"_",LOWER($E74),"""") -> "H74":"parcelassessmentwithdats_pesticidesusageinformation_averagequantity_2"
A75: pesticidesUsageInformation | B75: 51 | C75: Product 4 | D75: Name product n | E75: productName_3 | F75: H75 | K75: =CONCATENATE("""",F75,"""",":","""","parcelassessmentwithdats_",LOWER($A75),"_",LOWER($E75),"""") -> "H75":"parcelassessmentwithdats_pesticidesusageinformation_productname_3"
A76: pesticidesUsageInformation | B76: 52 | C76: Product 4 | D76: N. of treatements | E76: numberOfTreatments_3 | F76: H76 | K76: =CONCATENATE("""",F76,"""",":","""","parcelassessmentwithdats_",LOWER($A76),"_",LOWER($E76),"""") -> "H76":"parcelassessmentwithdats_pesticidesusageinformation_numberoftreatments_3"
A77: pesticidesUsageInformation | B77: 53 | C77: Product 4 | D77: Average quantity per application | E77: averageQuantity_3 | F77: H77 | K77: =CONCATENATE("""",F77,"""",":","""","parcelassessmentwithdats_",LOWER($A77),"_",LOWER($E77),"""") -> "H77":"parcelassessmentwithdats_pesticidesusageinformation_averagequantity_3"
... A95: pesticidesUsageInformation | B95: 71 | C95: Product 10 | D95: Average quantity per application | E95: averageQuantity_9 | F95: H95 | K95: =CONCATENATE("""",F95,"""",":","""","parcelassessmentwithdats_",LOWER($A95),"_",LOWER($E95),"""") -> "H95":"parcelassessmentwithdats_pesticidesusageinformation_averagequantity_9"
F96: H96 | K96: =CONCATENATE("""",F96,"""",":","""","parcelassessmentwithdats_",LOWER($A96),"_",LOWER($E96),"""") -> "H96":"parcelassessmentwithdats__"
B97: FERTILISER | F97: H97 | H97: Year 1 | K97: =CONCATENATE("""",F97,"""",":","""","parcelassessmentwithdats_",LOWER($A97),"_",LOWER($E97),"""") -> "H97":"parcelassessmentwithdats__"
B98: # | C98: data | F98: H98 | H98: Without DATSs | I98: Notes | K98: =CONCATENATE("""",F98,"""",":","""","parcelassessmentwithdats_",LOWER($A98),"_",LOWER($E98),"""") -> "H98":"parcelassessmentwithdats__"
A99: fertilizersUsageInformation | B99: 72 | C99: Fertilizer 1 | D99: Name fertiliser 1 | E99: productName_0 | F99: H99 | H99: 26-14-0 | K99: =CONCATENATE("""",F99,"""",":","""","parcelassessmentwithdats_",LOWER($A99),"_",LOWER($E99),"""") -> "H99":"parcelassessmentwithdats_fertilizersusageinformation_productname_0"
A100: fertilizersUsageInformation | B100: 73 | C100: Fertilizer 1 | D100: Mineral/Organic | E100: productType_0 | F100: H100 | H100: Mineral | K100: =CONCATENATE("""",F100,"""",":","""","parcelassessmentwithdats_",LOWER($A100),"_",LOWER($E100),"""") -> "H100":"parcelassessmentwithdats_fertilizersusageinformation_producttype_0"
A101: fertilizersUsageInformation | B101: 74 | C101: Fertilizer 1 | D101: N. of treatements | E101: numberOfTreatments_0 | F101: H101 | H101: 1 | K101: =CONCATENATE("""",F101,"""",":","""","parcelassessmentwithdats_",LOWER($A101),"_",LOWER($E101),"""") -> "H101":"parcelassessmentwithdats_fertilizersusageinformation_numberoftreatments_0"
A102: fertilizersUsageInformation | B102: 75 | C102: Fertilizer 1 | D102: Average quantity per application | E102: averageQuantity_0 | F102: H102 | H102: 173 | K102: =CONCATENATE("""",F102,"""",":","""","parcelassessmentwithdats_",LOWER($A102),"_",LOWER($E102),"""") -> "H102":"parcelassessmentwithdats_fertilizersusageinformation_averagequantity_0"
A103: fertilizersUsageInformation | B103: 76 | C103: Fertilizer 1 | D103: N concentration | E103: averageNitrogenQuantity_0 | F103: H103 | H103: 26 | K103: =CONCATENATE("""",F103,"""",":","""","parcelassessmentwithdats_",LOWER($A103),"_",LOWER($E103),"""") -> "H103":"parcelassessmentwithdats_fertilizersusageinformation_averagenitrogenquantity_0"
A104: fertilizersUsageInformation | B104: 77 | C104: Fertilizer 1 | D104: P concentration | E104: averagePhosphorusQuantity_0 | F104: H104 | H104: 14 | K104: =CONCATENATE("""",F104,"""",":","""","parcelassessmentwithdats_",LOWER($A104),"_",LOWER($E104),"""") -> "H104":"parcelassessmentwithdats_fertilizersusageinformation_averagephosphorusquantity_0"
A105: fertilizersUsageInformation | B105: 78 | C105: Fertilizer 1 | D105: K concentration | E105: averagePotassiumQuantity_0 | F105: H105 | H105: 0 | K105: =CONCATENATE("""",F105,"""",":","""","parcelassessmentwithdats_",LOWER($A105),"_",LOWER($E105),"""") -> "H105":"parcelassessmentwithdats_fertilizersusageinformation_averagepotassiumquantity_0"
A106: fertilizersUsageInformation | B106: 79 | C106: Fertilizer 2 | D106: Name fertiliser 2 | E106: productName_1 | F106: H106 | H106: Superstart | K106: =CONCATENATE("""",F106,"""",":","""","parcelassessmentwithdats_",LOWER($A106),"_",LOWER($E106),"""") -> "H106":"parcelassessmentwithdats_fertilizersusageinformation_productname_1"
A107: fertilizersUsageInformation | B107: 80 | C107: Fertilizer 2 | D107: Mineral/Organic | E107: productType_1 | F107: H107 | H107: Mineral | K107: =CONCATENATE("""",F107,"""",":","""","parcelassessmentwithdats_",LOWER($A107),"_",LOWER($E107),"""") -> "H107":"parcelassessmentwithdats_fertilizersusageinformation_producttype_1"
A108: fertilizersUsageInformation | B108: 81 | C108: Fertilizer 2 | D108: N. of treatements | E108: numberOfTreatments_1 | F108: H108 | H108: 1 | K108: =CONCATENATE("""",F108,"""",":","""","parcelassessmentwithdats_",LOWER($A108),"_",LOWER($E108),"""") -> "H108":"parcelassessmentwithdats_fertilizersusageinformation_numberoftreatments_1"
A109: fertilizersUsageInformation | B109: 82 | C109: Fertilizer 2 | D109: Average quantity per application | E109: averageQuantity_1 | F109: H109 | H109: 45 | K109: =CONCATENATE("""",F109,"""",":","""","parcelassessmentwithdats_",LOWER($A109),"_",LOWER($E109),"""") -> "H109":"parcelassessmentwithdats_fertilizersusageinformation_averagequantity_1"
A110: fertilizersUsageInformation | B110: 83 | C110: Fertilizer 2 | D110: N concentration | E110: averageNitrogenQuantity_1 | F110: H110 | H110: 10 | K110: =CONCATENATE("""",F110,"""",":","""","parcelassessmentwithdats_",LOWER($A110),"_",LOWER($E110),"""") -> "H110":"parcelassessmentwithdats_fertilizersusageinformation_averagenitrogenquantity_1"
A111: fertilizersUsageInformation | B111: 84 | C111: Fertilizer 2 | D111: P concentration | E111: averagePhosphorusQuantity_1 | F111: H111 | H111: 35 | K111: =CONCATENATE("""",F111,"""",":","""","parcelassessmentwithdats_",LOWER($A111),"_",LOWER($E111),"""") -> "H111":"parcelassessmentwithdats_fertilizersusageinformation_averagephosphorusquantity_1"
A112: fertilizersUsageInformation | B112: 85 | C112: Fertilizer 2 | D112: K concentration | E112: averagePotassiumQuantity_1 | F112: H112 | H112: 0 | K112: =CONCATENATE("""",F112,"""",":","""","parcelassessmentwithdats_",LOWER($A112),"_",LOWER($E112),"""") -> "H112":"parcelassessmentwithdats_fertilizersusageinformation_averagepotassiumquantity_1"
A113: fertilizersUsageInformation | B113: 86 | C113: Fertilizer 3 | D113: Name fertiliser 3 | E113: productName_2 | F113: H113 | H113: Kaliumsulfaat (English potassium sulfate) | K113: =CONCATENATE("""",F113,"""",":","""","parcelassessmentwithdats_",LOWER($A113),"_",LOWER($E113),"""") -> "H113":"parcelassessmentwithdats_fertilizersusageinformation_productname_2"
A114: fertilizersUsageInformation | B114: 87 | C114: Fertilizer 3 | D114: Mineral/Organic | E114: productType_2 | F114: H114 | H114: Mineral | K114: =CONCATENATE("""",F114,"""",":","""","parcelassessmentwithdats_",LOWER($A114),"_",LOWER($E114),"""") -> "H114":"parcelassessmentwithdats_fertilizersusageinformation_producttype_2"
A115: fertilizersUsageInformation | B115: 88 | C115: Fertilizer 3 | D115: N. of treatements | E115: numberOfTreatments_2 | F115: H115 | H115: 1 | K115: =CONCATENATE("""",F115,"""",":","""","parcelassessmentwithdats_",LOWER($A115),"_",LOWER($E115),"""") -> "H115":"parcelassessmentwithdats_fertilizersusageinformation_numberoftreatments_2"
A116: fertilizersUsageInformation | B116: 89 | C116: Fertilizer 3 | D116: Average quantity per application | E116: averageQuantity_2 | F116: H116 | H116: 134 | K116: =CONCATENATE("""",F116,"""",":","""","parcelassessmentwithdats_",LOWER($A116),"_",LOWER($E116),"""") -> "H116":"parcelassessmentwithdats_fertilizersusageinformation_averagequantity_2"
A117: fertilizersUsageInformation | B117: 90 | C117: Fertilizer 3 | D117: N concentration | E117: averageNitrogenQuantity_2 | F117: H117 | H117: 0 | K117: =CONCATENATE("""",F117,"""",":","""","parcelassessmentwithdats_",LOWER($A117),"_",LOWER($E117),"""") -> "H117":"parcelassessmentwithdats_fertilizersusageinformation_averagenitrogenquantity_2"
A118: fertilizersUsageInformation | B118: 91 | C118: Fertilizer 3 | D118: P concentration | E118: averagePhosphorusQuantity_2 | F118: H118 | H118: 0 | K118: =CONCATENATE("""",F118,"""",":","""","parcelassessmentwithdats_",LOWER($A118),"_",LOWER($E118),"""") -> "H118":"parcelassessmentwithdats_fertilizersusageinformation_averagephosphorusquantity_2"
A119: fertilizersUsageInformation | B119: 92 | C119: Fertilizer 3 | D119: K concentration | E119: averagePotassiumQuantity_2 | F119: H119 | H119: 50 | K119: =CONCATENATE("""",F119,"""",":","""","parcelassessmentwithdats_",LOWER($A119),"_",LOWER($E119),"""") -> "H119":"parcelassessmentwithdats_fertilizersusageinformation_averagepotassiumquantity_2"
A120: fertilizersUsageInformation | B120: 93 | C120: Fertilizer 4 | D120: Name fertiliser 4 | E120: productName_3 | F120: H120 | H120: Urean (mixture of ammonium nitrate and urea) | K120: =CONCATENATE("""",F120,"""",":","""","parcelassessmentwithdats_",LOWER($A120),"_",LOWER($E120),"""") -> "H120":"parcelassessmentwithdats_fertilizersusageinformation_productname_3"
A121: fertilizersUsageInformation | B121: 94 | C121: Fertilizer 4 | D121: Mineral/Organic | E121: productType_3 | F121: H121 | H121: Mineral | K121: =CONCATENATE("""",F121,"""",":","""","parcelassessmentwithdats_",LOWER($A121),"_",LOWER($E121),"""") -> "H121":"parcelassessmentwithdats_fertilizersusageinformation_producttype_3"
...

Sheet Cost-revenue DATS
A1: COST ANALYSIS
A2: INPUT | B2: INDICATOR | C2: SCENARIO | D2: UoM | E2: TOTAL | F2: FORMULAS
A3: WATER | B3: Cost of water | C3: With DATs | D3: =IFERROR(VLOOKUP('General Information'!$D$6, Validations!$L$2:$M$8, 2,FALSE), "") -> €/ha | E3: =('Parcel 1 with DATSs'!G29*'General Information'!D32)/(IF('General Information'!D6="crop",'Parcel 1 with DATSs'!G10,IF('General Information'!D6="milk",'Parcel 1 with DATSs'!G251,IF('General Information'!D6="meat",'Parcel 1 with DATSs'!G252,IF('General Information'!D6="animal",'Parcel 1 with DATSs'!G253,IF('General Information'!D6="oyster",'Parcel 1 with DATSs'!G254,IF('General Information'!D6="honey",'Parcel 1 with DATSs'!G255,'Parcel 1 with DATSs'!G256))))))) -> 0 | F3: IF(Total water used>0; (Total water used * water price)/Parcel dimension; Sum(water Irrigation+ water Fertigation + water Pest dilution + …) * water price) | G3: =CONCATENATE("cost revenue dats","_",$A$1,"_",A3,"_",B3) -> cost revenue dats_COST ANALYSIS_WATER _Cost of water | H3: E3
A4: FUEL | B4: Cost of fuel | C4: With DATs | D4: =IFERROR(VLOOKUP('General Information'!$D$6, Validations!$L$2:$M$8, 2,FALSE), "") -> €/ha | E4: ='Parcel 1 with DATSs'!G43*'General Information'!D33/(IF('General Information'!D6="crop",'Parcel 1 with DATSs'!G10,IF('General Information'!D6="milk",'Parcel 1 with DATSs'!G251,IF('General Information'!D6="meat",'Parcel 1 with DATSs'!G252,IF('General Information'!D6="animal",'Parcel 1 with DATSs'!G253,IF('General Information'!D6="oyster",'Parcel 1 with DATSs'!G254,IF('General Information'!D6="honey",'Parcel 1 with DATSs'!G255,'Parcel 1 with DATSs'!G256))))))) -> 0 | F4: IF(Total fuel used>0; (Total fuel used*fuel price)/Parcel dimension; sum(Fertilisation+Pesticides +Irrigation+Sowing_Planting+Pruning+…) * fuel price) | G4: =CONCATENATE("cost revenue dats","_",$A$1,"_",A4,"_",B4) -> cost revenue dats_COST ANALYSIS_FUEL _Cost of fuel | H4: E4
A5: ELECTRICITY | B5: Cost of electricity | C5: With DATs | D5: =IFERROR(VLOOKUP('General Information'!$D$6, Validations!$L$2:$M$8, 2,FALSE), "") -> €/ha | E5: ='Parcel 1 with DATSs'!G62*'General Information'!D38/(IF('General Information'!D6="crop",'Parcel 1 with DATSs'!G10,IF('General Information'!D6="milk",'Parcel 1 with DATSs'!G251,IF('General Information'!D6="meat",'Parcel 1 with DATSs'!G252,IF('General Information'!D6="animal",'Parcel 1 with DATSs'!G253,IF('General Information'!D6="oyster",'Parcel 1 with DATSs'!G254,IF('General Information'!D6="honey",'Parcel 1 with DATSs'!G255,'Parcel 1 with DATSs'!G256))))))) -> 2.5609756 | F5: IF(Total electricity used > 0; (Total electricity used* electricity price)/Parcel dimension; Sum(irrigation,…) *electricity price) | G5: =CONCATENATE("cost revenue dats","_",$A$1,"_",A5,"_",B5) -> cost revenue dats_COST ANALYSIS_ELECTRICITY_Cost of electricity | H5: E5
A6: PESTICIDE | B6: Cost for pesticide | C6: With DATs | D6: =IFERROR(VLOOKUP('General Information'!$D$6, Validations!$L$2:$M$8, 2,FALSE), "") -> €/ha | E6: =('Parcel 1 with DATSs'!G67*'Parcel 1 with DATSs'!G68*'General Information'!D43)+ ('Parcel 1 with DATSs'!G70*'Parcel 1 with DATSs'!G71*'General Information'!D44)+ ('Parcel 1 with DATSs'!G73*'Parcel 1 with DATSs'!G74*'General Information'!D45)+ ('Parcel 1 with DATSs'!G76*'Parcel 1 with DATSs'!G77*'General Information'!D46)+ ('Parcel 1 with DATSs'!G79*'Parcel 1 with DATSs'!G80*'General Information'!D47)+ ('Parcel 1 with DATSs'!G82*'Parcel 1 with DATSs'!G83*'General Information'!D48)+ ('Parcel 1 with DATSs'!G85*'Parcel 1 with DATSs'!G86*'General Information'!D49)+ ('Parcel 1 with DATSs'!G88*'Parcel 1 with DATSs'!G89*'General Information'!D50)+ ('Parcel 1 with DATSs'!G91*'Parcel 1 with DATSs'!G92*'General Information'!D51)+ ('Parcel 1 with DATSs'!G94*'Parcel 1 with DATSs'!G95*'General Information'!D52) -> 0 | F6: [(N. of treatements of pesticide 1*Amount of pesticide 1*pesticide 1 price)+(N. of treatements of pesticide 2 *Amount of pesticide 2 used *pesticide 2 price) + (N. of treatements of pesticide 3 *Amount of pesticide 3 used *pesticide 3 price (€/kg)] | G6: =CONCATENATE("cost revenue dats","_",$A$1,"_",A6,"_",B6) -> cost revenue dats_COST ANALYSIS_PESTICIDE _Cost for pesticide | H6: E6
A7: FERTILISER | B7: Cost of fertiliser | C7: With DATs | D7: =IFERROR(VLOOKUP('General Information'!$D$6, Validations!$L$2:$M$8, 2,FALSE), "") -> €/ha | E7: =('Parcel 1 with DATSs'!G101*'Parcel 1 with DATSs'!G102*'General Information'!D54)+ ('Parcel 1 with DATSs'!G108*'Parcel 1 with DATSs'!G109*'General Information'!D55)+ ('Parcel 1 with DATSs'!G115*'Parcel 1 with DATSs'!G116*'General Information'!D56)+ ('Parcel 1 with DATSs'!G122*'Parcel 1 with DATSs'!G123*'General Information'!D57)+ ('Parcel 1 with DATSs'!G129*'Parcel 1 with DATSs'!G130*'General Information'!D58)+ ('Parcel 1 with DATSs'!G136*'Parcel 1 with DATSs'!G137*'General Information'!D59)+ ('Parcel 1 with DATSs'!G143*'Parcel 1 with DATSs'!G144*'General Information'!D60)+ ('Parcel 1 with DATSs'!G150*'Parcel 1 with DATSs'!G151*'General Information'!D61)+ ('Parcel 1 with DATSs'!G157*'Parcel 1 with DATSs'!G158*'General Information'!D62)+ ('Parcel 1 with DATSs'!G164*'Parcel 1 with DATSs'!G165*'General Information'!D63) -> 1371.47 | F7: ((Amount of fertilisers 1 used *Number of fertilizer 1 applications *Fertilisers 1 price) + (Amount of fertilisers 2 used *Number of fertilizer 2 applications *Fertilisers 2 price) + (Amount of fertilisers 3 used *Number of fertilizer 3 applications *Fertilisers 3 price) | G7: =CONCATENATE("cost revenue dats","_",$A$1,"_",A7,"_",B7) -> cost revenue dats_COST ANALYSIS_FERTILISER_Cost of fertiliser | H7: E7
A8: FEED | B8: Cost of feed | C8: With DATs | D8: =IFERROR(VLOOKUP('General Information'!$D$6, Validations!$L$2:$M$8, 2,FALSE), "") -> €/ha | E8: =(('General Information'!D65*'Parcel 1 with DATSs'!G173)+('General Information'!D66*'Parcel 1 with DATSs'!G175)+('General Information'!D69*'Parcel 1 with DATSs'!G177))/(IF('General Information'!D6="crop",'Parcel 1 with DATSs'!G10,IF('General Information'!D6="milk",'Parcel 1 with DATSs'!G251,IF('General Information'!D6="meat",'Parcel 1 with DATSs'!G252,IF('General Information'!D6="animal",'Parcel 1 with DATSs'!G253,IF('General Information'!D6="oyster",'Parcel 1 with DATSs'!G254,IF('General Information'!D6="honey",'Parcel 1 with DATSs'!G255,'Parcel 1 with DATSs'!G256))))))) -> 0 | F8: (Amount of feed 1 * Feed 1 price) + (Amount of feed 2 * Feed 2 price) + … /animal | G8: =CONCATENATE("cost revenue dats","_",$A$1,"_",A8,"_",B8) -> cost revenue dats_COST ANALYSIS_FEED_Cost of feed | H8: E8
A9: DRUGS | B9: Cost of drugs | C9: With DATs | D9: =IFERROR(VLOOKUP('General Information'!$D$6, Validations!$L$2:$M$8, 2,FALSE), "") -> €/ha | E9: =(('General Information'!D71*'Parcel 1 with DATSs'!G186)+('General Information'!D72*'Parcel 1 with DATSs'!G188)+('General Information'!D73*'Parcel 1 with DATSs'!G190))/(IF('General Information'!D6="crop",'Parcel 1 with DATSs'!G10,IF('General Information'!D6="milk",'Parcel 1 with DATSs'!G251,IF('General Information'!D6="meat",'Parcel 1 with DATSs'!G252,IF('General Information'!D6="animal",'Parcel 1 with DATSs'!G253,IF('General Information'!D6="oyster",'Parcel 1 with DATSs'!G254,IF('General Information'!D6="honey",'Parcel 1 with DATSs'!G255,'Parcel 1 with DATSs'!G256))))))) -> 0 | F9: (Amount of drugs 1 * Feed 1 price) + (Amount of drugs 2 * Feed 2 price) + … /animal or beehives or pieces | G9: =CONCATENATE("cost revenue dats","_",$A$1,"_",A9,"_",B9) -> cost revenue dats_COST ANALYSIS_DRUGS _ Cost of drugs | H9: E9
A10: LABOUR | B10: Cost of labour for irrigation | C10: With DATs | D10: =IFERROR(VLOOKUP('General Information'!$D$6, Validations!$L$2:$M$8, 2,FALSE), "") -> €/ha | E10: ='Parcel 1 with DATSs'!G194*'General Information'!D39/'Parcel 1 with DATSs'!G10 -> 134.14634 | F10: number of hours for irrigation activities*Average salary /Parcel dimension | G10: =CONCATENATE("cost revenue dats","_",$A$1,"_",A10,"_",B10) -> cost revenue dats_COST ANALYSIS_LABOUR_Cost of labour for irrigation | H10: E10
A11: LABOUR | B11: Cost of labour for pesticide application | C11: With DATs | D11: =IFERROR(VLOOKUP('General Information'!$D$6, Validations!$L$2:$M$8, 2,FALSE), "") -> €/ha | E11: ='Parcel 1 with DATSs'!G195*'General Information'!D39/'Parcel 1 with DATSs'!G10 -> 0 | F11: number of hours for pesticide activities *Average salary /Parcel dimension | G11: =CONCATENATE("cost revenue dats","_",$A$1,"_",A11,"_",B11) -> cost revenue dats_COST ANALYSIS_LABOUR_Cost of labour for pesticide application | H11: E11
A12: LABOUR | B12: Cost of labour for fertilisation | C12: With DATs | D12: =IFERROR(VLOOKUP('General Information'!$D$6, Validations!$L$2:$M$8, 2,FALSE), "") -> €/ha | E12: ='Parcel 1 with DATSs'!G196*'General Information'!D39/'Parcel 1 with DATSs'!G10 -> 0 | F12: number of hours for fertilisation activities * Average salary /Parcel dimension | G12: =CONCATENATE("cost revenue dats","_",$A$1,"_",A12,"_",B12) -> cost revenue dats_COST ANALYSIS_LABOUR_Cost of labour for fertilisation | H12: E12
A13: LABOUR | B13: Cost of labour for sowing_planting | C13: With DATs | D13: =IFERROR(VLOOKUP('General Information'!$D$6, Validations!$L$2:$M$8, 2,FALSE), "") -> €/ha | E13: ='Parcel 1 with DATSs'!G197*'General Information'!D39/'Parcel 1 with DATSs'!G10 -> 0 | F13: number of hours for sowing_planting activities * Average salary /Parcel dimension | G13: =CONCATENATE("cost revenue dats","_",$A$1,"_",A13,"_",B13) -> cost revenue dats_COST ANALYSIS_LABOUR_Cost of labour for sowing_planting | H13: E13
A14: LABOUR | B14: Cost of labour for pruning | C14: With DATs | D14: =IFERROR(VLOOKUP('General Information'!$D$6, Validations!$L$2:$M$8, 2,FALSE), "") -> €/ha | E14: ='Parcel 1 with DATSs'!G198*'General Information'!D39/'Parcel 1 with DATSs'!G10 -> 0 | F14: number of hours for pruning activities *Average salary /Parcel dimension | G14: =CONCATENATE("cost revenue dats","_",$A$1,"_",A14,"_",B14) -> cost revenue dats_COST ANALYSIS_LABOUR_Cost of labour for pruning | H14: E14
A15: LABOUR | B15: Cost of labour for field visits | C15: With DATs | D15: =IFERROR(VLOOKUP('General Information'!$D$6, Validations!$L$2:$M$8, 2,FALSE), "") -> €/ha | E15: ='Parcel 1 with DATSs'!G199*'General Information'!D39/'Parcel 1 with DATSs'!G10 -> 0 | F15: number of hours for field visits activities * Average professional salary /Parcel dimension | G15: =CONCATENATE("cost revenue dats","_",$A$1,"_",A15,"_",B15) -> cost revenue dats_COST ANALYSIS_LABOUR_Cost of labour for field visits | H15: E15
A16: LABOUR | B16: Cost of labour for greenhouse maintenance | C16: With DATs | D16: =IFERROR(VLOOKUP('General Information'!$D$6, Validations!$L$2:$M$8, 2,FALSE), "") -> €/ha | E16: ='Parcel 1 with DATSs'!G200*'General Information'!D39/'Parcel 1 with DATSs'!G10 -> 0 | F16: number of hours for greenhouse management *Average salary /Parcel dimension | G16: =CONCATENATE("cost revenue dats","_",$A$1,"_",A16,"_",B16) -> cost revenue dats_COST ANALYSIS_LABOUR_Cost of labour for greenhouse maintenance | H16: E16
A17: LABOUR | B17: Cost of labour for tracking the quantity of grain available in the silo | C17: With DATs | D17: =IFERROR(VLOOKUP('General Information'!$D$6, Validations!$L$2:$M$8, 2,FALSE), "") -> €/ha | E17: ='Parcel 1 with DATSs'!G201*'General Information'!D39/'Parcel 1 with DATSs'!G256 -> #DIV/0! | F17: number of hours for tracking the quantity of grain available in the silo *Average salary | G17: =CONCATENATE("cost revenue dats","_",$A$1,"_",A17,"_",B17) -> cost revenue dats_COST ANALYSIS_LABOUR_Cost of labour for tracking the quantity of grain available in the silo | H17: E17
A18: LABOUR | B18: Cost of labour for assessing product quality | C18: With DATs | D18: =IFERROR(VLOOKUP('General Information'!$D$6, Validations!$L$2:$M$8, 2,FALSE), "") -> €/ha | E18: ='Parcel 1 with DATSs'!G202*'General Information'!D39/(IF('General Information'!D6="crop",'Parcel 1 with DATSs'!G10,IF('General Information'!D6="milk",'Parcel 1 with DATSs'!G251,IF('General Information'!D6="meat",'Parcel 1 with DATSs'!G252,IF('General Information'!D6="animal",'Parcel 1 with DATSs'!G253,IF('General Information'!D6="oyster",'Parcel 1 with DATSs'!G254,IF('General Information'!D6="honey",'Parcel 1 with DATSs'!G255,'Parcel 1 with DATSs'!G256))))))) -> 0 | F18: number of hours for assessing grain quality *Average salary | G18: =CONCATENATE("cost revenue dats","_",$A$1,"_",A18,"_",B18) -> cost revenue dats_COST ANALYSIS_LABOUR_Cost of labour for assessing product quality | H18: E18
A19: LABOUR | B19: Cost of labour for controlling purchase and sale prices and quantities | C19: With DATs | D19: =IFERROR(VLOOKUP('General Information'!$D$6, Validations!$L$2:$M$8, 2,FALSE), "") -> €/ha | E19: ='Parcel 1 with DATSs'!G203*'General Information'!D39/(IF('General Information'!D6="crop",'Parcel 1 with DATSs'!G10,IF('General Information'!D6="milk",'Parcel 1 with DATSs'!G251,IF('General Information'!D6="meat",'Parcel 1 with DATSs'!G252,IF('General Information'!D6="animal",'Parcel 1 with DATSs'!G253, IF('General Information'!D6="oyster",'Parcel 1 with DATSs'!G254,IF('General Information'!D6="honey",'Parcel 1 with DATSs'!G255,'Parcel 1 with DATSs'!G256))))))) -> 0 | F19: number of hours for controlling purchase and sale prices and quantities *Average salary | G19: =CONCATENATE("cost revenue dats","_",$A$1,"_",A19,"_",B19) -> cost revenue dats_COST ANALYSIS_LABOUR_Cost of labour for controlling purchase and sale prices and quantities | H19: E19
A20: LABOUR | B20: Cost of labour for organise logistics | C20: With DATs | D20: =IFERROR(VLOOKUP('General Information'!$D$6, Validations!$L$2:$M$8, 2,FALSE), "") -> €/ha | E20: ='Parcel 1 with DATSs'!G204*'General Information'!D39/(IF('General Information'!D6="crop",'Parcel 1 with DATSs'!G10,IF('General Information'!D6="milk",'Parcel 1 with DATSs'!G251,IF('General Information'!D6="meat",'Parcel 1 with DATSs'!G252,IF('General Information'!D6="animal",'Parcel 1 with DATSs'!G253, IF('General Information'!D6="oyster",'Parcel 1 with DATSs'!G254,IF('General Information'!D6="honey",'Parcel 1 with DATSs'!G255,'Parcel 1 with DATSs'!G256))))))) -> 0 | F20: number of hours for organise logistics *Average salary | G20: =CONCATENATE("cost revenue dats","_",$A$1,"_",A20,"_",B20) -> cost revenue dats_COST ANALYSIS_LABOUR_Cost of labour for organise logistics | H20: E20
A21: LABOUR | B21: Cost of labour for cleaning | C21: With DATs | D21: =IFERROR(VLOOKUP('General Information'!$D$6, Validations!$L$2:$M$8, 2,FALSE), "") -> €/ha | E21: ='Parcel 1 with DATSs'!G205*'General Information'!D39/(IF('General Information'!D6="crop",'Parcel 1 with DATSs'!G10,IF('General Information'!D6="milk",'Parcel 1 with DATSs'!G251,IF('General Information'!D6="meat",'Parcel 1 with DATSs'!G252,IF('General Information'!D6="animal",'Parcel 1 with DATSs'!G253, IF('General Information'!D6="oyster",'Parcel 1 with DATSs'!G254,IF('General Information'!D6="honey",'Parcel 1 with DATSs'!G255,'Parcel 1 with DATSs'!G256))))))) -> 0 | F21: number of hours for cleaning *Average salary /animal | G21: =CONCATENATE("cost revenue dats","_",$A$1,"_",A21,"_",B21) -> cost revenue dats_COST ANALYSIS_LABOUR_Cost of labour for cleaning | H21: E21
A22: LABOUR | B22: Cost of labour for stable visits | C22: With DATs | D22: =IFERROR(VLOOKUP('General Information'!$D$6, Validations!$L$2:$M$8, 2,FALSE), "") -> €/ha | E22: ='Parcel 1 with DATSs'!G206*'General Information'!D39/(IF('General Information'!D6="crop",'Parcel 1 with DATSs'!G10,IF('General Information'!D6="milk",'Parcel 1 with DATSs'!G251,IF('General Information'!D6="meat",'Parcel 1 with DATSs'!G252,IF('General Information'!D6="animal",'Parcel 1 with DATSs'!G253, IF('General Information'!D6="oyster",'Parcel 1 with DATSs'!G254,IF('General Information'!D6="honey",'Parcel 1 with DATSs'!G255,'Parcel 1 with DATSs'!G256))))))) -> 0 | F22: number of hours for stable visits*Average professional salary /animal | G22: =CONCATENATE("cost revenue dats","_",$A$1,"_",A22,"_",B22) -> cost revenue dats_COST ANALYSIS_LABOUR_Cost of labour for stable visits | H22: E22
A23: LABOUR | B23: Cost of labour for heat detection | C23: With DATs | D23: =IFERROR(VLOOKUP('General Information'!$D$6, Validations!$L$2:$M$8, 2,FALSE), "") -> €/ha | E23: ='Parcel 1 with DATSs'!G207*'General Information'!D39/(IF('General Information'!D6="crop",'Parcel 1 with DATSs'!G10,IF('General Information'!D6="milk",'Parcel 1 with DATSs'!G251,IF('General Information'!D6="meat",'Parcel 1 with DATSs'!G252,IF('General Information'!D6="animal",'Parcel 1 with DATSs'!G253, IF('General Information'!D6="oyster",'Parcel 1 with DATSs'!G254,IF('General Information'!D6="honey",'Parcel 1 with DATSs'!G255,'Parcel 1 with DATSs'!G256))))))) -> 0 | F23: number of hours for heat detection *Average salary /animal | G23: =CONCATENATE("cost revenue dats","_",$A$1,"_",A23,"_",B23) -> cost revenue dats_COST ANALYSIS_LABOUR_Cost of labour for heat detection | H23: E23
A24: LABOUR | B24: Cost of labour for calving detection | C24: With DATs | D24: =IFERROR(VLOOKUP('General Information'!$D$6, Validations!$L$2:$M$8, 2,FALSE), "") -> €/ha | E24: ='Parcel 1 with DATSs'!G208*'General Information'!D39/(IF('General Information'!D6="crop",'Parcel 1 with DATSs'!G10,IF('General Information'!D6="milk",'Parcel 1 with DATSs'!G251,IF('General Information'!D6="meat",'Parcel 1 with DATSs'!G252,IF('General Information'!D6="animal",'Parcel 1 with DATSs'!G253, IF('General Information'!D6="oyster",'Parcel 1 with DATSs'!G254,IF('General Information'!D6="honey",'Parcel 1 with DATSs'!G255,'Parcel 1 with DATSs'!G256))))))) -> 0 | F24: number of hours for calving detection *Average salary /animal | G24: =CONCATENATE("cost revenue dats","_",$A$1,"_",A24,"_",B24) -> cost revenue dats_COST ANALYSIS_LABOUR_Cost of labour for calving detection | H24: E24
A25: LABOUR | B25: Cost of labour for pigsty management | C25: With DATs | D25: =IFERROR(VLOOKUP('General Information'!$D$6, Validations!$L$2:$M$8, 2,FALSE), "") -> €/ha | E25: ='Parcel 1 with DATSs'!G209*'General Information'!D39/(IF('General Information'!D6="crop",'Parcel 1 with DATSs'!G10,IF('General Information'!D6="milk",'Parcel 1 with DATSs'!G251,IF('General Information'!D6="meat",'Parcel 1 with DATSs'!G252,IF('General Information'!D6="animal",'Parcel 1 with DATSs'!G253, IF('General Information'!D6="oyster",'Parcel 1 with DATSs'!G254,IF('General Information'!D6="honey",'Parcel 1 with DATSs'!G255,'Parcel 1 with DATSs'!G256))))))) -> 0 | F25: number of hours for pigsty management*Average salary /animal | G25: =CONCATENATE("cost revenue dats","_",$A$1,"_",A25,"_",B25) -> cost revenue dats_COST ANALYSIS_LABOUR_Cost of labour for pigsty management | H25: E25
A26: LABOUR | B26: Cost of milking | C26: With DATs | D26: =IFERROR(VLOOKUP('General Information'!$D$6, Validations!$L$2:$M$8, 2,FALSE), "") -> €/ha | E26: ='Parcel 1 with DATSs'!G210*'General Information'!D39/(IF('General Information'!D6="crop",'Parcel 1 with DATSs'!G10,IF('General Information'!D6="milk",'Parcel 1 with DATSs'!G251,IF('General Information'!D6="meat",'Parcel 1 with DATSs'!G252,IF('General Information'!D6="animal",'Parcel 1 with DATSs'!G253, IF('General Information'!D6="oyster",'Parcel 1 with DATSs'!G254,IF('General Information'!D6="honey",'Parcel 1 with DATSs'!G255,'Parcel 1 with DATSs'!G256))))))) -> 0 | F26: number of hours for milking *Average salary /animal | G26: =CONCATENATE("cost revenue dats","_",$A$1,"_",A26,"_",B26) -> cost revenue dats_COST ANALYSIS_LABOUR_Cost of milking | H26: E26
A27: LABOUR | B27: Cost of labour for (milk) quality assessment | C27: With DATs | D27: =IFERROR(VLOOKUP('General Information'!$D$6, Validations!$L$2:$M$8, 2,FALSE), "") -> €/ha | E27: ='Parcel 1 with DATSs'!G211*'General Information'!D39/(IF('General Information'!D6="crop",'Parcel 1 with DATSs'!G10,IF('General Information'!D6="milk",'Parcel 1 with DATSs'!G251,IF('General Information'!D6="meat",'Parcel 1 with DATSs'!G252,IF('General Information'!D6="animal",'Parcel 1 with DATSs'!G253, IF('General Information'!D6="oyster",'Parcel 1 with DATSs'!G254,IF('General Information'!D6="honey",'Parcel 1 with DATSs'!G255,'Parcel 1 with DATSs'!G256))))))) -> 0 | F27: number of hours for (milk) quality assessment*Average salary /animal | G27: =CONCATENATE("cost revenue dats","_",$A$1,"_",A27,"_",B27) -> cost revenue dats_COST ANALYSIS_LABOUR_Cost of labour for (milk) quality assessment | H27: E27
A28: LABOUR | B28: Cost of labour for feeding | C28: With DATs | D28: =IFERROR(VLOOKUP('General Information'!$D$6, Validations!$L$2:$M$8, 2,FALSE), "") -> €/ha | E28: ='Parcel 1 with DATSs'!G212*'General Information'!D39/(IF('General Information'!D6="crop",'Parcel 1 with DATSs'!G10,IF('General Information'!D6="milk",'Parcel 1 with DATSs'!G251,IF('General Information'!D6="meat",'Parcel 1 with DATSs'!G252,IF('General Information'!D6="animal",'Parcel 1 with DATSs'!G253, IF('General Information'!D6="oyster",'Parcel 1 with DATSs'!G254,IF('General Information'!D6="honey",'Parcel 1 with DATSs'!G255,'Parcel 1 with DATSs'!G256))))))) -> 0 | F28: number of hours for feeding *Average salary /animal | G28: =CONCATENATE("cost revenue dats","_",$A$1,"_",A28,"_",B28) -> cost revenue dats_COST ANALYSIS_LABOUR_Cost of labour for feeding | H28: E28
A29: LABOUR | B29: Cost of labour for beehives visits | C29: With DATs | D29: =IFERROR(VLOOKUP('General Information'!$D$6, Validations!$L$2:$M$8, 2,FALSE), "") -> €/ha | E29: ='Parcel 1 with DATSs'!G213*'General Information'!D39/'Parcel 1 with DATSs'!G255 -> #DIV/0! | F29: number of hours for beehives visits *Average salary / beehive | G29: =CONCATENATE("cost revenue dats","_",$A$1,"_",A29,"_",B29) -> cost revenue dats_COST ANALYSIS_LABOUR_Cost of labour for beehives visits | H29: E29
A30: LABOUR | B30: Cost of labour for sampling of oysters | C30: With DATs | D30: =IFERROR(VLOOKUP('General Information'!$D$6, Validations!$L$2:$M$8, 2,FALSE), "") -> €/ha | E30: ='Parcel 1 with DATSs'!G214*'General Information'!D39/'Parcel 1 with DATSs'!G254 -> #DIV/0! | F30: number of hours for sampling of oysters* Average salary /piece | G30: =CONCATENATE("cost revenue dats","_",$A$1,"_",A30,"_",B30) -> cost revenue dats_COST ANALYSIS_LABOUR_Cost of labour for sampling of oysters | H30: E30
A31: LABOUR | B31: Cost of labour for transporting oysters to the laboratory | C31: With DATs | D31: =IFERROR(VLOOKUP('General Information'!$D$6, Validations!$L$2:$M$8, 2,FALSE), "") -> €/ha | E31: ='Parcel 1 with DATSs'!G215*'General Information'!D39/'Parcel 1 with DATSs'!G254 -> #DIV/0! | F31: number of hours for transporting oysters to the laboratory*Average salary /piece | G31: =CONCATENATE("cost revenue dats","_",$A$1,"_",A31,"_",B31) -> cost revenue dats_COST ANALYSIS_LABOUR_Cost of labour for transporting oysters to the laboratory | H31: E31
A32: LABOUR | B32: Cost of labour for harvesting | C32: With DATs | D32: =IFERROR(VLOOKUP('General Information'!$D$6, Validations!$L$2:$M$8, 2,FALSE), "") -> €/ha | E32: ='Parcel 1 with DATSs'!G216*'General Information'!$D$39/(IF('General Information'!D6="crop",'Parcel 1 with DATSs'!G10,IF('General Information'!D6="milk",'Parcel 1 with DATSs'!G251,IF('General Information'!D6="meat",'Parcel 1 with DATSs'!G252,IF('General Information'!D6="animal",'Parcel 1 with DATSs'!G253, IF('General Information'!D6="oyster",'Parcel 1 with DATSs'!G254,IF('General Information'!D6="honey",'Parcel 1 with DATSs'!G255,'Parcel 1 with DATSs'!G256))))))) -> 0 | F32: number of hours for harvesting oyster*Average salary /piece | G32: =CONCATENATE("cost revenue dats","_",$A$1,"_",A32,"_",B32) -> cost revenue dats_COST ANALYSIS_LABOUR_Cost of labour for harvesting | H32: E32
A33: LABOUR | B33: Cost of labour for storage | C33: With DATs | D33: =IFERROR(VLOOKUP('General Information'!$D$6, Validations!$L$2:$M$8, 2,FALSE), "") -> €/ha | E33: ='Parcel 1 with DATSs'!G217*'General Information'!D39/(IF('General Information'!D6="crop",'Parcel 1 with DATSs'!G10,IF('General Information'!D6="milk",'Parcel 1 with DATSs'!G251,IF('General Information'!D6="meat",'Parcel 1 with DATSs'!G252,IF('General Information'!D6="animal",'Parcel 1 with DATSs'!G253, IF('General Information'!D6="oyster",'Parcel 1 with DATSs'!G254,IF('General Information'!D6="honey",'Parcel 1 with DATSs'!G255,'Parcel 1 with DATSs'!G256))))))) -> 0 | F33: number of hours for storage *Average salary /piece | G33: =CONCATENATE("cost revenue dats","_",$A$1,"_",A33,"_",B33) -> cost revenue dats_COST ANALYSIS_LABOUR_Cost of labour for storage | H33: E33
A34: LABOUR | B34: Cost of administrative activities, data collection, etc. | C34: With DATs | D34: =IFERROR(VLOOKUP('General Information'!$D$6, Validations!$L$2:$M$8, 2,FALSE), "") -> €/ha | E34: ='Parcel 1 with DATSs'!G218*'General Information'!$D$39/(IF('General Information'!D6="crop",'Parcel 1 with DATSs'!G10,IF('General Information'!D6="milk",'Parcel 1 with DATSs'!G251,IF('General Information'!D6="meat",'Parcel 1 with DATSs'!G252,IF('General Information'!D6="animal",'Parcel 1 with DATSs'!G253, IF('General Information'!D6="oyster",'Parcel 1 with DATSs'!G254,IF('General Information'!D6="honey",'Parcel 1 with DATSs'!G255,'Parcel 1 with DATSs'!G256))))))) -> 0 | F34: number of hours foradministrative activities *Average salary /parcel dimension or animal or beehives or pieces | G34: =CONCATENATE("cost revenue dats","_",$A$1,"_",A34,"_",B34) -> cost revenue dats_COST ANALYSIS_LABOUR_Cost of administrative activities, data collection, etc. | H34: E34
A35: COST | B35: TOT Cost | C35: With DATs | D35: =IFERROR(VLOOKUP('General Information'!$D$6, Validations!$L$2:$M$8, 2,FALSE), "") -> €/ha | E35: =_xlfn.AGGREGATE(9,6,E3:E34) -> 1508.1773 | F35: Sum(Cost of labour for irrigation + Cost of labour for fertilisation + … /parcel dimension or animal or beehives or pieces | G35: =CONCATENATE("cost revenue dats","_",$A$1,"_",A35,"_",B35) -> cost revenue dats_COST ANALYSIS_COST_TOT Cost | H35: E35
A36: DATSs | B36: Cost of DATSs | C36: With DATs | D36: =IFERROR(VLOOKUP('General Information'!$D$6, Validations!$L$2:$M$8, 2,FALSE), "") -> €/ha | E36: =(('General Information'!D23+'General Information'!D24)+('General Information'!I23+'General Information'!I24)+('General Information'!M23+'General Information'!M24))/(IF('General Information'!D6="crop",'Parcel 1 with DATSs'!G10,IF('General Information'!D6="milk",'Parcel 1 with DATSs'!G251,IF('General Information'!D6="meat",'Parcel 1 with DATSs'!G252,IF('General Information'!D6="animal",'Parcel 1 with DATSs'!G253, IF('General Information'!D6="oyster",'Parcel 1 with DATSs'!G254,IF('General Information'!D6="honey",'Parcel 1 with DATSs'!G255,'Parcel 1 with DATSs'!G256))))))) -> 73.170732 | F36: DAT maintenance + (Training hours*salary) /parcel dimension or animal or beehives or pieces | G36: =CONCATENATE("cost revenue dats","_",$A$1,"_",A36,"_",B36) -> cost revenue dats_COST ANALYSIS_DATSs_Cost of DATSs | H36: E36
A37: DATSs | B37: Cost of Training | C37: With DATs | D37: =IFERROR(VLOOKUP('General Information'!$D$6, Validations!$L$2:$M$8, 2,FALSE), "") -> €/ha | E37: ='General Information'!D27/(IF('General Information'!D6="crop",'Parcel 1 with DATSs'!G10,IF('General Information'!D6="milk",'Parcel 1 with DATSs'!G251,IF('General Information'!D6="meat",'Parcel 1 with DATSs'!G252,IF('General Information'!D6="animal",'Parcel 1 with DATSs'!G253, IF('General Information'!D6="oyster",'Parcel 1 with DATSs'!G254,IF('General Information'!D6="honey",'Parcel 1 with DATSs'!G255,'Parcel 1 with DATSs'!G256))))))) -> 0 | F37: Costs of external persons being paid to train employees on the use of DAT /parcel dimension or animal or beehives or pieces | G37: =CONCATENATE("cost revenue dats","_",$A$1,"_",A37,"_",B37) -> cost revenue dats_COST ANALYSIS_DATSs_Cost of Training | H37: E37
A39: REVENUES ANALYSIS
A40: CATEGORY | B40: INDICATOR | C40: SCENARIO | D40: UoM | E40: TOTAL | F40: FORMULAS
A41: OUTPUT | B41: Crop revenue | C41: With DATs | D41: €/ha | E41: ='Parcel 1 with DATSs'!G250/'Parcel 1 with DATSs'!G10*'General Information'!$D$41 -> 12070 | F41: Yield*Product market price | G41: =CONCATENATE("cost revenue dats","_",$A$39,"_",A41,"_",B41) -> cost revenue dats_REVENUES ANALYSIS_OUTPUT_Crop revenue | H41: E41
A42: OUTPUT | B42: Milk revenue | C42: With DATs | D42: =IFERROR(VLOOKUP('General Information'!$D$6, Validations!$L$2:$M$8, 2,FALSE), "") -> €/ha | E42: =('Parcel 1 with DATSs'!G251*'General Information'!$D$41/(IF('General Information'!D6="crop",'Parcel 1 with DATSs'!G10,IF('General Information'!D6="milk",'Parcel 1 with DATSs'!G251,IF('General Information'!D6="meat",'Parcel 1 with DATSs'!G252,IF('General Information'!D6="animal",'Parcel 1 with DATSs'!G253,IF('General Information'!D6="oyster",'Parcel 1 with DATSs'!G254,IF('General Information'!D6="honey",'Parcel 1 with DATSs'!G255,'Parcel 1 with DATSs'!G256))))))))*1000 -> 0 | F42: Milk *Product market price | G42: =CONCATENATE("cost revenue dats","_",$A$39,"_",A42,"_",B42) -> cost revenue dats_REVENUES ANALYSIS_OUTPUT_Milk revenue | H42: E42
A43: OUTPUT | B43: Meat revenue | C43: With DATs | D43: =IFERROR(VLOOKUP('General Information'!$D$6, Validations!$L$2:$M$8, 2,FALSE), "") -> €/ha | E43: =('Parcel 1 with DATSs'!G252*'General Information'!D41/(IF('General Information'!D6="crop",'Parcel 1 with DATSs'!G10,IF('General Information'!D6="milk",'Parcel 1 with DATSs'!G251,IF('General Information'!D6="meat",'Parcel 1 with DATSs'!G252,IF('General Information'!D6="animal",'Parcel 1 with DATSs'!G253,IF('General Information'!D6="oyster",'Parcel 1 with DATSs'!G254,IF('General Information'!D6="honey",'Parcel 1 with DATSs'!G255,'Parcel 1 with DATSs'!G256))))))))/10 -> 0 | F43: Meat*Product market price | G43: =CONCATENATE("cost revenue dats","_",$A$39,"_",A43,"_",B43) -> cost revenue dats_REVENUES ANALYSIS_OUTPUT_Meat revenue | H43: E43
A44: OUTPUT | B44: Oyster revenue | C44: With DATs | D44: €/m2 | E44: ='Parcel 1 with DATSs'!G254*'General Information'!$I$41/'Parcel 1 with DATSs'!G20 -> #DIV/0! | F44: Oyster*Product market price | G44: =CONCATENATE("cost revenue dats","_",$A$39,"_",A44,"_",B44) -> cost revenue dats_REVENUES ANALYSIS_OUTPUT_Oyster revenue | H44: E44
A45: OUTPUT | B45: Honey revenue | C45: With DATs | D45: €/beehive | E45: ='Parcel 1 with DATSs'!G255*'General Information'!$I$41/'Parcel 1 with DATSs'!G19 -> #DIV/0! | F45: Honey*Product market price | G45: =CONCATENATE("cost revenue dats","_",$A$39,"_",A45,"_",B45) -> cost revenue dats_REVENUES ANALYSIS_OUTPUT_Honey revenue | H45: E45
A46: OUTPUT | B46: Grain (silos) revenue | C46: With DATs | D46: €/t | E46: ='Parcel 1 with DATSs'!G256*'General Information'!D41 -> 0 | G46: =CONCATENATE("cost revenue dats","_",$A$39,"_",A46,"_",B46) -> cost revenue dats_REVENUES ANALYSIS_OUTPUT_Grain (silos) revenue | H46: E46
A47: ADDITIONAL REVENUES | B47: Additional revenues | C47: With DATs | D47: =IFERROR(VLOOKUP('General Information'!$D$6, Validations!$L$2:$M$8, 2,FALSE), "") -> €/ha | E47: ='Parcel 1 with DATSs'!G225 -> 0 | F47: Additional revenues | G47: =CONCATENATE("cost revenue dats","_",$A$39,"_",A47,"_",B47) -> cost revenue dats_REVENUES ANALYSIS_ADDITIONAL REVENUES_Additional revenues | H47: E47

Sheet Cost-revenue NO DATS
A1: COST ANALYSIS
A2: INPUT | B2: INDICATOR | C2: SCENARIO | D2: UoM | E2: TOTAL | F2: FORMULAS
A3: WATER | B3: Cost of water | C3: Without DATs | D3: =IFERROR(VLOOKUP('General Information'!$D$6, Validations!$L$2:$M$8, 2,FALSE), "") -> €/ha | E3: =('Parcel 1 without DATSs'!H29*'General Information'!I32)/(IF('General Information'!D6="crop",'Parcel 1 without DATSs'!E10,IF('General Information'!D6="milk",'Parcel 1 without DATSs'!H251,IF('General Information'!D6="meat",'Parcel 1 without DATSs'!H252,IF('General Information'!D6="animal",'Parcel 1 without DATSs'!H253,IF('General Information'!D6="oyster",'Parcel 1 without DATSs'!H254,IF('General Information'!D6="honey",'Parcel 1 without DATSs'!H255,'Parcel 1 without DATSs'!H256))))))) -> #VALUE! | F3: IF(Total water used>0; (Total water used * water price)/Parcel dimension; Sum(water Irrigation+ water Fertigation + water Pest dilution + …) * water price) | G3: =CONCATENATE("cost revenue no dats","_",$A$1,"_",A3,"_",B3) -> cost revenue no dats_COST ANALYSIS_WATER _Cost of water | H3: E3
A4: FUEL | B4: Cost of fuel | C4: Without DATs | D4: =IFERROR(VLOOKUP('General Information'!$D$6, Validations!$L$2:$M$8, 2,FALSE), "") -> €/ha | E4: ='Parcel 1 without DATSs'!H43*'General Information'!I33/(IF('General Information'!D6="crop",'Parcel 1 without DATSs'!E10,IF('General Information'!D6="milk",'Parcel 1 without DATSs'!H251,IF('General Information'!D6="meat",'Parcel 1 without DATSs'!H252,IF('General Information'!D6="animal",'Parcel 1 without DATSs'!H253,IF('General Information'!D6="oyster",'Parcel 1 without DATSs'!H254,IF('General Information'!D6="honey",'Parcel 1 without DATSs'!H255,'Parcel 1 without DATSs'!H256))))))) -> #VALUE! | F4: IF(Total fuel used>0; (Total fuel used*fuel price)/Parcel dimension; sum(Fertilisation+Pesticides +Irrigation+Sowing_Planting+Pruning+…) * fuel price) | G4: =CONCATENATE("cost revenue no dats","_",$A$1,"_",A4,"_",B4) -> cost revenue no dats_COST ANALYSIS_FUEL _Cost of fuel | H4: E4
A5: ELECTRICITY | B5: Cost of electricity | C5: Without DATs | D5: =IFERROR(VLOOKUP('General Information'!$D$6, Validations!$L$2:$M$8, 2,FALSE), "") -> €/ha | E5: ='Parcel 1 without DATSs'!H62*'General Information'!I38/(IF('General Information'!D6="crop",'Parcel 1 without DATSs'!E10,IF('General Information'!D6="milk",'Parcel 1 without DATSs'!H251,IF('General Information'!D6="meat",'Parcel 1 without DATSs'!H252,IF('General Information'!D6="animal",'Parcel 1 without DATSs'!H253,IF('General Information'!D6="oyster",'Parcel 1 without DATSs'!H254,IF('General Information'!D6="honey",'Parcel 1 without DATSs'!H255,'Parcel 1 without DATSs'!H256))))))) -> #VALUE! | F5: IF(Total electricity used > 0; (Total electricity used* electricity price)/Parcel dimension; Sum(irrigation,…) *electricity price) | G5: =CONCATENATE("cost revenue no dats","_",$A$1,"_",A5,"_",B5) -> cost revenue no dats_COST ANALYSIS_ELECTRICITY_Cost of electricity | H5: E5
A6: PESTICIDE | B6: Cost for pesticide | C6: Without DATs | D6: =IFERROR(VLOOKUP('General Information'!$D$6, Validations!$L$2:$M$8, 2,FALSE), "") -> €/ha | E6: =('Parcel 1 without DATSs'!H67*'Parcel 1 without DATSs'!H68*'General Information'!I43)+ ('Parcel 1 without DATSs'!H70*'Parcel 1 without DATSs'!H71*'General Information'!I44)+ ('Parcel 1 without DATSs'!H73*'Parcel 1 without DATSs'!H74*'General Information'!I45)+ ('Parcel 1 without DATSs'!H76*'Parcel 1 without DATSs'!H77*'General Information'!I46)+ ('Parcel 1 without DATSs'!H79*'Parcel 1 without DATSs'!H80*'General Information'!I47)+ ('Parcel 1 without DATSs'!H82*'Parcel 1 without DATSs'!H83*'General Information'!I48)+ ('Parcel 1 without DATSs'!H85*'Parcel 1 without DATSs'!H86*'General Information'!I49)+ ('Parcel 1 without DATSs'!H88*'Parcel 1 without DATSs'!H89*'General Information'!I50)+ ('Parcel 1 without DATSs'!H91*'Parcel 1 without DATSs'!H92*'General Information'!I51)+ ('Parcel 1 without DATSs'!H94*'Parcel 1 without DATSs'!H95*'General Information'!I52) -> 0 | F6: [(N. of treatements of pesticide 1*Amount of pesticide 1*pesticide 1 price)+(N. of treatements of pesticide 2 *Amount of pesticide 2 used *pesticide 2 price) + (N. of treatements of pesticide 3 *Amount of pesticide 3 used *pesticide 3 price (€/kg)] | G6: =CONCATENATE("cost revenue no dats","_",$A$1,"_",A6,"_",B6) -> cost revenue no dats_COST ANALYSIS_PESTICIDE _Cost for pesticide | H6: E6
A7: FERTILISER | B7: Cost of fertiliser | C7: Without DATs | D7: =IFERROR(VLOOKUP('General Information'!$D$6, Validations!$L$2:$M$8, 2,FALSE), "") -> €/ha | E7: =('Parcel 1 without DATSs'!H101*'Parcel 1 without DATSs'!H102*'General Information'!I54)+ ('Parcel 1 without DATSs'!H108*'Parcel 1 without DATSs'!H109*'General Information'!I55)+ ('Parcel 1 without DATSs'!H115*'Parcel 1 without DATSs'!H116*'General Information'!I56)+ ('Parcel 1 without DATSs'!H122*'Parcel 1 without DATSs'!H123*'General Information'!I57)+ ('Parcel 1 without DATSs'!H129*'Parcel 1 without DATSs'!H130*'General Information'!I58)+ ('Parcel 1 without DATSs'!H136*'Parcel 1 without DATSs'!H137*'General Information'!I59)+ ('Parcel 1 without DATSs'!H143*'Parcel 1 without DATSs'!H144*'General Information'!I60)+ ('Parcel 1 without DATSs'!H150*'Parcel 1 without DATSs'!H151*'General Information'!I61)+ ('Parcel 1 without DATSs'!H157*'Parcel 1 without DATSs'!H158*'General Information'!I62)+ ('Parcel 1 without DATSs'!H164*'Parcel 1 without DATSs'!H165*'General Information'!I63) -> 1371.47 | F7: ((Amount of fertilisers 1 used *Number of fertilizer 1 applications *Fertilisers 1 price) + (Amount of fertilisers 2 used *Number of fertilizer 2 applications *Fertilisers 2 price) + (Amount of fertilisers 3 used *Number of fertilizer 3 applications *Fertilisers 3 price) | G7: =CONCATENATE("cost revenue no dats","_",$A$1,"_",A7,"_",B7) -> cost revenue no dats_COST ANALYSIS_FERTILISER_Cost of fertiliser | H7: E7
A8: FEED | B8: Cost of feed | C8: Without DATs | D8: =IFERROR(VLOOKUP('General Information'!$D$6, Validations!$L$2:$M$8, 2,FALSE), "") -> €/ha | E8: =('General Information'!I65*'Parcel 1 without DATSs'!H173+'General Information'!I66*'Parcel 1 without DATSs'!H175+'General Information'!I69*'Parcel 1 without DATSs'!H177)/(IF('General Information'!D6="crop",'Parcel 1 without DATSs'!E10,IF('General Information'!D6="milk",'Parcel 1 without DATSs'!H251,IF('General Information'!D6="meat",'Parcel 1 without DATSs'!H252,IF('General Information'!D6="animal",'Parcel 1 without DATSs'!H253,IF('General Information'!D6="oyster",'Parcel 1 without DATSs'!H254,IF('General Information'!D6="honey",'Parcel 1 without DATSs'!H255,'Parcel 1 without DATSs'!H256))))))) -> #VALUE! | F8: (Amount of feed 1 * Feed 1 price) + (Amount of feed 2 * Feed 2 price) + … /animal | G8: =CONCATENATE("cost revenue no dats","_",$A$1,"_",A8,"_",B8) -> cost revenue no dats_COST ANALYSIS_FEED_Cost of feed | H8: E8
A9: DRUGS | B9: Cost of drugs | C9: Without DATs | D9: =IFERROR(VLOOKUP('General Information'!$D$6, Validations!$L$2:$M$8, 2,FALSE), "") -> €/ha | E9: =('General Information'!I71*'Parcel 1 without DATSs'!H186+'General Information'!I72*'Parcel 1 without DATSs'!H188+'General Information'!I73*'Parcel 1 without DATSs'!H190)/(IF('General Information'!D6="crop",'Parcel 1 without DATSs'!E10,IF('General Information'!D6="milk",'Parcel 1 without DATSs'!H251,IF('General Information'!D6="meat",'Parcel 1 without DATSs'!H252,IF('General Information'!D6="animal",'Parcel 1 without DATSs'!H253,IF('General Information'!D6="oyster",'Parcel 1 without DATSs'!H254,IF('General Information'!D6="honey",'Parcel 1 without DATSs'!H255,'Parcel 1 without DATSs'!H256))))))) -> #VALUE! | F9: (Amount of drugs 1 * Feed 1 price) + (Amount of drugs 2 * Feed 2 price) + … /animal or beehives or pieces | G9: =CONCATENATE("cost revenue no dats","_",$A$1,"_",A9,"_",B9) -> cost revenue no dats_COST ANALYSIS_DRUGS _ Cost of drugs | H9: E9
A10: LABOUR | B10: Cost of labour for irrigation | C10: Without DATs | D10: =IFERROR(VLOOKUP('General Information'!$D$6, Validations!$L$2:$M$8, 2,FALSE), "") -> €/ha | E10: ='Parcel 1 without DATSs'!H194*'General Information'!I39/'Parcel 1 without DATSs'!E10 -> #VALUE! | F10: number of hours for irrigation activities*Average salary /Parcel dimension | G10: =CONCATENATE("cost revenue no dats","_",$A$1,"_",A10,"_",B10) -> cost revenue no dats_COST ANALYSIS_LABOUR_Cost of labour for irrigation | H10: E10
A11: LABOUR | B11: Cost of labour for pesticide | C11: Without DATs | D11: =IFERROR(VLOOKUP('General Information'!$D$6, Validations!$L$2:$M$8, 2,FALSE), "") -> €/ha | E11: ='Parcel 1 without DATSs'!H195*'General Information'!I39/'Parcel 1 without DATSs'!E10 -> #VALUE! | F11: number of hours for pesticide activities *Average salary /Parcel dimension | G11: =CONCATENATE("cost revenue no dats","_",$A$1,"_",A11,"_",B11) -> cost revenue no dats_COST ANALYSIS_LABOUR_Cost of labour for pesticide | H11: E11
A12: LABOUR | B12: Cost of labour for fertilisation | C12: Without DATs | D12: =IFERROR(VLOOKUP('General Information'!$D$6, Validations!$L$2:$M$8, 2,FALSE), "") -> €/ha | E12: ='Parcel 1 without DATSs'!H196*'General Information'!I39/'Parcel 1 without DATSs'!E10 -> #VALUE! | F12: number of hours for fertilisation activities * Average salary /Parcel dimension | G12: =CONCATENATE("cost revenue no dats","_",$A$1,"_",A12,"_",B12) -> cost revenue no dats_COST ANALYSIS_LABOUR_Cost of labour for fertilisation | H12: E12
A13: LABOUR | B13: Cost of labour for sowing_planting | C13: Without DATs | D13: =IFERROR(VLOOKUP('General Information'!$D$6, Validations!$L$2:$M$8, 2,FALSE), "") -> €/ha | E13: ='Parcel 1 without DATSs'!H197*'General Information'!I39/'Parcel 1 without DATSs'!E10 -> #VALUE! | F13: number of hours for sowing_planting activities * Average salary /Parcel dimension | G13: =CONCATENATE("cost revenue no dats","_",$A$1,"_",A13,"_",B13) -> cost revenue no dats_COST ANALYSIS_LABOUR_Cost of labour for sowing_planting | H13: E13
A14: LABOUR | B14: Cost of labour for pruning | C14: Without DATs | D14: =IFERROR(VLOOKUP('General Information'!$D$6, Validations!$L$2:$M$8, 2,FALSE), "") -> €/ha | E14: ='Parcel 1 without DATSs'!H198*'General Information'!I39/'Parcel 1 without DATSs'!E10 -> #VALUE! | F14: number of hours for pruning activities *Average salary /Parcel dimension | G14: =CONCATENATE("cost revenue no dats","_",$A$1,"_",A14,"_",B14) -> cost revenue no dats_COST ANALYSIS_LABOUR_Cost of labour for pruning | H14: E14
A15: LABOUR | B15: Cost of labour for field visits | C15: Without DATs | D15: =IFERROR(VLOOKUP('General Information'!$D$6, Validations!$L$2:$M$8, 2,FALSE), "") -> €/ha | E15: ='Parcel 1 without DATSs'!H199*'General Information'!I39/'Parcel 1 without DATSs'!E10 -> #VALUE! | F15: number of hours for field visits activities * Average professional salary /Parcel dimension | G15: =CONCATENATE("cost revenue no dats","_",$A$1,"_",A15,"_",B15) -> cost revenue no dats_COST ANALYSIS_LABOUR_Cost of labour for field visits | H15: E15
A16: LABOUR | B16: Cost of labour for greenhouse management | C16: Without DATs | D16: =IFERROR(VLOOKUP('General Information'!$D$6, Validations!$L$2:$M$8, 2,FALSE), "") -> €/ha | E16: ='Parcel 1 without DATSs'!H200*'General Information'!I39/'Parcel 1 without DATSs'!E10 -> #VALUE! | F16: number of hours for greenhouse management *Average salary /Parcel dimension | G16: =CONCATENATE("cost revenue no dats","_",$A$1,"_",A16,"_",B16) -> cost revenue no dats_COST ANALYSIS_LABOUR_Cost of labour for greenhouse management | H16: E16
A17: LABOUR | B17: Cost of labour for tracking the quantity of grain available in the silo | C17: Without DATs | D17: =IFERROR(VLOOKUP('General Information'!$D$6, Validations!$L$2:$M$8, 2,FALSE), "") -> €/ha | E17: ='Parcel 1 without DATSs'!H201*'General Information'!I39/'Parcel 1 without DATSs'!E10 -> #VALUE! | F17: number of hours for tracking the quantity of grain available in the silo *Average salary | G17: =CONCATENATE("cost revenue no dats","_",$A$1,"_",A17,"_",B17) -> cost revenue no dats_COST ANALYSIS_LABOUR_Cost of labour for tracking the quantity of grain available in the silo | H17: E17
A18: LABOUR | B18: Cost of labour for assessing product quality | C18: Without DATs | D18: =IFERROR(VLOOKUP('General Information'!$D$6, Validations!$L$2:$M$8, 2,FALSE), "") -> €/ha | E18: ='Parcel 1 without DATSs'!H202*'General Information'!I39/(IF('General Information'!D6="crop",'Parcel 1 without DATSs'!E10,IF('General Information'!D6="milk",'Parcel 1 without DATSs'!H251,IF('General Information'!D6="meat",'Parcel 1 without DATSs'!H252,IF('General Information'!D6="animal",'Parcel 1 without DATSs'!H253,IF('General Information'!D6="oyster",'Parcel 1 without DATSs'!H254,IF('General Information'!D6="honey",'Parcel 1 without DATSs'!H255,'Parcel 1 without DATSs'!H256))))))) -> #VALUE! | F18: number of hours for assessing grain quality *Average salary | G18: =CONCATENATE("cost revenue no dats","_",$A$1,"_",A18,"_",B18) -> cost revenue no dats_COST ANALYSIS_LABOUR_Cost of labour for assessing product quality | H18: E18
A19: LABOUR | B19: Cost of labour for controlling purchase and sale prices and quantities | C19: Without DATs | D19: =IFERROR(VLOOKUP('General Information'!$D$6, Validations!$L$2:$M$8, 2,FALSE), "") -> €/ha | E19: ='Parcel 1 without DATSs'!H203*'General Information'!I39/(IF('General Information'!D6="crop",'Parcel 1 without DATSs'!E10,IF('General Information'!D6="milk",'Parcel 1 without DATSs'!H251,IF('General Information'!D6="meat",'Parcel 1 without DATSs'!H252,IF('General Information'!D6="animal",'Parcel 1 without DATSs'!H253,IF('General Information'!D6="oyster",'Parcel 1 without DATSs'!H254,IF('General Information'!D6="honey",'Parcel 1 without DATSs'!H255,'Parcel 1 without DATSs'!H256))))))) -> #VALUE! | F19: number of hours for controlling purchase and sale prices and quantities *Average salary | G19: =CONCATENATE("cost revenue no dats","_",$A$1,"_",A19,"_",B19) -> cost revenue no dats_COST ANALYSIS_LABOUR_Cost of labour for controlling purchase and sale prices and quantities | H19: E19
A20: LABOUR | B20: Cost of labour for organising logistics | C20: Without DATs | D20: =IFERROR(VLOOKUP('General Information'!$D$6, Validations!$L$2:$M$8, 2,FALSE), "") -> €/ha | E20: ='Parcel 1 without DATSs'!H204*'General Information'!I39/(IF('General Information'!D6="crop",'Parcel 1 without DATSs'!E10,IF('General Information'!D6="milk",'Parcel 1 without DATSs'!H251,IF('General Information'!D6="meat",'Parcel 1 without DATSs'!H252,IF('General Information'!D6="animal",'Parcel 1 without DATSs'!H253,IF('General Information'!D6="oyster",'Parcel 1 without DATSs'!H254,IF('General Information'!D6="honey",'Parcel 1 without DATSs'!H255,'Parcel 1 without DATSs'!H256))))))) -> #VALUE! | F20: number of hours for organise logistics *Average salary | G20: =CONCATENATE("cost revenue no dats","_",$A$1,"_",A20,"_",B20) -> cost revenue no dats_COST ANALYSIS_LABOUR_Cost of labour for organising logistics | H20: E20
A21: LABOUR | B21: Cost of labour for cleaning | C21: Without DATs | D21: =IFERROR(VLOOKUP('General Information'!$D$6, Validations!$L$2:$M$8, 2,FALSE), "") -> €/ha | E21: ='Parcel 1 without DATSs'!H205*'General Information'!I39/(IF('General Information'!D6="crop",'Parcel 1 without DATSs'!E10,IF('General Information'!D6="milk",'Parcel 1 without DATSs'!H251,IF('General Information'!D6="meat",'Parcel 1 without DATSs'!H252,IF('General Information'!D6="animal",'Parcel 1 without DATSs'!H253,IF('General Information'!D6="oyster",'Parcel 1 without DATSs'!H254,IF('General Information'!D6="honey",'Parcel 1 without DATSs'!H255,'Parcel 1 without DATSs'!H256))))))) -> #VALUE! | F21: number of hours for cleaning *Average salary /animal | G21: =CONCATENATE("cost revenue no dats","_",$A$1,"_",A21,"_",B21) -> cost revenue no dats_COST ANALYSIS_LABOUR_Cost of labour for cleaning | H21: E21
A22: LABOUR | B22: Cost of labour for stable visits | C22: Without DATs | D22: =IFERROR(VLOOKUP('General Information'!$D$6, Validations!$L$2:$M$8, 2,FALSE), "") -> €/ha | E22: ='Parcel 1 without DATSs'!H206*'General Information'!I39/(IF('General Information'!D6="crop",'Parcel 1 without DATSs'!E10,IF('General Information'!D6="milk",'Parcel 1 without DATSs'!H251,IF('General Information'!D6="meat",'Parcel 1 without DATSs'!H252,IF('General Information'!D6="animal",'Parcel 1 without DATSs'!H253,IF('General Information'!D6="oyster",'Parcel 1 without DATSs'!H254,IF('General Information'!D6="honey",'Parcel 1 without DATSs'!H255,'Parcel 1 without DATSs'!H256))))))) -> #VALUE! | F22: number of hours for stable visits*Average professional salary /animal | G22: =CONCATENATE("cost revenue no dats","_",$A$1,"_",A22,"_",B22) -> cost revenue no dats_COST ANALYSIS_LABOUR_Cost of labour for stable visits | H22: E22
A23: LABOUR | B23: Cost of labour for heat detection | C23: Without DATs | D23: =IFERROR(VLOOKUP('General Information'!$D$6, Validations!$L$2:$M$8, 2,FALSE), "") -> €/ha | E23: ='Parcel 1 without DATSs'!H207*'General Information'!I39/(IF('General Information'!D6="crop",'Parcel 1 without DATSs'!E10,IF('General Information'!D6="milk",'Parcel 1 without DATSs'!H251,IF('General Information'!D6="meat",'Parcel 1 without DATSs'!H252,IF('General Information'!D6="animal",'Parcel 1 without DATSs'!H253,IF('General Information'!D6="oyster",'Parcel 1 without DATSs'!H254,IF('General Information'!D6="honey",'Parcel 1 without DATSs'!H255,'Parcel 1 without DATSs'!H256))))))) -> #VALUE! | F23: number of hours for heat detection *Average salary /animal | G23: =CONCATENATE("cost revenue no dats","_",$A$1,"_",A23,"_",B23) -> cost revenue no dats_COST ANALYSIS_LABOUR_Cost of labour for heat detection | H23: E23
A24: LABOUR | B24: Cost of labour for calving detection | C24: Without DATs | D24: =IFERROR(VLOOKUP('General Information'!$D$6, Validations!$L$2:$M$8, 2,FALSE), "") -> €/ha | E24: ='Parcel 1 without DATSs'!H208*'General Information'!I39/(IF('General Information'!D6="crop",'Parcel 1 without DATSs'!E10,IF('General Information'!D6="milk",'Parcel 1 without DATSs'!H251,IF('General Information'!D6="meat",'Parcel 1 without DATSs'!H252,IF('General Information'!D6="animal",'Parcel 1 without DATSs'!H253,IF('General Information'!D6="oyster",'Parcel 1 without DATSs'!H254,IF('General Information'!D6="honey",'Parcel 1 without DATSs'!H255,'Parcel 1 without DATSs'!H256))))))) -> #VALUE! | F24: number of hours for calving detection *Average salary /animal | G24: =CONCATENATE("cost revenue no dats","_",$A$1,"_",A24,"_",B24) -> cost revenue no dats_COST ANALYSIS_LABOUR_Cost of labour for calving detection | H24: E24
A25: LABOUR | B25: Cost of labour for pigsty management | C25: Without DATs | D25: =IFERROR(VLOOKUP('General Information'!$D$6, Validations!$L$2:$M$8, 2,FALSE), "") -> €/ha | E25: ='Parcel 1 without DATSs'!H209*'General Information'!I39/(IF('General Information'!D6="crop",'Parcel 1 without DATSs'!E10,IF('General Information'!D6="milk",'Parcel 1 without DATSs'!H251,IF('General Information'!D6="meat",'Parcel 1 without DATSs'!H252,IF('General Information'!D6="animal",'Parcel 1 without DATSs'!H253,IF('General Information'!D6="oyster",'Parcel 1 without DATSs'!H254,IF('General Information'!D6="honey",'Parcel 1 without DATSs'!H255,'Parcel 1 without DATSs'!H256))))))) -> #VALUE! | F25: number of hours for pigsty management*Average salary /animal | G25: =CONCATENATE("cost revenue no dats","_",$A$1,"_",A25,"_",B25) -> cost revenue no dats_COST ANALYSIS_LABOUR_Cost of labour for pigsty management | H25: E25
A26: LABOUR | B26: Cost of milking | C26: Without DATs | D26: =IFERROR(VLOOKUP('General Information'!$D$6, Validations!$L$2:$M$8, 2,FALSE), "") -> €/ha | E26: ='Parcel 1 without DATSs'!H210*'General Information'!I39/(IF('General Information'!D6="crop",'Parcel 1 without DATSs'!E10,IF('General Information'!D6="milk",'Parcel 1 without DATSs'!H251,IF('General Information'!D6="meat",'Parcel 1 without DATSs'!H252,IF('General Information'!D6="animal",'Parcel 1 without DATSs'!H253,IF('General Information'!D6="oyster",'Parcel 1 without DATSs'!H254,IF('General Information'!D6="honey",'Parcel 1 without DATSs'!H255,'Parcel 1 without DATSs'!H256))))))) -> #VALUE! | F26: number of hours for milking *Average salary /animal | G26: =CONCATENATE("cost revenue no dats","_",$A$1,"_",A26,"_",B26) -> cost revenue no dats_COST ANALYSIS_LABOUR_Cost of milking | H26: E26
A27: LABOUR | B27: Cost of labour for (milk) quality assessment | C27: Without DATs | D27: =IFERROR(VLOOKUP('General Information'!$D$6, Validations!$L$2:$M$8, 2,FALSE), "") -> €/ha | E27: ='Parcel 1 without DATSs'!H211*'General Information'!I39/(IF('General Information'!D6="crop",'Parcel 1 without DATSs'!E10,IF('General Information'!D6="milk",'Parcel 1 without DATSs'!H251,IF('General Information'!D6="meat",'Parcel 1 without DATSs'!H252,IF('General Information'!D6="animal",'Parcel 1 without DATSs'!H253,IF('General Information'!D6="oyster",'Parcel 1 without DATSs'!H254,IF('General Information'!D6="honey",'Parcel 1 without DATSs'!H255,'Parcel 1 without DATSs'!H256))))))) -> #VALUE! | F27: number of hours for (milk) quality assessment*Average salary /animal | G27: =CONCATENATE("cost revenue no dats","_",$A$1,"_",A27,"_",B27) -> cost revenue no dats_COST ANALYSIS_LABOUR_Cost of labour for (milk) quality assessment | H27: E27
A28: LABOUR | B28: Cost of labour for feeding | C28: Without DATs | D28: =IFERROR(VLOOKUP('General Information'!$D$6, Validations!$L$2:$M$8, 2,FALSE), "") -> €/ha | E28: ='Parcel 1 without DATSs'!H212*'General Information'!I39/(IF('General Information'!D6="crop",'Parcel 1 without DATSs'!E10,IF('General Information'!D6="milk",'Parcel 1 without DATSs'!H251,IF('General Information'!D6="meat",'Parcel 1 without DATSs'!H252,IF('General Information'!D6="animal",'Parcel 1 without DATSs'!H253,IF('General Information'!D6="oyster",'Parcel 1 without DATSs'!H254,IF('General Information'!D6="honey",'Parcel 1 without DATSs'!H255,'Parcel 1 without DATSs'!H256))))))) -> #VALUE! | F28: number of hours for feeding *Average salary /animal | G28: =CONCATENATE("cost revenue no dats","_",$A$1,"_",A28,"_",B28) -> cost revenue no dats_COST ANALYSIS_LABOUR_Cost of labour for feeding | H28: E28
A29: LABOUR | B29: Cost of labour for beehives visits | C29: Without DATs | D29: =IFERROR(VLOOKUP('General Information'!$D$6, Validations!$L$2:$M$8, 2,FALSE), "") -> €/ha | E29: ='Parcel 1 without DATSs'!H213*'General Information'!I39/'Parcel 1 without DATSs'!E19 -> #VALUE! | F29: number of hours for beehives visits *Average salary / beehive | G29: =CONCATENATE("cost revenue no dats","_",$A$1,"_",A29,"_",B29) -> cost revenue no dats_COST ANALYSIS_LABOUR_Cost of labour for beehives visits | H29: E29
A30: LABOUR | B30: Cost of labour for sampling of oysters | C30: Without DATs | D30: =IFERROR(VLOOKUP('General Information'!$D$6, Validations!$L$2:$M$8, 2,FALSE), "") -> €/ha | E30: ='Parcel 1 without DATSs'!H214*'General Information'!I39/'Parcel 1 without DATSs'!H254 -> #DIV/0! | F30: number of hours for sampling of oysters* Average salary /piece | G30: =CONCATENATE("cost revenue no dats","_",$A$1,"_",A30,"_",B30) -> cost revenue no dats_COST ANALYSIS_LABOUR_Cost of labour for sampling of oysters | H30: E30
A31: LABOUR | B31: Cost of labour for transporting oysters to the laboratory | C31: Without DATs | D31: =IFERROR(VLOOKUP('General Information'!$D$6, Validations!$L$2:$M$8, 2,FALSE), "") -> €/ha | E31: ='Parcel 1 without DATSs'!H215*'General Information'!I39/'Parcel 1 without DATSs'!H254 -> #DIV/0! | F31: number of hours for transporting oysters to the laboratory*Average salary /piece | G31: =CONCATENATE("cost revenue no dats","_",$A$1,"_",A31,"_",B31) -> cost revenue no dats_COST ANALYSIS_LABOUR_Cost of labour for transporting oysters to the laboratory | H31: E31
A32: LABOUR | B32: Cost of labour for harvesting | C32: Without DATs | D32: =IFERROR(VLOOKUP('General Information'!$D$6, Validations!$L$2:$M$8, 2,FALSE), "") -> €/ha | E32: ='Parcel 1 without DATSs'!H216*'General Information'!I39/(IF('General Information'!D6="crop",'Parcel 1 without DATSs'!E10,IF('General Information'!D6="milk",'Parcel 1 without DATSs'!H251,IF('General Information'!D6="meat",'Parcel 1 without DATSs'!H252,IF('General Information'!D6="animal",'Parcel 1 without DATSs'!H253,IF('General Information'!D6="oyster",'Parcel 1 without DATSs'!H254,IF('General Information'!D6="honey",'Parcel 1 without DATSs'!H255,'Parcel 1 without DATSs'!H256))))))) -> #VALUE! | F32: number of hours for harvesting oyster*Average salary /piece | G32: =CONCATENATE("cost revenue no dats","_",$A$1,"_",A32,"_",B32) -> cost revenue no dats_COST ANALYSIS_LABOUR_Cost of labour for harvesting | H32: E32
A33: LABOUR | B33: Cost of labour for storage | C33: Without DATs | D33: =IFERROR(VLOOKUP('General Information'!$D$6, Validations!$L$2:$M$8, 2,FALSE), "") -> €/ha | E33: ='Parcel 1 without DATSs'!H217*'General Information'!I39/(IF('General Information'!D6="crop",'Parcel 1 without DATSs'!E10,IF('General Information'!D6="milk",'Parcel 1 without DATSs'!H251,IF('General Information'!D6="meat",'Parcel 1 without DATSs'!H252,IF('General Information'!D6="animal",'Parcel 1 without DATSs'!H253,IF('General Information'!D6="oyster",'Parcel 1 without DATSs'!H254,IF('General Information'!D6="honey",'Parcel 1 without DATSs'!H255,'Parcel 1 without DATSs'!H256))))))) -> #VALUE! | F33: number of hours for storage *Average salary /piece | G33: =CONCATENATE("cost revenue no dats","_",$A$1,"_",A33,"_",B33) -> cost revenue no dats_COST ANALYSIS_LABOUR_Cost of labour for storage | H33: E33
A34: LABOUR | B34: Cost of administrative activities, data collection, etc. | C34: Without DATs | D34: =IFERROR(VLOOKUP('General Information'!$D$6, Validations!$L$2:$M$8, 2,FALSE), "") -> €/ha | E34: ='Parcel 1 without DATSs'!H218*'General Information'!I39/(IF('General Information'!D6="crop",'Parcel 1 without DATSs'!E10,IF('General Information'!D6="milk",'Parcel 1 without DATSs'!H251,IF('General Information'!D6="meat",'Parcel 1 without DATSs'!H252,IF('General Information'!D6="animal",'Parcel 1 without DATSs'!H253,IF('General Information'!D6="oyster",'Parcel 1 without DATSs'!H254,IF('General Information'!D6="honey",'Parcel 1 without DATSs'!H255,'Parcel 1 without DATSs'!H256))))))) -> #VALUE! | F34: number of hours foradministrative activities *Average salary /parcel dimension or animal or beehives or pieces | G34: =CONCATENATE("cost revenue no dats","_",$A$1,"_",A34,"_",B34) -> cost revenue no dats_COST ANALYSIS_LABOUR_Cost of administrative activities, data collection, etc. | H34: E34
A35: COST | B35: TOT Cost | C35: Without DATs | D35: =IFERROR(VLOOKUP('General Information'!$D$6, Validations!$L$2:$M$8, 2,FALSE), "") -> €/ha | E35: =_xlfn.AGGREGATE(9,6,E3:E34) -> 1371.47 | F35: Sum(Cost of labour for irrigation + Cost of labour for fertilisation + … /parcel dimension or animal or beehives or pieces | G35: =CONCATENATE("cost revenue no dats","_",$A$1,"_",A35,"_",B35) -> cost revenue no dats_COST ANALYSIS_COST_TOT Cost | H35: E35
A36: DAT | B36: Cost of DAT | C36: Without DATs | E36: 0 | G36: =CONCATENATE("cost revenue no dats","_",$A$1,"_",A36,"_",B36) -> cost revenue no dats_COST ANALYSIS_DAT_Cost of DAT | H36: E36
A37: DAT | B37: Cost of Training | C37: Without DATs | E37: 0 | G37: =CONCATENATE("cost revenue no dats","_",$A$1,"_",A37,"_",B37) -> cost revenue no dats_COST ANALYSIS_DAT_Cost of Training | H37: E37
A39: REVENUES ANALYSIS
A40: CATEGORY | B40: INDICATOR | C40: SCENARIO | D40: UoM | E40: TOTAL | F40: FORMULAS
A41: OUTPUT | B41: Crop revenue | C41: Without DATs | D41: €/ha | E41: ='Parcel 1 without DATSs'!H250/'Parcel 1 without DATSs'!E10*'General Information'!I41 -> #VALUE! | F41: Yield*Product market price | G41: =CONCATENATE("cost revenue no dats","_",$A$39,"_",A41,"_",B41) -> cost revenue no dats_REVENUES ANALYSIS_OUTPUT_Crop revenue | H41: E41
A42: OUTPUT | B42: Milk revenue | C42: Without DATs | D42: =IFERROR(VLOOKUP('General Information'!$D$6, Validations!$L$2:$M$8, 2,FALSE), "") -> €/ha | E42: =('Parcel 1 without DATSs'!H251*'General Information'!I41/(IF('General Information'!D6="crop",'Parcel 1 without DATSs'!E10,IF('General Information'!D6="milk",'Parcel 1 without DATSs'!H251,IF('General Information'!D6="meat",'Parcel 1 without DATSs'!H252,IF('General Information'!D6="animal",'Parcel 1 without DATSs'!H253,IF('General Information'!D6="oyster",'Parcel 1 without DATSs'!H254,IF('General Information'!D6="honey",'Parcel 1 without DATSs'!H255,'Parcel 1 without DATSs'!H256))))))))*1000 -> #VALUE! | F42: Milk *Product market price | G42: =CONCATENATE("cost revenue no dats","_",$A$39,"_",A42,"_",B42) -> cost revenue no dats_REVENUES ANALYSIS_OUTPUT_Milk revenue | H42: E42
A43: OUTPUT | B43: Meat revenue | C43: Without DATs | D43: =IFERROR(VLOOKUP('General Information'!$D$6, Validations!$L$2:$M$8, 2,FALSE), "") -> €/ha | E43: =('Parcel 1 without DATSs'!H252*'General Information'!I41/(IF('General Information'!D6="crop",'Parcel 1 without DATSs'!E10,IF('General Information'!D6="milk",'Parcel 1 without DATSs'!H251,IF('General Information'!D6="meat",'Parcel 1 without DATSs'!H252,IF('General Information'!D6="animal",'Parcel 1 without DATSs'!H253,IF('General Information'!D6="oyster",'Parcel 1 without DATSs'!H254,IF('General Information'!D6="honey",'Parcel 1 without DATSs'!H255,'Parcel 1 without DATSs'!H256))))))))/10 -> #VALUE! | F43: Meat*Product market price | G43: =CONCATENATE("cost revenue no dats","_",$A$39,"_",A43,"_",B43) -> cost revenue no dats_REVENUES ANALYSIS_OUTPUT_Meat revenue | H43: E43
A44: OUTPUT | B44: Oyster revenue | C44: Without DATs | D44: €/m2 | E44: ='Parcel 1 without DATSs'!H254*'General Information'!I41/'Parcel 1 without DATSs'!E20 -> #VALUE! | F44: Oyster*Product market price | G44: =CONCATENATE("cost revenue no dats","_",$A$39,"_",A44,"_",B44) -> cost revenue no dats_REVENUES ANALYSIS_OUTPUT_Oyster revenue | H44: E44
A45: OUTPUT | B45: Honey revenue | C45: Without DATs | D45: €/beehive | E45: ='Parcel 1 without DATSs'!H255/'Parcel 1 without DATSs'!E19*'General Information'!I41 -> #VALUE! | F45: Honey*Product market price | G45: =CONCATENATE("cost revenue no dats","_",$A$39,"_",A45,"_",B45) -> cost revenue no dats_REVENUES ANALYSIS_OUTPUT_Honey revenue | H45: E45
A46: OUTPUT | B46: Grain (silos) revenue | C46: Without DATs | D46: €/t | E46: ='Parcel 1 without DATSs'!H256*'General Information'!I41 -> 0 | G46: =CONCATENATE("cost revenue no dats","_",$A$39,"_",A46,"_",B46) -> cost revenue no dats_REVENUES ANALYSIS_OUTPUT_Grain (silos) revenue | H46: E46
A47: ADDITIONAL REVENUES | B47: Additional revenues | C47: Without DATs | D47: =IFERROR(VLOOKUP('General Information'!$D$6, Validations!$L$2:$M$8, 2,FALSE), "") -> €/ha | E47: ='Parcel 1 without DATSs'!H225 -> 0 | F47: Additional revenues | G47: =CONCATENATE("cost revenue no dats","_",$A$39,"_",A47,"_",B47) -> cost revenue no dats_REVENUES ANALYSIS_ADDITIONAL REVENUES_Additional revenues | H47: E47

Sheet sust. impact KPIs DATS
A1: Economic - PRODUCTIVITY
B2: INDICATOR | C2: SCENARIO | D2: UoM | E2: TOTAL | F2: FORMULAS
A3: PRODUCTIVITY | B3: Yield | C3: With DATs | D3: t / ha | E3: ='Parcel 1 with DATSs'!G250/'Parcel 1 with DATSs'!G10 -> 71 | F3: total production / parcel area | G3: =CONCATENATE("sust kpis dats","_",A3,"_",B3) -> sust kpis dats_PRODUCTIVITY _Yield | H3: E3
A4: PRODUCTIVITY | B4: Labour productivity (arable and horticulture) | C4: With DATs | D4: t / h | E4: ='Parcel 1 with DATSs'!G250/SUM('Parcel 1 with DATSs'!G194:G218) -> 26.463636 | F4: total production / hours of labour employed | G4: =CONCATENATE("sust kpis dats","_",A4,"_",B4) -> sust kpis dats_PRODUCTIVITY _Labour productivity (arable and horticulture) | H4: E4
A5: PRODUCTIVITY | B5: Labour productivity (dairy livestock) | C5: With DATs | D5: l milk/h | E5: ='Parcel 1 with DATSs'!G251/SUM('Parcel 1 with DATSs'!G194:G218) -> 0 | F5: total production / hours of labour employed | G5: =CONCATENATE("sust kpis dats","_",A5,"_",B5) -> sust kpis dats_PRODUCTIVITY _Labour productivity (dairy livestock) | H5: E5
A6: PRODUCTIVITY | B6: Labour productivity (meat livestock) | C6: With DATs | D6: kg meat/h | E6: ='Parcel 1 with DATSs'!G252/SUM('Parcel 1 with DATSs'!G194:G218) -> 0 | F6: total production / hours of labour employed | G6: =CONCATENATE("sust kpis dats","_",A6,"_",B6) -> sust kpis dats_PRODUCTIVITY _Labour productivity (meat livestock) | H6: E6
A7: PRODUCTIVITY | B7: Labour productivity (aquaculture) | C7: With DATs | D7: pieces/h | E7: ='Parcel 1 with DATSs'!G254/SUM('Parcel 1 with DATSs'!G194:G218) -> 0 | F7: total production / hours of labour employed | G7: =CONCATENATE("sust kpis dats","_",A7,"_",B7) -> sust kpis dats_PRODUCTIVITY _Labour productivity (aquaculture) | H7: E7
A8: PRODUCTIVITY | B8: Labour productivity (apiculture) | C8: With DATs | D8: kg honey/h | E8: ='Parcel 1 with DATSs'!G255/SUM('Parcel 1 with DATSs'!G194:G218) -> 0 | F8: total production / hours of labour employed | G8: =CONCATENATE("sust kpis dats","_",A8,"_",B8) -> sust kpis dats_PRODUCTIVITY _Labour productivity (apiculture) | H8: E8
A9: PRODUCTIVITY | B9: Labour productivity (silos) | C9: With DATs | D9: t/h | E9: ='Parcel 1 with DATSs'!G256/SUM('Parcel 1 with DATSs'!G194:G218) -> 0 | G9: =CONCATENATE("sust kpis dats","_",A9,"_",B9) -> sust kpis dats_PRODUCTIVITY _Labour productivity (silos) | H9: E9
A10: PRODUCTIVITY | B10: Milk productivity | C10: With DATs | D10: l milk/cow/day | E10: ='Parcel 1 with DATSs'!G251/'Parcel 1 with DATSs'!G17/365 -> #DIV/0! | F10: total milk production / total number of cows | G10: =CONCATENATE("sust kpis dats","_",A10,"_",B10) -> sust kpis dats_PRODUCTIVITY _Milk productivity | H10: E10
A11: PRODUCTIVITY | B11: Meat productivity | C11: With DATs | D11: kg meat/animal/day | E11: ='Parcel 1 with DATSs'!G252/'Parcel 1 with DATSs'!G17/365 -> #DIV/0! | F11: total production / animals | G11: =CONCATENATE("sust kpis dats","_",A11,"_",B11) -> sust kpis dats_PRODUCTIVITY _Meat productivity | H11: E11
A12: PRODUCTIVITY | B12: Bees productivity | C12: With DATs | D12: kg honey/beehive | E12: ='Parcel 1 with DATSs'!G255/'Parcel 1 with DATSs'!G19 -> #DIV/0! | F12: total production / beehives | G12: =CONCATENATE("sust kpis dats","_",A12,"_",B12) -> sust kpis dats_PRODUCTIVITY _Bees productivity | H12: E12
A13: PRODUCTIVITY | B13: Oyster productivity | C13: With DATs | D13: number of oysters/m2 | E13: ='Parcel 1 with DATSs'!G254/'Parcel 1 with DATSs'!G20 -> #DIV/0! | F13: production / area used | G13: =CONCATENATE("sust kpis dats","_",A13,"_",B13) -> sust kpis dats_PRODUCTIVITY _Oyster productivity | H13: E13
A15: Economic - EFFICIENCY
B16: INDICATOR | C16: SCENARIO | D16: UoM | E16: TOTAL | F16: FORMULAS
A17: EFFICIENCY | B17: Rate of time for quality analysis | C17: With DATs | D17: % | E17: =('Parcel 1 with DATSs'!G202/SUM('Parcel 1 with DATSs'!G201:G204))*100 -> #DIV/0! | F17: (hours spent for quality analysis / total number of working hours) *100 | G17: =CONCATENATE("sust kpis dats","_",A17,"_",B17) -> sust kpis dats_EFFICIENCY _Rate of time for quality analysis | H17: E17
A18: EFFICIENCY | B18: Rate of on-time fulfilled orders | C18: With DATs | D18: % | E18: =('Parcel 1 with DATSs'!G222/'Parcel 1 with DATSs'!G223)*100 -> #DIV/0! | F18: (number of on-time fulfilled orders / number of orders received) * 100 | G18: =CONCATENATE("sust kpis dats","_",A18,"_",B18) -> sust kpis dats_EFFICIENCY _Rate of on-time fulfilled orders | H18: E18
A19: EFFICIENCY | B19: Number of wrong orders | C19: With DATs | D19: n | E19: ='Parcel 1 with DATSs'!G224 -> 0 | F19: Number of wrong orders | G19: =CONCATENATE("sust kpis dats","_",A19,"_",B19) -> sust kpis dats_EFFICIENCY _Number of wrong orders | H19: E19
A21: PRODUCT QUALITY
A22: INPUT | B22: INDICATOR | C22: SCENARIO | D22: UoM | E22: TOTAL | F22: FORMULAS
A23: PRODUCT QUALITY | B23: Intrinsic product quality | C23: With DATs | G23: =CONCATENATE("sust kpis dats","_",A23,"_",B23) -> sust kpis dats_PRODUCT QUALITY _Intrinsic product quality | H23: E23
A24: PRODUCT QUALITY | B24: Protein % DRY MATTER | C24: With DATs | D24: % | E24: ='Parcel 1 with DATSs'!G226 -> 0 | G24: =CONCATENATE("sust kpis dats","_",A24,"_",B24) -> sust kpis dats_PRODUCT QUALITY _Protein % DRY MATTER | H24: E24
A25: PRODUCT QUALITY | B25: Humidity | C25: With DATs | D25: % | E25: ='Parcel 1 with DATSs'!G227 -> 0 | G25: =CONCATENATE("sust kpis dats","_",A25,"_",B25) -> sust kpis dats_PRODUCT QUALITY _Humidity | H25: E25
A26: PRODUCT QUALITY | B26: Test Weight | C26: With DATs | D26: kg/hl | E26: ='Parcel 1 with DATSs'!G228 -> 0 | G26: =CONCATENATE("sust kpis dats","_",A26,"_",B26) -> sust kpis dats_PRODUCT QUALITY _Test Weight | H26: E26
A28: ENVIRONMENTAL KPIs
A29: INPUT | B29: INDICATOR | C29: SCENARIO | D29: UoM | E29: TOTAL | F29: Formula
A30: FERTILISER | B30: Nitrogen applied | C30: With DATs | D30: kg/ha | E30: =('Parcel 1 with DATSs'!G101*'Parcel 1 with DATSs'!G102*('Parcel 1 with DATSs'!G103/100))+ ('Parcel 1 with DATSs'!G108*'Parcel 1 with DATSs'!G109*('Parcel 1 with DATSs'!G110/100))+ ('Parcel 1 with DATSs'!G115*'Parcel 1 with DATSs'!G116*('Parcel 1 with DATSs'!G117/100))+ ('Parcel 1 with DATSs'!G122*'Parcel 1 with DATSs'!G123*('Parcel 1 with DATSs'!G124/100))+ ('Parcel 1 with DATSs'!G129*'Parcel 1 with DATSs'!G130*('Parcel 1 with DATSs'!G131/100))+ ('Parcel 1 with DATSs'!G136*'Parcel 1 with DATSs'!G137*('Parcel 1 with DATSs'!G138/100))+ ('Parcel 1 with DATSs'!G143*'Parcel 1 with DATSs'!G144*('Parcel 1 with DATSs'!G145/100))+ ('Parcel 1 with DATSs'!G150*'Parcel 1 with DATSs'!G151*('Parcel 1 with DATSs'!G152/100))+ ('Parcel 1 with DATSs'!G157*'Parcel 1 with DATSs'!G158*('Parcel 1 with DATSs'!G159/100))+ ('Parcel 1 with DATSs'!G164*'Parcel 1 with DATSs'!G165*('Parcel 1 with DATSs'!G166/100)) -> 522.412 | F30: Amount of N fertilizer used/total area | G30: =CONCATENATE("sust kpis dats","_",A30,"_",B30) -> sust kpis dats_FERTILISER_Nitrogen applied | H30: E30
A31: FERTILISER | B31: Nitrogen use efficiency | C31: With DATs | D31: % | E31: =((('Parcel 1 with DATSs'!G250*1000/'Parcel 1 with DATSs'!G10)*C100)/(E30)*100) -> 40.772417 | F31: (yield *Average N content (%))/(Amount of N fertilizer applied/ha)*100 | G31: =CONCATENATE("sust kpis dats","_",A31,"_",B31) -> sust kpis dats_FERTILISER_Nitrogen use efficiency | H31: E31
A32: FERTILISER | B32: Phosphorus applied | C32: With DATs | D32: kg/ha | E32: =('Parcel 1 with DATSs'!G101*'Parcel 1 with DATSs'!G102*('Parcel 1 with DATSs'!G104/100))+ ('Parcel 1 with DATSs'!G108*'Parcel 1 with DATSs'!G109*('Parcel 1 with DATSs'!G111/100))+ ('Parcel 1 with DATSs'!G115*'Parcel 1 with DATSs'!G116*('Parcel 1 with DATSs'!G118/100))+ ('Parcel 1 with DATSs'!G122*'Parcel 1 with DATSs'!G123*('Parcel 1 with DATSs'!G125/100))+ ('Parcel 1 with DATSs'!G129*'Parcel 1 with DATSs'!G130*('Parcel 1 with DATSs'!G132/100))+ ('Parcel 1 with DATSs'!G136*'Parcel 1 with DATSs'!G137*('Parcel 1 with DATSs'!G139/100))+ ('Parcel 1 with DATSs'!G143*'Parcel 1 with DATSs'!G144*('Parcel 1 with DATSs'!G146/100))+ ('Parcel 1 with DATSs'!G150*'Parcel 1 with DATSs'!G151*('Parcel 1 with DATSs'!G153/100))+ ('Parcel 1 with DATSs'!G157*'Parcel 1 with DATSs'!G158*('Parcel 1 with DATSs'!G160/100))+ ('Parcel 1 with DATSs'!G164*'Parcel 1 with DATSs'!G165*('Parcel 1 with DATSs'!G167/100)) -> 39.97 | F32: Amount of P fertilizer used/total area | G32: =CONCATENATE("sust kpis dats","_",A32,"_",B32) -> sust kpis dats_FERTILISER_Phosphorus applied | H32: E32
A33: FERTILISER | B33: Phosphorus use efficiency | C33: With DATs | D33: % | E33: =((('Parcel 1 with DATSs'!G250*1000/'Parcel 1 with DATSs'!G10)*C101)/E32*100) -> 213.15987 | F33: (yield*Average P content (%))/(Amount of P fertilizer used/ha)*100 | G33: =CONCATENATE("sust kpis dats","_",A33,"_",B33) -> sust kpis dats_FERTILISER_Phosphorus use efficiency | H33: E33
A34: FERTILISER | B34: Potassium applied | C34: With DATs | D34: % | E34: =('Parcel 1 with DATSs'!G101*'Parcel 1 with DATSs'!G102*('Parcel 1 with DATSs'!G105/100))+ ('Parcel 1 with DATSs'!G108*'Parcel 1 with DATSs'!G109*('Parcel 1 with DATSs'!G112/100))+ ('Parcel 1 with DATSs'!G115*'Parcel 1 with DATSs'!G116*('Parcel 1 with DATSs'!G119/100))+ ('Parcel 1 with DATSs'!G122*'Parcel 1 with DATSs'!G123*('Parcel 1 with DATSs'!G126/100))+ ('Parcel 1 with DATSs'!G129*'Parcel 1 with DATSs'!G130*('Parcel 1 with DATSs'!G133/100))+ ('Parcel 1 with DATSs'!G136*'Parcel 1 with DATSs'!G137*('Parcel 1 with DATSs'!G140/100))+ ('Parcel 1 with DATSs'!G143*'Parcel 1 with DATSs'!G144*('Parcel 1 with DATSs'!G147/100))+ ('Parcel 1 with DATSs'!G150*'Parcel 1 with DATSs'!G151*('Parcel 1 with DATSs'!G154/100))+ ('Parcel 1 with DATSs'!G157*'Parcel 1 with DATSs'!G158*('Parcel 1 with DATSs'!G161/100))+ ('Parcel 1 with DATSs'!G164*'Parcel 1 with DATSs'!G165*('Parcel 1 with DATSs'!G168/100)) -> 198.052 | F34: Amount of K fertilizer used/total area | G34: =CONCATENATE("sust kpis dats","_",A34,"_",B34) -> sust kpis dats_FERTILISER_ Potassium applied | H34: E34
A35: FERTILISER | B35: Potassium use efficiency | C35: With DATs | D35: % | E35: =(((('Parcel 1 with DATSs'!G250*1000)/'Parcel 1 with DATSs'!G10)*'sust. impact KPIs DATS'!C102)/E34*100) -> 143.39668 | F35: (yield*Average K content (%))/(Amount of K fertilizer used/ha)*100 | G35: =CONCATENATE("sust kpis dats","_",A35,"_",B35) -> sust kpis dats_FERTILISER_Potassium use efficiency | H35: E35
A36: PESTICIDE | B36: pesticides, herbicides and fungicides use | C36: With DATs | D36: kg/ha | E36: =('Parcel 1 with DATSs'!G67*'Parcel 1 with DATSs'!G68)+ ('Parcel 1 with DATSs'!G70*'Parcel 1 with DATSs'!G71)+ ('Parcel 1 with DATSs'!G73*'Parcel 1 with DATSs'!G74)+ ('Parcel 1 with DATSs'!G76*'Parcel 1 with DATSs'!G77)+ ('Parcel 1 with DATSs'!G79*'Parcel 1 with DATSs'!G80)+ ('Parcel 1 with DATSs'!G82*'Parcel 1 with DATSs'!G83)+ ('Parcel 1 with DATSs'!G85*'Parcel 1 with DATSs'!G86)+ ('Parcel 1 with DATSs'!G88*'Parcel 1 with DATSs'!G89)+ ('Parcel 1 with DATSs'!G91*'Parcel 1 with DATSs'!G92)+ ('Parcel 1 with DATSs'!G94*'Parcel 1 with DATSs'!G95) -> 0 | F36: Amount of pesticides, herbicides and fungicide used/total area | G36: =CONCATENATE("sust kpis dats","_",A36,"_",B36) -> sust kpis dats_PESTICIDE _pesticides, herbicides and fungicides use | H36: E36
A37: WATER | B37: Water consumption | C37: With DATs | D37: =IFERROR(VLOOKUP('General Information'!$D$6, Validations!$J$2:$K$8, 2,FALSE), "") -> m3/ha | E37: ='Parcel 1 with DATSs'!G29/(IF('General Information'!D6="crop",'Parcel 1 with DATSs'!G10,IF('General Information'!D6="milk",'Parcel 1 with DATSs'!G251,IF('General Information'!D6="meat",'Parcel 1 with DATSs'!G252,IF('General Information'!D6="animal",'Parcel 1 with DATSs'!G253,IF('General Information'!D6="oyster",'Parcel 1 with DATSs'!G254,IF('General Information'!D6="honey",'Parcel 1 with DATSs'!G255,'Parcel 1 with DATSs'!G256))))))) -> 318.53659 | F37: Amount of water used/total area | G37: =CONCATENATE("sust kpis dats","_",A37,"_",B37) -> sust kpis dats_WATER _Water consumption | H37: E37
A38: WATER | B38: Aquaculture water productivity | C38: With DATs | D38: l/pieces | F38: Amount of water used/production | G38: =CONCATENATE("sust kpis dats","_",A38,"_",B38) -> sust kpis dats_WATER _Aquaculture water productivity | H38: E38
A39: WATER | B39: Irrigation water productivity | C39: With DATs | D39: kg/m3 | E39: =(('Parcel 1 with DATSs'!G250)*1000)/(IF(('Parcel 1 with DATSs'!G24+'Parcel 1 with DATSs'!G25)>0,('Parcel 1 with DATSs'!G24+'Parcel 1 with DATSs'!G25),'Parcel 1 with DATSs'!G29)) -> 222.89433 | F39: Yield/Amount of water used for irrigation | G39: =CONCATENATE("sust kpis dats","_",A39,"_",B39) -> sust kpis dats_WATER _Irrigation water productivity | H39: E39
A40: ELECTRICITY | B40: Electricity consumption | C40: With DATs | D40: =IFERROR(VLOOKUP('General Information'!$D$6, Validations!$W$2:$X$8, 2,FALSE), "") -> kWh/ha | E40: ='Parcel 1 with DATSs'!G62/(IF('General Information'!D6="crop",'Parcel 1 with DATSs'!G10,IF('General Information'!D6="milk",'Parcel 1 with DATSs'!G251,IF('General Information'!D6="meat",'Parcel 1 with DATSs'!G252,IF('General Information'!D6="animal",'Parcel 1 with DATSs'!G253,IF('General Information'!D6="oyster",'Parcel 1 with DATSs'!G254,IF('General Information'!D6="honey",'Parcel 1 with DATSs'!G255,'Parcel 1 with DATSs'!G256))))))) -> 17.073171 | F40: Tot. amount of electricity used/tot area or m2 or animal | G40: =CONCATENATE("sust kpis dats","_",A40,"_",B40) -> sust kpis dats_ELECTRICITY_Electricity consumption | H40: E40
A41: ANIMAL | B41: Ease of movement | C41: With DATs | D41: d/y | E41: ='Parcel 1 with DATSs'!G235/'Parcel 1 with DATSs'!G236 -> #DIV/0! | F41: number of days per year with access to pasture and outdoor loafing area | G41: =CONCATENATE("sust kpis dats","_",A41,"_",B41) -> sust kpis dats_ANIMAL _Ease of movement | H41: E41
A42: ANIMAL | B42: Mortality rate (livestock) | C42: With DATs | D42: % | E42: ='Parcel 1 with DATSs'!G232/'Parcel 1 with DATSs'!G17*100 -> #DIV/0! | F42: (Number of deaths in a year/Average herd size) | G42: =CONCATENATE("sust kpis dats","_",A42,"_",B42) -> sust kpis dats_ANIMAL _Mortality rate (livestock) | H42: E42
A43: ANIMAL | B43: Mortality rate (aquaculture) | C43: With DATs | D43: Oysters/m2 | E43: ='Parcel 1 with DATSs'!G232/'Parcel 1 with DATSs'!G20 -> #DIV/0! | F43: (Number of deaths in a year/total animals) | G43: =CONCATENATE("sust kpis dats","_",A43,"_",B43) -> sust kpis dats_ANIMAL _Mortality rate (aquaculture) | H43: E43
A44: ANIMAL | B44: Mortality rate (apiculture) | C44: With DATs | D44: % | E44: ='Parcel 1 with DATSs'!G232/'Parcel 1 with DATSs'!G19*100 -> #DIV/0! | F44: (Number of deaths in a year/total animals) | G44: =CONCATENATE("sust kpis dats","_",A44,"_",B44) -> sust kpis dats_ANIMAL _Mortality rate (apiculture) | H44: E44
A45: ANIMAL | B45: Mortality rate at birth | C45: With DATs | D45: % | E45: ='Parcel 1 with DATSs'!G233/'Parcel 1 with DATSs'!G234 -> #DIV/0! | F45: (Calves died in the first 24 h / Total number of calves born) | G45: =CONCATENATE("sust kpis dats","_",A45,"_",B45) -> sust kpis dats_ANIMAL _Mortality rate at birth | H45: E45
A46: ANIMAL | B46: Cows with high SCC | C46: With DATs | D46: % | E46: ='Parcel 1 with DATSs'!G237/'Parcel 1 with DATSs'!G17 -> #DIV/0! | F46: number of cows producing high SCC milk / Total number of cows * 100 | G46: =CONCATENATE("sust kpis dats","_",A46,"_",B46) -> sust kpis dats_ANIMAL _Cows with high SCC | H46: E46
A47: DRUGS | B47: Drugs use in dairy livestock | C47: With DATs | D47: =IFERROR(VLOOKUP('General Information'!$D$6, Validations!$AA$2:$AB$8, 2,FALSE), "") -> 0 | E47: =('Parcel 1 with DATSs'!G186+'Parcel 1 with DATSs'!G188+'Parcel 1 with DATSs'!G190)/(IF('General Information'!D6="crop",'Parcel 1 with DATSs'!G10,IF('General Information'!D6="milk",'Parcel 1 with DATSs'!G251,IF('General Information'!D6="meat",'Parcel 1 with DATSs'!G252,IF('General Information'!D6="animal",'Parcel 1 with DATSs'!G253,IF('General Information'!D6="oyster",'Parcel 1 with DATSs'!G254,IF('General Information'!D6="honey",'Parcel 1 with DATSs'!G255,'Parcel 1 with DATSs'!G256))))))) -> 0 | F47: Amount of drugs used/ output | G47: =CONCATENATE("sust kpis dats","_",A47,"_",B47) -> sust kpis dats_DRUGS _Drugs use in dairy livestock | H47: E47
A48: DRUGS | B48: Drugs use in meat livestock | C48: With DATs | D48: =IFERROR(VLOOKUP('General Information'!$D$6, Validations!$AA$2:$AB$8, 2,FALSE), "") -> 0 | E48: =('Parcel 1 with DATSs'!G186+'Parcel 1 with DATSs'!G188+'Parcel 1 with DATSs'!G190)/(IF('General Information'!D6="crop",'Parcel 1 with DATSs'!G10,IF('General Information'!D6="milk",'Parcel 1 with DATSs'!G251,IF('General Information'!D6="meat",'Parcel 1 with DATSs'!G252,IF('General Information'!D6="animal",'Parcel 1 with DATSs'!G253,IF('General Information'!D6="oyster",'Parcel 1 with DATSs'!G254,IF('General Information'!D6="honey",'Parcel 1 with DATSs'!G255,'Parcel 1 with DATSs'!G256))))))) -> 0 | F48: Amount of drugs used/ output | G48: =CONCATENATE("sust kpis dats","_",A48,"_",B48) -> sust kpis dats_DRUGS _Drugs use in meat livestock | H48: E48
A49: DRUGS | B49: Drugs use in aquaculture | C49: With DATs | D49: g/m2 | E49: =('Parcel 1 with DATSs'!G187+'Parcel 1 with DATSs'!G189+'Parcel 1 with DATSs'!#REF!)/'Parcel 1 with DATSs'!G20 -> #REF! | F49: Amount of drugs used/ output | G49: =CONCATENATE("sust kpis dats","_",A49,"_",B49) -> sust kpis dats_DRUGS _Drugs use in aquaculture | H49: E49
A50: DRUGS | B50: Drugs use in apiculture | C50: With DATs | D50: g/beehive | E50: =('Parcel 1 with DATSs'!G187+'Parcel 1 with DATSs'!G189+'Parcel 1 with DATSs'!#REF!)/'Parcel 1 with DATSs'!G19 -> #REF! | F50: Amount of drugs used/ output | G50: =CONCATENATE("sust kpis dats","_",A50,"_",B50) -> sust kpis dats_DRUGS _Drugs use in apiculture | H50: E50
A51: FUEL | B51: Fuel GHG emission | C51: With DATs | D51: =IFERROR(VLOOKUP('General Information'!$D$6, Validations!$AA$2:$AC$8, 3,FALSE), "") -> kg CO2 eq/ha | E51: =('Parcel 1 with DATSs'!G43*'sust. impact KPIs DATS'!C96*'sust. impact KPIs DATS'!C97)/(IF('General Information'!D6="crop",'Parcel 1 with DATSs'!G10,IF('General Information'!D6="milk",'Parcel 1 with DATSs'!G251,IF('General Information'!D6="meat",'Parcel 1 with DATSs'!G252,IF('General Information'!D6="animal",'Parcel 1 with DATSs'!G253,IF('General Information'!D6="oyster",'Parcel 1 with DATSs'!G254,IF('General Information'!D6="honey",'Parcel 1 with DATSs'!G255,'Parcel 1 with DATSs'!G256))))))) -> 0 | F51: Tot. amount of fuel used *Lower heating value*Emission factor | G51: =CONCATENATE("sust kpis dats","_",A51,"_",B51) -> sust kpis dats_FUEL _Fuel GHG emission | H51: E51
A52: FUEL | B52: Arable and horticulture fuel consumption | C52: With DATs | D52: l/ha | E52: ='Parcel 1 with DATSs'!G43/'Parcel 1 with DATSs'!G10 -> 0 | F52: Tot. amount of fuel used/tot area | G52: =CONCATENATE("sust kpis dats","_",A52,"_",B52) -> sust kpis dats_FUEL _Arable and horticulture fuel consumption | H52: E52
A53: FUEL | B53: Livestock fuel consumption | C53: With DATs | D53: =IFERROR(VLOOKUP('General Information'!$D$6, Validations!$AA$2:$AD$8, 4,FALSE), "") -> l/ha | E53: ='Parcel 1 with DATSs'!G43/'Parcel 1 with DATSs'!G17 -> #DIV/0! | F53: Tot. amount of fuel used/LSU | G53: =CONCATENATE("sust kpis dats","_",A53,"_",B53) -> sust kpis dats_FUEL _Livestock fuel consumption | H53: E53
A54: FUEL | B54: Aquaculture fuel consumption | C54: With DATs | D54: l/m2 | E54: ='Parcel 1 with DATSs'!G43/'Parcel 1 with DATSs'!G20 -> #DIV/0! | F54: Tot. amount of fuel used/ area under aquaculture | G54: =CONCATENATE("sust kpis dats","_",A54,"_",B54) -> sust kpis dats_FUEL _Aquaculture fuel consumption | H54: E54
A55: FUEL | B55: Apiculture fuel consumption | C55: With DATs | D55: l/beehive | E55: ='Parcel 1 with DATSs'!G43/'Parcel 1 with DATSs'!G19 -> #DIV/0! | F55: Tot. amount of fuel used/Number of beehives | G55: =CONCATENATE("sust kpis dats","_",A55,"_",B55) -> sust kpis dats_FUEL _Apiculture fuel consumption | H55: E55
A56: FERTILISER | B56: indirect leaching/runoff | C56: With DATs | E56: =E30*C89*C91 -> 1.3791677 | F56: Amount of N fertilizer used (kg-N) * fraction of leaching or runoff * emission factor 5 | G56: =CONCATENATE("sust kpis dats","_",A56,"_",B56) -> sust kpis dats_FERTILISER_indirect leaching/runoff | H56: E56
A57: FERTILISER | B57: indirect volatilisation | C57: With DATs | E57: =((((IF('Parcel 1 with DATSs'!G100="Mineral",'Parcel 1 with DATSs'!G101*'Parcel 1 with DATSs'!G102*'Parcel 1 with DATSs'!G103/100,0))+ (IF('Parcel 1 with DATSs'!G107="Mineral",'Parcel 1 with DATSs'!G108*'Parcel 1 with DATSs'!G109*'Parcel 1 with DATSs'!G110/100,0))+ (IF('Parcel 1 with DATSs'!G114="Mineral",'Parcel 1 with DATSs'!G115*'Parcel 1 with DATSs'!G116*'Parcel 1 with DATSs'!G117/100,0))+ (IF('Parcel 1 with DATSs'!G121="Mineral",'Parcel 1 with DATSs'!G122*'Parcel 1 with DATSs'!G123*'Parcel 1 with DATSs'!G124/100,0))+ (IF('Parcel 1 with DATSs'!G128="Mineral",'Parcel 1 with DATSs'!G129*'Parcel 1 with DATSs'!G130*'Parcel 1 with DATSs'!G131/100,0))+ (IF('Parcel 1 with DATSs'!G135="Mineral",'Parcel 1 with DATSs'!G136*'Parcel 1 with DATSs'!G137*'Parcel 1 with DATSs'!G138/100,0))+ (IF('Parcel 1 with DATSs'!G142="Mineral",'Parcel 1 with DATSs'!G143*'Parcel 1 with DATSs'!G144*'Parcel 1 with DATSs'!G145/100,0))+ (IF('Parcel 1 with DATSs'!G149="Mineral",'Parcel 1 with DATSs'!G150*'Parcel 1 with DATSs'!G151*'Parcel 1 with DATSs'!G152/100,0))+ (IF('Parcel 1 with DATSs'!G156="Mineral",'Parcel 1 with DATSs'!G157*'Parcel 1 with DATSs'!G158*'Parcel 1 with DATSs'!G159/100,0))+ (IF('Parcel 1 with DATSs'!G163="Mineral",'Parcel 1 with DATSs'!G164*'Parcel 1 with DATSs'!G165*'Parcel 1 with DATSs'!G166/100,0))) *'sust. impact KPIs DATS'!C87) + (((IF('Parcel 1 with DATSs'!G100="Organic",'Parcel 1 with DATSs'!G101*'Parcel 1 with DATSs'!G102*'Parcel 1 with DATSs'!G103/100,0))+ (IF('Parcel 1 with DATSs'!G107="Organic",'Parcel 1 with DATSs'!G108*'Parcel 1 with DATSs'!G109*'Parcel 1 with DATSs'!G110/100,0))+ (IF('Parcel 1 with DATSs'!G114="Organic",'Parcel 1 with DATSs'!G115*'Parcel 1 with DATSs'!G116*'Parcel 1 with DATSs'!G117/100,0))+ (IF('Parcel 1 with DATSs'!G121="Organic",'Parcel 1 with DATSs'!G122*'Parcel 1 with DATSs'!G123*'Parcel 1 with DATSs'!G124/100,0))+ (IF('Parcel 1 with DATSs'!G128="Organic",'Parcel 1 with DATSs'!G129*'Parcel 1 with DATSs'!G130*'Parcel 1 with DATSs'!G131/100,0))+ (IF('Parcel 1 with DATSs'!G135="Organic",'Parcel 1 with DATSs'!G136*'Parcel 1 with DATSs'!G137*'Parcel 1 with DATSs'!G138/100,0))+ (IF('Parcel 1 with DATSs'!G142="Organic",'Parcel 1 with DATSs'!G143*'Parcel 1 with DATSs'!G144*'Parcel 1 with DATSs'!G145/100,0))+ (IF('Parcel 1 with DATSs'!G149="Organic",'Parcel 1 with DATSs'!G150*'Parcel 1 with DATSs'!G151*'Parcel 1 with DATSs'!G152/100,0))+ (IF('Parcel 1 with DATSs'!G156="Organic",'Parcel 1 with DATSs'!G157*'Parcel 1 with DATSs'!G158*'Parcel 1 with DATSs'!G159/100,0))+ (IF('Parcel 1 with DATSs'!G163="Organic",'Parcel 1 with DATSs'!G164*'Parcel 1 with DATSs'!G165*'Parcel 1 with DATSs'!G166/100,0))) *'sust. impact KPIs DATS'!C88)) *'sust. impact KPIs DATS'!C84 -> 0.5746532 | F57: [(Amount of synthetic N fertilizer used (kg-N) * fraction volatilized) + (Amount of organic N fertilizer used (kg-N) *fraction volatilized)] * Emission factor 4 | G57: =CONCATENATE("sust kpis dats","_",A57,"_",B57) -> sust kpis dats_FERTILISER_indirect volatilisation | H57: E57
A58: FERTILISER | B58: direct | C58: With DATs | E58: =E30*C79 -> 5.22412 | F58: Amount of N fertilizer used (kg-N) * Emission factor 1 | G58: =CONCATENATE("sust kpis dats","_",A58,"_",B58) -> sust kpis dats_FERTILISER_direct | H58: E58
A59: FERTILISER | B59: N2O GHG emission | C59: With DATs | D59: kg Co2e/ha | E59: =(E58+E57+E56)*C92*C93 -> 3079.3366 | F59: direct + indirect N2O emissions | G59: =CONCATENATE("sust kpis dats","_",A59,"_",B59) -> sust kpis dats_FERTILISER_N2O GHG emission | H59: E59
A60: GHG | B60: total ghg emissions | C60: With DATs | D60: =D51 -> kg CO2 eq/ha | E60: =E59+E51 -> 3079.3366 | F60: total ghg emissions | G60: =CONCATENATE("sust kpis dats","_",A60,"_",B60) -> sust kpis dats_GHG_total ghg emissions | H60: E60 | I60: =IF(ISERR((((('Parcel 1 with DATSs'!G101*'Parcel 1 with DATSs'!G102*100/'Parcel 1 with DATSs'!G103)+('Parcel 1 with DATSs'!G108*'Parcel 1 with DATSs'!G109*100/'Parcel 1 with DATSs'!G110))*'sust. impact KPIs DATS'!C87)+(('Parcel 1 with DATSs'!G115*'Parcel 1 with DATSs'!G116*100/'Parcel 1 with DATSs'!G117)*'sust. impact KPIs DATS'!C88))*C84),0,(((('Parcel 1 with DATSs'!G101*'Parcel 1 with DATSs'!G102*100/'Parcel 1 with DATSs'!G103)+('Parcel 1 with DATSs'!G108*'Parcel 1 with DATSs'!G109*100/'Parcel 1 with DATSs'!G110))*'sust. impact KPIs DATS'!C87)+(('Parcel 1 with DATSs'!G115*'Parcel 1 with DATSs'!G116*100/'Parcel 1 with DATSs'!G117)*'sust. impact KPIs DATS'!C88))*C84) -> 0
A61: SOCIAL KPIs
B62: INDICATOR | C62: SCENARIO | D62: UoM | E62: TOTAL | F62: Formula
A63: SOCIAL KPIs | B63: Training hours (for the use of DATs) | C63: With DATs | D63: h/employee | E63: ='General Information'!D25/'General Information'!D14 -> #DIV/0! | F63: Time spent for training hours for all the employee/number of employees | G63: =CONCATENATE("sust kpis dats","_",A63,"_",B63) -> sust kpis dats_SOCIAL KPIs_Training hours (for the use of DATs) | H63: E63
A64: SOCIAL KPIs | B64: Working time | C64: With DATs | D64: =IFERROR(VLOOKUP('General Information'!$D$6, Validations!$L$2:$N$8, 3,FALSE), "") -> h/ha | E64: {=(SUM(SUMIFS('Parcel 1 with DATSs'!G194:G218,'Parcel 1 with DATSs'!C194:C218,'Analysis DATS vs. NO DATS'!C12:C36,'Analysis DATS vs. NO DATS'!J12:J36,1)))/(IF('General Information'!D6="crop",'Parcel 1 with DATSs'!G10,IF('General Information'!D6="milk",'Parcel 1 with DATSs'!G251,IF('General Information'!D6="meat",'Parcel 1 with DATSs'!G252,IF('General Information'!D6="animal",'Parcel 1 with DATSs'!G253,IF('General Information'!D6="oyster",'Parcel 1 with DATSs'!G254,IF('General Information'!D6="honey",'Parcel 1 with DATSs'!G255,'Parcel 1 with DATSs'!G256)))))))} -> 2.6829268 | F64: Hours worked for the specific activities impacted by DATSs | G64: =CONCATENATE("sust kpis dats","_",A64,"_",B64) -> sust kpis dats_SOCIAL KPIs_Working time | H64: E64
A65: SOCIAL KPIs | B65: Frequency rate of occupational injuries | C65: With DATs | D65: n./hours | E65: ='Parcel 1 with DATSs'!G241/'Parcel 1 with DATSs'!G243 -> #DIV/0! | F65: Number of new injury cases/Total number of working hours | G65: =CONCATENATE("sust kpis dats","_",A65,"_",B65) -> sust kpis dats_SOCIAL KPIs_Frequency rate of occupational injuries | H65: E65
A66: SOCIAL KPIs | B66: Incidence of occupational injuries | C66: With DATs | D66: % | E66: ='Parcel 1 with DATSs'!G242/'Parcel 1 with DATSs'!G243 -> #DIV/0! | F66: Total number of lost working hours due to occupational injuries/Total number of working hours | G66: =CONCATENATE("sust kpis dats","_",A66,"_",B66) -> sust kpis dats_SOCIAL KPIs_Incidence of occupational injuries | H66: E66
A67: SOCIAL KPIs | B67: Contribution to local employment | C67: With DATs | D67: % | E67: ='Parcel 1 with DATSs'!G245/'Parcel 1 with DATSs'!G246 -> #DIV/0! | F67: Number of new local employees/Total new employees hired | G67: =CONCATENATE("sust kpis dats","_",A67,"_",B67) -> sust kpis dats_SOCIAL KPIs_Contribution to local employment | H67: E67
E69: {=SUM(SUMIFS('Parcel 1 with DATSs'!G194:G218,'Parcel 1 with DATSs'!C194:C218,'Analysis DATS vs. NO DATS'!C12:C36,'Analysis DATS vs. NO DATS'!J12:J36,1))} -> 11
B76: IPCC 2006 methodology (2019 refinement) - Tier 1 | D76: (Fixed values)
A77: N2O EMISSIONS | B77: UoM | C77: value | D77: description
A78: direct emissions
A79: EF1 | B79: (Kg N2O-N)/(kg N input) | C79: 0.01 | D79: Emission Factor default value for direct emissions
A80: EF1 SW | B80: (Kg N2O-N)/(kg N input) | C80: 0.016 | D80: Emission Factor for Synthetic fertilizers in Wet climates (optional)
A81: EF1 OW | B81: (Kg N2O-N)/(kg N input) | C81: 0.006 | D81: Other N inputs in Wet climates (optional)
A82: EF1 AD | B82: (Kg N2O-N)/(kg N input) | C82: 0.006 | D82: All N inputs in Dry climates (optional)
A83: indirect emissions
A84: EF4 | B84: (Kg N2O-N)/(kg N volatilised) | C84: 0.01 | D84: Emission Factor default value for volatilization of N
A85: EF4 W | B85: (Kg N2O-N)/(kg N volatilised) | C85: 0.014 | D85: Emission Factor default value for volatilization of N in wet cliamtes
A86: EF4 D | B86: (Kg N2O-N)/(kg N volatilised) | C86: 0.005 | D86: Emission Factor default value for volatilization of N in dry climates
A87: Frac GASF | B87: (kg N volatilised)/(Kg of N input) | C87: 0.11 | D87: Fraction of synthetic fertiliser N that volatilises
A88: Frac GASM | B88: (kg N volatilised)/(Kg of N input) | C88: 0.21 | D88: Fraction of organic fertiliser N that volatilies
A89: FracLEACH | B89: (kg Nleaching&runoff)/(Kg N input) | C89: 0.24 | D89: For all N inputs
A90: FracLEACH D | B90: (kg Nleaching&runoff)/(Kg N input) | C90: 0 | D90: 0 if leaching & runoff process assumed to be absent or in dry climates
A91: EF5 | B91: (kg N2O–N)/(kg N leached and runoff) | C91: 0.011 | D91: Emission factor for N2O emissions from N leaching and runoff
A92: CF1 | B92: Kg/kg | C92: =44/28 -> 1.5714286 | D92: Coversion factor from N to N2O
A93: GWP-N2O | C93: 273 | D93: Global Warming Potential of N2O compared to CO2 (IPCC AR6)
A95: CO2 EMISSIONS FUEL
A96: Lower Heating Value Diesel | B96: Mj/l | C96: 35.9 | D96: Castoldi & Bechini, 2006
A97: EF diesel agri | B97: kg Co2e/Mj | C97: 0.0741 | D97: IPCC 2006
A99: Average nutrient content kg/kg
A100: ='General Information'!D7 -> Onion | B100: Average N content | C100: =IFERROR(VLOOKUP('General Information'!$D$7, Validations!$P$2:$Q$18, 2,FALSE), "") -> 0.003
A101: ='General Information'!D7 -> Onion | B101: Average P content | C101: =IFERROR(VLOOKUP('General Information'!$D$7, Validations!$R$2:$S$18, 2,FALSE), "") -> 0.0012
A102: ='General Information'!D7 -> Onion | B102: Average K content | C102: =IFERROR(VLOOKUP('General Information'!$D$7, Validations!$T$2:$U$18, 2,FALSE), "") -> 0.004

Sheet sust. impact KPIs NO DATS
A1: PRODUCTIVITY
A2: INPUT | B2: INDICATOR | C2: SCENARIO | D2: UoM | E2: TOTAL | F2: FORMULAS
A3: PRODUCTIVITY | B3: Land Productivity | C3: Without DATs | D3: t/ha | E3: ='Parcel 1 without DATSs'!H250/'Parcel 1 without DATSs'!E10 -> #VALUE! | F3: total production / parcel area | G3: =CONCATENATE("sust kpis no dats","_",A3,"_",B3) -> sust kpis no dats_PRODUCTIVITY _Land Productivity | H3: E3
A4: PRODUCTIVITY | B4: Labour productivity (arable and horticulture) | C4: Without DATs | D4: t/h | E4: ='Parcel 1 without DATSs'!H250/SUM('Parcel 1 without DATSs'!H194:H218) -> 21.32 | F4: total production / hours of labour employed | G4: =CONCATENATE("sust kpis no dats","_",A4,"_",B4) -> sust kpis no dats_PRODUCTIVITY _Labour productivity (arable and horticulture) | H4: E4
A5: PRODUCTIVITY | B5: Labour productivity (dairy livestock) | C5: Without DATs | D5: l/h | E5: ='Parcel 1 without DATSs'!H251/SUM('Parcel 1 without DATSs'!H194:H218) -> 0 | F5: total production / hours of labour employed | G5: =CONCATENATE("sust kpis no dats","_",A5,"_",B5) -> sust kpis no dats_PRODUCTIVITY _Labour productivity (dairy livestock) | H5: E5
A6: PRODUCTIVITY | B6: Labour productivity (meat livestock) | C6: Without DATs | D6: kg/h | E6: ='Parcel 1 without DATSs'!H252/SUM('Parcel 1 without DATSs'!H194:H218) -> 0 | F6: total production / hours of labour employed | G6: =CONCATENATE("sust kpis no dats","_",A6,"_",B6) -> sust kpis no dats_PRODUCTIVITY _Labour productivity (meat livestock) | H6: E6
A7: PRODUCTIVITY | B7: Labour productivity (aquaculture) | C7: Without DATs | D7: pieces/h | E7: ='Parcel 1 without DATSs'!H254/SUM('Parcel 1 without DATSs'!H194:H218) -> 0 | F7: total production / hours of labour employed | G7: =CONCATENATE("sust kpis no dats","_",A7,"_",B7) -> sust kpis no dats_PRODUCTIVITY _Labour productivity (aquaculture) | H7: E7
A8: PRODUCTIVITY | B8: Labour productivity (apiculture) | C8: Without DATs | D8: kg/h | E8: ='Parcel 1 without DATSs'!H255/SUM('Parcel 1 without DATSs'!H194:H218) -> 0 | F8: total production / hours of labour employed | G8: =CONCATENATE("sust kpis no dats","_",A8,"_",B8) -> sust kpis no dats_PRODUCTIVITY _Labour productivity (apiculture) | H8: E8
A9: PRODUCTIVITY | B9: Labour productivity (silos) | C9: Without DATs | D9: t/h | E9: ='Parcel 1 without DATSs'!H256/SUM('Parcel 1 without DATSs'!H194:H218) -> 0 | G9: =CONCATENATE("sust kpis no dats","_",A9,"_",B9) -> sust kpis no dats_PRODUCTIVITY _Labour productivity (silos) | H9: E9
A10: PRODUCTIVITY | B10: Milk productivity | C10: Without DATs | D10: l milk/cow/day | E10: ='Parcel 1 without DATSs'!H251/'Parcel 1 without DATSs'!E17/365 -> #VALUE! | F10: total milk production / total number of cows | G10: =CONCATENATE("sust kpis no dats","_",A10,"_",B10) -> sust kpis no dats_PRODUCTIVITY _Milk productivity | H10: E10
A11: PRODUCTIVITY | B11: Meat productivity | C11: Without DATs | D11: kg / animals / day | E11: ='Parcel 1 without DATSs'!H252/'Parcel 1 without DATSs'!E17/365 -> #VALUE! | F11: total production / animals | G11: =CONCATENATE("sust kpis no dats","_",A11,"_",B11) -> sust kpis no dats_PRODUCTIVITY _Meat productivity | H11: E11
A12: PRODUCTIVITY | B12: Bees productivity | C12: Without DATs | D12: kg / beehives | E12: ='Parcel 1 without DATSs'!H255/'Parcel 1 without DATSs'!E19 -> #VALUE! | F12: total production / beehives | G12: =CONCATENATE("sust kpis no dats","_",A12,"_",B12) -> sust kpis no dats_PRODUCTIVITY _Bees productivity | H12: E12
A13: PRODUCTIVITY | B13: Oyster productivity | C13: Without DATs | D13: number of oysters/m2 | E13: ='Parcel 1 without DATSs'!H254/'Parcel 1 without DATSs'!E20 -> #VALUE! | F13: production / area used | G13: =CONCATENATE("sust kpis no dats","_",A13,"_",B13) -> sust kpis no dats_PRODUCTIVITY _Oyster productivity | H13: E13
A15: EFFICIENCY
A16: INPUT | B16: INDICATOR | C16: SCENARIO | D16: UoM | E16: TOTAL | F16: FORMULAS
A17: EFFICIENCY | B17: Rate of time for quality analysis | C17: Without DATs | D17: % | E17: =('Parcel 1 without DATSs'!H202/SUM('Parcel 1 without DATSs'!H201:H204))*100 -> #DIV/0! | F17: (hours assessing grain quality / total number of working hours) *100 | G17: =CONCATENATE("sust kpis no dats","_",A17,"_",B17) -> sust kpis no dats_EFFICIENCY _Rate of time for quality analysis | H17: E17
A18: EFFICIENCY | B18: Rate of on-time fulfilled orders | C18: Without DATs | D18: % | E18: =('Parcel 1 without DATSs'!H222/'Parcel 1 without DATSs'!H223)*100 -> #DIV/0! | F18: (number of on-time fulfilled orders / number of orders received) * 100 | G18: =CONCATENATE("sust kpis no dats","_",A18,"_",B18) -> sust kpis no dats_EFFICIENCY _Rate of on-time fulfilled orders | H18: E18
A19: EFFICIENCY | B19: Number of wrong orders | C19: Without DATs | D19: n | E19: ='Parcel 1 without DATSs'!H224 -> 0 | F19: Number of wrong orders | G19: =CONCATENATE("sust kpis no dats","_",A19,"_",B19) -> sust kpis no dats_EFFICIENCY _Number of wrong orders | H19: E19
A21: PRODUCT QUALITY
A22: INPUT | B22: INDICATOR | C22: SCENARIO | D22: UoM | E22: TOTAL | F22: FORMULAS
A23: PRODUCT QUALITY | B23: Intrinsic product quality | C23: Without DATs | G23: =CONCATENATE("sust kpis no dats","_",A23,"_",B23) -> sust kpis no dats_PRODUCT QUALITY _Intrinsic product quality | H23: E23
A24: PRODUCT QUALITY | B24: Protein % DRY MATTER | C24: Without DATs | D24: % | E24: ='Parcel 1 without DATSs'!H226 -> 0 | G24: =CONCATENATE("sust kpis no dats","_",A24,"_",B24) -> sust kpis no dats_PRODUCT QUALITY _Protein % DRY MATTER | H24: E24
A25: PRODUCT QUALITY | B25: Humidity | C25: Without DATs | D25: % | E25: ='Parcel 1 without DATSs'!H227 -> 0 | G25: =CONCATENATE("sust kpis no dats","_",A25,"_",B25) -> sust kpis no dats_PRODUCT QUALITY _Humidity | H25: E25
A26: PRODUCT QUALITY | B26: Test Weight | C26: Without DATs | D26: kg/hl | E26: ='Parcel 1 without DATSs'!H228 -> 0 | G26: =CONCATENATE("sust kpis no dats","_",A26,"_",B26) -> sust kpis no dats_PRODUCT QUALITY _Test Weight | H26: E26
A28: ENVIRONMENTAL ANALYSIS
A29: INPUT | B29: INDICATOR | C29: SCENARIO | D29: UoM | E29: TOTAL | F29: Formula
A30: FERTILISER | B30: Nitrogen applied | C30: Without DATs | D30: kg/ha | E30: =('Parcel 1 without DATSs'!H101*'Parcel 1 without DATSs'!H102*('Parcel 1 without DATSs'!H103/100))+ ('Parcel 1 without DATSs'!H108*'Parcel 1 without DATSs'!H109*('Parcel 1 without DATSs'!H110/100))+ ('Parcel 1 without DATSs'!H115*'Parcel 1 without DATSs'!H116*('Parcel 1 without DATSs'!H117/100))+ ('Parcel 1 without DATSs'!H122*'Parcel 1 without DATSs'!H123*('Parcel 1 without DATSs'!H124/100))+ ('Parcel 1 without DATSs'!H129*'Parcel 1 without DATSs'!H130*('Parcel 1 without DATSs'!H131/100))+ ('Parcel 1 without DATSs'!H136*'Parcel 1 without DATSs'!H137*('Parcel 1 without DATSs'!H138/100))+ ('Parcel 1 without DATSs'!H143*'Parcel 1 without DATSs'!H144*('Parcel 1 without DATSs'!H145/100))+ ('Parcel 1 without DATSs'!H150*'Parcel 1 without DATSs'!H151*('Parcel 1 without DATSs'!H152/100))+ ('Parcel 1 without DATSs'!H157*'Parcel 1 without DATSs'!H158*('Parcel 1 without DATSs'!H159/100))+ ('Parcel 1 without DATSs'!H164*'Parcel 1 without DATSs'!H165*('Parcel 1 without DATSs'!H166/100)) -> 522.412 | F30: Amount of N fertilizer used/total area | G30: =CONCATENATE("sust kpis no dats","_",A30,"_",B30) -> sust kpis no dats_FERTILISER_Nitrogen applied | H30: E30
A31: FERTILISER | B31: Nitrogen use efficiency | C31: Without DATs | D31: % | E31: =(('Parcel 1 without DATSs'!H250*1000/'Parcel 1 without DATSs'!E10)*'sust. impact KPIs NO DATS'!C100)/E30*100 -> #VALUE! | F31: (yield *Average N content (%))/(Amount of N fertilizer used /total area)*100 | G31: =CONCATENATE("sust kpis no dats","_",A31,"_",B31) -> sust kpis no dats_FERTILISER_Nitrogen use efficiency | H31: E31
A32: FERTILISER | B32: Phosphorus applied | C32: Without DATs | D32: kg/ha | E32: =('Parcel 1 without DATSs'!H101*'Parcel 1 without DATSs'!H102*('Parcel 1 without DATSs'!H104/100))+ ('Parcel 1 without DATSs'!H108*'Parcel 1 without DATSs'!H109*('Parcel 1 without DATSs'!H111/100))+ ('Parcel 1 without DATSs'!H115*'Parcel 1 without DATSs'!H116*('Parcel 1 without DATSs'!H118/100))+ ('Parcel 1 without DATSs'!H122*'Parcel 1 without DATSs'!H123*('Parcel 1 without DATSs'!H125/100))+ ('Parcel 1 without DATSs'!H129*'Parcel 1 without DATSs'!H130*('Parcel 1 without DATSs'!H132/100))+ ('Parcel 1 without DATSs'!H136*'Parcel 1 without DATSs'!H137*('Parcel 1 without DATSs'!H139/100))+ ('Parcel 1 without DATSs'!H143*'Parcel 1 without DATSs'!H144*('Parcel 1 without DATSs'!H146/100))+ ('Parcel 1 without DATSs'!H150*'Parcel 1 without DATSs'!H151*('Parcel 1 without DATSs'!H153/100))+ ('Parcel 1 without DATSs'!H157*'Parcel 1 without DATSs'!H158*('Parcel 1 without DATSs'!H160/100))+ ('Parcel 1 without DATSs'!H164*'Parcel 1 without DATSs'!H165*('Parcel 1 without DATSs'!H167/100)) -> 39.97 | F32: Amount of P fertilizer used/total area | G32: =CONCATENATE("sust kpis no dats","_",A32,"_",B32) -> sust kpis no dats_FERTILISER_Phosphorus applied | H32: E32
A33: FERTILISER | B33: Phosphorus use efficiency | C33: Without DATs | D33: % | E33: =(('Parcel 1 without DATSs'!H250*1000/'Parcel 1 without DATSs'!E10)*'sust. impact KPIs NO DATS'!C101)/E32*100 -> #VALUE! | F33: (yield*Average P content (%))/(Amount of P fertilizer used/total area)*100 | G33: =CONCATENATE("sust kpis no dats","_",A33,"_",B33) -> sust kpis no dats_FERTILISER_Phosphorus use efficiency | H33: E33
A34: FERTILISER | B34: Potassium applied | C34: Without DATs | D34: kg/ha | E34: =('Parcel 1 without DATSs'!H101*'Parcel 1 without DATSs'!H102*('Parcel 1 without DATSs'!H105/100))+ ('Parcel 1 without DATSs'!H108*'Parcel 1 without DATSs'!H109*('Parcel 1 without DATSs'!H112/100))+ ('Parcel 1 without DATSs'!H115*'Parcel 1 without DATSs'!H116*('Parcel 1 without DATSs'!H119/100))+ ('Parcel 1 without DATSs'!H122*'Parcel 1 without DATSs'!H123*('Parcel 1 without DATSs'!H126/100))+ ('Parcel 1 without DATSs'!H129*'Parcel 1 without DATSs'!H130*('Parcel 1 without DATSs'!H133/100))+ ('Parcel 1 without DATSs'!H136*'Parcel 1 without DATSs'!H137*('Parcel 1 without DATSs'!H140/100))+ ('Parcel 1 without DATSs'!H143*'Parcel 1 without DATSs'!H144*('Parcel 1 without DATSs'!H147/100))+ ('Parcel 1 without DATSs'!H150*'Parcel 1 without DATSs'!H151*('Parcel 1 without DATSs'!H154/100))+ ('Parcel 1 without DATSs'!H157*'Parcel 1 without DATSs'!H158*('Parcel 1 without DATSs'!H161/100))+ ('Parcel 1 without DATSs'!H164*'Parcel 1 without DATSs'!H165*('Parcel 1 without DATSs'!H168/100)) -> 198.052 | F34: Amount of K fertilizer used/total area | G34: =CONCATENATE("sust kpis no dats","_",A34,"_",B34) -> sust kpis no dats_FERTILISER_Potassium applied | H34: E34
A35: FERTILISER | B35: Potassium use efficiency | C35: Without DATs | D35: % | E35: =(('Parcel 1 without DATSs'!H250*1000/'Parcel 1 without DATSs'!E10)*'sust. impact KPIs NO DATS'!C102)/E34*100 -> #VALUE! | F35: (yield*Average K content (%))/(Amount of K fertilizer used/total area)*100 | G35: =CONCATENATE("sust kpis no dats","_",A35,"_",B35) -> sust kpis no dats_FERTILISER_Potassium use efficiency | H35: E35
A36: PESTICIDE | B36: Pesticides, herbicides and fungicides use | C36: Without DATs | D36: kg/ha | E36: =('Parcel 1 without DATSs'!H67*'Parcel 1 without DATSs'!H68)+ ('Parcel 1 without DATSs'!H70*'Parcel 1 without DATSs'!H71)+ ('Parcel 1 without DATSs'!H73*'Parcel 1 without DATSs'!H74)+ ('Parcel 1 without DATSs'!H76*'Parcel 1 without DATSs'!H77)+ ('Parcel 1 without DATSs'!H79*'Parcel 1 without DATSs'!H80)+ ('Parcel 1 without DATSs'!H82*'Parcel 1 without DATSs'!H83)+ ('Parcel 1 without DATSs'!H85*'Parcel 1 without DATSs'!H86)+ ('Parcel 1 without DATSs'!H88*'Parcel 1 without DATSs'!H89)+ ('Parcel 1 without DATSs'!H91*'Parcel 1 without DATSs'!H92)+ ('Parcel 1 without DATSs'!H94*'Parcel 1 without DATSs'!H95) -> 0 | F36: Amount of pesticides, herbicides and fungicides used/total area | G36: =CONCATENATE("sust kpis no dats","_",A36,"_",B36) -> sust kpis no dats_PESTICIDE _Pesticides, herbicides and fungicides use | H36: E36
A37: WATER | B37: Water consumption | C37: Without DATs | D37: =IFERROR(VLOOKUP('General Information'!$D$6, Validations!$J$2:$K$8, 2,FALSE), "") -> m3/ha | E37: ='Parcel 1 without DATSs'!H29/(IF('General Information'!D6="crop",'Parcel 1 without DATSs'!E10,IF('General Information'!D6="milk",'Parcel 1 without DATSs'!H251,IF('General Information'!D6="meat",'Parcel 1 without DATSs'!H252,IF('General Information'!D6="animal",'Parcel 1 without DATSs'!H253,IF('General Information'!D6="oyster",'Parcel 1 without DATSs'!H254,IF('General Information'!D6="honey",'Parcel 1 without DATSs'!H255,'Parcel 1 without DATSs'!H256))))))) -> #VALUE! | F37: Amount of water used/total area | G37: =CONCATENATE("sust kpis no dats","_",A37,"_",B37) -> sust kpis no dats_WATER _Water consumption | H37: E37
A38: WATER | B38: Aquaculture water productivity | C38: Without DATs | D38: l/pieces | F38: Amount of water used/production | G38: =CONCATENATE("sust kpis no dats","_",A38,"_",B38) -> sust kpis no dats_WATER _Aquaculture water productivity | H38: E38
A39: WATER | B39: Irrigation water productivity | C39: Without DATs | D39: kg/m3 | E39: =(('Parcel 1 without DATSs'!H250)*1000)/(IF(('Parcel 1 without DATSs'!H24+'Parcel 1 without DATSs'!H25)>0,('Parcel 1 without DATSs'!H24+'Parcel 1 without DATSs'!H25),'Parcel 1 without DATSs'!H29)) -> 58.539264 | F39: Yield/Amount of water used for irrigation | G39: =CONCATENATE("sust kpis no dats","_",A39,"_",B39) -> sust kpis no dats_WATER _Irrigation water productivity | H39: E39
A40: ELECTRICITY | B40: Electricity consumption | C40: Without DATs | D40: =IFERROR(VLOOKUP('General Information'!$D$6, Validations!$W$2:$X$8, 2,FALSE), "") -> kWh/ha | E40: ='Parcel 1 without DATSs'!H62/(IF('General Information'!D6="crop",'Parcel 1 without DATSs'!E10,IF('General Information'!D6="milk",'Parcel 1 without DATSs'!H251,IF('General Information'!D6="meat",'Parcel 1 without DATSs'!H252,IF('General Information'!D6="animal",'Parcel 1 without DATSs'!H253,IF('General Information'!D6="oyster",'Parcel 1 without DATSs'!H254,IF('General Information'!D6="honey",'Parcel 1 without DATSs'!H255,'Parcel 1 without DATSs'!H256))))))) -> #VALUE! | F40: Tot. amount of electricity used/tot area | G40: =CONCATENATE("sust kpis no dats","_",A40,"_",B40) -> sust kpis no dats_ELECTRICITY_Electricity consumption | H40: E40
A41: ANIMAL | B41: Ease of movement | C41: Without DATs | D41: d/y | E41: ='Parcel 1 without DATSs'!H235/'Parcel 1 without DATSs'!H236 -> #DIV/0! | F41: number of days per year with access to pasture and outdoor loafing area | G41: =CONCATENATE("sust kpis no dats","_",A41,"_",B41) -> sust kpis no dats_ANIMAL _Ease of movement | H41: E41
A42: ANIMAL | B42: Mortality rate (livestock) | C42: Without DATs | D42: % | E42: ='Parcel 1 without DATSs'!H232/'Parcel 1 without DATSs'!E17*100 -> #VALUE! | F42: (Number of deaths in a year/Average herd size) | G42: =CONCATENATE("sust kpis no dats","_",A42,"_",B42) -> sust kpis no dats_ANIMAL _Mortality rate (livestock) | H42: E42
A43: ANIMAL | B43: Mortality rate (aquaculture) | C43: Without DATs | D43: % | E43: ='Parcel 1 without DATSs'!H232/'Parcel 1 without DATSs'!E20 -> #VALUE! | F43: (Number of deaths in a year/total animals) | G43: =CONCATENATE("sust kpis no dats","_",A43,"_",B43) -> sust kpis no dats_ANIMAL _Mortality rate (aquaculture) | H43: E43
A44: ANIMAL | B44: Mortality rate (apiculture) | C44: Without DATs | D44: % | E44: ='Parcel 1 without DATSs'!H232/'Parcel 1 without DATSs'!E19*100 -> #VALUE! | F44: (Number of deaths in a year/total animals) | G44: =CONCATENATE("sust kpis no dats","_",A44,"_",B44) -> sust kpis no dats_ANIMAL _Mortality rate (apiculture) | H44: E44
A45: ANIMAL | B45: Mortality rate at birth | C45: Without DATs | D45: % | E45: ='Parcel 1 without DATSs'!H233/'Parcel 1 without DATSs'!H234 -> #DIV/0! | F45: (Calves died in the first 24 h / Total number of calves born) | G45: =CONCATENATE("sust kpis no dats","_",A45,"_",B45) -> sust kpis no dats_ANIMAL _Mortality rate at birth | H45: E45
A46: ANIMAL | B46: Cows with high SCC | C46: Without DATs | D46: % | E46: ='Parcel 1 without DATSs'!H237/'Parcel 1 without DATSs'!E17 -> #VALUE! | F46: number of cows producing high SCC milk / Total number of cows * 100 | G46: =CONCATENATE("sust kpis no dats","_",A46,"_",B46) -> sust kpis no dats_ANIMAL _Cows with high SCC | H46: E46
A47: DRUGS | B47: Drugs use in dairy livestock | C47: Without DATs | D47: =IFERROR(VLOOKUP('General Information'!$D$6, Validations!$AA$2:$AB$8, 2,FALSE), "") -> 0 | E47: =('Parcel 1 without DATSs'!H186+'Parcel 1 without DATSs'!H188+'Parcel 1 without DATSs'!H190)/(IF('General Information'!D6="crop",'Parcel 1 without DATSs'!E10,IF('General Information'!D6="milk",'Parcel 1 without DATSs'!H251,IF('General Information'!D6="meat",'Parcel 1 without DATSs'!H252,IF('General Information'!D6="animal",'Parcel 1 without DATSs'!H253,IF('General Information'!D6="oyster",'Parcel 1 without DATSs'!H254,IF('General Information'!D6="honey",'Parcel 1 without DATSs'!H255,'Parcel 1 without DATSs'!H256))))))) -> #VALUE! | F47: Amount of drugs used/ output | G47: =CONCATENATE("sust kpis no dats","_",A47,"_",B47) -> sust kpis no dats_DRUGS _Drugs use in dairy livestock | H47: E47
A48: DRUGS | B48: Drugs use in meat livestock | C48: Without DATs | D48: =IFERROR(VLOOKUP('General Information'!$D$6, Validations!$AA$2:$AB$8, 2,FALSE), "") -> 0 | E48: =('Parcel 1 without DATSs'!H186+'Parcel 1 without DATSs'!H188+'Parcel 1 without DATSs'!H190)/(IF('General Information'!D6="crop",'Parcel 1 without DATSs'!E10,IF('General Information'!D6="milk",'Parcel 1 without DATSs'!H251,IF('General Information'!D6="meat",'Parcel 1 without DATSs'!H252,IF('General Information'!D6="animal",'Parcel 1 without DATSs'!H253,IF('General Information'!D6="oyster",'Parcel 1 without DATSs'!H254,IF('General Information'!D6="honey",'Parcel 1 without DATSs'!H255,'Parcel 1 without DATSs'!H256))))))) -> #VALUE! | F48: Amount of drugs used/ output | G48: =CONCATENATE("sust kpis no dats","_",A48,"_",B48) -> sust kpis no dats_DRUGS _Drugs use in meat livestock | H48: E48
A49: DRUGS | B49: Drugs use in aquaculture | C49: Without DATs | D49: g/m2 | E49: =('Parcel 1 without DATSs'!H186+'Parcel 1 without DATSs'!H188+'Parcel 1 without DATSs'!H190)/'Parcel 1 without DATSs'!E20 -> #VALUE! | F49: Amount of drugs used/ output | G49: =CONCATENATE("sust kpis no dats","_",A49,"_",B49) -> sust kpis no dats_DRUGS _Drugs use in aquaculture | H49: E49
A50: DRUGS | B50: Drugs use in apiculture | C50: Without DATs | D50: g/beehive | E50: =('Parcel 1 without DATSs'!H186+'Parcel 1 without DATSs'!H188+'Parcel 1 without DATSs'!H190)/'Parcel 1 without DATSs'!E19 -> #VALUE! | F50: Amount of drugs used/ output | G50: =CONCATENATE("sust kpis no dats","_",A50,"_",B50) -> sust kpis no dats_DRUGS _Drugs use in apiculture | H50: E50
A51: FUEL | B51: Fuel GHG emission | C51: Without DATs | D51: =IFERROR(VLOOKUP('General Information'!$D$6, Validations!$AA$2:$AC$8, 3,FALSE), "") -> kg CO2 eq/ha | E51: =('Parcel 1 without DATSs'!H43*'sust. impact KPIs NO DATS'!C96*'sust. impact KPIs NO DATS'!C97)/(IF('General Information'!D6="crop",'Parcel 1 without DATSs'!E10,IF('General Information'!D6="milk",'Parcel 1 without DATSs'!H251,IF('General Information'!D6="meat",'Parcel 1 without DATSs'!H252,IF('General Information'!D6="animal",'Parcel 1 without DATSs'!H253,IF('General Information'!D6="oyster",'Parcel 1 without DATSs'!H254,IF('General Information'!D6="honey",'Parcel 1 without DATSs'!H255,'Parcel 1 without DATSs'!H256))))))) -> #VALUE! | F51: Tot. amount of fuel used *Lower heating value*Emission factor | G51: =CONCATENATE("sust kpis no dats","_",A51,"_",B51) -> sust kpis no dats_FUEL _Fuel GHG emission | H51: E51
A52: FUEL | B52: Arable and horticulture fuel consumption | C52: Without DATs | D52: l/ha | E52: ='Parcel 1 without DATSs'!H43/'Parcel 1 without DATSs'!E10 -> #VALUE! | F52: Tot. amount of fuel used/tot area | G52: =CONCATENATE("sust kpis no dats","_",A52,"_",B52) -> sust kpis no dats_FUEL _Arable and horticulture fuel consumption | H52: E52
A53: FUEL | B53: Livestock fuel consumption | C53: Without DATs | D53: =IFERROR(VLOOKUP('General Information'!$D$6, Validations!$AA$2:$AD$8, 4,FALSE), "") -> l/ha | E53: ='Parcel 1 without DATSs'!H43/'Parcel 1 without DATSs'!E17 -> #VALUE! | F53: Tot. amount of fuel used/number of animals | G53: =CONCATENATE("sust kpis no dats","_",A53,"_",B53) -> sust kpis no dats_FUEL _Livestock fuel consumption | H53: E53
A54: FUEL | B54: Aquaculture fuel consumption | C54: Without DATs | D54: l/m2 | E54: ='Parcel 1 without DATSs'!H43/'Parcel 1 without DATSs'!E20 -> #VALUE! | F54: Tot. amount of fuel used/ area under aquaculture | G54: =CONCATENATE("sust kpis no dats","_",A54,"_",B54) -> sust kpis no dats_FUEL _Aquaculture fuel consumption | H54: E54
A55: FUEL | B55: Apiculture fuel consumption | C55: Without DATs | D55: kg/beehives | E55: ='Parcel 1 without DATSs'!H43/'Parcel 1 without DATSs'!E19 -> #VALUE! | F55: Tot. amount of fuel used/Number of beehives | G55: =CONCATENATE("sust kpis no dats","_",A55,"_",B55) -> sust kpis no dats_FUEL _Apiculture fuel consumption | H55: E55
A56: FERTILISER | B56: indirect leaching/runoff | C56: Without DATs | E56: =E30*C89*C91 -> 1.3791677 | F56: Amount of N fertilizer used (kg-N) * fraction of leaching or runoff * emission factor 5 | G56: =CONCATENATE("sust kpis no dats","_",A56,"_",B56) -> sust kpis no dats_FERTILISER_indirect leaching/runoff | H56: E56
A57: FERTILISER | B57: indirect volatilisation | C57: Without DATs | E57: =((((IF('Parcel 1 without DATSs'!H100="Mineral",'Parcel 1 without DATSs'!H101*'Parcel 1 without DATSs'!H102*'Parcel 1 without DATSs'!H103/100,0)) + (IF('Parcel 1 without DATSs'!H107="Mineral",'Parcel 1 without DATSs'!H108*'Parcel 1 without DATSs'!H109*'Parcel 1 without DATSs'!H110/100,0)) + (IF('Parcel 1 without DATSs'!H114="Mineral",'Parcel 1 without DATSs'!H115*'Parcel 1 without DATSs'!H116*'Parcel 1 without DATSs'!H117/100,0)) + (IF('Parcel 1 without DATSs'!H121="Mineral",'Parcel 1 without DATSs'!H122*'Parcel 1 without DATSs'!H123*'Parcel 1 without DATSs'!H124/100,0)) + (IF('Parcel 1 without DATSs'!H128="Mineral",'Parcel 1 without DATSs'!H129*'Parcel 1 without DATSs'!H130*'Parcel 1 without DATSs'!H131/100,0)) + (IF('Parcel 1 without DATSs'!H135="Mineral",'Parcel 1 without DATSs'!H136*'Parcel 1 without DATSs'!H137*'Parcel 1 without DATSs'!H138/100,0)) + (IF('Parcel 1 without DATSs'!H142="Mineral",'Parcel 1 without DATSs'!H143*'Parcel 1 without DATSs'!H144*'Parcel 1 without DATSs'!H145/100,0)) + (IF('Parcel 1 without DATSs'!H149="Mineral",'Parcel 1 without DATSs'!H150*'Parcel 1 without DATSs'!H151*'Parcel 1 without DATSs'!H152/100,0)) + (IF('Parcel 1 without DATSs'!H156="Mineral",'Parcel 1 without DATSs'!H157*'Parcel 1 without DATSs'!H158*'Parcel 1 without DATSs'!H159/100,0)) + (IF('Parcel 1 without DATSs'!H163="Mineral",'Parcel 1 without DATSs'!H164*'Parcel 1 without DATSs'!H165*'Parcel 1 without DATSs'!H166/100,0)))*'sust. impact KPIs DATS'!C87) + (((IF('Parcel 1 without DATSs'!H100="Organic",'Parcel 1 without DATSs'!H101*'Parcel 1 without DATSs'!H102*'Parcel 1 without DATSs'!H103/100,0)) + (IF('Parcel 1 without DATSs'!H107="Organic",'Parcel 1 without DATSs'!H108*'Parcel 1 without DATSs'!H109*'Parcel 1 without DATSs'!H110/100,0)) + (IF('Parcel 1 without DATSs'!H114="Organic",'Parcel 1 without DATSs'!H115*'Parcel 1 without DATSs'!H116*'Parcel 1 without DATSs'!H117/100,0)) + (IF('Parcel 1 without DATSs'!H121="Organic",'Parcel 1 without DATSs'!H122*'Parcel 1 without DATSs'!H123*'Parcel 1 without DATSs'!H124/100,0)) + (IF('Parcel 1 without DATSs'!H128="Organic",'Parcel 1 without DATSs'!H129*'Parcel 1 without DATSs'!H130*'Parcel 1 without DATSs'!H131/100,0)) + (IF('Parcel 1 without DATSs'!H135="Organic",'Parcel 1 without DATSs'!H136*'Parcel 1 without DATSs'!H137*'Parcel 1 without DATSs'!H138/100,0)) + (IF('Parcel 1 without DATSs'!H142="Organic",'Parcel 1 without DATSs'!H143*'Parcel 1 without DATSs'!H144*'Parcel 1 without DATSs'!H145/100,0)) + (IF('Parcel 1 without DATSs'!H149="Organic",'Parcel 1 without DATSs'!H150*'Parcel 1 without DATSs'!H151*'Parcel 1 without DATSs'!H152/100,0)) + (IF('Parcel 1 without DATSs'!H156="Organic",'Parcel 1 without DATSs'!H157*'Parcel 1 without DATSs'!H158*'Parcel 1 without DATSs'!H159/100,0)) + (IF('Parcel 1 without DATSs'!H163="Organic",'Parcel 1 without DATSs'!H164*'Parcel 1 without DATSs'!H165*'Parcel 1 without DATSs'!H166/100,0)))*'sust. impact KPIs DATS'!C88)) *'sust. impact KPIs DATS'!C84 -> 0.5746532 | F57: [(Amount of synthetic N fertilizer used (kg-N) * fraction volatilized) + (Amount of organic N fertilizer used (kg-N) *fraction volatilized)] * Emission factor 4 | G57: =CONCATENATE("sust kpis no dats","_",A57,"_",B57) -> sust kpis no dats_FERTILISER_indirect volatilisation | H57: E57
A58: FERTILISER | B58: direct | C58: Without DATs | E58: =E30*C79 -> 5.22412 | F58: Amount of N fertilizer used (kg-N) * Emission factor 1 | G58: =CONCATENATE("sust kpis no dats","_",A58,"_",B58) -> sust kpis no dats_FERTILISER_direct | H58: E58
A59: FERTILISER | B59: N2O GHG emission | C59: Without DATs | D59: kg Co2e/ha | E59: =(E58+E57+E56)*C92*C93 -> 3079.3366 | F59: direct + indirect N2O emissions | G59: =CONCATENATE("sust kpis no dats","_",A59,"_",B59) -> sust kpis no dats_FERTILISER_N2O GHG emission | H59: E59
A60: GHG | B60: total ghg emissions | C60: Without DATs | D60: =D51 -> kg CO2 eq/ha | E60: =E59+E51 -> #VALUE! | G60: =CONCATENATE("sust kpis no dats","_",A60,"_",B60) -> sust kpis no dats_GHG_total ghg emissions | H60: E60
A61: SOCIAL KPIs
B62: INDICATOR | C62: SCENARIO | D62: UoM | E62: TOTAL | F62: Formula
A63: SOCIAL KPIs | B63: Training hours (for the use of DATs) | C63: With DATs | D63: h/employee | E63: 0 | F63: Time spent for training hours for all the employee/number of employees | G63: =CONCATENATE("sust kpis no dats","_",A63,"_",B63) -> sust kpis no dats_SOCIAL KPIs_Training hours (for the use of DATs) | H63: E63
A64: SOCIAL KPIs | B64: Working time | C64: Without DATs | D64: =IFERROR(VLOOKUP('General Information'!$D$6, Validations!$L$2:$N$8, 3,FALSE), "") -> h/ha | E64: {=(SUM(SUMIFS('Parcel 1 without DATSs'!H194:H218,'Parcel 1 without DATSs'!C194:C218,'Analysis DATS vs. NO DATS'!C12:C36,'Analysis DATS vs. NO DATS'!J12:J36,1)))/(IF('General Information'!D6="crop",'Parcel 1 without DATSs'!E10,IF('General Information'!D6="milk",'Parcel 1 without DATSs'!H251,IF('General Information'!D6="meat",'Parcel 1 without DATSs'!H252,IF('General Information'!D6="animal",'Parcel 1 without DATSs'!H253,IF('General Information'!D6="oyster",'Parcel 1 without DATSs'!H254,IF('General Information'!D6="honey",'Parcel 1 without DATSs'!H255,'Parcel 1 without DATSs'!H256)))))))} -> #VALUE! | F64: Hours worked for the specific activities that could be impacted by DATSs | G64: =CONCATENATE("sust kpis no dats","_",A64,"_",B64) -> sust kpis no dats_SOCIAL KPIs_Working time | H64: E64
A65: SOCIAL KPIs | B65: Frequency rate of occupational injuries | C65: Without DATs | D65: n./hours | E65: ='Parcel 1 without DATSs'!H241/'Parcel 1 without DATSs'!H243 -> #DIV/0! | F65: Number of new injury cases/Total number of working hours | G65: =CONCATENATE("sust kpis no dats","_",A65,"_",B65) -> sust kpis no dats_SOCIAL KPIs_Frequency rate of occupational injuries | H65: E65
A66: SOCIAL KPIs | B66: Incidence of occupational injuries | C66: Without DATs | D66: % | E66: ='Parcel 1 without DATSs'!H242/'Parcel 1 without DATSs'!H243 -> #DIV/0! | F66: Total number of lost working hours due to occupational injuries/Total number of working hours | G66: =CONCATENATE("sust kpis no dats","_",A66,"_",B66) -> sust kpis no dats_SOCIAL KPIs_Incidence of occupational injuries | H66: E66
A67: SOCIAL KPIs | B67: Contribution to local employment | C67: Without DATs | D67: % | E67: ='Parcel 1 without DATSs'!H245/'Parcel 1 without DATSs'!H246 -> #DIV/0! | F67: Number of new local employees/Total new employees hired | G67: =CONCATENATE("sust kpis no dats","_",A67,"_",B67) -> sust kpis no dats_SOCIAL KPIs_Contribution to local employment | H67: E67
B76: IPCC 2006 methodology (2019 refinement) - Tier 1 | D76: (Fixed values)
A77: N2O EMISSIONS | B77: UoM | C77: value | D77: description
A78: direct emissions
A79: EF1 | B79: (Kg N2O-N)/(kg N input) | C79: 0.01 | D79: Emission Factor default value for direct emissions
A80: EF1 SW | B80: (Kg N2O-N)/(kg N input) | C80: 0.016 | D80: Emission Factor for Synthetic fertilizers in Wet climates (optional)
A81: EF1 OW | B81: (Kg N2O-N)/(kg N input) | C81: 0.006 | D81: Other N inputs in Wet climates (optional)
A82: EF1 AD | B82: (Kg N2O-N)/(kg N input) | C82: 0.006 | D82: All N inputs in Dry climates (optional)
A83: indirect emissions
A84: EF4 | B84: (Kg N2O-N)/(kg N volatilised) | C84: 0.01 | D84: Emission Factor default value for volatilization of N
A85: EF4 W | B85: (Kg N2O-N)/(kg N volatilised) | C85: 0.014 | D85: Emission Factor default value for volatilization of N in wet cliamtes
A86: EF4 D | B86: (Kg N2O-N)/(kg N volatilised) | C86: 0.005 | D86: Emission Factor default value for volatilization of N in dry climates
A87: Frac GASF | B87: (kg N volatilised)/(Kg of N input) | C87: 0.11 | D87: Fraction of synthetic fertiliser N that volatilises
A88: Frac GASM | B88: (kg N volatilised)/(Kg of N input) | C88: 0.21 | D88: Fraction of organic fertiliser N that volatilies
A89: FracLEACH | B89: (kg Nleaching&runoff)/(Kg N input) | C89: 0.24 | D89: For all N inputs
A90: FracLEACH D | B90: (kg Nleaching&runoff)/(Kg N input) | C90: 0 | D90: 0 if leaching & runoff process assumed to be absent or in dry climates
A91: EF5 | B91: (kg N2O–N)/(kg N leached and runoff) | C91: 0.011 | D91: Emission factor for N2O emissions from N leaching and runoff
A92: CF1 | B92: Kg/kg | C92: =44/28 -> 1.5714286 | D92: Coversion factor from N to N2O
A93: GWP-N2O | C93: 273 | D93: Global Warming Potential of N2O compared to CO2 (IPCC AR6)
A95: CO2 EMISSIONS FUEL
A96: Lower Heating Value Diesel | B96: MJ/l | C96: 35.9 | D96: Castoldi & Bechini, 2006
A97: EF diesel agri | B97: kg Co2e/Mj | C97: 0.0741 | D97: IPCC 2006
A99: Average nutrient content kg/kg
A100: ='General Information'!D7 -> Onion | B100: Average N content | C100: =IFERROR(VLOOKUP('General Information'!$D$7, Validations!$P$2:$Q$18, 2,FALSE), "") -> 0.003
A101: ='General Information'!D7 -> Onion | B101: Average P content | C101: =IFERROR(VLOOKUP('General Information'!$D$7, Validations!$R$2:$S$18, 2,FALSE), "") -> 0.0012
A102: ='General Information'!D7 -> Onion | B102: Average K content | C102: =IFERROR(VLOOKUP('General Information'!$D$7, Validations!$T$2:$U$18, 2,FALSE), "") -> 0.004

Sheet Analysis DATS vs. NO DATS
T1: IMPACT CATEGORY AGGREGATION | Y1: SUSTAINABILITY CATEGORY AGGREGATION
A2: Sustainability category | B2: Impact category | C2: KPI | D2: UNIT | E2: Abs. Value | F2: % | I2: if > is good = 1 | J2: Impacted KPIs | K2: Main Impacts | L2: Monetary Impacts | M2: Aggregated Impacts | N2: Title (for column J) | O2: Subtitle (for column J) | P2: Short description (for column K) | Q2: Icon | R2: Colour | T2: KPI category | U2: % aggregated | V2: % aggregated (max range) | W2: Icon | X2: Colour | Y2: Sustainability category | Z2: Sustainability category | AA2: overall score (%) | AC2: code | AD2: meaning | AE2: colour
