Workbook

Sheet Instructions 
B2: Instructions to be followed to complete the Data Collection Template
B3: This form is intended to be filled out by each farmer involved in the Test Case (TC) and aims at collecting information that will be used for assessing the impacts of Digital agriculture technology solutions (DATSs). Please read carefully the following instructions. - We kindly ask you to be as accurate as possible in providing the data and monitor them periodically as these will be the input for performance assessment. - Please ensure you keep track of the data requested and regularly check its availability. It's crucial that these values align for both user and non-user parcels. If they differ, kindly notify us promptly via email at the provided contact details. - The data included in the template have been carefully chosen based on their link with the DATSs used in your TC and they were further customised following your feedback. If some of the data cannot be applicable/available to your TC, please enter ‘n.a.’ in the corresponding cell and provide a comment explaining why they are not applicable. Additionally, in case some of the data cannot be collected due to some problems you may encounter during the season, please inform us promptly by writing an e-mail to the contact details provided below. - In order to obtain the assessment of the impacts of DATS, it is necessary to provide data for the farm(s) using DATS and for the one without. According to the QuantiFarm project proposal, each parcel using DATSs is associated with a comparable non-DATs parcel (in terms of size, geographical area, production, etc.). - Recall that: - the term DATS refers to the combinations or set of technological solutions implemented within the TC; For any doubts or clarifications, please do not hesitate to contact us at the following email address: francesco.parigi@polimi.it and andrea.bianchi@polimi.it (cc: dmoniz@consulai.com) This form is intended to be filled out by each farmer involved in the Test Case (TC) and aims at collecting information that will be used for assessing the impacts of Digital agriculture technology solutions (DATSs).
B5: Table of abbreviations
B6: - | C6: number (1, 2, 3, …)
B7: € | C7: euro
B8: cm3 | C8: cubic centimetre
B9: dm3 | C9: cubic decimetre
B10: g | C10: grams
B11: h | C11: hour
B12: ha | C12: hectare
B13: K | C13: potassium
B14: k€ | C14: kiloeuro (€ 1,000)
B15: kg | C15: kilograms
B16: kWh | C16: kilowatt-hour
B17: l | C17: litre
... B27: y | C27: year

Sheet General Information
A2: Ivaylo Parent | B2: Jack Naming | E2: Question | F2: Unit of measure | G2: Value
B3: testcaseNumber | C3: =CONCATENATE("""",D3,"""",":","""",LOWER(A3),"_",LOWER(B3),"""") -> "G3":"_testcasenumber" | D3: G3 | E3: TC Number | F3: n
B4: testcaseLeader | C4: =CONCATENATE("""",D4,"""",":","""",LOWER(A4),"_",LOWER(B4),"""") -> "G4":"_testcaseleader" | D4: G4 | E4: TC Leader | F4: -
C5: =CONCATENATE("""",D5,"""",":","""",LOWER(A5),"_",LOWER(B5),"""") -> "G5":"_" | D5: G5 | E5: FARM DATA
A6: parcelInformation | B6: cultivationType | C6: =CONCATENATE("""",D6,"""",":","""",LOWER(A6),"_",LOWER(B6),"""") -> "G6":"parcelinformation_cultivationtype" | D6: G6 | E6: Type of output/product | F6: - | G6: Milk
A7: parcelInformation | B7: productType | C7: =CONCATENATE("""",D7,"""",":","""",LOWER(A7),"_",LOWER(B7),"""") -> "G7":"parcelinformation_producttype" | D7: G7 | E7: Crop | F7: - | G7: Apple | H7: of parcel per comparison per year
A8: parcelInformation | B8: productType | C8: =CONCATENATE("""",D8,"""",":","""",LOWER(A8),"_",LOWER(B8),"""") -> "G8":"parcelinformation_producttype" | D8: G8 | E8: Animal | H8: of parcel per comparison per year
A9: parcelInformation | B9: startMonth | C9: =CONCATENATE("""",D9,"""",":","""",LOWER(A9),"_",LOWER(B9),"""") -> "G9":"parcelinformation_startmonth" | D9: G9 | E9: Start of the growing/production season | F9: (gg/mm/yyyy) | H9: of parcel per comparison per year
A10: parcelInformation | B10: endMonth | C10: =CONCATENATE("""",D10,"""",":","""",LOWER(A10),"_",LOWER(B10),"""") -> "G10":"parcelinformation_endmonth" | D10: G10 | E10: End of the growing/production season | F10: (gg/mm/yyyy) | H10: of parcel per comparison per year
A11: parcelInformation | B11: biogeographicalRegion | C11: =CONCATENATE("""",D11,"""",":","""",LOWER(A11),"_",LOWER(B11),"""") -> "G11":"parcelinformation_biogeographicalregion" | D11: G11 | E11: Biogeographical region | F11: - | G11: 1
A12: parcelInformation | B12: totalFarmSize | C12: =CONCATENATE("""",D12,"""",":","""",LOWER(A12),"_",LOWER(B12),"""") -> "G12":"parcelinformation_totalfarmsize" | D12: G12 | E12: Total farm size | F12: ha | G12: 1
A13: parcelInformation | B13: numberOfComparisons | C13: =CONCATENATE("""",D13,"""",":","""",LOWER(A13),"_",LOWER(B13),"""") -> "G13":"parcelinformation_numberofcomparisons" | D13: G13 | E13: Number of comparison(s) | F13: n | G13: 1
A14: parcelInformation | B14: numberOfEmployees | C14: =CONCATENATE("""",D14,"""",":","""",LOWER(A14),"_",LOWER(B14),"""") -> "G14":"parcelinformation_numberofemployees" | D14: G14 | E14: Number of employees | F14: n | G14: 1 | H14: of parcel per comparison per year
A15: parcelInformation | B15: numberofFullTimeEmployees | C15: =CONCATENATE("""",D15,"""",":","""",LOWER(A15),"_",LOWER(B15),"""") -> "G15":"parcelinformation_numberoffulltimeemployees" | D15: G15 | E15: Number of full-time employees | F15: n | G15: 1 | H15: of parcel per comparison per year
A16: parcelInformation | B16: numberOfSeasonalEmployees | C16: =CONCATENATE("""",D16,"""",":","""",LOWER(A16),"_",LOWER(B16),"""") -> "G16":"parcelinformation_numberofseasonalemployees" | D16: G16 | E16: Number of seasonal employees | F16: n | G16: 1 | H16: of parcel per comparison per year
C17: =CONCATENATE("""",D17,"""",":","""",LOWER(A17),"_",LOWER(B17),"""") -> "G17":"_" | D17: G17
C18: =CONCATENATE("""",D18,"""",":","""",LOWER(A18),"_",LOWER(B18),"""") -> "G18":"_" | D18: G18 | E18: DATSs DATA
C19: =CONCATENATE("""",D19,"""",":","""",LOWER(A19),"_",LOWER(B19),"""") -> "G19":"_" | D19: G19 | E19: Question | F19: Unit of measure | G19: Value
A20: datsInformation | B20: datsInitialInvestmentCosts | C20: =CONCATENATE("""",D20,"""",":","""",LOWER(A20),"_",LOWER(B20),"""") -> "G20":"datsinformation_datsinitialinvestmentcosts" | D20: G20 | E20: Initial investment for DATSs (the total for all the solutions assessed in the project) | F20: € | G20: 1
A21: datsInformation | B21: datsExpectedLifespan | C21: =CONCATENATE("""",D21,"""",":","""",LOWER(A21),"_",LOWER(B21),"""") -> "G21":"datsinformation_datsexpectedlifespan" | D21: G21 | E21: Expected life span of each DATSs | F21: y | G21: 1
A22: datsInformation | B22: datsInstallationTime | C22: =CONCATENATE("""",D22,"""",":","""",LOWER(A22),"_",LOWER(B22),"""") -> "G22":"datsinformation_datsinstallationtime" | D22: G22 | E22: Time to install and make DATSs operational | F22: h | G22: 1
A23: datsInformation | B23: datsMaintenanceCosts | C23: =CONCATENATE("""",D23,"""",":","""",LOWER(A23),"_",LOWER(B23),"""") -> "G23":"datsinformation_datsmaintenancecosts" | D23: G23 | E23: DATs maintenance costs | F23: €/y | G23: 1
A24: datsInformation | B24: datsAnnualFees | C24: =CONCATENATE("""",D24,"""",":","""",LOWER(A24),"_",LOWER(B24),"""") -> "G24":"datsinformation_datsannualfees" | D24: G24 | E24: DATS annual fees | F24: €/y | G24: 1
A25: datsInformation | B25: datsTrainingTime | C25: =CONCATENATE("""",D25,"""",":","""",LOWER(A25),"_",LOWER(B25),"""") -> "G25":"datsinformation_datstrainingtime" | D25: G25 | E25: Training hours for the use of the DATSs in a year | F25: h | G25: 1
A26: datsInformation | B26: datsTrainers | C26: =CONCATENATE("""",D26,"""",":","""",LOWER(A26),"_",LOWER(B26),"""") -> "G26":"datsinformation_datstrainers" | D26: G26 | E26: Number of people involved in the training | F26: n | G26: 1
A27: datsInformation | B27: datsTrainingCosts | C27: =CONCATENATE("""",D27,"""",":","""",LOWER(A27),"_",LOWER(B27),"""") -> "G27":"datsinformation_datstrainingcosts" | D27: G27 | E27: Cost of training service by external people (advisor, DATS providers, ...) | F27: €/y | G27: 1
A28: datsInformation | B28: datsName | C28: =CONCATENATE("""",D28,"""",":","""",LOWER(A28),"_",LOWER(B28),"""") -> "G28":"datsinformation_datsname" | D28: G28 | E28: DATSs name | F28: - | G28: 1
C29: =CONCATENATE("""",D29,"""",":","""",LOWER(A29),"_",LOWER(B29),"""") -> "G29":"_" | D29: G29
C30: =CONCATENATE("""",D30,"""",":","""",LOWER(A30),"_",LOWER(B30),"""") -> "G30":"_" | D30: G30 | E30: MARKET DATA FOR DATSs USER
C31: =CONCATENATE("""",D31,"""",":","""",LOWER(A31),"_",LOWER(B31),"""") -> "G31":"_" | D31: G31 | E31: Question | F31: Unit of measure | G31: Value
A32: marketinformation | B32: waterPrice | C32: =CONCATENATE("""",D32,"""",":","""","parcelassessmentwithdats_",LOWER(A32),"_",LOWER(B32),"""") -> "G32":"parcelassessmentwithdats_marketinformation_waterprice" | D32: G32 | E32: Water price | F32: €/m3 | G32: 1
A33: marketinformation | B33: fuelPrice | C33: =CONCATENATE("""",D33,"""",":","""","parcelassessmentwithdats_",LOWER(A33),"_",LOWER(B33),"""") -> "G33":"parcelassessmentwithdats_marketinformation_fuelprice" | D33: G33 | E33: Fuel price | F33: €/l | G33: 1
A34: marketinformation | B34: n_fuel_for_greenhouse | C34: =CONCATENATE("""",D34,"""",":","""","parcelassessmentwithdats_",LOWER(A34),"_",LOWER(B34),"""") -> "G34":"parcelassessmentwithdats_marketinformation_n_fuel_for_greenhouse" | D34: G34 | E34: Number of fuel for greehnouse temperature control price | F34: n | G34: 1
A35: fuelfortemperaturecontrolinformation | B35: productPrice_0 | C35: =CONCATENATE("""",D35,"""",":","""","parcelassessmentwithdats_",LOWER(A35),"_",LOWER(B35),"""") -> "G35":"parcelassessmentwithdats_fuelfortemperaturecontrolinformation_productprice_0" | D35: G35 | E35: Fuel 1 for greehnouse temperature control price | F35: €/m3 | G35: 1
A36: fuelfortemperaturecontrolinformation | B36: productPrice_1 | C36: =CONCATENATE("""",D36,"""",":","""","parcelassessmentwithdats_",LOWER(A36),"_",LOWER(B36),"""") -> "G36":"parcelassessmentwithdats_fuelfortemperaturecontrolinformation_productprice_1" | D36: G36 | E36: Fuel 2 for greehnouse temperature control price | F36: €/m3 | G36: 1
A37: fuelfortemperaturecontrolinformation | B37: productPrice_2 | C37: =CONCATENATE("""",D37,"""",":","""","parcelassessmentwithdats_",LOWER(A37),"_",LOWER(B37),"""") -> "G37":"parcelassessmentwithdats_fuelfortemperaturecontrolinformation_productprice_2" | D37: G37 | E37: Fuel 3 for greehnouse temperature control price | F37: €/m3 | G37: 1
A38: fuelfortemperaturecontrolinformation | B38: productPrice_3 | C38: =CONCATENATE("""",D38,"""",":","""","parcelassessmentwithdats_",LOWER(A38),"_",LOWER(B38),"""") -> "G38":"parcelassessmentwithdats_fuelfortemperaturecontrolinformation_productprice_3" | D38: G38 | E38: Fuel 1 for greehnouse temperature control price | F38: €/m3 | G38: 1
A39: fuelfortemperaturecontrolinformation | B39: productPrice_4 | C39: =CONCATENATE("""",D39,"""",":","""","parcelassessmentwithdats_",LOWER(A39),"_",LOWER(B39),"""") -> "G39":"parcelassessmentwithdats_fuelfortemperaturecontrolinformation_productprice_4" | D39: G39 | E39: Fuel 1 for greehnouse temperature control price | F39: €/m3 | G39: 1
A40: fuelfortemperaturecontrolinformation | B40: productPrice_5 | C40: =CONCATENATE("""",D40,"""",":","""","parcelassessmentwithdats_",LOWER(A40),"_",LOWER(B40),"""") -> "G40":"parcelassessmentwithdats_fuelfortemperaturecontrolinformation_productprice_5" | D40: G40 | E40: Fuel 2 for greehnouse temperature control price | F40: €/m3 | G40: 1
A41: fuelfortemperaturecontrolinformation | B41: productPrice_6 | C41: =CONCATENATE("""",D41,"""",":","""","parcelassessmentwithdats_",LOWER(A41),"_",LOWER(B41),"""") -> "G41":"parcelassessmentwithdats_fuelfortemperaturecontrolinformation_productprice_6" | D41: G41 | E41: Fuel 3 for greehnouse temperature control price | F41: €/m3 | G41: 1
A42: fuelfortemperaturecontrolinformation | B42: productPrice_7 | C42: =CONCATENATE("""",D42,"""",":","""","parcelassessmentwithdats_",LOWER(A42),"_",LOWER(B42),"""") -> "G42":"parcelassessmentwithdats_fuelfortemperaturecontrolinformation_productprice_7" | D42: G42 | E42: Fuel 1 for greehnouse temperature control price | F42: €/m3 | G42: 1
A43: fuelfortemperaturecontrolinformation | B43: productPrice_8 | C43: =CONCATENATE("""",D43,"""",":","""","parcelassessmentwithdats_",LOWER(A43),"_",LOWER(B43),"""") -> "G43":"parcelassessmentwithdats_fuelfortemperaturecontrolinformation_productprice_8" | D43: G43 | E43: Fuel 2 for greehnouse temperature control price | F43: €/m3 | G43: 1
... A51: pesticidesusageinformation | B51: productPrice_1 | C51: =CONCATENATE("""",D51,"""",":","""","parcelassessmentwithdats_",LOWER(A51),"_",LOWER(B51),"""") -> "G51":"parcelassessmentwithdats_pesticidesusageinformation_productprice_1" | D51: G51 | E51: Pesticide 2 price | F51: €/kg | G51: 1
A52: pesticidesusageinformation | B52: productPrice_2 | C52: =CONCATENATE("""",D52,"""",":","""","parcelassessmentwithdats_",LOWER(A52),"_",LOWER(B52),"""") -> "G52":"parcelassessmentwithdats_pesticidesusageinformation_productprice_2" | D52: G52 | E52: Pesticide 3 price | F52: €/kg
A53: pesticidesusageinformation | B53: productPrice_3 | C53: =CONCATENATE("""",D53,"""",":","""","parcelassessmentwithdats_",LOWER(A53),"_",LOWER(B53),"""") -> "G53":"parcelassessmentwithdats_pesticidesusageinformation_productprice_3" | D53: G53 | E53: Pesticide 4 price | F53: €/kg | G53: 1
A54: pesticidesusageinformation | B54: productPrice_4 | C54: =CONCATENATE("""",D54,"""",":","""","parcelassessmentwithdats_",LOWER(A54),"_",LOWER(B54),"""") -> "G54":"parcelassessmentwithdats_pesticidesusageinformation_productprice_4" | D54: G54 | E54: Pesticide 5 price | F54: €/kg | G54: 1
A55: pesticidesusageinformation | B55: productPrice_5 | C55: =CONCATENATE("""",D55,"""",":","""","parcelassessmentwithdats_",LOWER(A55),"_",LOWER(B55),"""") -> "G55":"parcelassessmentwithdats_pesticidesusageinformation_productprice_5" | D55: G55 | E55: Pesticide 6 price | F55: €/kg
A56: pesticidesusageinformation | B56: productPrice_6 | C56: =CONCATENATE("""",D56,"""",":","""","parcelassessmentwithdats_",LOWER(A56),"_",LOWER(B56),"""") -> "G56":"parcelassessmentwithdats_pesticidesusageinformation_productprice_6" | D56: G56 | E56: Pesticide 7 price | F56: €/kg | G56: 1
A57: pesticidesusageinformation | B57: productPrice_7 | C57: =CONCATENATE("""",D57,"""",":","""","parcelassessmentwithdats_",LOWER(A57),"_",LOWER(B57),"""") -> "G57":"parcelassessmentwithdats_pesticidesusageinformation_productprice_7" | D57: G57 | E57: Pesticide 8 price | F57: €/kg | G57: 1
A58: pesticidesusageinformation | B58: productPrice_8 | C58: =CONCATENATE("""",D58,"""",":","""","parcelassessmentwithdats_",LOWER(A58),"_",LOWER(B58),"""") -> "G58":"parcelassessmentwithdats_pesticidesusageinformation_productprice_8" | D58: G58 | E58: Pesticide 9 price | F58: €/kg | G58: 1
A59: pesticidesusageinformation | B59: productPrice_9 | C59: =CONCATENATE("""",D59,"""",":","""","parcelassessmentwithdats_",LOWER(A59),"_",LOWER(B59),"""") -> "G59":"parcelassessmentwithdats_pesticidesusageinformation_productprice_9" | D59: G59 | E59: Pesticide 10 price | F59: €/kg | G59: 1
A60: marketinformation | B60: n_of_fertilizers_used | C60: =CONCATENATE("""",D60,"""",":","""","parcelassessmentwithdats_",LOWER(A60),"_",LOWER(B60),"""") -> "G60":"parcelassessmentwithdats_marketinformation_n_of_fertilizers_used" | D60: G60 | E60: Number of fertilizers used | F60: n | G60: 1
A61: fertilizersusageinformation | B61: productPrice_0 | C61: =CONCATENATE("""",D61,"""",":","""","parcelassessmentwithdats_",LOWER(A61),"_",LOWER(B61),"""") -> "G61":"parcelassessmentwithdats_fertilizersusageinformation_productprice_0" | D61: G61 | E61: Fertiliser n price | F61: €/t | G61: 1
A62: fertilizersusageinformation | B62: productPrice_1 | C62: =CONCATENATE("""",D62,"""",":","""","parcelassessmentwithdats_",LOWER(A62),"_",LOWER(B62),"""") -> "G62":"parcelassessmentwithdats_fertilizersusageinformation_productprice_1" | D62: G62 | E62: Fertiliser n price | F62: €/t | G62: 1
A63: fertilizersusageinformation | B63: productPrice_2 | C63: =CONCATENATE("""",D63,"""",":","""","parcelassessmentwithdats_",LOWER(A63),"_",LOWER(B63),"""") -> "G63":"parcelassessmentwithdats_fertilizersusageinformation_productprice_2" | D63: G63 | E63: Fertiliser n price | F63: €/t | G63: 1
A64: fertilizersusageinformation | B64: productPrice_3 | C64: =CONCATENATE("""",D64,"""",":","""","parcelassessmentwithdats_",LOWER(A64),"_",LOWER(B64),"""") -> "G64":"parcelassessmentwithdats_fertilizersusageinformation_productprice_3" | D64: G64 | E64: Fertiliser n price | F64: €/t | G64: 1
A65: fertilizersusageinformation | B65: productPrice_4 | C65: =CONCATENATE("""",D65,"""",":","""","parcelassessmentwithdats_",LOWER(A65),"_",LOWER(B65),"""") -> "G65":"parcelassessmentwithdats_fertilizersusageinformation_productprice_4" | D65: G65 | E65: Fertiliser n price | F65: €/t | G65: 1
A66: fertilizersusageinformation | B66: productPrice_5 | C66: =CONCATENATE("""",D66,"""",":","""","parcelassessmentwithdats_",LOWER(A66),"_",LOWER(B66),"""") -> "G66":"parcelassessmentwithdats_fertilizersusageinformation_productprice_5" | D66: G66 | E66: Fertiliser n price | F66: €/t | G66: 1
A67: fertilizersusageinformation | B67: productPrice_6 | C67: =CONCATENATE("""",D67,"""",":","""","parcelassessmentwithdats_",LOWER(A67),"_",LOWER(B67),"""") -> "G67":"parcelassessmentwithdats_fertilizersusageinformation_productprice_6" | D67: G67 | E67: Fertiliser n price | F67: €/t | G67: 1
... A92: drugsusageinformation | B92: productPrice_9 | C92: =CONCATENATE("""",D92,"""",":","""","parcelassessmentwithdats_",LOWER(A92),"_",LOWER(B92),"""") -> "G92":"parcelassessmentwithdats_drugsusageinformation_productprice_9" | D92: G92 | E92: Drug n price | F92: €/g | G92: 1
C93: =CONCATENATE("""",D93,"""",":","""",LOWER(A93),"_",LOWER(B93),"""") -> "G93":"_" | D93: G93
C94: =CONCATENATE("""",D94,"""",":","""",LOWER(A94),"_",LOWER(B94),"""") -> "G94":"_" | D94: G94 | E94: MARKET DATA FOR NON-DATSs USER
C95: =CONCATENATE("""",D95,"""",":","""",LOWER(A95),"_",LOWER(B95),"""") -> "G95":"_" | D95: G95 | E95: Question | F95: Unit of measure | G95: Value
A96: marketinformation | B96: waterPrice | C96: =CONCATENATE("""",D96,"""",":","""","parcelassessmentwithoutdats_",LOWER(A96),"_",LOWER(B96),"""") -> "G96":"parcelassessmentwithoutdats_marketinformation_waterprice" | D96: G96 | E96: Water price | F96: €/m3 | G96: 1
A97: marketinformation | B97: fuelPrice | C97: =CONCATENATE("""",D97,"""",":","""","parcelassessmentwithoutdats_",LOWER(A97),"_",LOWER(B97),"""") -> "G97":"parcelassessmentwithoutdats_marketinformation_fuelprice" | D97: G97 | E97: Fuel price | F97: €/l | G97: 1
A98: marketinformation | B98: n_fuel_for_greenhouse | C98: =CONCATENATE("""",D98,"""",":","""","parcelassessmentwithoutdats_",LOWER(A98),"_",LOWER(B98),"""") -> "G98":"parcelassessmentwithoutdats_marketinformation_n_fuel_for_greenhouse" | D98: G98 | E98: Number of fuel for greehnouse temperature control price | F98: n | G98: 1
A99: fuelfortemperaturecontrolinformation | B99: productPrice_0 | C99: =CONCATENATE("""",D99,"""",":","""","parcelassessmentwithoutdats_",LOWER(A99),"_",LOWER(B99),"""") -> "G99":"parcelassessmentwithoutdats_fuelfortemperaturecontrolinformation_productprice_0" | D99: G99 | E99: Fuel 1 for greehnouse temperature control price | F99: €/m3 | G99: 1
A100: fuelfortemperaturecontrolinformation | B100: productPrice_1 | C100: =CONCATENATE("""",D100,"""",":","""","parcelassessmentwithoutdats_",LOWER(A100),"_",LOWER(B100),"""") -> "G100":"parcelassessmentwithoutdats_fuelfortemperaturecontrolinformation_productprice_1" | D100: G100 | E100: Fuel 2 for greehnouse temperature control price | F100: €/m3 | G100: 1
A101: fuelfortemperaturecontrolinformation | B101: productPrice_2 | C101: =CONCATENATE("""",D101,"""",":","""","parcelassessmentwithoutdats_",LOWER(A101),"_",LOWER(B101),"""") -> "G101":"parcelassessmentwithoutdats_fuelfortemperaturecontrolinformation_productprice_2" | D101: G101 | E101: Fuel 3 for greehnouse temperature control price | F101: €/m4 | G101: 1
A102: marketinformation | B102: electricityPrice | C102: =CONCATENATE("""",D102,"""",":","""","parcelassessmentwithoutdats_",LOWER(A102),"_",LOWER(B102),"""") -> "G102":"parcelassessmentwithoutdats_marketinformation_electricityprice" | D102: G102 | E102: Electricity price | F102: €/kWh | G102: 1
A103: marketinformation | B103: averageSalary | C103: =CONCATENATE("""",D103,"""",":","""","parcelassessmentwithoutdats_",LOWER(A103),"_",LOWER(B103),"""") -> "G103":"parcelassessmentwithoutdats_marketinformation_averagesalary" | D103: G103 | E103: Average salary (farmer and emloyees) | F103: €/h | G103: 1
A104: marketinformation | B104: averageProfessionalSalary | C104: =CONCATENATE("""",D104,"""",":","""","parcelassessmentwithoutdats_",LOWER(A104),"_",LOWER(B104),"""") -> "G104":"parcelassessmentwithoutdats_marketinformation_averageprofessionalsalary" | D104: G104 | E104: Average professional salary (agronomist, veterinary, ...) | F104: €/h | G104: 1
A105: marketinformation | B105: productMarketPrice | C105: =CONCATENATE("""",D105,"""",":","""","parcelassessmentwithoutdats_",LOWER(A105),"_",LOWER(B105),"""") -> "G105":"parcelassessmentwithoutdats_marketinformation_productmarketprice" | D105: G105 | E105: Sold product market price | F105: €/t | G105: 1
A106: marketinformation | B106: n_of_pesticide_used | C106: =CONCATENATE("""",D106,"""",":","""","parcelassessmentwithoutdats_",LOWER(A106),"_",LOWER(B106),"""") -> "G106":"parcelassessmentwithoutdats_marketinformation_n_of_pesticide_used" | D106: G106 | E106: Number of pesticide used (herbicides, fungicides, insecticides) | F106: n | G106: 1
A107: pesticidesusageinformation | B107: productPrice_0 | C107: =CONCATENATE("""",D107,"""",":","""","parcelassessmentwithoutdats_",LOWER(A107),"_",LOWER(B107),"""") -> "G107":"parcelassessmentwithoutdats_pesticidesusageinformation_productprice_0" | D107: G107 | E107: Pesticide 1 price | F107: €/kg | G107: 1
... A121: drugsusageinformation | B121: productPrice_2 | C121: =CONCATENATE("""",D121,"""",":","""","parcelassessmentwithoutdats_",LOWER(A121),"_",LOWER(B121),"""") -> "G121":"parcelassessmentwithoutdats_drugsusageinformation_productprice_2" | D121: G121 | E121: Drug n price | F121: €/g | G121: 1

Sheet Parcel 1 with DATSs
BJ1: yes
K2: PARCEL WITH DATSs | BJ2: no
G4: Identification | H4: Parcel Name
A9: Ivaylo Parent | B9: Jack Naming | G9: data | H9: u.m. | K9: value | L9: value
A10: parcelInformation | B10: parcelDimension | C10: =CONCATENATE("""",D10,"""",":","""","parcelassessmentwithdats_",LOWER($A10),"_",LOWER($B10),"""") -> "J10":"parcelassessmentwithdats_parcelinformation_parceldimension" | D10: J10 | E10: =CONCATENATE("""",F10,"""",":","""","parcelassessmentwithdats_",LOWER(A10),"_",LOWER(B10),"""") -> "K10":"parcelassessmentwithdats_parcelinformation_parceldimension" | F10: K10 | G10: Parcel dimension | H10: ha | I10: =CONCATENATE("""",J10,"""",":","""","parcelassessmentwithoutdats_",LOWER($A10),"_",LOWER($B10),"""") -> "L10":"parcelassessmentwithoutdats_parcelinformation_parceldimension" | J10: L10 | K10: 1 | L10: 1
A11: parcelInformation | B11: numberOfPlants | C11: =CONCATENATE("""",D11,"""",":","""","parcelassessmentwithdats_",LOWER($A11),"_",LOWER($B11),"""") -> "J11":"parcelassessmentwithdats_parcelinformation_numberofplants" | D11: J11 | E11: =CONCATENATE("""",F11,"""",":","""","parcelassessmentwithdats_",LOWER(A11),"_",LOWER(B11),"""") -> "K11":"parcelassessmentwithdats_parcelinformation_numberofplants" | F11: K11 | G11: Number of plants/trees | H11: n | I11: =CONCATENATE("""",J11,"""",":","""","parcelassessmentwithoutdats_",LOWER($A11),"_",LOWER($B11),"""") -> "L11":"parcelassessmentwithoutdats_parcelinformation_numberofplants" | J11: L11 | K11: 1 | L11: 1
A12: parcelInformation | B12: soilFractionSand | C12: =CONCATENATE("""",D12,"""",":","""","parcelassessmentwithdats_",LOWER($A12),"_",LOWER($B12),"""") -> "J12":"parcelassessmentwithdats_parcelinformation_soilfractionsand" | D12: J12 | E12: =CONCATENATE("""",F12,"""",":","""","parcelassessmentwithdats_",LOWER(A12),"_",LOWER(B12),"""") -> "K12":"parcelassessmentwithdats_parcelinformation_soilfractionsand" | F12: K12 | G12: Sand content in the soil | H12: % | I12: =CONCATENATE("""",J12,"""",":","""","parcelassessmentwithoutdats_",LOWER($A12),"_",LOWER($B12),"""") -> "L12":"parcelassessmentwithoutdats_parcelinformation_soilfractionsand" | J12: L12 | K12: 1 | L12: 1
A13: parcelInformation | B13: soilFractionClay | C13: =CONCATENATE("""",D13,"""",":","""","parcelassessmentwithdats_",LOWER($A13),"_",LOWER($B13),"""") -> "J13":"parcelassessmentwithdats_parcelinformation_soilfractionclay" | D13: J13 | E13: =CONCATENATE("""",F13,"""",":","""","parcelassessmentwithdats_",LOWER(A13),"_",LOWER(B13),"""") -> "K13":"parcelassessmentwithdats_parcelinformation_soilfractionclay" | F13: K13 | G13: Clay content in the soil | H13: % | I13: =CONCATENATE("""",J13,"""",":","""","parcelassessmentwithoutdats_",LOWER($A13),"_",LOWER($B13),"""") -> "L13":"parcelassessmentwithoutdats_parcelinformation_soilfractionclay" | J13: L13 | K13: 1 | L13: 1
A14: parcelInformation | B14: soilFractionSilt | C14: =CONCATENATE("""",D14,"""",":","""","parcelassessmentwithdats_",LOWER($A14),"_",LOWER($B14),"""") -> "J14":"parcelassessmentwithdats_parcelinformation_soilfractionsilt" | D14: J14 | E14: =CONCATENATE("""",F14,"""",":","""","parcelassessmentwithdats_",LOWER(A14),"_",LOWER(B14),"""") -> "K14":"parcelassessmentwithdats_parcelinformation_soilfractionsilt" | F14: K14 | G14: Silt content in the soil | H14: % | I14: =CONCATENATE("""",J14,"""",":","""","parcelassessmentwithoutdats_",LOWER($A14),"_",LOWER($B14),"""") -> "L14":"parcelassessmentwithoutdats_parcelinformation_soilfractionsilt" | J14: L14 | K14: 1 | L14: 1
A15: parcelInformation | B15: bulkDensity | C15: =CONCATENATE("""",D15,"""",":","""","parcelassessmentwithdats_",LOWER($A15),"_",LOWER($B15),"""") -> "J15":"parcelassessmentwithdats_parcelinformation_bulkdensity" | D15: J15 | E15: =CONCATENATE("""",F15,"""",":","""","parcelassessmentwithdats_",LOWER(A15),"_",LOWER(B15),"""") -> "K15":"parcelassessmentwithdats_parcelinformation_bulkdensity" | F15: K15 | G15: Soil Bulk Density | H15: g/cm3 | I15: =CONCATENATE("""",J15,"""",":","""","parcelassessmentwithoutdats_",LOWER($A15),"_",LOWER($B15),"""") -> "L15":"parcelassessmentwithoutdats_parcelinformation_bulkdensity" | J15: L15 | K15: 1 | L15: 1
A16: parcelInformation | B16: soilOrganicCarbon | C16: =CONCATENATE("""",D16,"""",":","""","parcelassessmentwithdats_",LOWER($A16),"_",LOWER($B16),"""") -> "J16":"parcelassessmentwithdats_parcelinformation_soilorganiccarbon" | D16: J16 | E16: =CONCATENATE("""",F16,"""",":","""","parcelassessmentwithdats_",LOWER(A16),"_",LOWER(B16),"""") -> "K16":"parcelassessmentwithdats_parcelinformation_soilorganiccarbon" | F16: K16 | G16: Soil Organic Carbon | H16: % | I16: =CONCATENATE("""",J16,"""",":","""","parcelassessmentwithoutdats_",LOWER($A16),"_",LOWER($B16),"""") -> "L16":"parcelassessmentwithoutdats_parcelinformation_soilorganiccarbon" | J16: L16 | K16: 1 | L16: 1
A17: parcelInformation | B17: numberOfAnimals | C17: =CONCATENATE("""",D17,"""",":","""","parcelassessmentwithdats_",LOWER($A17),"_",LOWER($B17),"""") -> "J17":"parcelassessmentwithdats_parcelinformation_numberofanimals" | D17: J17 | E17: =CONCATENATE("""",F17,"""",":","""","parcelassessmentwithdats_",LOWER(A17),"_",LOWER(B17),"""") -> "K17":"parcelassessmentwithdats_parcelinformation_numberofanimals" | F17: K17 | G17: Number of animals | H17: n | I17: =CONCATENATE("""",J17,"""",":","""","parcelassessmentwithoutdats_",LOWER($A17),"_",LOWER($B17),"""") -> "L17":"parcelassessmentwithoutdats_parcelinformation_numberofanimals" | J17: L17 | K17: 1 | L17: 1
A18: parcelInformation | B18: livestockUnits | C18: =CONCATENATE("""",D18,"""",":","""","parcelassessmentwithdats_",LOWER($A18),"_",LOWER($B18),"""") -> "J18":"parcelassessmentwithdats_parcelinformation_livestockunits" | D18: J18 | E18: =CONCATENATE("""",F18,"""",":","""","parcelassessmentwithdats_",LOWER(A18),"_",LOWER(B18),"""") -> "K18":"parcelassessmentwithdats_parcelinformation_livestockunits" | F18: K18 | G18: Livestock units per hectare | H18: LSU/ha | I18: =CONCATENATE("""",J18,"""",":","""","parcelassessmentwithoutdats_",LOWER($A18),"_",LOWER($B18),"""") -> "L18":"parcelassessmentwithoutdats_parcelinformation_livestockunits" | J18: L18 | K18: 1 | L18: 1
A19: parcelInformation | B19: numberOfBeehives | C19: =CONCATENATE("""",D19,"""",":","""","parcelassessmentwithdats_",LOWER($A19),"_",LOWER($B19),"""") -> "J19":"parcelassessmentwithdats_parcelinformation_numberofbeehives" | D19: J19 | E19: =CONCATENATE("""",F19,"""",":","""","parcelassessmentwithdats_",LOWER(A19),"_",LOWER(B19),"""") -> "K19":"parcelassessmentwithdats_parcelinformation_numberofbeehives" | F19: K19 | G19: Number of beehives | H19: n | I19: =CONCATENATE("""",J19,"""",":","""","parcelassessmentwithoutdats_",LOWER($A19),"_",LOWER($B19),"""") -> "L19":"parcelassessmentwithoutdats_parcelinformation_numberofbeehives" | J19: L19 | K19: 1 | L19: 1
A20: parcelInformation | B20: aquacultureArea | C20: =CONCATENATE("""",D20,"""",":","""","parcelassessmentwithdats_",LOWER($A20),"_",LOWER($B20),"""") -> "J20":"parcelassessmentwithdats_parcelinformation_aquaculturearea" | D20: J20 | E20: =CONCATENATE("""",F20,"""",":","""","parcelassessmentwithdats_",LOWER(A20),"_",LOWER(B20),"""") -> "K20":"parcelassessmentwithdats_parcelinformation_aquaculturearea" | F20: K20 | G20: Area under aquaculture | H20: m2 | I20: =CONCATENATE("""",J20,"""",":","""","parcelassessmentwithoutdats_",LOWER($A20),"_",LOWER($B20),"""") -> "L20":"parcelassessmentwithoutdats_parcelinformation_aquaculturearea" | J20: L20 | K20: 1 | L20: 1
C21: =CONCATENATE("""",D21,"""",":","""","parcelassessmentwithdats_",LOWER($A21),"_",LOWER($B21),"""") -> "J21":"parcelassessmentwithdats__" | D21: J21 | E21: =CONCATENATE("""",F21,"""",":","""","parcelassessmentwithdats_",LOWER(A21),"_",LOWER(B21),"""") -> "K21":"parcelassessmentwithdats__" | F21: K21 | I21: =CONCATENATE("""",J21,"""",":","""","parcelassessmentwithoutdats_",LOWER($A21),"_",LOWER($B21),"""") -> "L21":"parcelassessmentwithoutdats__" | J21: L21
C22: =CONCATENATE("""",D22,"""",":","""","parcelassessmentwithdats_",LOWER($A22),"_",LOWER($B22),"""") -> "J22":"parcelassessmentwithdats__" | D22: J22 | E22: =CONCATENATE("""",F22,"""",":","""","parcelassessmentwithdats_",LOWER(A22),"_",LOWER(B22),"""") -> "K22":"parcelassessmentwithdats__" | F22: K22 | I22: =CONCATENATE("""",J22,"""",":","""","parcelassessmentwithoutdats_",LOWER($A22),"_",LOWER($B22),"""") -> "L22":"parcelassessmentwithoutdats__" | J22: L22 | K22: Year 1 | L22: Year 1 | N22: Year 2 | Q22: Year 3
C23: =CONCATENATE("""",D23,"""",":","""","parcelassessmentwithdats_",LOWER($A23),"_",LOWER($B23),"""") -> "J23":"parcelassessmentwithdats__" | D23: J23 | E23: =CONCATENATE("""",F23,"""",":","""","parcelassessmentwithdats_",LOWER(A23),"_",LOWER(B23),"""") -> "K23":"parcelassessmentwithdats__" | F23: K23 | G23: data | H23: u.m. | I23: =CONCATENATE("""",J23,"""",":","""","parcelassessmentwithoutdats_",LOWER($A23),"_",LOWER($B23),"""") -> "L23":"parcelassessmentwithoutdats__" | J23: L23 | K23: With DATSs | L23: With DATSs | N23: With DATSs | O23: Notes | Q23: With DATSs | R23: Notes
A24: waterUsageInformation | B24: waterUsageForIrrigation | C24: =CONCATENATE("""",D24,"""",":","""","parcelassessmentwithdats_",LOWER($A24),"_",LOWER($B24),"""") -> "J24":"parcelassessmentwithdats_waterusageinformation_waterusageforirrigation" | D24: J24 | E24: =CONCATENATE("""",F24,"""",":","""","parcelassessmentwithdats_",LOWER(A24),"_",LOWER(B24),"""") -> "K24":"parcelassessmentwithdats_waterusageinformation_waterusageforirrigation" | F24: K24 | G24: Irrigation | H24: m3 | I24: =CONCATENATE("""",J24,"""",":","""","parcelassessmentwithoutdats_",LOWER($A24),"_",LOWER($B24),"""") -> "L24":"parcelassessmentwithoutdats_waterusageinformation_waterusageforirrigation" | J24: L24 | K24: 1 | L24: 1
A25: waterUsageInformation | B25: waterUsageForFertigation | C25: =CONCATENATE("""",D25,"""",":","""","parcelassessmentwithdats_",LOWER($A25),"_",LOWER($B25),"""") -> "J25":"parcelassessmentwithdats_waterusageinformation_waterusageforfertigation" | D25: J25 | E25: =CONCATENATE("""",F25,"""",":","""","parcelassessmentwithdats_",LOWER(A25),"_",LOWER(B25),"""") -> "K25":"parcelassessmentwithdats_waterusageinformation_waterusageforfertigation" | F25: K25 | G25: Fertigation | H25: m3 | I25: =CONCATENATE("""",J25,"""",":","""","parcelassessmentwithoutdats_",LOWER($A25),"_",LOWER($B25),"""") -> "L25":"parcelassessmentwithoutdats_waterusageinformation_waterusageforfertigation" | J25: L25 | K25: 1 | L25: 1
A26: waterUsageInformation | B26: waterUsageForPestDilution | C26: =CONCATENATE("""",D26,"""",":","""","parcelassessmentwithdats_",LOWER($A26),"_",LOWER($B26),"""") -> "J26":"parcelassessmentwithdats_waterusageinformation_waterusageforpestdilution" | D26: J26 | E26: =CONCATENATE("""",F26,"""",":","""","parcelassessmentwithdats_",LOWER(A26),"_",LOWER(B26),"""") -> "K26":"parcelassessmentwithdats_waterusageinformation_waterusageforpestdilution" | F26: K26 | G26: Pest dilution | H26: m3 | I26: =CONCATENATE("""",J26,"""",":","""","parcelassessmentwithoutdats_",LOWER($A26),"_",LOWER($B26),"""") -> "L26":"parcelassessmentwithoutdats_waterusageinformation_waterusageforpestdilution" | J26: L26 | K26: 1 | L26: 1
A27: waterUsageInformation | B27: waterUsageForCleaning | C27: =CONCATENATE("""",D27,"""",":","""","parcelassessmentwithdats_",LOWER($A27),"_",LOWER($B27),"""") -> "J27":"parcelassessmentwithdats_waterusageinformation_waterusageforcleaning" | D27: J27 | E27: =CONCATENATE("""",F27,"""",":","""","parcelassessmentwithdats_",LOWER(A27),"_",LOWER(B27),"""") -> "K27":"parcelassessmentwithdats_waterusageinformation_waterusageforcleaning" | F27: K27 | G27: Cleaning | H27: m3 | I27: =CONCATENATE("""",J27,"""",":","""","parcelassessmentwithoutdats_",LOWER($A27),"_",LOWER($B27),"""") -> "L27":"parcelassessmentwithoutdats_waterusageinformation_waterusageforcleaning" | J27: L27 | K27: 1 | L27: 1
A28: waterUsageInformation | B28: waterUsageForDrinking | C28: =CONCATENATE("""",D28,"""",":","""","parcelassessmentwithdats_",LOWER($A28),"_",LOWER($B28),"""") -> "J28":"parcelassessmentwithdats_waterusageinformation_waterusagefordrinking" | D28: J28 | E28: =CONCATENATE("""",F28,"""",":","""","parcelassessmentwithdats_",LOWER(A28),"_",LOWER(B28),"""") -> "K28":"parcelassessmentwithdats_waterusageinformation_waterusagefordrinking" | F28: K28 | G28: Drinking | H28: m3 | I28: =CONCATENATE("""",J28,"""",":","""","parcelassessmentwithoutdats_",LOWER($A28),"_",LOWER($B28),"""") -> "L28":"parcelassessmentwithoutdats_waterusageinformation_waterusagefordrinking" | J28: L28 | K28: 1 | L28: 1
A29: waterUsageInformation | B29: totalWaterUsage | C29: =CONCATENATE("""",D29,"""",":","""","parcelassessmentwithdats_",LOWER($A29),"_",LOWER($B29),"""") -> "J29":"parcelassessmentwithdats_waterusageinformation_totalwaterusage" | D29: J29 | E29: =CONCATENATE("""",F29,"""",":","""","parcelassessmentwithdats_",LOWER(A29),"_",LOWER(B29),"""") -> "K29":"parcelassessmentwithdats_waterusageinformation_totalwaterusage" | F29: K29 | G29: Total water used | H29: m3 | I29: =CONCATENATE("""",J29,"""",":","""","parcelassessmentwithoutdats_",LOWER($A29),"_",LOWER($B29),"""") -> "L29":"parcelassessmentwithoutdats_waterusageinformation_totalwaterusage" | J29: L29 | K29: 1 | L29: 1
C30: =CONCATENATE("""",D30,"""",":","""","parcelassessmentwithdats_",LOWER($A30),"_",LOWER($B30),"""") -> "J30":"parcelassessmentwithdats__" | D30: J30 | E30: =CONCATENATE("""",F30,"""",":","""","parcelassessmentwithdats_",LOWER(A30),"_",LOWER(B30),"""") -> "K30":"parcelassessmentwithdats__" | F30: K30 | I30: =CONCATENATE("""",J30,"""",":","""","parcelassessmentwithoutdats_",LOWER($A30),"_",LOWER($B30),"""") -> "L30":"parcelassessmentwithoutdats__" | J30: L30
C31: =CONCATENATE("""",D31,"""",":","""","parcelassessmentwithdats_",LOWER($A31),"_",LOWER($B31),"""") -> "J31":"parcelassessmentwithdats__" | D31: J31 | E31: =CONCATENATE("""",F31,"""",":","""","parcelassessmentwithdats_",LOWER(A31),"_",LOWER(B31),"""") -> "K31":"parcelassessmentwithdats__" | F31: K31 | I31: =CONCATENATE("""",J31,"""",":","""","parcelassessmentwithoutdats_",LOWER($A31),"_",LOWER($B31),"""") -> "L31":"parcelassessmentwithoutdats__" | J31: L31 | K31: Year 1 | L31: Year 1 | N31: Year 2 | Q31: Year 3
C32: =CONCATENATE("""",D32,"""",":","""","parcelassessmentwithdats_",LOWER($A32),"_",LOWER($B32),"""") -> "J32":"parcelassessmentwithdats__" | D32: J32 | E32: =CONCATENATE("""",F32,"""",":","""","parcelassessmentwithdats_",LOWER(A32),"_",LOWER(B32),"""") -> "K32":"parcelassessmentwithdats__" | F32: K32 | G32: data | H32: u.m. | I32: =CONCATENATE("""",J32,"""",":","""","parcelassessmentwithoutdats_",LOWER($A32),"_",LOWER($B32),"""") -> "L32":"parcelassessmentwithoutdats__" | J32: L32 | K32: With DATSs | L32: Without DATSs | N32: With DATSs | O32: Notes | Q32: With DATSs | R32: Notes
A33: fuelUsageInformation | B33: fuelUsageForFertilisation | C33: =CONCATENATE("""",D33,"""",":","""","parcelassessmentwithdats_",LOWER($A33),"_",LOWER($B33),"""") -> "J33":"parcelassessmentwithdats_fuelusageinformation_fuelusageforfertilisation" | D33: J33 | E33: =CONCATENATE("""",F33,"""",":","""","parcelassessmentwithdats_",LOWER(A33),"_",LOWER(B33),"""") -> "K33":"parcelassessmentwithdats_fuelusageinformation_fuelusageforfertilisation" | F33: K33 | G33: Fertilisation | H33: l | I33: =CONCATENATE("""",J33,"""",":","""","parcelassessmentwithoutdats_",LOWER($A33),"_",LOWER($B33),"""") -> "L33":"parcelassessmentwithoutdats_fuelusageinformation_fuelusageforfertilisation" | J33: L33 | K33: 1 | L33: 1
A34: fuelUsageInformation | B34: fuelUsageForPesticides | C34: =CONCATENATE("""",D34,"""",":","""","parcelassessmentwithdats_",LOWER($A34),"_",LOWER($B34),"""") -> "J34":"parcelassessmentwithdats_fuelusageinformation_fuelusageforpesticides" | D34: J34 | E34: =CONCATENATE("""",F34,"""",":","""","parcelassessmentwithdats_",LOWER(A34),"_",LOWER(B34),"""") -> "K34":"parcelassessmentwithdats_fuelusageinformation_fuelusageforpesticides" | F34: K34 | G34: Pesticides | H34: l | I34: =CONCATENATE("""",J34,"""",":","""","parcelassessmentwithoutdats_",LOWER($A34),"_",LOWER($B34),"""") -> "L34":"parcelassessmentwithoutdats_fuelusageinformation_fuelusageforpesticides" | J34: L34 | K34: 1 | L34: 1
A35: fuelUsageInformation | B35: fuelUsageForIrrigation | C35: =CONCATENATE("""",D35,"""",":","""","parcelassessmentwithdats_",LOWER($A35),"_",LOWER($B35),"""") -> "J35":"parcelassessmentwithdats_fuelusageinformation_fuelusageforirrigation" | D35: J35 | E35: =CONCATENATE("""",F35,"""",":","""","parcelassessmentwithdats_",LOWER(A35),"_",LOWER(B35),"""") -> "K35":"parcelassessmentwithdats_fuelusageinformation_fuelusageforirrigation" | F35: K35 | G35: Irrigation | H35: l | I35: =CONCATENATE("""",J35,"""",":","""","parcelassessmentwithoutdats_",LOWER($A35),"_",LOWER($B35),"""") -> "L35":"parcelassessmentwithoutdats_fuelusageinformation_fuelusageforirrigation" | J35: L35 | K35: 1 | L35: 1
A36: fuelUsageInformation | B36: fuelUsageForSowing | C36: =CONCATENATE("""",D36,"""",":","""","parcelassessmentwithdats_",LOWER($A36),"_",LOWER($B36),"""") -> "J36":"parcelassessmentwithdats_fuelusageinformation_fuelusageforsowing" | D36: J36 | E36: =CONCATENATE("""",F36,"""",":","""","parcelassessmentwithdats_",LOWER(A36),"_",LOWER(B36),"""") -> "K36":"parcelassessmentwithdats_fuelusageinformation_fuelusageforsowing" | F36: K36 | G36: Sowing / Planting | H36: l | I36: =CONCATENATE("""",J36,"""",":","""","parcelassessmentwithoutdats_",LOWER($A36),"_",LOWER($B36),"""") -> "L36":"parcelassessmentwithoutdats_fuelusageinformation_fuelusageforsowing" | J36: L36 | K36: 1 | L36: 1
A37: fuelUsageInformation | B37: fuelUsageForPruning | C37: =CONCATENATE("""",D37,"""",":","""","parcelassessmentwithdats_",LOWER($A37),"_",LOWER($B37),"""") -> "J37":"parcelassessmentwithdats_fuelusageinformation_fuelusageforpruning" | D37: J37 | E37: =CONCATENATE("""",F37,"""",":","""","parcelassessmentwithdats_",LOWER(A37),"_",LOWER(B37),"""") -> "K37":"parcelassessmentwithdats_fuelusageinformation_fuelusageforpruning" | F37: K37 | G37: Temperature and Humidity Control | H37: l | I37: =CONCATENATE("""",J37,"""",":","""","parcelassessmentwithoutdats_",LOWER($A37),"_",LOWER($B37),"""") -> "L37":"parcelassessmentwithoutdats_fuelusageinformation_fuelusageforpruning" | J37: L37 | K37: 1 | L37: 1
A38: fuelUsageInformation | B38: fuelUsageForTemperatureHumidityControl | C38: =CONCATENATE("""",D38,"""",":","""","parcelassessmentwithdats_",LOWER($A38),"_",LOWER($B38),"""") -> "J38":"parcelassessmentwithdats_fuelusageinformation_fuelusagefortemperaturehumiditycontrol" | D38: J38 | E38: =CONCATENATE("""",F38,"""",":","""","parcelassessmentwithdats_",LOWER(A38),"_",LOWER(B38),"""") -> "K38":"parcelassessmentwithdats_fuelusageinformation_fuelusagefortemperaturehumiditycontrol" | F38: K38 | G38: Pruning | H38: l | I38: =CONCATENATE("""",J38,"""",":","""","parcelassessmentwithoutdats_",LOWER($A38),"_",LOWER($B38),"""") -> "L38":"parcelassessmentwithoutdats_fuelusageinformation_fuelusagefortemperaturehumiditycontrol" | J38: L38 | K38: 1 | L38: 1
A39: fuelUsageInformation | B39: fuelUsageForBeehivesVisits | C39: =CONCATENATE("""",D39,"""",":","""","parcelassessmentwithdats_",LOWER($A39),"_",LOWER($B39),"""") -> "J39":"parcelassessmentwithdats_fuelusageinformation_fuelusageforbeehivesvisits" | D39: J39 | E39: =CONCATENATE("""",F39,"""",":","""","parcelassessmentwithdats_",LOWER(A39),"_",LOWER(B39),"""") -> "K39":"parcelassessmentwithdats_fuelusageinformation_fuelusageforbeehivesvisits" | F39: K39 | G39: Beehives visits | H39: l | I39: =CONCATENATE("""",J39,"""",":","""","parcelassessmentwithoutdats_",LOWER($A39),"_",LOWER($B39),"""") -> "L39":"parcelassessmentwithoutdats_fuelusageinformation_fuelusageforbeehivesvisits" | J39: L39 | K39: 1 | L39: 1
A40: fuelUsageInformation | B40: fuelUsageForTransportingOysters | C40: =CONCATENATE("""",D40,"""",":","""","parcelassessmentwithdats_",LOWER($A40),"_",LOWER($B40),"""") -> "J40":"parcelassessmentwithdats_fuelusageinformation_fuelusagefortransportingoysters" | D40: J40 | E40: =CONCATENATE("""",F40,"""",":","""","parcelassessmentwithdats_",LOWER(A40),"_",LOWER(B40),"""") -> "K40":"parcelassessmentwithdats_fuelusageinformation_fuelusagefortransportingoysters" | F40: K40 | G40: Transporting oysters to the laboratory | H40: l | I40: =CONCATENATE("""",J40,"""",":","""","parcelassessmentwithoutdats_",LOWER($A40),"_",LOWER($B40),"""") -> "L40":"parcelassessmentwithoutdats_fuelusageinformation_fuelusagefortransportingoysters" | J40: L40 | K40: 1 | L40: 1
A41: fuelUsageInformation | B41: fuelUsageForMilking | C41: =CONCATENATE("""",D41,"""",":","""","parcelassessmentwithdats_",LOWER($A41),"_",LOWER($B41),"""") -> "J41":"parcelassessmentwithdats_fuelusageinformation_fuelusageformilking" | D41: J41 | E41: =CONCATENATE("""",F41,"""",":","""","parcelassessmentwithdats_",LOWER(A41),"_",LOWER(B41),"""") -> "K41":"parcelassessmentwithdats_fuelusageinformation_fuelusageformilking" | F41: K41 | G41: Milking | H41: l | I41: =CONCATENATE("""",J41,"""",":","""","parcelassessmentwithoutdats_",LOWER($A41),"_",LOWER($B41),"""") -> "L41":"parcelassessmentwithoutdats_fuelusageinformation_fuelusageformilking" | J41: L41 | K41: 1 | L41: 1
A42: fuelUsageInformation | B42: fuelUsageForFeeding | C42: =CONCATENATE("""",D42,"""",":","""","parcelassessmentwithdats_",LOWER($A42),"_",LOWER($B42),"""") -> "J42":"parcelassessmentwithdats_fuelusageinformation_fuelusageforfeeding" | D42: J42 | E42: =CONCATENATE("""",F42,"""",":","""","parcelassessmentwithdats_",LOWER(A42),"_",LOWER(B42),"""") -> "K42":"parcelassessmentwithdats_fuelusageinformation_fuelusageforfeeding" | F42: K42 | G42: Feeding | H42: l | I42: =CONCATENATE("""",J42,"""",":","""","parcelassessmentwithoutdats_",LOWER($A42),"_",LOWER($B42),"""") -> "L42":"parcelassessmentwithoutdats_fuelusageinformation_fuelusageforfeeding" | J42: L42 | K42: 1 | L42: 1
A43: fuelUsageInformation | B43: totalFuelUsage | C43: =CONCATENATE("""",D43,"""",":","""","parcelassessmentwithdats_",LOWER($A43),"_",LOWER($B43),"""") -> "J43":"parcelassessmentwithdats_fuelusageinformation_totalfuelusage" | D43: J43 | E43: =CONCATENATE("""",F43,"""",":","""","parcelassessmentwithdats_",LOWER(A43),"_",LOWER(B43),"""") -> "K43":"parcelassessmentwithdats_fuelusageinformation_totalfuelusage" | F43: K43 | G43: Total fuel used | H43: l | I43: =CONCATENATE("""",J43,"""",":","""","parcelassessmentwithoutdats_",LOWER($A43),"_",LOWER($B43),"""") -> "L43":"parcelassessmentwithoutdats_fuelusageinformation_totalfuelusage" | J43: L43 | K43: 1 | L43: 1
C44: =CONCATENATE("""",D44,"""",":","""","parcelassessmentwithdats_",LOWER($A44),"_",LOWER($B44),"""") -> "J44":"parcelassessmentwithdats__" | D44: J44 | E44: =CONCATENATE("""",F44,"""",":","""","parcelassessmentwithdats_",LOWER(A44),"_",LOWER(B44),"""") -> "K44":"parcelassessmentwithdats__" | F44: K44 | I44: =CONCATENATE("""",J44,"""",":","""","parcelassessmentwithoutdats_",LOWER($A44),"_",LOWER($B44),"""") -> "L44":"parcelassessmentwithoutdats__" | J44: L44
C45: =CONCATENATE("""",D45,"""",":","""","parcelassessmentwithdats_",LOWER($A45),"_",LOWER($B45),"""") -> "J45":"parcelassessmentwithdats__" | D45: J45 | E45: =CONCATENATE("""",F45,"""",":","""","parcelassessmentwithdats_",LOWER(A45),"_",LOWER(B45),"""") -> "K45":"parcelassessmentwithdats__" | F45: K45 | I45: =CONCATENATE("""",J45,"""",":","""","parcelassessmentwithoutdats_",LOWER($A45),"_",LOWER($B45),"""") -> "L45":"parcelassessmentwithoutdats__" | J45: L45 | K45: Year 1 | L45: Year 1 | N45: Year 2 | Q45: Year 3
C46: =CONCATENATE("""",D46,"""",":","""","parcelassessmentwithdats_",LOWER($A46),"_",LOWER($B46),"""") -> "J46":"parcelassessmentwithdats__" | D46: J46 | E46: =CONCATENATE("""",F46,"""",":","""","parcelassessmentwithdats_",LOWER(A46),"_",LOWER(B46),"""") -> "K46":"parcelassessmentwithdats__" | F46: K46 | G46: data | I46: =CONCATENATE("""",J46,"""",":","""","parcelassessmentwithoutdats_",LOWER($A46),"_",LOWER($B46),"""") -> "L46":"parcelassessmentwithoutdats__" | J46: L46 | K46: With DATSs | L46: Without DATSs | N46: With DATSs | O46: Notes | Q46: With DATSs | R46: Notes
A47: fuelForTemperatureControlInformation | B47: productName_0 | C47: =CONCATENATE("""",D47,"""",":","""","parcelassessmentwithdats_",LOWER($A47),"_",LOWER($B47),"""") -> "J47":"parcelassessmentwithdats_fuelfortemperaturecontrolinformation_productname_0" | D47: J47 | E47: =CONCATENATE("""",F47,"""",":","""","parcelassessmentwithdats_",LOWER(A47),"_",LOWER(B47),"""") -> "K47":"parcelassessmentwithdats_fuelfortemperaturecontrolinformation_productname_0" | F47: K47 | G47: Fuel 1 | H47: Name fuel 1 | I47: =CONCATENATE("""",J47,"""",":","""","parcelassessmentwithoutdats_",LOWER($A47),"_",LOWER($B47),"""") -> "L47":"parcelassessmentwithoutdats_fuelfortemperaturecontrolinformation_productname_0" | J47: L47 | K47: 1 | L47: 1
A48: fuelForTemperatureControlInformation | B48: quantity_0 | C48: =CONCATENATE("""",D48,"""",":","""","parcelassessmentwithdats_",LOWER($A48),"_",LOWER($B48),"""") -> "J48":"parcelassessmentwithdats_fuelfortemperaturecontrolinformation_quantity_0" | D48: J48 | E48: =CONCATENATE("""",F48,"""",":","""","parcelassessmentwithdats_",LOWER(A48),"_",LOWER(B48),"""") -> "K48":"parcelassessmentwithdats_fuelfortemperaturecontrolinformation_quantity_0" | F48: K48 | G48: Fuel 1 | H48: Quantity | I48: =CONCATENATE("""",J48,"""",":","""","parcelassessmentwithoutdats_",LOWER($A48),"_",LOWER($B48),"""") -> "L48":"parcelassessmentwithoutdats_fuelfortemperaturecontrolinformation_quantity_0" | J48: L48 | K48: 1 | L48: 1
A49: fuelForTemperatureControlInformation | B49: productName_1 | C49: =CONCATENATE("""",D49,"""",":","""","parcelassessmentwithdats_",LOWER($A49),"_",LOWER($B49),"""") -> "J49":"parcelassessmentwithdats_fuelfortemperaturecontrolinformation_productname_1" | D49: J49 | E49: =CONCATENATE("""",F49,"""",":","""","parcelassessmentwithdats_",LOWER(A49),"_",LOWER(B49),"""") -> "K49":"parcelassessmentwithdats_fuelfortemperaturecontrolinformation_productname_1" | F49: K49 | G49: Fuel 2 | H49: Name fuel 2 | I49: =CONCATENATE("""",J49,"""",":","""","parcelassessmentwithoutdats_",LOWER($A49),"_",LOWER($B49),"""") -> "L49":"parcelassessmentwithoutdats_fuelfortemperaturecontrolinformation_productname_1" | J49: L49 | K49: 1 | L49: 1
A50: fuelForTemperatureControlInformation | B50: quantity_1 | C50: =CONCATENATE("""",D50,"""",":","""","parcelassessmentwithdats_",LOWER($A50),"_",LOWER($B50),"""") -> "J50":"parcelassessmentwithdats_fuelfortemperaturecontrolinformation_quantity_1" | D50: J50 | E50: =CONCATENATE("""",F50,"""",":","""","parcelassessmentwithdats_",LOWER(A50),"_",LOWER(B50),"""") -> "K50":"parcelassessmentwithdats_fuelfortemperaturecontrolinformation_quantity_1" | F50: K50 | G50: Fuel 2 | H50: Quantity | I50: =CONCATENATE("""",J50,"""",":","""","parcelassessmentwithoutdats_",LOWER($A50),"_",LOWER($B50),"""") -> "L50":"parcelassessmentwithoutdats_fuelfortemperaturecontrolinformation_quantity_1" | J50: L50 | K50: 1 | L50: 1
A51: fuelForTemperatureControlInformation | B51: productName_2 | C51: =CONCATENATE("""",D51,"""",":","""","parcelassessmentwithdats_",LOWER($A51),"_",LOWER($B51),"""") -> "J51":"parcelassessmentwithdats_fuelfortemperaturecontrolinformation_productname_2" | D51: J51 | E51: =CONCATENATE("""",F51,"""",":","""","parcelassessmentwithdats_",LOWER(A51),"_",LOWER(B51),"""") -> "K51":"parcelassessmentwithdats_fuelfortemperaturecontrolinformation_productname_2" | F51: K51 | G51: Fuel n | H51: Name fuel n | I51: =CONCATENATE("""",J51,"""",":","""","parcelassessmentwithoutdats_",LOWER($A51),"_",LOWER($B51),"""") -> "L51":"parcelassessmentwithoutdats_fuelfortemperaturecontrolinformation_productname_2" | J51: L51 | K51: 1 | L51: 1
A52: fuelForTemperatureControlInformation | B52: quantity_2 | C52: =CONCATENATE("""",D52,"""",":","""","parcelassessmentwithdats_",LOWER($A52),"_",LOWER($B52),"""") -> "J52":"parcelassessmentwithdats_fuelfortemperaturecontrolinformation_quantity_2" | D52: J52 | E52: =CONCATENATE("""",F52,"""",":","""","parcelassessmentwithdats_",LOWER(A52),"_",LOWER(B52),"""") -> "K52":"parcelassessmentwithdats_fuelfortemperaturecontrolinformation_quantity_2" | F52: K52 | G52: Fuel n | H52: Quantity | I52: =CONCATENATE("""",J52,"""",":","""","parcelassessmentwithoutdats_",LOWER($A52),"_",LOWER($B52),"""") -> "L52":"parcelassessmentwithoutdats_fuelfortemperaturecontrolinformation_quantity_2" | J52: L52 | K52: 1 | L52: 1
A53: fuelForTemperatureControlInformation | B53: productName_3 | C53: =CONCATENATE("""",D53,"""",":","""","parcelassessmentwithdats_",LOWER($A53),"_",LOWER($B53),"""") -> "J53":"parcelassessmentwithdats_fuelfortemperaturecontrolinformation_productname_3" | D53: J53 | E53: =CONCATENATE("""",F53,"""",":","""","parcelassessmentwithdats_",LOWER(A53),"_",LOWER(B53),"""") -> "K53":"parcelassessmentwithdats_fuelfortemperaturecontrolinformation_productname_3" | F53: K53 | G53: Fuel 1 | H53: Name fuel 1 | I53: =CONCATENATE("""",J53,"""",":","""","parcelassessmentwithoutdats_",LOWER($A53),"_",LOWER($B53),"""") -> "L53":"parcelassessmentwithoutdats_fuelfortemperaturecontrolinformation_productname_3" | J53: L53 | K53: 1 | L53: 1
A54: fuelForTemperatureControlInformation | B54: quantity_3 | C54: =CONCATENATE("""",D54,"""",":","""","parcelassessmentwithdats_",LOWER($A54),"_",LOWER($B54),"""") -> "J54":"parcelassessmentwithdats_fuelfortemperaturecontrolinformation_quantity_3" | D54: J54 | E54: =CONCATENATE("""",F54,"""",":","""","parcelassessmentwithdats_",LOWER(A54),"_",LOWER(B54),"""") -> "K54":"parcelassessmentwithdats_fuelfortemperaturecontrolinformation_quantity_3" | F54: K54 | G54: Fuel 1 | H54: Quantity | I54: =CONCATENATE("""",J54,"""",":","""","parcelassessmentwithoutdats_",LOWER($A54),"_",LOWER($B54),"""") -> "L54":"parcelassessmentwithoutdats_fuelfortemperaturecontrolinformation_quantity_3" | J54: L54 | K54: 1 | L54: 1
A55: fuelForTemperatureControlInformation | B55: productName_4 | C55: =CONCATENATE("""",D55,"""",":","""","parcelassessmentwithdats_",LOWER($A55),"_",LOWER($B55),"""") -> "J55":"parcelassessmentwithdats_fuelfortemperaturecontrolinformation_productname_4" | D55: J55 | E55: =CONCATENATE("""",F55,"""",":","""","parcelassessmentwithdats_",LOWER(A55),"_",LOWER(B55),"""") -> "K55":"parcelassessmentwithdats_fuelfortemperaturecontrolinformation_productname_4" | F55: K55 | G55: Fuel 2 | H55: Name fuel 2 | I55: =CONCATENATE("""",J55,"""",":","""","parcelassessmentwithoutdats_",LOWER($A55),"_",LOWER($B55),"""") -> "L55":"parcelassessmentwithoutdats_fuelfortemperaturecontrolinformation_productname_4" | J55: L55 | K55: 1 | L55: 1
A56: fuelForTemperatureControlInformation | B56: quantity_4 | C56: =CONCATENATE("""",D56,"""",":","""","parcelassessmentwithdats_",LOWER($A56),"_",LOWER($B56),"""") -> "J56":"parcelassessmentwithdats_fuelfortemperaturecontrolinformation_quantity_4" | D56: J56 | E56: =CONCATENATE("""",F56,"""",":","""","parcelassessmentwithdats_",LOWER(A56),"_",LOWER(B56),"""") -> "K56":"parcelassessmentwithdats_fuelfortemperaturecontrolinformation_quantity_4" | F56: K56 | G56: Fuel 2 | H56: Quantity | I56: =CONCATENATE("""",J56,"""",":","""","parcelassessmentwithoutdats_",LOWER($A56),"_",LOWER($B56),"""") -> "L56":"parcelassessmentwithoutdats_fuelfortemperaturecontrolinformation_quantity_4" | J56: L56 | K56: 1 | L56: 1
A57: fuelForTemperatureControlInformation | B57: productName_5 | C57: =CONCATENATE("""",D57,"""",":","""","parcelassessmentwithdats_",LOWER($A57),"_",LOWER($B57),"""") -> "J57":"parcelassessmentwithdats_fuelfortemperaturecontrolinformation_productname_5" | D57: J57 | E57: =CONCATENATE("""",F57,"""",":","""","parcelassessmentwithdats_",LOWER(A57),"_",LOWER(B57),"""") -> "K57":"parcelassessmentwithdats_fuelfortemperaturecontrolinformation_productname_5" | F57: K57 | G57: Fuel n | H57: Name fuel n | I57: =CONCATENATE("""",J57,"""",":","""","parcelassessmentwithoutdats_",LOWER($A57),"_",LOWER($B57),"""") -> "L57":"parcelassessmentwithoutdats_fuelfortemperaturecontrolinformation_productname_5" | J57: L57 | K57: 1 | L57: 1
A58: fuelForTemperatureControlInformation | B58: quantity_5 | C58: =CONCATENATE("""",D58,"""",":","""","parcelassessmentwithdats_",LOWER($A58),"_",LOWER($B58),"""") -> "J58":"parcelassessmentwithdats_fuelfortemperaturecontrolinformation_quantity_5" | D58: J58 | E58: =CONCATENATE("""",F58,"""",":","""","parcelassessmentwithdats_",LOWER(A58),"_",LOWER(B58),"""") -> "K58":"parcelassessmentwithdats_fuelfortemperaturecontrolinformation_quantity_5" | F58: K58 | G58: Fuel n | H58: Quantity | I58: =CONCATENATE("""",J58,"""",":","""","parcelassessmentwithoutdats_",LOWER($A58),"_",LOWER($B58),"""") -> "L58":"parcelassessmentwithoutdats_fuelfortemperaturecontrolinformation_quantity_5" | J58: L58 | K58: 1 | L58: 1
C59: =CONCATENATE("""",D59,"""",":","""","parcelassessmentwithdats_",LOWER($A59),"_",LOWER($B59),"""") -> "J59":"parcelassessmentwithdats__" | D59: J59 | E59: =CONCATENATE("""",F59,"""",":","""","parcelassessmentwithdats_",LOWER(A59),"_",LOWER(B59),"""") -> "K59":"parcelassessmentwithdats__" | F59: K59 | I59: =CONCATENATE("""",J59,"""",":","""","parcelassessmentwithoutdats_",LOWER($A59),"_",LOWER($B59),"""") -> "L59":"parcelassessmentwithoutdats__" | J59: L59
C60: =CONCATENATE("""",D60,"""",":","""","parcelassessmentwithdats_",LOWER($A60),"_",LOWER($B60),"""") -> "J60":"parcelassessmentwithdats__" | D60: J60 | E60: =CONCATENATE("""",F60,"""",":","""","parcelassessmentwithdats_",LOWER(A60),"_",LOWER(B60),"""") -> "K60":"parcelassessmentwithdats__" | F60: K60 | I60: =CONCATENATE("""",J60,"""",":","""","parcelassessmentwithoutdats_",LOWER($A60),"_",LOWER($B60),"""") -> "L60":"parcelassessmentwithoutdats__" | J60: L60 | K60: Year 1 | L60: Year 1 | N60: Year 2 | Q60: Year 3
C61: =CONCATENATE("""",D61,"""",":","""","parcelassessmentwithdats_",LOWER($A61),"_",LOWER($B61),"""") -> "J61":"parcelassessmentwithdats__" | D61: J61 | E61: =CONCATENATE("""",F61,"""",":","""","parcelassessmentwithdats_",LOWER(A61),"_",LOWER(B61),"""") -> "K61":"parcelassessmentwithdats__" | F61: K61 | G61: data | H61: u.m. | I61: =CONCATENATE("""",J61,"""",":","""","parcelassessmentwithoutdats_",LOWER($A61),"_",LOWER($B61),"""") -> "L61":"parcelassessmentwithoutdats__" | J61: L61 | K61: With DATSs | L61: Without DATSs | N61: With DATSs | O61: Notes | Q61: With DATSs | R61: Notes
A62: electricityUsageInformation | B62: electricityUsageForTemperatureHumidityControl | C62: =CONCATENATE("""",D62,"""",":","""","parcelassessmentwithdats_",LOWER($A62),"_",LOWER($B62),"""") -> "J62":"parcelassessmentwithdats_electricityusageinformation_electricityusagefortemperaturehumiditycontrol" | D62: J62 | E62: =CONCATENATE("""",F62,"""",":","""","parcelassessmentwithdats_",LOWER(A62),"_",LOWER(B62),"""") -> "K62":"parcelassessmentwithdats_electricityusageinformation_electricityusagefortemperaturehumiditycontrol" | F62: K62 | G62: Temperature and Humidity Control | H62: kWh | I62: =CONCATENATE("""",J62,"""",":","""","parcelassessmentwithoutdats_",LOWER($A62),"_",LOWER($B62),"""") -> "L62":"parcelassessmentwithoutdats_electricityusageinformation_electricityusagefortemperaturehumiditycontrol" | J62: L62 | K62: 1 | L62: 1
A63: electricityUsageInformation | B63: electricityUsageForIrrigation | C63: =CONCATENATE("""",D63,"""",":","""","parcelassessmentwithdats_",LOWER($A63),"_",LOWER($B63),"""") -> "J63":"parcelassessmentwithdats_electricityusageinformation_electricityusageforirrigation" | D63: J63 | E63: =CONCATENATE("""",F63,"""",":","""","parcelassessmentwithdats_",LOWER(A63),"_",LOWER(B63),"""") -> "K63":"parcelassessmentwithdats_electricityusageinformation_electricityusageforirrigation" | F63: K63 | G63: Irrigation | H63: kWh | I63: =CONCATENATE("""",J63,"""",":","""","parcelassessmentwithoutdats_",LOWER($A63),"_",LOWER($B63),"""") -> "L63":"parcelassessmentwithoutdats_electricityusageinformation_electricityusageforirrigation" | J63: L63 | K63: 1 | L63: 1
A64: electricityUsageInformation | B64: electricityUsageForMilking | C64: =CONCATENATE("""",D64,"""",":","""","parcelassessmentwithdats_",LOWER($A64),"_",LOWER($B64),"""") -> "J64":"parcelassessmentwithdats_electricityusageinformation_electricityusageformilking" | D64: J64 | E64: =CONCATENATE("""",F64,"""",":","""","parcelassessmentwithdats_",LOWER(A64),"_",LOWER(B64),"""") -> "K64":"parcelassessmentwithdats_electricityusageinformation_electricityusageformilking" | F64: K64 | G64: Milking | H64: kWh | I64: =CONCATENATE("""",J64,"""",":","""","parcelassessmentwithoutdats_",LOWER($A64),"_",LOWER($B64),"""") -> "L64":"parcelassessmentwithoutdats_electricityusageinformation_electricityusageformilking" | J64: L64 | K64: 1 | L64: 1
A65: electricityUsageInformation | B65: electricityUsageForHeatDetection | C65: =CONCATENATE("""",D65,"""",":","""","parcelassessmentwithdats_",LOWER($A65),"_",LOWER($B65),"""") -> "J65":"parcelassessmentwithdats_electricityusageinformation_electricityusageforheatdetection" | D65: J65 | E65: =CONCATENATE("""",F65,"""",":","""","parcelassessmentwithdats_",LOWER(A65),"_",LOWER(B65),"""") -> "K65":"parcelassessmentwithdats_electricityusageinformation_electricityusageforheatdetection" | F65: K65 | G65: Heat detection | H65: kWh | I65: =CONCATENATE("""",J65,"""",":","""","parcelassessmentwithoutdats_",LOWER($A65),"_",LOWER($B65),"""") -> "L65":"parcelassessmentwithoutdats_electricityusageinformation_electricityusageforheatdetection" | J65: L65 | K65: 1 | L65: 1
A66: electricityUsageInformation | B66: electricityUsageForCalvingDetection | C66: =CONCATENATE("""",D66,"""",":","""","parcelassessmentwithdats_",LOWER($A66),"_",LOWER($B66),"""") -> "J66":"parcelassessmentwithdats_electricityusageinformation_electricityusageforcalvingdetection" | D66: J66 | E66: =CONCATENATE("""",F66,"""",":","""","parcelassessmentwithdats_",LOWER(A66),"_",LOWER(B66),"""") -> "K66":"parcelassessmentwithdats_electricityusageinformation_electricityusageforcalvingdetection" | F66: K66 | G66: Calving detection | H66: kWh | I66: =CONCATENATE("""",J66,"""",":","""","parcelassessmentwithoutdats_",LOWER($A66),"_",LOWER($B66),"""") -> "L66":"parcelassessmentwithoutdats_electricityusageinformation_electricityusageforcalvingdetection" | J66: L66 | K66: 1 | L66: 1
A67: electricityUsageInformation | B67: electricityUsageForFeeding | C67: =CONCATENATE("""",D67,"""",":","""","parcelassessmentwithdats_",LOWER($A67),"_",LOWER($B67),"""") -> "J67":"parcelassessmentwithdats_electricityusageinformation_electricityusageforfeeding" | D67: J67 | E67: =CONCATENATE("""",F67,"""",":","""","parcelassessmentwithdats_",LOWER(A67),"_",LOWER(B67),"""") -> "K67":"parcelassessmentwithdats_electricityusageinformation_electricityusageforfeeding" | F67: K67 | G67: Feeding | H67: kWh | I67: =CONCATENATE("""",J67,"""",":","""","parcelassessmentwithoutdats_",LOWER($A67),"_",LOWER($B67),"""") -> "L67":"parcelassessmentwithoutdats_electricityusageinformation_electricityusageforfeeding" | J67: L67 | K67: 1 | L67: 1
A68: electricityUsageInformation | B68: totalElectricityUsage | C68: =CONCATENATE("""",D68,"""",":","""","parcelassessmentwithdats_",LOWER($A68),"_",LOWER($B68),"""") -> "J68":"parcelassessmentwithdats_electricityusageinformation_totalelectricityusage" | D68: J68 | E68: =CONCATENATE("""",F68,"""",":","""","parcelassessmentwithdats_",LOWER(A68),"_",LOWER(B68),"""") -> "K68":"parcelassessmentwithdats_electricityusageinformation_totalelectricityusage" | F68: K68 | G68: Total electricity used | H68: kWh | I68: =CONCATENATE("""",J68,"""",":","""","parcelassessmentwithoutdats_",LOWER($A68),"_",LOWER($B68),"""") -> "L68":"parcelassessmentwithoutdats_electricityusageinformation_totalelectricityusage" | J68: L68 | K68: 1 | L68: 1
C69: =CONCATENATE("""",D69,"""",":","""","parcelassessmentwithdats_",LOWER($A69),"_",LOWER($B69),"""") -> "J69":"parcelassessmentwithdats__" | D69: J69 | E69: =CONCATENATE("""",F69,"""",":","""","parcelassessmentwithdats_",LOWER(A69),"_",LOWER(B69),"""") -> "K69":"parcelassessmentwithdats__" | F69: K69 | I69: =CONCATENATE("""",J69,"""",":","""","parcelassessmentwithoutdats_",LOWER($A69),"_",LOWER($B69),"""") -> "L69":"parcelassessmentwithoutdats__" | J69: L69
C70: =CONCATENATE("""",D70,"""",":","""","parcelassessmentwithdats_",LOWER($A70),"_",LOWER($B70),"""") -> "J70":"parcelassessmentwithdats__" | D70: J70 | E70: =CONCATENATE("""",F70,"""",":","""","parcelassessmentwithdats_",LOWER(A70),"_",LOWER(B70),"""") -> "K70":"parcelassessmentwithdats__" | F70: K70 | I70: =CONCATENATE("""",J70,"""",":","""","parcelassessmentwithoutdats_",LOWER($A70),"_",LOWER($B70),"""") -> "L70":"parcelassessmentwithoutdats__" | J70: L70 | K70: Year 1 | L70: Year 1 | N70: Year 2 | Q70: Year 3
C71: =CONCATENATE("""",D71,"""",":","""","parcelassessmentwithdats_",LOWER($A71),"_",LOWER($B71),"""") -> "J71":"parcelassessmentwithdats__" | D71: J71 | E71: =CONCATENATE("""",F71,"""",":","""","parcelassessmentwithdats_",LOWER(A71),"_",LOWER(B71),"""") -> "K71":"parcelassessmentwithdats__" | F71: K71 | G71: data | I71: =CONCATENATE("""",J71,"""",":","""","parcelassessmentwithoutdats_",LOWER($A71),"_",LOWER($B71),"""") -> "L71":"parcelassessmentwithoutdats__" | J71: L71 | K71: With DATSs | L71: Without DATSs | N71: With DATSs | O71: Notes | Q71: With DATSs | R71: Notes
A72: pesticidesUsageInformation | B72: productName_0 | C72: =CONCATENATE("""",D72,"""",":","""","parcelassessmentwithdats_",LOWER($A72),"_",LOWER($B72),"""") -> "J72":"parcelassessmentwithdats_pesticidesusageinformation_productname_0" | D72: J72 | E72: =CONCATENATE("""",F72,"""",":","""","parcelassessmentwithdats_",LOWER(A72),"_",LOWER(B72),"""") -> "K72":"parcelassessmentwithdats_pesticidesusageinformation_productname_0" | F72: K72 | G72: Product 1 | H72: Name product 1 | I72: =CONCATENATE("""",J72,"""",":","""","parcelassessmentwithoutdats_",LOWER($A72),"_",LOWER($B72),"""") -> "L72":"parcelassessmentwithoutdats_pesticidesusageinformation_productname_0" | J72: L72 | K72: 1 | L72: 1
A73: pesticidesUsageInformation | B73: numberOfTreatments_0 | C73: =CONCATENATE("""",D73,"""",":","""","parcelassessmentwithdats_",LOWER($A73),"_",LOWER($B73),"""") -> "J73":"parcelassessmentwithdats_pesticidesusageinformation_numberoftreatments_0" | D73: J73 | E73: =CONCATENATE("""",F73,"""",":","""","parcelassessmentwithdats_",LOWER(A73),"_",LOWER(B73),"""") -> "K73":"parcelassessmentwithdats_pesticidesusageinformation_numberoftreatments_0" | F73: K73 | G73: Product 1 | H73: N. of treatements | I73: =CONCATENATE("""",J73,"""",":","""","parcelassessmentwithoutdats_",LOWER($A73),"_",LOWER($B73),"""") -> "L73":"parcelassessmentwithoutdats_pesticidesusageinformation_numberoftreatments_0" | J73: L73 | K73: 1 | L73: 1
A74: pesticidesUsageInformation | B74: averageQuantity_0 | C74: =CONCATENATE("""",D74,"""",":","""","parcelassessmentwithdats_",LOWER($A74),"_",LOWER($B74),"""") -> "J74":"parcelassessmentwithdats_pesticidesusageinformation_averagequantity_0" | D74: J74 | E74: =CONCATENATE("""",F74,"""",":","""","parcelassessmentwithdats_",LOWER(A74),"_",LOWER(B74),"""") -> "K74":"parcelassessmentwithdats_pesticidesusageinformation_averagequantity_0" | F74: K74 | G74: Product 1 | H74: Average quantity per application | I74: =CONCATENATE("""",J74,"""",":","""","parcelassessmentwithoutdats_",LOWER($A74),"_",LOWER($B74),"""") -> "L74":"parcelassessmentwithoutdats_pesticidesusageinformation_averagequantity_0" | J74: L74 | K74: 1 | L74: 1
A75: pesticidesUsageInformation | B75: productName_1 | C75: =CONCATENATE("""",D75,"""",":","""","parcelassessmentwithdats_",LOWER($A75),"_",LOWER($B75),"""") -> "J75":"parcelassessmentwithdats_pesticidesusageinformation_productname_1" | D75: J75 | E75: =CONCATENATE("""",F75,"""",":","""","parcelassessmentwithdats_",LOWER(A75),"_",LOWER(B75),"""") -> "K75":"parcelassessmentwithdats_pesticidesusageinformation_productname_1" | F75: K75 | G75: Product 2 | H75: Name product 2 | I75: =CONCATENATE("""",J75,"""",":","""","parcelassessmentwithoutdats_",LOWER($A75),"_",LOWER($B75),"""") -> "L75":"parcelassessmentwithoutdats_pesticidesusageinformation_productname_1" | J75: L75 | K75: 1 | L75: 1
A76: pesticidesUsageInformation | B76: numberOfTreatments_1 | C76: =CONCATENATE("""",D76,"""",":","""","parcelassessmentwithdats_",LOWER($A76),"_",LOWER($B76),"""") -> "J76":"parcelassessmentwithdats_pesticidesusageinformation_numberoftreatments_1" | D76: J76 | E76: =CONCATENATE("""",F76,"""",":","""","parcelassessmentwithdats_",LOWER(A76),"_",LOWER(B76),"""") -> "K76":"parcelassessmentwithdats_pesticidesusageinformation_numberoftreatments_1" | F76: K76 | G76: Product 2 | H76: N. of treatements | I76: =CONCATENATE("""",J76,"""",":","""","parcelassessmentwithoutdats_",LOWER($A76),"_",LOWER($B76),"""") -> "L76":"parcelassessmentwithoutdats_pesticidesusageinformation_numberoftreatments_1" | J76: L76 | K76: 1 | L76: 1
A77: pesticidesUsageInformation | B77: averageQuantity_1 | C77: =CONCATENATE("""",D77,"""",":","""","parcelassessmentwithdats_",LOWER($A77),"_",LOWER($B77),"""") -> "J77":"parcelassessmentwithdats_pesticidesusageinformation_averagequantity_1" | D77: J77 | E77: =CONCATENATE("""",F77,"""",":","""","parcelassessmentwithdats_",LOWER(A77),"_",LOWER(B77),"""") -> "K77":"parcelassessmentwithdats_pesticidesusageinformation_averagequantity_1" | F77: K77 | G77: Product 2 | H77: Average quantity per application | I77: =CONCATENATE("""",J77,"""",":","""","parcelassessmentwithoutdats_",LOWER($A77),"_",LOWER($B77),"""") -> "L77":"parcelassessmentwithoutdats_pesticidesusageinformation_averagequantity_1" | J77: L77 | K77: 1 | L77: 1
A78: pesticidesUsageInformation | B78: productName_2 | C78: =CONCATENATE("""",D78,"""",":","""","parcelassessmentwithdats_",LOWER($A78),"_",LOWER($B78),"""") -> "J78":"parcelassessmentwithdats_pesticidesusageinformation_productname_2" | D78: J78 | E78: =CONCATENATE("""",F78,"""",":","""","parcelassessmentwithdats_",LOWER(A78),"_",LOWER(B78),"""") -> "K78":"parcelassessmentwithdats_pesticidesusageinformation_productname_2" | F78: K78 | G78: Product n | H78: Name product n | I78: =CONCATENATE("""",J78,"""",":","""","parcelassessmentwithoutdats_",LOWER($A78),"_",LOWER($B78),"""") -> "L78":"parcelassessmentwithoutdats_pesticidesusageinformation_productname_2" | J78: L78 | K78: 1 | L78: 1
A79: pesticidesUsageInformation | B79: numberOfTreatments_2 | C79: =CONCATENATE("""",D79,"""",":","""","parcelassessmentwithdats_",LOWER($A79),"_",LOWER($B79),"""") -> "J79":"parcelassessmentwithdats_pesticidesusageinformation_numberoftreatments_2" | D79: J79 | E79: =CONCATENATE("""",F79,"""",":","""","parcelassessmentwithdats_",LOWER(A79),"_",LOWER(B79),"""") -> "K79":"parcelassessmentwithdats_pesticidesusageinformation_numberoftreatments_2" | F79: K79 | G79: Product n | H79: N. of treatements | I79: =CONCATENATE("""",J79,"""",":","""","parcelassessmentwithoutdats_",LOWER($A79),"_",LOWER($B79),"""") -> "L79":"parcelassessmentwithoutdats_pesticidesusageinformation_numberoftreatments_2" | J79: L79 | K79: 1 | L79: 1
A80: pesticidesUsageInformation | B80: averageQuantity_2 | C80: =CONCATENATE("""",D80,"""",":","""","parcelassessmentwithdats_",LOWER($A80),"_",LOWER($B80),"""") -> "J80":"parcelassessmentwithdats_pesticidesusageinformation_averagequantity_2" | D80: J80 | E80: =CONCATENATE("""",F80,"""",":","""","parcelassessmentwithdats_",LOWER(A80),"_",LOWER(B80),"""") -> "K80":"parcelassessmentwithdats_pesticidesusageinformation_averagequantity_2" | F80: K80 | G80: Product n | H80: Average quantity per application | I80: =CONCATENATE("""",J80,"""",":","""","parcelassessmentwithoutdats_",LOWER($A80),"_",LOWER($B80),"""") -> "L80":"parcelassessmentwithoutdats_pesticidesusageinformation_averagequantity_2" | J80: L80 | K80: 1 | L80: 1
A81: pesticidesUsageInformation | B81: productName_3 | C81: =CONCATENATE("""",D81,"""",":","""","parcelassessmentwithdats_",LOWER($A81),"_",LOWER($B81),"""") -> "J81":"parcelassessmentwithdats_pesticidesusageinformation_productname_3" | D81: J81 | E81: =CONCATENATE("""",F81,"""",":","""","parcelassessmentwithdats_",LOWER(A81),"_",LOWER(B81),"""") -> "K81":"parcelassessmentwithdats_pesticidesusageinformation_productname_3" | F81: K81 | G81: Product 1 | H81: Name product 1 | I81: =CONCATENATE("""",J81,"""",":","""","parcelassessmentwithoutdats_",LOWER($A81),"_",LOWER($B81),"""") -> "L81":"parcelassessmentwithoutdats_pesticidesusageinformation_productname_3" | J81: L81 | K81: 1 | L81: 1
A82: pesticidesUsageInformation | B82: numberOfTreatments_3 | C82: =CONCATENATE("""",D82,"""",":","""","parcelassessmentwithdats_",LOWER($A82),"_",LOWER($B82),"""") -> "J82":"parcelassessmentwithdats_pesticidesusageinformation_numberoftreatments_3" | D82: J82 | E82: =CONCATENATE("""",F82,"""",":","""","parcelassessmentwithdats_",LOWER(A82),"_",LOWER(B82),"""") -> "K82":"parcelassessmentwithdats_pesticidesusageinformation_numberoftreatments_3" | F82: K82 | G82: Product 1 | H82: N. of treatements | I82: =CONCATENATE("""",J82,"""",":","""","parcelassessmentwithoutdats_",LOWER($A82),"_",LOWER($B82),"""") -> "L82":"parcelassessmentwithoutdats_pesticidesusageinformation_numberoftreatments_3" | J82: L82 | K82: 1 | L82: 1
A83: pesticidesUsageInformation | B83: averageQuantity_3 | C83: =CONCATENATE("""",D83,"""",":","""","parcelassessmentwithdats_",LOWER($A83),"_",LOWER($B83),"""") -> "J83":"parcelassessmentwithdats_pesticidesusageinformation_averagequantity_3" | D83: J83 | E83: =CONCATENATE("""",F83,"""",":","""","parcelassessmentwithdats_",LOWER(A83),"_",LOWER(B83),"""") -> "K83":"parcelassessmentwithdats_pesticidesusageinformation_averagequantity_3" | F83: K83 | G83: Product 1 | H83: Average quantity per application | I83: =CONCATENATE("""",J83,"""",":","""","parcelassessmentwithoutdats_",LOWER($A83),"_",LOWER($B83),"""") -> "L83":"parcelassessmentwithoutdats_pesticidesusageinformation_averagequantity_3" | J83: L83 | K83: 1 | L83: 1
... A89: pesticidesUsageInformation | B89: averageQuantity_5 | C89: =CONCATENATE("""",D89,"""",":","""","parcelassessmentwithdats_",LOWER($A89),"_",LOWER($B89),"""") -> "J89":"parcelassessmentwithdats_pesticidesusageinformation_averagequantity_5" | D89: J89 | E89: =CONCATENATE("""",F89,"""",":","""","parcelassessmentwithdats_",LOWER(A89),"_",LOWER(B89),"""") -> "K89":"parcelassessmentwithdats_pesticidesusageinformation_averagequantity_5" | F89: K89 | G89: Product n | H89: Average quantity per application | I89: =CONCATENATE("""",J89,"""",":","""","parcelassessmentwithoutdats_",LOWER($A89),"_",LOWER($B89),"""") -> "L89":"parcelassessmentwithoutdats_pesticidesusageinformation_averagequantity_5" | J89: L89 | K89: 1 | L89: 1
C90: =CONCATENATE("""",D90,"""",":","""","parcelassessmentwithdats_",LOWER($A90),"_",LOWER($B90),"""") -> "J90":"parcelassessmentwithdats__" | D90: J90 | E90: =CONCATENATE("""",F90,"""",":","""","parcelassessmentwithdats_",LOWER(A90),"_",LOWER(B90),"""") -> "K90":"parcelassessmentwithdats__" | F90: K90 | I90: =CONCATENATE("""",J90,"""",":","""","parcelassessmentwithoutdats_",LOWER($A90),"_",LOWER($B90),"""") -> "L90":"parcelassessmentwithoutdats__" | J90: L90
C91: =CONCATENATE("""",D91,"""",":","""","parcelassessmentwithdats_",LOWER($A91),"_",LOWER($B91),"""") -> "J91":"parcelassessmentwithdats__" | D91: J91 | E91: =CONCATENATE("""",F91,"""",":","""","parcelassessmentwithdats_",LOWER(A91),"_",LOWER(B91),"""") -> "K91":"parcelassessmentwithdats__" | F91: K91 | I91: =CONCATENATE("""",J91,"""",":","""","parcelassessmentwithoutdats_",LOWER($A91),"_",LOWER($B91),"""") -> "L91":"parcelassessmentwithoutdats__" | J91: L91 | K91: Year 1 | L91: Year 1 | N91: Year 2 | Q91: Year 3
C92: =CONCATENATE("""",D92,"""",":","""","parcelassessmentwithdats_",LOWER($A92),"_",LOWER($B92),"""") -> "J92":"parcelassessmentwithdats__" | D92: J92 | E92: =CONCATENATE("""",F92,"""",":","""","parcelassessmentwithdats_",LOWER(A92),"_",LOWER(B92),"""") -> "K92":"parcelassessmentwithdats__" | F92: K92 | G92: data | I92: =CONCATENATE("""",J92,"""",":","""","parcelassessmentwithoutdats_",LOWER($A92),"_",LOWER($B92),"""") -> "L92":"parcelassessmentwithoutdats__" | J92: L92 | K92: With DATSs | L92: Without DATSs | N92: With DATSs | O92: Notes | Q92: With DATSs | R92: Notes
A93: fertilizersUsageInformation | B93: productName_0 | C93: =CONCATENATE("""",D93,"""",":","""","parcelassessmentwithdats_",LOWER($A93),"_",LOWER($B93),"""") -> "J93":"parcelassessmentwithdats_fertilizersusageinformation_productname_0" | D93: J93 | E93: =CONCATENATE("""",F93,"""",":","""","parcelassessmentwithdats_",LOWER(A93),"_",LOWER(B93),"""") -> "K93":"parcelassessmentwithdats_fertilizersusageinformation_productname_0" | F93: K93 | G93: Fertiliser 1 | H93: Name fertiliser 1 | I93: =CONCATENATE("""",J93,"""",":","""","parcelassessmentwithoutdats_",LOWER($A93),"_",LOWER($B93),"""") -> "L93":"parcelassessmentwithoutdats_fertilizersusageinformation_productname_0" | J93: L93 | K93: 1 | L93: 1
A94: fertilizersUsageInformation | B94: productType_0 | C94: =CONCATENATE("""",D94,"""",":","""","parcelassessmentwithdats_",LOWER($A94),"_",LOWER($B94),"""") -> "J94":"parcelassessmentwithdats_fertilizersusageinformation_producttype_0" | D94: J94 | E94: =CONCATENATE("""",F94,"""",":","""","parcelassessmentwithdats_",LOWER(A94),"_",LOWER(B94),"""") -> "K94":"parcelassessmentwithdats_fertilizersusageinformation_producttype_0" | F94: K94 | G94: Fertiliser 1 | H94: Mineral/Organic | I94: =CONCATENATE("""",J94,"""",":","""","parcelassessmentwithoutdats_",LOWER($A94),"_",LOWER($B94),"""") -> "L94":"parcelassessmentwithoutdats_fertilizersusageinformation_producttype_0" | J94: L94 | K94: 1 | L94: 1
A95: fertilizersUsageInformation | B95: numberOfTreatments_0 | C95: =CONCATENATE("""",D95,"""",":","""","parcelassessmentwithdats_",LOWER($A95),"_",LOWER($B95),"""") -> "J95":"parcelassessmentwithdats_fertilizersusageinformation_numberoftreatments_0" | D95: J95 | E95: =CONCATENATE("""",F95,"""",":","""","parcelassessmentwithdats_",LOWER(A95),"_",LOWER(B95),"""") -> "K95":"parcelassessmentwithdats_fertilizersusageinformation_numberoftreatments_0" | F95: K95 | G95: Fertiliser 1 | H95: N. of treatements | I95: =CONCATENATE("""",J95,"""",":","""","parcelassessmentwithoutdats_",LOWER($A95),"_",LOWER($B95),"""") -> "L95":"parcelassessmentwithoutdats_fertilizersusageinformation_numberoftreatments_0" | J95: L95 | K95: 1 | L95: 1
A96: fertilizersUsageInformation | B96: averageQuantity_0 | C96: =CONCATENATE("""",D96,"""",":","""","parcelassessmentwithdats_",LOWER($A96),"_",LOWER($B96),"""") -> "J96":"parcelassessmentwithdats_fertilizersusageinformation_averagequantity_0" | D96: J96 | E96: =CONCATENATE("""",F96,"""",":","""","parcelassessmentwithdats_",LOWER(A96),"_",LOWER(B96),"""") -> "K96":"parcelassessmentwithdats_fertilizersusageinformation_averagequantity_0" | F96: K96 | G96: Fertiliser 1 | H96: Average quantity per application | I96: =CONCATENATE("""",J96,"""",":","""","parcelassessmentwithoutdats_",LOWER($A96),"_",LOWER($B96),"""") -> "L96":"parcelassessmentwithoutdats_fertilizersusageinformation_averagequantity_0" | J96: L96 | K96: 1 | L96: 1
A97: fertilizersUsageInformation | B97: averageNitrogenQuantity_0 | C97: =CONCATENATE("""",D97,"""",":","""","parcelassessmentwithdats_",LOWER($A97),"_",LOWER($B97),"""") -> "J97":"parcelassessmentwithdats_fertilizersusageinformation_averagenitrogenquantity_0" | D97: J97 | E97: =CONCATENATE("""",F97,"""",":","""","parcelassessmentwithdats_",LOWER(A97),"_",LOWER(B97),"""") -> "K97":"parcelassessmentwithdats_fertilizersusageinformation_averagenitrogenquantity_0" | F97: K97 | G97: Fertiliser 1 | H97: N concentration | I97: =CONCATENATE("""",J97,"""",":","""","parcelassessmentwithoutdats_",LOWER($A97),"_",LOWER($B97),"""") -> "L97":"parcelassessmentwithoutdats_fertilizersusageinformation_averagenitrogenquantity_0" | J97: L97 | K97: 1 | L97: 1
A98: fertilizersUsageInformation | B98: averagePhosphorusQuantity_0 | C98: =CONCATENATE("""",D98,"""",":","""","parcelassessmentwithdats_",LOWER($A98),"_",LOWER($B98),"""") -> "J98":"parcelassessmentwithdats_fertilizersusageinformation_averagephosphorusquantity_0" | D98: J98 | E98: =CONCATENATE("""",F98,"""",":","""","parcelassessmentwithdats_",LOWER(A98),"_",LOWER(B98),"""") -> "K98":"parcelassessmentwithdats_fertilizersusageinformation_averagephosphorusquantity_0" | F98: K98 | G98: Fertiliser 1 | H98: P concentration | I98: =CONCATENATE("""",J98,"""",":","""","parcelassessmentwithoutdats_",LOWER($A98),"_",LOWER($B98),"""") -> "L98":"parcelassessmentwithoutdats_fertilizersusageinformation_averagephosphorusquantity_0" | J98: L98 | K98: 1 | L98: 1
A99: fertilizersUsageInformation | B99: averagePotassiumQuantity_0 | C99: =CONCATENATE("""",D99,"""",":","""","parcelassessmentwithdats_",LOWER($A99),"_",LOWER($B99),"""") -> "J99":"parcelassessmentwithdats_fertilizersusageinformation_averagepotassiumquantity_0" | D99: J99 | E99: =CONCATENATE("""",F99,"""",":","""","parcelassessmentwithdats_",LOWER(A99),"_",LOWER(B99),"""") -> "K99":"parcelassessmentwithdats_fertilizersusageinformation_averagepotassiumquantity_0" | F99: K99 | G99: Fertiliser 1 | H99: K concentration | I99: =CONCATENATE("""",J99,"""",":","""","parcelassessmentwithoutdats_",LOWER($A99),"_",LOWER($B99),"""") -> "L99":"parcelassessmentwithoutdats_fertilizersusageinformation_averagepotassiumquantity_0" | J99: L99 | K99: 1 | L99: 1
A100: fertilizersUsageInformation | B100: productName_1 | C100: =CONCATENATE("""",D100,"""",":","""","parcelassessmentwithdats_",LOWER($A100),"_",LOWER($B100),"""") -> "J100":"parcelassessmentwithdats_fertilizersusageinformation_productname_1" | D100: J100 | E100: =CONCATENATE("""",F100,"""",":","""","parcelassessmentwithdats_",LOWER(A100),"_",LOWER(B100),"""") -> "K100":"parcelassessmentwithdats_fertilizersusageinformation_productname_1" | F100: K100 | G100: Fertiliser 2 | H100: Name fertiliser 2 | I100: =CONCATENATE("""",J100,"""",":","""","parcelassessmentwithoutdats_",LOWER($A100),"_",LOWER($B100),"""") -> "L100":"parcelassessmentwithoutdats_fertilizersusageinformation_productname_1" | J100: L100 | K100: 1 | L100: 1
A101: fertilizersUsageInformation | B101: productType_1 | C101: =CONCATENATE("""",D101,"""",":","""","parcelassessmentwithdats_",LOWER($A101),"_",LOWER($B101),"""") -> "J101":"parcelassessmentwithdats_fertilizersusageinformation_producttype_1" | D101: J101 | E101: =CONCATENATE("""",F101,"""",":","""","parcelassessmentwithdats_",LOWER(A101),"_",LOWER(B101),"""") -> "K101":"parcelassessmentwithdats_fertilizersusageinformation_producttype_1" | F101: K101 | G101: Fertiliser 2 | H101: Mineral/Organic | I101: =CONCATENATE("""",J101,"""",":","""","parcelassessmentwithoutdats_",LOWER($A101),"_",LOWER($B101),"""") -> "L101":"parcelassessmentwithoutdats_fertilizersusageinformation_producttype_1" | J101: L101 | K101: 1 | L101: 1
A102: fertilizersUsageInformation | B102: numberOfTreatments_1 | C102: =CONCATENATE("""",D102,"""",":","""","parcelassessmentwithdats_",LOWER($A102),"_",LOWER($B102),"""") -> "J102":"parcelassessmentwithdats_fertilizersusageinformation_numberoftreatments_1" | D102: J102 | E102: =CONCATENATE("""",F102,"""",":","""","parcelassessmentwithdats_",LOWER(A102),"_",LOWER(B102),"""") -> "K102":"parcelassessmentwithdats_fertilizersusageinformation_numberoftreatments_1" | F102: K102 | G102: Fertiliser 2 | H102: N. of treatements | I102: =CONCATENATE("""",J102,"""",":","""","parcelassessmentwithoutdats_",LOWER($A102),"_",LOWER($B102),"""") -> "L102":"parcelassessmentwithoutdats_fertilizersusageinformation_numberoftreatments_1" | J102: L102 | K102: 1 | L102: 1
A103: fertilizersUsageInformation | B103: averageQuantity_1 | C103: =CONCATENATE("""",D103,"""",":","""","parcelassessmentwithdats_",LOWER($A103),"_",LOWER($B103),"""") -> "J103":"parcelassessmentwithdats_fertilizersusageinformation_averagequantity_1" | D103: J103 | E103: =CONCATENATE("""",F103,"""",":","""","parcelassessmentwithdats_",LOWER(A103),"_",LOWER(B103),"""") -> "K103":"parcelassessmentwithdats_fertilizersusageinformation_averagequantity_1" | F103: K103 | G103: Fertiliser 2 | H103: Average quantity per application | I103: =CONCATENATE("""",J103,"""",":","""","parcelassessmentwithoutdats_",LOWER($A103),"_",LOWER($B103),"""") -> "L103":"parcelassessmentwithoutdats_fertilizersusageinformation_averagequantity_1" | J103: L103 | K103: 1 | L103: 1
A104: fertilizersUsageInformation | B104: averageNitrogenQuantity_1 | C104: =CONCATENATE("""",D104,"""",":","""","parcelassessmentwithdats_",LOWER($A104),"_",LOWER($B104),"""") -> "J104":"parcelassessmentwithdats_fertilizersusageinformation_averagenitrogenquantity_1" | D104: J104 | E104: =CONCATENATE("""",F104,"""",":","""","parcelassessmentwithdats_",LOWER(A104),"_",LOWER(B104),"""") -> "K104":"parcelassessmentwithdats_fertilizersusageinformation_averagenitrogenquantity_1" | F104: K104 | G104: Fertiliser 2 | H104: N concentration | I104: =CONCATENATE("""",J104,"""",":","""","parcelassessmentwithoutdats_",LOWER($A104),"_",LOWER($B104),"""") -> "L104":"parcelassessmentwithoutdats_fertilizersusageinformation_averagenitrogenquantity_1" | J104: L104 | K104: 1 | L104: 1
... A134: fertilizersUsageInformation | B134: averagePotassiumQuantity_5 | C134: =CONCATENATE("""",D134,"""",":","""","parcelassessmentwithdats_",LOWER($A134),"_",LOWER($B134),"""") -> "J134":"parcelassessmentwithdats_fertilizersusageinformation_averagepotassiumquantity_5" | D134: J134 | E134: =CONCATENATE("""",F134,"""",":","""","parcelassessmentwithdats_",LOWER(A134),"_",LOWER(B134),"""") -> "K134":"parcelassessmentwithdats_fertilizersusageinformation_averagepotassiumquantity_5" | F134: K134 | G134: Fertiliser n | H134: K concentration | I134: =CONCATENATE("""",J134,"""",":","""","parcelassessmentwithoutdats_",LOWER($A134),"_",LOWER($B134),"""") -> "L134":"parcelassessmentwithoutdats_fertilizersusageinformation_averagepotassiumquantity_5" | J134: L134 | K134: 1 | L134: 1
C135: =CONCATENATE("""",D135,"""",":","""","parcelassessmentwithdats_",LOWER($A135),"_",LOWER($B135),"""") -> "J135":"parcelassessmentwithdats__" | D135: J135 | E135: =CONCATENATE("""",F135,"""",":","""","parcelassessmentwithdats_",LOWER(A135),"_",LOWER(B135),"""") -> "K135":"parcelassessmentwithdats__" | F135: K135 | I135: =CONCATENATE("""",J135,"""",":","""","parcelassessmentwithoutdats_",LOWER($A135),"_",LOWER($B135),"""") -> "L135":"parcelassessmentwithoutdats__" | J135: L135
C136: =CONCATENATE("""",D136,"""",":","""","parcelassessmentwithdats_",LOWER($A136),"_",LOWER($B136),"""") -> "J136":"parcelassessmentwithdats__" | D136: J136 | E136: =CONCATENATE("""",F136,"""",":","""","parcelassessmentwithdats_",LOWER(A136),"_",LOWER(B136),"""") -> "K136":"parcelassessmentwithdats__" | F136: K136 | I136: =CONCATENATE("""",J136,"""",":","""","parcelassessmentwithoutdats_",LOWER($A136),"_",LOWER($B136),"""") -> "L136":"parcelassessmentwithoutdats__" | J136: L136 | K136: Year 1 | L136: Year 1 | N136: Year 2 | Q136: Year 3
C137: =CONCATENATE("""",D137,"""",":","""","parcelassessmentwithdats_",LOWER($A137),"_",LOWER($B137),"""") -> "J137":"parcelassessmentwithdats__" | D137: J137 | E137: =CONCATENATE("""",F137,"""",":","""","parcelassessmentwithdats_",LOWER(A137),"_",LOWER(B137),"""") -> "K137":"parcelassessmentwithdats__" | F137: K137 | G137: data | I137: =CONCATENATE("""",J137,"""",":","""","parcelassessmentwithoutdats_",LOWER($A137),"_",LOWER($B137),"""") -> "L137":"parcelassessmentwithoutdats__" | J137: L137 | K137: With DATSs | L137: Without DATSs | N137: With DATSs | O137: Notes | Q137: With DATSs | R137: Notes
A138: feedUsageInformation | B138: productName_0 | C138: =CONCATENATE("""",D138,"""",":","""","parcelassessmentwithdats_",LOWER($A138),"_",LOWER($B138),"""") -> "J138":"parcelassessmentwithdats_feedusageinformation_productname_0" | D138: J138 | E138: =CONCATENATE("""",F138,"""",":","""","parcelassessmentwithdats_",LOWER(A138),"_",LOWER(B138),"""") -> "K138":"parcelassessmentwithdats_feedusageinformation_productname_0" | F138: K138 | G138: Feed 1 | H138: Name feed 1 | I138: =CONCATENATE("""",J138,"""",":","""","parcelassessmentwithoutdats_",LOWER($A138),"_",LOWER($B138),"""") -> "L138":"parcelassessmentwithoutdats_feedusageinformation_productname_0" | J138: L138 | K138: 1 | L138: 1
A139: feedUsageInformation | B139: quantity_0 | C139: =CONCATENATE("""",D139,"""",":","""","parcelassessmentwithdats_",LOWER($A139),"_",LOWER($B139),"""") -> "J139":"parcelassessmentwithdats_feedusageinformation_quantity_0" | D139: J139 | E139: =CONCATENATE("""",F139,"""",":","""","parcelassessmentwithdats_",LOWER(A139),"_",LOWER(B139),"""") -> "K139":"parcelassessmentwithdats_feedusageinformation_quantity_0" | F139: K139 | G139: Feed 1 | H139: Quantity feed 1 | I139: =CONCATENATE("""",J139,"""",":","""","parcelassessmentwithoutdats_",LOWER($A139),"_",LOWER($B139),"""") -> "L139":"parcelassessmentwithoutdats_feedusageinformation_quantity_0" | J139: L139 | K139: 1 | L139: 1
...

Sheet Parcel 1 without DATSs
BA1: yes
G2: PARCEL WITHOUT DATSs | BA2: no
C4: Identification | D4: Parcel Name
B8: Information about the TC
B9: # | C9: data | D9: u.m. | E9: value | G9: Notes
B10: 1 | C10: Parcel dimension | D10: ha | E10: 1
B11: 2 | C11: Number of plants/trees | D11: n | E11: 1
B12: 3 | C12: Sand content in the soil | D12: % | E12: 1
B13: 4 | C13: Clay content in the soil | D13: % | E13: 1
B14: 5 | C14: Silt content in the soil | D14: % | E14: 1
B15: 6 | C15: Soil Bulk Density | D15: g/cm3 | E15: 1
B16: 7 | C16: Soil Organic Carbon | D16: % | E16: 1
B17: 8 | C17: Number of animals | D17: n | E17: 1
B18: 9 | C18: Livestock units per hectare | D18: LSU/ha | E18: 1
B19: 10 | C19: Number of beehives | D19: n | E19: 1
B20: 11 | C20: Area under aquaculture | D20: m2 | E20: 1
B22: WATER | G22: Year 1
B23: # | C23: data | D23: u.m. | G23: Without DATSs | H23: Notes
B24: 12 | C24: Irrigation | D24: m3 | G24: 1
B25: 13 | C25: Fertigation | D25: m3 | G25: 1
B26: 14 | C26: Pest dilution | D26: m3 | G26: 1
B27: 15 | C27: Cleaning | D27: m3 | G27: 1
B28: 16 | C28: Drinking | D28: m3 | G28: 1
B29: 17 | C29: or Total water used | D29: m3 | G29: 1
B31: FUEL | G31: Year 1
B32: # | C32: data | D32: u.m. | G32: Without DATSs | H32: Notes
B33: 18 | C33: Fertilisation | D33: l | G33: 1
B34: 19 | C34: Pesticides | D34: l | G34: 1
B35: 20 | C35: Irrigation | D35: l | G35: 1
B36: 21 | C36: Sowing / Planting | D36: l | G36: 1
B37: 22 | C37: Temperature and Humidity Control | D37: l | G37: 1
B38: 23 | C38: Pruning | D38: l | G38: 1
B39: 24 | C39: Beehives visits | D39: l | G39: 1
B40: 25 | C40: Transporting oysters to the laboratory | D40: l | G40: 1
B41: 26 | C41: Milking | D41: l | G41: 1
B42: 27 | C42: Feeding | D42: l | G42: 1
B43: 28 | C43: or Total fuel used | D43: l | G43: 1
B45: FUEL FOR GREENHOUSE TEMPERATURE CONTROL | G45: Year 1
B46: # | C46: data | E46: u.m. | G46: Without DATSs | H46: Notes
B47: 29 | C47: Fuel 1 | D47: Name fuel 1 | G47: 1
B48: 30 | C48: Fuel 1 | D48: Quantity | E48: m3 | G48: 1
B49: 31 | C49: Fuel 2 | D49: Name fuel 2 | G49: 1
B50: 32 | C50: Fuel 2 | D50: Quantity | E50: m3 | G50: 1
B51: 33 | C51: Fuel n | D51: Name fuel 2 | G51: 1
B52: 34 | C52: Fuel n | D52: Quantity | E52: m3 | G52: 1
B53: 29 | C53: Fuel 1 | D53: Name fuel 1 | G53: 1
B54: 30 | C54: Fuel 1 | D54: Quantity | E54: m3 | G54: 1
B55: 31 | C55: Fuel 2 | D55: Name fuel 2 | G55: 1
B56: 32 | C56: Fuel 2 | D56: Quantity | E56: m3 | G56: 1
B57: 33 | C57: Fuel n | D57: Name fuel 2 | G57: 1
B58: 34 | C58: Fuel n | D58: Quantity | E58: m3 | G58: 1
B60: ELECTRICITY | G60: Year 1
B61: # | C61: data | D61: u.m. | G61: Without DATSs | H61: Notes
B62: 35 | C62: Temperature and Humidity Control | D62: kWh | G62: 1
B63: 36 | C63: Irrigation | D63: kWh | G63: 1
B64: 37 | C64: Milking | D64: kWh | G64: 1
B65: 38 | C65: Heat detection | D65: kWh | G65: 1
B66: 39 | C66: Calving detection | D66: kWh | G66: 1
B67: 40 | C67: Feeding | D67: kWh | G67: 1
B68: 41 | C68: or Total electricity used | D68: kWh | G68: 1
B70: PESTICIDES (HERBICIDES, FUNGICIDES, INSECTICIDES) | G70: Year 1
B71: # | C71: data | E71: u.m. | G71: Without DATSs | H71: Notes
B72: 42 | C72: Product 1 | D72: Name product 1 | G72: 1
B73: 43 | C73: Product 1 | D73: N. of treatements | E73: n | G73: 1
B74: 44 | C74: Product 1 | D74: Average quantity per application | E74: =IF('General Information'!F50="€/kg","kg/ha","l/ha") -> kg/ha | G74: 1
B75: 45 | C75: Product 2 | D75: Name product 2 | G75: 1
B76: 46 | C76: Product 2 | D76: N. of treatements | E76: n | G76: 1
B77: 47 | C77: Product 2 | D77: Average quantity per application | E77: =IF('General Information'!F51="€/kg","kg/ha","l/ha") -> kg/ha | G77: 1
B78: 48 | C78: Product n | D78: Name product n | G78: 1
B79: 49 | C79: Product n | D79: N. of treatements | E79: n | G79: 1
B80: 50 | C80: Product n | D80: Average quantity per application | E80: =IF('General Information'!F59="€/kg","kg/ha","l/ha") -> kg/ha | G80: 1
B81: 42 | C81: Product 1 | D81: Name product 1 | G81: 1
B82: 43 | C82: Product 1 | D82: N. of treatements | E82: n | G82: 1
B83: 44 | C83: Product 1 | D83: Average quantity per application | E83: =IF('General Information'!F59="€/kg","kg/ha","l/ha") -> kg/ha | G83: 1
B84: 45 | C84: Product 2 | D84: Name product 2 | G84: 1
B85: 46 | C85: Product 2 | D85: N. of treatements | E85: n | G85: 1
B86: 47 | C86: Product 2 | D86: Average quantity per application | E86: =IF('General Information'!F60="€/kg","kg/ha","l/ha") -> l/ha | G86: 1
B87: 48 | C87: Product n | D87: Name product n | G87: 1
B88: 49 | C88: Product n | D88: N. of treatements | E88: n | G88: 1
B89: 50 | C89: Product n | D89: Average quantity per application | E89: =IF('General Information'!F68="€/kg","kg/ha","l/ha") -> l/ha | G89: 1
B91: FERTILISER | G91: Year 1
B92: # | C92: data | E92: u.m. | G92: Without DATSs | H92: Notes
B93: 51 | C93: Fertiliser 1 | D93: Name fertiliser 1 | G93: 1
B94: 52 | C94: Fertiliser 1 | D94: Mineral/Organic | G94: 1
B95: 53 | C95: Fertiliser 1 | D95: N. of treatements | E95: n | G95: 1
B96: 54 | C96: Fertiliser 1 | D96: Average quantity per application | E96: =IF('General Information'!F68="€/t","t/ha","kg/ha") -> t/ha | G96: 1
B97: 55 | C97: Fertiliser 1 | D97: N concentration | E97: % | G97: 1
B98: 56 | C98: Fertiliser 1 | D98: P concentration | E98: % | G98: 1
B99: 57 | C99: Fertiliser 1 | D99: K concentration | E99: % | G99: 1
B100: 58 | C100: Fertiliser 2 | D100: Name fertiliser 2 | G100: 1
B101: 59 | C101: Fertiliser 2 | D101: Mineral/Organic | G101: 1
B102: 60 | C102: Fertiliser 2 | D102: N. of treatements | E102: n | G102: 1
B103: 61 | C103: Fertiliser 2 | D103: Average quantity per application | E103: =IF('General Information'!F69="€/t","t/ha","kg/ha") -> t/ha | G103: 1
B104: 62 | C104: Fertiliser 2 | D104: N concentration | E104: % | G104: 1
B105: 63 | C105: Fertiliser 2 | D105: P concentration | E105: % | G105: 1
B106: 64 | C106: Fertiliser 2 | D106: K concentration | E106: % | G106: 1
B107: 65 | C107: Fertiliser n | D107: Name fertiliser n | G107: 1
B108: 66 | C108: Fertiliser n | D108: Mineral/Organic | G108: 1
B109: 67 | C109: Fertiliser n | D109: N. of treatements | E109: n | G109: 1
B110: 68 | C110: Fertiliser n | D110: Average quantity per application | E110: =IF('General Information'!F70="€/t","t/ha","kg/ha") -> t/ha | G110: 1
...

Sheet Cost-revenue DATS
A1: COST ANALYSIS
A2: INPUT | B2: INDICATOR | C2: SCENARIO | D2: UoM | E2: TOTAL | F2: FORMULAS
A3: WATER | B3: Cost of water | C3: With DATs | D3: =IFERROR(VLOOKUP('General Information'!$G$6, Convalide!$L$2:$M$8, 2,FALSE), "") -> €/l milk | E3: =('Parcel 1 with DATSs'!K29*'General Information'!G32)/(IF('General Information'!G6="crop",'Parcel 1 with DATSs'!K10,IF('General Information'!G6="milk",'Parcel 1 with DATSs'!K241,IF('General Information'!G6="meat",'Parcel 1 with DATSs'!K242,IF('General Information'!G6="animal",'Parcel 1 with DATSs'!K243,IF('General Information'!G6="oyster",'Parcel 1 with DATSs'!K244,IF('General Information'!G6="honey",'Parcel 1 with DATSs'!K245,'Parcel 1 with DATSs'!K246))))))) -> 1 | F3: IF(Total water used>0; (Total water used * water price)/Parcel dimension; Sum(water Irrigation+ water Fertigation + water Pest dilution + …) * water price) | G3: =CONCATENATE("cost revenue dats","_",$A$1,"_",A3,"_",B3) -> cost revenue dats_COST ANALYSIS_WATER _Cost of water | H3: E3
A4: FUEL | B4: Cost of fuel | C4: With DATs | D4: =IFERROR(VLOOKUP('General Information'!$G$6, Convalide!$L$2:$M$8, 2,FALSE), "") -> €/l milk | E4: ='Parcel 1 with DATSs'!K43*'General Information'!G33/(IF('General Information'!G6="crop",'Parcel 1 with DATSs'!K10,IF('General Information'!G6="milk",'Parcel 1 with DATSs'!K241,IF('General Information'!G6="meat",'Parcel 1 with DATSs'!K242,IF('General Information'!G6="animal",'Parcel 1 with DATSs'!K243,IF('General Information'!G6="oyster",'Parcel 1 with DATSs'!K244,IF('General Information'!G6="honey",'Parcel 1 with DATSs'!K245,'Parcel 1 with DATSs'!K246))))))) -> 1 | F4: IF(Total fuel used>0; (Total fuel used*fuel price)/Parcel dimension; sum(Fertilisation+Pesticides +Irrigation+Sowing_Planting+Pruning+…) * fuel price) | G4: =CONCATENATE("cost revenue dats","_",$A$1,"_",A4,"_",B4) -> cost revenue dats_COST ANALYSIS_FUEL _Cost of fuel | H4: E4
A5: GREENHOUSE FUEL | B5: Cost of fuel for greenhouse | C5: With DATs | D5: =IFERROR(VLOOKUP('General Information'!$G$6, Convalide!$L$2:$M$8, 2,FALSE), "") -> €/l milk | E5: =(('Parcel 1 with DATSs'!K54*'General Information'!G42)+('Parcel 1 with DATSs'!K56*'General Information'!G43)+('Parcel 1 with DATSs'!K58*'General Information'!G44))/'Parcel 1 with DATSs'!K10 -> 3 | G5: =CONCATENATE("cost revenue dats","_",$A$1,"_",A5,"_",B5) -> cost revenue dats_COST ANALYSIS_GREENHOUSE FUEL_Cost of fuel for greenhouse | H5: E5
A6: ELECTRICITY | B6: Cost of electricity | C6: With DATs | D6: =IFERROR(VLOOKUP('General Information'!$G$6, Convalide!$L$2:$M$8, 2,FALSE), "") -> €/l milk | E6: ='Parcel 1 with DATSs'!K68*'General Information'!G45/(IF('General Information'!G6="crop",'Parcel 1 with DATSs'!K10,IF('General Information'!G6="milk",'Parcel 1 with DATSs'!K241,IF('General Information'!G6="meat",'Parcel 1 with DATSs'!K242,IF('General Information'!G6="animal",'Parcel 1 with DATSs'!K243,IF('General Information'!G6="oyster",'Parcel 1 with DATSs'!K244,IF('General Information'!G6="honey",'Parcel 1 with DATSs'!K245,'Parcel 1 with DATSs'!K246))))))) -> 1 | F6: IF(Total electricity used > 0; (Total electricity used* electricity price)/Parcel dimension; Sum(irrigation,…) *electricity price) | G6: =CONCATENATE("cost revenue dats","_",$A$1,"_",A6,"_",B6) -> cost revenue dats_COST ANALYSIS_ELECTRICITY_Cost of electricity | H6: E6
A7: PESTICIDE | B7: Cost for pesticide | C7: With DATs | D7: =IFERROR(VLOOKUP('General Information'!$G$6, Convalide!$L$2:$M$8, 2,FALSE), "") -> €/l milk | E7: =('Parcel 1 with DATSs'!K82*'Parcel 1 with DATSs'!K83*'General Information'!G50)+('Parcel 1 with DATSs'!K85*'Parcel 1 with DATSs'!K86*'General Information'!G51)+('Parcel 1 with DATSs'!K88*'Parcel 1 with DATSs'!K89*'General Information'!G59) -> 3 | F7: [(N. of treatements of pesticide 1*Amount of pesticide 1*pesticide 1 price)+(N. of treatements of pesticide 2 *Amount of pesticide 2 used *pesticide 2 price) + (N. of treatements of pesticide 3 *Amount of pesticide 3 used *pesticide 3 price (€/kg)] | G7: =CONCATENATE("cost revenue dats","_",$A$1,"_",A7,"_",B7) -> cost revenue dats_COST ANALYSIS_PESTICIDE _Cost for pesticide | H7: E7
A8: FERTILISER | B8: Cost of fertiliser | C8: With DATs | D8: =IFERROR(VLOOKUP('General Information'!$G$6, Convalide!$L$2:$M$8, 2,FALSE), "") -> €/l milk | E8: =('Parcel 1 with DATSs'!K95*'Parcel 1 with DATSs'!K96*'General Information'!G68)+('Parcel 1 with DATSs'!K102*'Parcel 1 with DATSs'!K103*'General Information'!G69)+('Parcel 1 with DATSs'!K109*'Parcel 1 with DATSs'!K110*'General Information'!G70) -> 3 | F8: ((Amount of fertilisers 1 used *Number of fertilizer 1 applications *Fertilisers 1 price) + (Amount of fertilisers 2 used *Number of fertilizer 2 applications *Fertilisers 2 price) + (Amount of fertilisers 3 used *Number of fertilizer 3 applications *Fertilisers 3 price) | G8: =CONCATENATE("cost revenue dats","_",$A$1,"_",A8,"_",B8) -> cost revenue dats_COST ANALYSIS_FERTILISER_Cost of fertiliser | H8: E8
A9: FEED | B9: Cost of feed | C9: With DATs | D9: =IFERROR(VLOOKUP('General Information'!$G$6, Convalide!$L$2:$M$8, 2,FALSE), "") -> €/l milk | E9: =(('General Information'!G79*'Parcel 1 with DATSs'!K151)+('General Information'!G80*'Parcel 1 with DATSs'!K153)+('General Information'!G81*'Parcel 1 with DATSs'!K157))/(IF('General Information'!G6="crop",'Parcel 1 with DATSs'!K10,IF('General Information'!G6="milk",'Parcel 1 with DATSs'!K241,IF('General Information'!G6="meat",'Parcel 1 with DATSs'!K242,IF('General Information'!G6="animal",'Parcel 1 with DATSs'!K243,IF('General Information'!G6="oyster",'Parcel 1 with DATSs'!K244,IF('General Information'!G6="honey",'Parcel 1 with DATSs'!K245,'Parcel 1 with DATSs'!K246))))))) -> 3 | F9: (Amount of feed 1 * Feed 1 price) + (Amount of feed 2 * Feed 2 price) + … /animal | G9: =CONCATENATE("cost revenue dats","_",$A$1,"_",A9,"_",B9) -> cost revenue dats_COST ANALYSIS_FEED_Cost of feed | H9: E9
A10: DRUGS | B10: Cost of drugs | C10: With DATs | D10: =IFERROR(VLOOKUP('General Information'!$G$6, Convalide!$L$2:$M$8, 2,FALSE), "") -> €/l milk | E10: =(('General Information'!G90*'Parcel 1 with DATSs'!K174)+('General Information'!G91*'Parcel 1 with DATSs'!K176)+('General Information'!G92*'Parcel 1 with DATSs'!K178))/(IF('General Information'!G6="crop",'Parcel 1 with DATSs'!K10,IF('General Information'!G6="milk",'Parcel 1 with DATSs'!K241,IF('General Information'!G6="meat",'Parcel 1 with DATSs'!K242,IF('General Information'!G6="animal",'Parcel 1 with DATSs'!K243,IF('General Information'!G6="oyster",'Parcel 1 with DATSs'!K244,IF('General Information'!G6="honey",'Parcel 1 with DATSs'!K245,'Parcel 1 with DATSs'!K246))))))) -> 3 | F10: (Amount of drugs 1 * Feed 1 price) + (Amount of drugs 2 * Feed 2 price) + … /animal or beehives or pieces | G10: =CONCATENATE("cost revenue dats","_",$A$1,"_",A10,"_",B10) -> cost revenue dats_COST ANALYSIS_DRUGS _ Cost of drugs | H10: E10
A11: LABOUR | B11: Cost of labour for irrigation | C11: With DATs | D11: =IFERROR(VLOOKUP('General Information'!$G$6, Convalide!$L$2:$M$8, 2,FALSE), "") -> €/l milk | E11: ='Parcel 1 with DATSs'!K184*'General Information'!G46/'Parcel 1 with DATSs'!K10 -> 1 | F11: number of hours for irrigation activities*Average salary /Parcel dimension | G11: =CONCATENATE("cost revenue dats","_",$A$1,"_",A11,"_",B11) -> cost revenue dats_COST ANALYSIS_LABOUR_Cost of labour for irrigation | H11: E11
A12: LABOUR | B12: Cost of labour for pesticide application | C12: With DATs | D12: =IFERROR(VLOOKUP('General Information'!$G$6, Convalide!$L$2:$M$8, 2,FALSE), "") -> €/l milk | E12: ='Parcel 1 with DATSs'!K185*'General Information'!G46/'Parcel 1 with DATSs'!K10 -> 1 | F12: number of hours for pesticide activities *Average salary /Parcel dimension | G12: =CONCATENATE("cost revenue dats","_",$A$1,"_",A12,"_",B12) -> cost revenue dats_COST ANALYSIS_LABOUR_Cost of labour for pesticide application | H12: E12
A13: LABOUR | B13: Cost of labour for fertilisation | C13: With DATs | D13: =IFERROR(VLOOKUP('General Information'!$G$6, Convalide!$L$2:$M$8, 2,FALSE), "") -> €/l milk | E13: ='Parcel 1 with DATSs'!K186*'General Information'!G46/'Parcel 1 with DATSs'!K10 -> 1 | F13: number of hours for fertilisation activities * Average salary /Parcel dimension | G13: =CONCATENATE("cost revenue dats","_",$A$1,"_",A13,"_",B13) -> cost revenue dats_COST ANALYSIS_LABOUR_Cost of labour for fertilisation | H13: E13
A14: LABOUR | B14: Cost of labour for sowing_planting | C14: With DATs | D14: =IFERROR(VLOOKUP('General Information'!$G$6, Convalide!$L$2:$M$8, 2,FALSE), "") -> €/l milk | E14: ='Parcel 1 with DATSs'!K187*'General Information'!G46/'Parcel 1 with DATSs'!K10 -> 1 | F14: number of hours for sowing_planting activities * Average salary /Parcel dimension | G14: =CONCATENATE("cost revenue dats","_",$A$1,"_",A14,"_",B14) -> cost revenue dats_COST ANALYSIS_LABOUR_Cost of labour for sowing_planting | H14: E14
A15: LABOUR | B15: Cost of labour for pruning | C15: With DATs | D15: =IFERROR(VLOOKUP('General Information'!$G$6, Convalide!$L$2:$M$8, 2,FALSE), "") -> €/l milk | E15: ='Parcel 1 with DATSs'!K188*'General Information'!G46/'Parcel 1 with DATSs'!K10 -> 1 | F15: number of hours for pruning activities *Average salary /Parcel dimension | G15: =CONCATENATE("cost revenue dats","_",$A$1,"_",A15,"_",B15) -> cost revenue dats_COST ANALYSIS_LABOUR_Cost of labour for pruning | H15: E15
A16: LABOUR | B16: Cost of labour for field visits | C16: With DATs | D16: =IFERROR(VLOOKUP('General Information'!$G$6, Convalide!$L$2:$M$8, 2,FALSE), "") -> €/l milk | E16: ='Parcel 1 with DATSs'!K189*'General Information'!G46/'Parcel 1 with DATSs'!K10 -> 1 | F16: number of hours for field visits activities * Average professional salary /Parcel dimension | G16: =CONCATENATE("cost revenue dats","_",$A$1,"_",A16,"_",B16) -> cost revenue dats_COST ANALYSIS_LABOUR_Cost of labour for field visits | H16: E16
A17: LABOUR | B17: Cost of labour for greenhouse maintenance | C17: With DATs | D17: =IFERROR(VLOOKUP('General Information'!$G$6, Convalide!$L$2:$M$8, 2,FALSE), "") -> €/l milk | E17: ='Parcel 1 with DATSs'!K190*'General Information'!G46/'Parcel 1 with DATSs'!K10 -> 1 | F17: number of hours for greenhouse management *Average salary /Parcel dimension | G17: =CONCATENATE("cost revenue dats","_",$A$1,"_",A17,"_",B17) -> cost revenue dats_COST ANALYSIS_LABOUR_Cost of labour for greenhouse maintenance | H17: E17
A18: LABOUR | B18: Cost of labour for tracking the quantity of grain available in the silo | C18: With DATs | D18: =IFERROR(VLOOKUP('General Information'!$G$6, Convalide!$L$2:$M$8, 2,FALSE), "") -> €/l milk | E18: ='Parcel 1 with DATSs'!K191*'General Information'!G46/'Parcel 1 with DATSs'!K246 -> 1 | F18: number of hours for tracking the quantity of grain available in the silo *Average salary | G18: =CONCATENATE("cost revenue dats","_",$A$1,"_",A18,"_",B18) -> cost revenue dats_COST ANALYSIS_LABOUR_Cost of labour for tracking the quantity of grain available in the silo | H18: E18
A19: LABOUR | B19: Cost of labour for assessing product quality | C19: With DATs | D19: =IFERROR(VLOOKUP('General Information'!$G$6, Convalide!$L$2:$M$8, 2,FALSE), "") -> €/l milk | E19: ='Parcel 1 with DATSs'!K192*'General Information'!G46/(IF('General Information'!G6="crop",'Parcel 1 with DATSs'!K10,IF('General Information'!G6="milk",'Parcel 1 with DATSs'!K241,IF('General Information'!G6="meat",'Parcel 1 with DATSs'!K242,IF('General Information'!G6="animal",'Parcel 1 with DATSs'!K243,IF('General Information'!G6="oyster",'Parcel 1 with DATSs'!K244,IF('General Information'!G6="honey",'Parcel 1 with DATSs'!K245,'Parcel 1 with DATSs'!K246))))))) -> 1 | F19: number of hours for assessing grain quality *Average salary | G19: =CONCATENATE("cost revenue dats","_",$A$1,"_",A19,"_",B19) -> cost revenue dats_COST ANALYSIS_LABOUR_Cost of labour for assessing product quality | H19: E19
A20: LABOUR | B20: Cost of labour for controlling purchase and sale prices and quantities | C20: With DATs | D20: =IFERROR(VLOOKUP('General Information'!$G$6, Convalide!$L$2:$M$8, 2,FALSE), "") -> €/l milk | E20: ='Parcel 1 with DATSs'!K193*'General Information'!G46/(IF('General Information'!G6="crop",'Parcel 1 with DATSs'!K10,IF('General Information'!G6="milk",'Parcel 1 with DATSs'!K241,IF('General Information'!G6="meat",'Parcel 1 with DATSs'!K242,IF('General Information'!G6="animal",'Parcel 1 with DATSs'!K243, IF('General Information'!G6="oyster",'Parcel 1 with DATSs'!K244,IF('General Information'!G6="honey",'Parcel 1 with DATSs'!K245,'Parcel 1 with DATSs'!K246))))))) -> 1 | F20: number of hours for controlling purchase and sale prices and quantities *Average salary | G20: =CONCATENATE("cost revenue dats","_",$A$1,"_",A20,"_",B20) -> cost revenue dats_COST ANALYSIS_LABOUR_Cost of labour for controlling purchase and sale prices and quantities | H20: E20
A21: LABOUR | B21: Cost of labour for organise logistics | C21: With DATs | D21: =IFERROR(VLOOKUP('General Information'!$G$6, Convalide!$L$2:$M$8, 2,FALSE), "") -> €/l milk | E21: ='Parcel 1 with DATSs'!K194*'General Information'!G46/(IF('General Information'!G6="crop",'Parcel 1 with DATSs'!K10,IF('General Information'!G6="milk",'Parcel 1 with DATSs'!K241,IF('General Information'!G6="meat",'Parcel 1 with DATSs'!K242,IF('General Information'!G6="animal",'Parcel 1 with DATSs'!K243, IF('General Information'!G6="oyster",'Parcel 1 with DATSs'!K244,IF('General Information'!G6="honey",'Parcel 1 with DATSs'!K245,'Parcel 1 with DATSs'!K246))))))) -> 1 | F21: number of hours for organise logistics *Average salary | G21: =CONCATENATE("cost revenue dats","_",$A$1,"_",A21,"_",B21) -> cost revenue dats_COST ANALYSIS_LABOUR_Cost of labour for organise logistics | H21: E21
A22: LABOUR | B22: Cost of labour for cleaning | C22: With DATs | D22: =IFERROR(VLOOKUP('General Information'!$G$6, Convalide!$L$2:$M$8, 2,FALSE), "") -> €/l milk | E22: ='Parcel 1 with DATSs'!K195*'General Information'!G46/(IF('General Information'!G6="crop",'Parcel 1 with DATSs'!K10,IF('General Information'!G6="milk",'Parcel 1 with DATSs'!K241,IF('General Information'!G6="meat",'Parcel 1 with DATSs'!K242,IF('General Information'!G6="animal",'Parcel 1 with DATSs'!K243, IF('General Information'!G6="oyster",'Parcel 1 with DATSs'!K244,IF('General Information'!G6="honey",'Parcel 1 with DATSs'!K245,'Parcel 1 with DATSs'!K246))))))) -> 1 | F22: number of hours for cleaning *Average salary /animal | G22: =CONCATENATE("cost revenue dats","_",$A$1,"_",A22,"_",B22) -> cost revenue dats_COST ANALYSIS_LABOUR_Cost of labour for cleaning | H22: E22
A23: LABOUR | B23: Cost of labour for stable visits | C23: With DATs | D23: =IFERROR(VLOOKUP('General Information'!$G$6, Convalide!$L$2:$M$8, 2,FALSE), "") -> €/l milk | E23: ='Parcel 1 with DATSs'!K196*'General Information'!G46/(IF('General Information'!G6="crop",'Parcel 1 with DATSs'!K10,IF('General Information'!G6="milk",'Parcel 1 with DATSs'!K241,IF('General Information'!G6="meat",'Parcel 1 with DATSs'!K242,IF('General Information'!G6="animal",'Parcel 1 with DATSs'!K243, IF('General Information'!G6="oyster",'Parcel 1 with DATSs'!K244,IF('General Information'!G6="honey",'Parcel 1 with DATSs'!K245,'Parcel 1 with DATSs'!K246))))))) -> 1 | F23: number of hours for stable visits*Average professional salary /animal | G23: =CONCATENATE("cost revenue dats","_",$A$1,"_",A23,"_",B23) -> cost revenue dats_COST ANALYSIS_LABOUR_Cost of labour for stable visits | H23: E23
A24: LABOUR | B24: Cost of labour for heat detection | C24: With DATs | D24: =IFERROR(VLOOKUP('General Information'!$G$6, Convalide!$L$2:$M$8, 2,FALSE), "") -> €/l milk | E24: ='Parcel 1 with DATSs'!K197*'General Information'!G46/(IF('General Information'!G6="crop",'Parcel 1 with DATSs'!K10,IF('General Information'!G6="milk",'Parcel 1 with DATSs'!K241,IF('General Information'!G6="meat",'Parcel 1 with DATSs'!K242,IF('General Information'!G6="animal",'Parcel 1 with DATSs'!K243, IF('General Information'!G6="oyster",'Parcel 1 with DATSs'!K244,IF('General Information'!G6="honey",'Parcel 1 with DATSs'!K245,'Parcel 1 with DATSs'!K246))))))) -> 1 | F24: number of hours for heat detection *Average salary /animal | G24: =CONCATENATE("cost revenue dats","_",$A$1,"_",A24,"_",B24) -> cost revenue dats_COST ANALYSIS_LABOUR_Cost of labour for heat detection | H24: E24
A25: LABOUR | B25: Cost of labour for calving detection | C25: With DATs | D25: =IFERROR(VLOOKUP('General Information'!$G$6, Convalide!$L$2:$M$8, 2,FALSE), "") -> €/l milk | E25: ='Parcel 1 with DATSs'!K198*'General Information'!G46/(IF('General Information'!G6="crop",'Parcel 1 with DATSs'!K10,IF('General Information'!G6="milk",'Parcel 1 with DATSs'!K241,IF('General Information'!G6="meat",'Parcel 1 with DATSs'!K242,IF('General Information'!G6="animal",'Parcel 1 with DATSs'!K243, IF('General Information'!G6="oyster",'Parcel 1 with DATSs'!K244,IF('General Information'!G6="honey",'Parcel 1 with DATSs'!K245,'Parcel 1 with DATSs'!K246))))))) -> 1 | F25: number of hours for calving detection *Average salary /animal | G25: =CONCATENATE("cost revenue dats","_",$A$1,"_",A25,"_",B25) -> cost revenue dats_COST ANALYSIS_LABOUR_Cost of labour for calving detection | H25: E25
A26: LABOUR | B26: Cost of labour for pigsty management | C26: With DATs | D26: =IFERROR(VLOOKUP('General Information'!$G$6, Convalide!$L$2:$M$8, 2,FALSE), "") -> €/l milk | E26: ='Parcel 1 with DATSs'!K199*'General Information'!G46/(IF('General Information'!G6="crop",'Parcel 1 with DATSs'!K10,IF('General Information'!G6="milk",'Parcel 1 with DATSs'!K241,IF('General Information'!G6="meat",'Parcel 1 with DATSs'!K242,IF('General Information'!G6="animal",'Parcel 1 with DATSs'!K243, IF('General Information'!G6="oyster",'Parcel 1 with DATSs'!K244,IF('General Information'!G6="honey",'Parcel 1 with DATSs'!K245,'Parcel 1 with DATSs'!K246))))))) -> 1 | F26: number of hours for pigsty management*Average salary /animal | G26: =CONCATENATE("cost revenue dats","_",$A$1,"_",A26,"_",B26) -> cost revenue dats_COST ANALYSIS_LABOUR_Cost of labour for pigsty management | H26: E26
A27: LABOUR | B27: Cost of milking | C27: With DATs | D27: =IFERROR(VLOOKUP('General Information'!$G$6, Convalide!$L$2:$M$8, 2,FALSE), "") -> €/l milk | E27: ='Parcel 1 with DATSs'!K200*'General Information'!G46/(IF('General Information'!G6="crop",'Parcel 1 with DATSs'!K10,IF('General Information'!G6="milk",'Parcel 1 with DATSs'!K241,IF('General Information'!G6="meat",'Parcel 1 with DATSs'!K242,IF('General Information'!G6="animal",'Parcel 1 with DATSs'!K243, IF('General Information'!G6="oyster",'Parcel 1 with DATSs'!K244,IF('General Information'!G6="honey",'Parcel 1 with DATSs'!K245,'Parcel 1 with DATSs'!K246))))))) -> 1 | F27: number of hours for milking *Average salary /animal | G27: =CONCATENATE("cost revenue dats","_",$A$1,"_",A27,"_",B27) -> cost revenue dats_COST ANALYSIS_LABOUR_Cost of milking | H27: E27
A28: LABOUR | B28: Cost of labour for (milk) quality assessment | C28: With DATs | D28: =IFERROR(VLOOKUP('General Information'!$G$6, Convalide!$L$2:$M$8, 2,FALSE), "") -> €/l milk | E28: ='Parcel 1 with DATSs'!K201*'General Information'!G46/(IF('General Information'!G6="crop",'Parcel 1 with DATSs'!K10,IF('General Information'!G6="milk",'Parcel 1 with DATSs'!K241,IF('General Information'!G6="meat",'Parcel 1 with DATSs'!K242,IF('General Information'!G6="animal",'Parcel 1 with DATSs'!K243, IF('General Information'!G6="oyster",'Parcel 1 with DATSs'!K244,IF('General Information'!G6="honey",'Parcel 1 with DATSs'!K245,'Parcel 1 with DATSs'!K246))))))) -> 1 | F28: number of hours for (milk) quality assessment*Average salary /animal | G28: =CONCATENATE("cost revenue dats","_",$A$1,"_",A28,"_",B28) -> cost revenue dats_COST ANALYSIS_LABOUR_Cost of labour for (milk) quality assessment | H28: E28
A29: LABOUR | B29: Cost of labour for feeding | C29: With DATs | D29: =IFERROR(VLOOKUP('General Information'!$G$6, Convalide!$L$2:$M$8, 2,FALSE), "") -> €/l milk | E29: ='Parcel 1 with DATSs'!K202*'General Information'!G46/(IF('General Information'!G6="crop",'Parcel 1 with DATSs'!K10,IF('General Information'!G6="milk",'Parcel 1 with DATSs'!K241,IF('General Information'!G6="meat",'Parcel 1 with DATSs'!K242,IF('General Information'!G6="animal",'Parcel 1 with DATSs'!K243, IF('General Information'!G6="oyster",'Parcel 1 with DATSs'!K244,IF('General Information'!G6="honey",'Parcel 1 with DATSs'!K245,'Parcel 1 with DATSs'!K246))))))) -> 1 | F29: number of hours for feeding *Average salary /animal | G29: =CONCATENATE("cost revenue dats","_",$A$1,"_",A29,"_",B29) -> cost revenue dats_COST ANALYSIS_LABOUR_Cost of labour for feeding | H29: E29
A30: LABOUR | B30: Cost of labour for beehives visits | C30: With DATs | D30: =IFERROR(VLOOKUP('General Information'!$G$6, Convalide!$L$2:$M$8, 2,FALSE), "") -> €/l milk | E30: ='Parcel 1 with DATSs'!K203*'General Information'!G46/'Parcel 1 with DATSs'!K245 -> 1 | F30: number of hours for beehives visits *Average salary / beehive | G30: =CONCATENATE("cost revenue dats","_",$A$1,"_",A30,"_",B30) -> cost revenue dats_COST ANALYSIS_LABOUR_Cost of labour for beehives visits | H30: E30
A31: LABOUR | B31: Cost of labour for sampling of oysters | C31: With DATs | D31: =IFERROR(VLOOKUP('General Information'!$G$6, Convalide!$L$2:$M$8, 2,FALSE), "") -> €/l milk | E31: ='Parcel 1 with DATSs'!K204*'General Information'!G46/'Parcel 1 with DATSs'!K244 -> 1 | F31: number of hours for sampling of oysters* Average salary /piece | G31: =CONCATENATE("cost revenue dats","_",$A$1,"_",A31,"_",B31) -> cost revenue dats_COST ANALYSIS_LABOUR_Cost of labour for sampling of oysters | H31: E31
A32: LABOUR | B32: Cost of labour for transporting oysters to the laboratory | C32: With DATs | D32: =IFERROR(VLOOKUP('General Information'!$G$6, Convalide!$L$2:$M$8, 2,FALSE), "") -> €/l milk | E32: ='Parcel 1 with DATSs'!K205*'General Information'!G46/'Parcel 1 with DATSs'!K244 -> 1 | F32: number of hours for transporting oysters to the laboratory*Average salary /piece | G32: =CONCATENATE("cost revenue dats","_",$A$1,"_",A32,"_",B32) -> cost revenue dats_COST ANALYSIS_LABOUR_Cost of labour for transporting oysters to the laboratory | H32: E32
A33: LABOUR | B33: Cost of labour for harvesting | C33: With DATs | D33: =IFERROR(VLOOKUP('General Information'!$G$6, Convalide!$L$2:$M$8, 2,FALSE), "") -> €/l milk | E33: ='Parcel 1 with DATSs'!K206*'General Information'!$G$46/(IF('General Information'!G6="crop",'Parcel 1 with DATSs'!K10,IF('General Information'!G6="milk",'Parcel 1 with DATSs'!K241,IF('General Information'!G6="meat",'Parcel 1 with DATSs'!K242,IF('General Information'!G6="animal",'Parcel 1 with DATSs'!K243, IF('General Information'!G6="oyster",'Parcel 1 with DATSs'!K244,IF('General Information'!G6="honey",'Parcel 1 with DATSs'!K245,'Parcel 1 with DATSs'!K246))))))) -> 1 | F33: number of hours for harvesting oyster*Average salary /piece | G33: =CONCATENATE("cost revenue dats","_",$A$1,"_",A33,"_",B33) -> cost revenue dats_COST ANALYSIS_LABOUR_Cost of labour for harvesting | H33: E33
A34: LABOUR | B34: Cost of labour for storage | C34: With DATs | D34: =IFERROR(VLOOKUP('General Information'!$G$6, Convalide!$L$2:$M$8, 2,FALSE), "") -> €/l milk | E34: ='Parcel 1 with DATSs'!K207*'General Information'!G46/(IF('General Information'!G6="crop",'Parcel 1 with DATSs'!K10,IF('General Information'!G6="milk",'Parcel 1 with DATSs'!K241,IF('General Information'!G6="meat",'Parcel 1 with DATSs'!K242,IF('General Information'!G6="animal",'Parcel 1 with DATSs'!K243, IF('General Information'!G6="oyster",'Parcel 1 with DATSs'!K244,IF('General Information'!G6="honey",'Parcel 1 with DATSs'!K245,'Parcel 1 with DATSs'!K246))))))) -> 1 | F34: number of hours for storage *Average salary /piece | G34: =CONCATENATE("cost revenue dats","_",$A$1,"_",A34,"_",B34) -> cost revenue dats_COST ANALYSIS_LABOUR_Cost of labour for storage | H34: E34
A35: LABOUR | B35: Cost of administrative activities, data collection, etc. | C35: With DATs | D35: =IFERROR(VLOOKUP('General Information'!$G$6, Convalide!$L$2:$M$8, 2,FALSE), "") -> €/l milk | E35: ='Parcel 1 with DATSs'!K208*'General Information'!$G$46/(IF('General Information'!G6="crop",'Parcel 1 with DATSs'!K10,IF('General Information'!G6="milk",'Parcel 1 with DATSs'!K241,IF('General Information'!G6="meat",'Parcel 1 with DATSs'!K242,IF('General Information'!G6="animal",'Parcel 1 with DATSs'!K243, IF('General Information'!G6="oyster",'Parcel 1 with DATSs'!K244,IF('General Information'!G6="honey",'Parcel 1 with DATSs'!K245,'Parcel 1 with DATSs'!K246))))))) -> 1 | F35: number of hours foradministrative activities *Average salary /parcel dimension or animal or beehives or pieces | G35: =CONCATENATE("cost revenue dats","_",$A$1,"_",A35,"_",B35) -> cost revenue dats_COST ANALYSIS_LABOUR_Cost of administrative activities, data collection, etc. | H35: E35
A36: COST | B36: TOT Cost | C36: With DATs | D36: =IFERROR(VLOOKUP('General Information'!$G$6, Convalide!$L$2:$M$8, 2,FALSE), "") -> €/l milk | E36: =SUM(E3:E35) -> 43 | F36: Sum(Cost of labour for irrigation + Cost of labour for fertilisation + … /parcel dimension or animal or beehives or pieces | G36: =CONCATENATE("cost revenue dats","_",$A$1,"_",A36,"_",B36) -> cost revenue dats_COST ANALYSIS_COST_TOT Cost | H36: E36
A37: DATSs | B37: Cost of DATSs | C37: With DATs | D37: =IFERROR(VLOOKUP('General Information'!$G$6, Convalide!$L$2:$M$8, 2,FALSE), "") -> €/l milk | E37: =('General Information'!G23+'General Information'!G24)/(IF('General Information'!G6="crop",'Parcel 1 with DATSs'!K10,IF('General Information'!G6="milk",'Parcel 1 with DATSs'!K241,IF('General Information'!G6="meat",'Parcel 1 with DATSs'!K242,IF('General Information'!G6="animal",'Parcel 1 with DATSs'!K243, IF('General Information'!G6="oyster",'Parcel 1 with DATSs'!K244,IF('General Information'!G6="honey",'Parcel 1 with DATSs'!K245,'Parcel 1 with DATSs'!K246))))))) -> 2 | F37: DAT maintenance + (Training hours*salary) /parcel dimension or animal or beehives or pieces | G37: =CONCATENATE("cost revenue dats","_",$A$1,"_",A37,"_",B37) -> cost revenue dats_COST ANALYSIS_DATSs_Cost of DATSs | H37: E37
A38: DATSs | B38: Cost of Training | C38: With DATs | D38: =IFERROR(VLOOKUP('General Information'!$G$6, Convalide!$L$2:$M$8, 2,FALSE), "") -> €/l milk | E38: ='General Information'!G27/(IF('General Information'!G6="crop",'Parcel 1 with DATSs'!K10,IF('General Information'!G6="milk",'Parcel 1 with DATSs'!K241,IF('General Information'!G6="meat",'Parcel 1 with DATSs'!K242,IF('General Information'!G6="animal",'Parcel 1 with DATSs'!K243, IF('General Information'!G6="oyster",'Parcel 1 with DATSs'!K244,IF('General Information'!G6="honey",'Parcel 1 with DATSs'!K245,'Parcel 1 with DATSs'!K246))))))) -> 1 | F38: Costs of external persons being paid to train employees on the use of DAT /parcel dimension or animal or beehives or pieces | G38: =CONCATENATE("cost revenue dats","_",$A$1,"_",A38,"_",B38) -> cost revenue dats_COST ANALYSIS_DATSs_Cost of Training | H38: E38
G39: No Data | H39: E39
A40: REVENUES ANALYSIS | G40: No Data | H40: E40
A41: CATEGORY | B41: INDICATOR | C41: SCENARIO | D41: UoM | E41: TOTAL | F41: FORMULAS | G41: No Data | H41: E41
A42: OUTPUT | B42: Crop revenue | C42: With DATs | D42: €/ha | E42: ='Parcel 1 with DATSs'!K240/'Parcel 1 with DATSs'!K10*'General Information'!$G$48 -> 1 | F42: Yield*Product market price | G42: =CONCATENATE("cost revenue dats","_",$A$40,"_",A42,"_",B42) -> cost revenue dats_REVENUES ANALYSIS_OUTPUT_Crop revenue | H42: E42
A43: OUTPUT | B43: Milk revenue | C43: With DATs | D43: €/animal | E43: ='Parcel 1 with DATSs'!K241*'General Information'!$G$105/'Parcel 1 with DATSs'!K17 -> 1 | F43: Milk *Product market price | G43: =CONCATENATE("cost revenue dats","_",$A$40,"_",A43,"_",B43) -> cost revenue dats_REVENUES ANALYSIS_OUTPUT_Milk revenue | H43: E43
A44: OUTPUT | B44: Meat revenue | C44: With DATs | D44: €/animal | E44: ='Parcel 1 with DATSs'!K242*'General Information'!G48/'Parcel 1 with DATSs'!K17 -> 1 | F44: Meat*Product market price | G44: =CONCATENATE("cost revenue dats","_",$A$40,"_",A44,"_",B44) -> cost revenue dats_REVENUES ANALYSIS_OUTPUT_Meat revenue | H44: E44
A45: OUTPUT | B45: Oyster revenue | C45: With DATs | D45: €/m2 | E45: ='Parcel 1 with DATSs'!K244*'General Information'!$G$105/'Parcel 1 with DATSs'!K20 -> 1 | F45: Oyster*Product market price | G45: =CONCATENATE("cost revenue dats","_",$A$40,"_",A45,"_",B45) -> cost revenue dats_REVENUES ANALYSIS_OUTPUT_Oyster revenue | H45: E45
A46: OUTPUT | B46: Honey revenue | C46: With DATs | D46: €/beehive | E46: ='Parcel 1 with DATSs'!K245*'General Information'!$G$105/'Parcel 1 with DATSs'!K19 -> 1 | F46: Honey*Product market price | G46: =CONCATENATE("cost revenue dats","_",$A$40,"_",A46,"_",B46) -> cost revenue dats_REVENUES ANALYSIS_OUTPUT_Honey revenue | H46: E46
A47: OUTPUT | B47: Grain (silos) revenue | C47: With DATs | D47: €/t | E47: ='Parcel 1 with DATSs'!K246*'General Information'!G48 -> 1 | G47: =CONCATENATE("cost revenue dats","_",$A$40,"_",A47,"_",B47) -> cost revenue dats_REVENUES ANALYSIS_OUTPUT_Grain (silos) revenue | H47: E47
A48: ADDITIONAL REVENUES | B48: Additional revenues | C48: With DATs | D48: =IFERROR(VLOOKUP('General Information'!$G$6, Convalide!$L$2:$M$8, 2,FALSE), "") -> €/l milk | E48: ='Parcel 1 with DATSs'!K215 -> 1 | F48: Additional revenues | G48: =CONCATENATE("cost revenue dats","_",$A$40,"_",A48,"_",B48) -> cost revenue dats_REVENUES ANALYSIS_ADDITIONAL REVENUES_Additional revenues | H48: E48

Sheet Cost-revenue NO DATS
A1: COST ANALYSIS
A2: INPUT | B2: INDICATOR | C2: SCENARIO | D2: UoM | E2: TOTAL | F2: FORMULAS
A3: WATER | B3: Cost of water | C3: Without DATs | D3: =IFERROR(VLOOKUP('General Information'!$G$6, Convalide!$L$2:$M$8, 2,FALSE), "") -> €/l milk | E3: =('Parcel 1 without DATSs'!G29*'General Information'!G96)/(IF('General Information'!G6="crop",'Parcel 1 without DATSs'!E10,IF('General Information'!G6="milk",'Parcel 1 without DATSs'!G241,IF('General Information'!G6="meat",'Parcel 1 without DATSs'!G242,IF('General Information'!G6="animal",'Parcel 1 without DATSs'!G243,IF('General Information'!G6="oyster",'Parcel 1 without DATSs'!G244,IF('General Information'!G6="honey",'Parcel 1 without DATSs'!G245,'Parcel 1 without DATSs'!G246))))))) -> 1 | F3: IF(Total water used>0; (Total water used * water price)/Parcel dimension; Sum(water Irrigation+ water Fertigation + water Pest dilution + …) * water price) | G3: =CONCATENATE("cost revenue no dats","_",$A$1,"_",A3,"_",B3) -> cost revenue no dats_COST ANALYSIS_WATER _Cost of water | H3: E3
A4: FUEL | B4: Cost of fuel | C4: Without DATs | D4: =IFERROR(VLOOKUP('General Information'!$G$6, Convalide!$L$2:$M$8, 2,FALSE), "") -> €/l milk | E4: ='Parcel 1 without DATSs'!G43*'General Information'!G97/(IF('General Information'!G6="crop",'Parcel 1 without DATSs'!E10,IF('General Information'!G6="milk",'Parcel 1 without DATSs'!G241,IF('General Information'!G6="meat",'Parcel 1 without DATSs'!G242,IF('General Information'!G6="animal",'Parcel 1 without DATSs'!G243,IF('General Information'!G6="oyster",'Parcel 1 without DATSs'!G244,IF('General Information'!G6="honey",'Parcel 1 without DATSs'!G245,'Parcel 1 without DATSs'!G246))))))) -> 1 | F4: IF(Total fuel used>0; (Total fuel used*fuel price)/Parcel dimension; sum(Fertilisation+Pesticides +Irrigation+Sowing_Planting+Pruning+…) * fuel price) | G4: =CONCATENATE("cost revenue no dats","_",$A$1,"_",A4,"_",B4) -> cost revenue no dats_COST ANALYSIS_FUEL _Cost of fuel | H4: E4
A5: GREENHOUSE FUEL | B5: Cost of fuel for greenhouse | C5: Without DATs | D5: =IFERROR(VLOOKUP('General Information'!$G$6, Convalide!$L$2:$M$8, 2,FALSE), "") -> €/l milk | E5: =(('Parcel 1 without DATSs'!G48*'General Information'!G99)+('Parcel 1 without DATSs'!G50*'General Information'!G100)+('Parcel 1 without DATSs'!G52*'General Information'!G101))/'Parcel 1 without DATSs'!E10 -> 3 | G5: =CONCATENATE("cost revenue no dats","_",$A$1,"_",A5,"_",B5) -> cost revenue no dats_COST ANALYSIS_GREENHOUSE FUEL_Cost of fuel for greenhouse | H5: E5
A6: ELECTRICITY | B6: Cost of electricity | C6: Without DATs | D6: =IFERROR(VLOOKUP('General Information'!$G$6, Convalide!$L$2:$M$8, 2,FALSE), "") -> €/l milk | E6: ='Parcel 1 without DATSs'!G68*'General Information'!G102/(IF('General Information'!G6="crop",'Parcel 1 without DATSs'!E10,IF('General Information'!G6="milk",'Parcel 1 without DATSs'!G241,IF('General Information'!G6="meat",'Parcel 1 without DATSs'!G242,IF('General Information'!G6="animal",'Parcel 1 without DATSs'!G243,IF('General Information'!G6="oyster",'Parcel 1 without DATSs'!G244,IF('General Information'!G6="honey",'Parcel 1 without DATSs'!G245,'Parcel 1 without DATSs'!G246))))))) -> 1 | F6: IF(Total electricity used > 0; (Total electricity used* electricity price)/Parcel dimension; Sum(irrigation,…) *electricity price) | G6: =CONCATENATE("cost revenue no dats","_",$A$1,"_",A6,"_",B6) -> cost revenue no dats_COST ANALYSIS_ELECTRICITY_Cost of electricity | H6: E6
A7: PESTICIDE | B7: Cost for pesticide | C7: Without DATs | D7: =IFERROR(VLOOKUP('General Information'!$G$6, Convalide!$L$2:$M$8, 2,FALSE), "") -> €/l milk | E7: =('Parcel 1 without DATSs'!G73*'Parcel 1 without DATSs'!G74*'General Information'!G107)+('Parcel 1 without DATSs'!G76*'Parcel 1 without DATSs'!G77*'General Information'!G108)+('Parcel 1 without DATSs'!G79*'Parcel 1 without DATSs'!G80*'General Information'!G109) -> 3 | F7: [(N. of treatements of pesticide 1*Amount of pesticide 1*pesticide 1 price)+(N. of treatements of pesticide 2 *Amount of pesticide 2 used *pesticide 2 price) + (N. of treatements of pesticide 3 *Amount of pesticide 3 used *pesticide 3 price (€/kg)] | G7: =CONCATENATE("cost revenue no dats","_",$A$1,"_",A7,"_",B7) -> cost revenue no dats_COST ANALYSIS_PESTICIDE _Cost for pesticide | H7: E7
A8: FERTILISER | B8: Cost of fertiliser | C8: Without DATs | D8: =IFERROR(VLOOKUP('General Information'!$G$6, Convalide!$L$2:$M$8, 2,FALSE), "") -> €/l milk | E8: =('Parcel 1 without DATSs'!G95*'Parcel 1 without DATSs'!G96*'General Information'!G111)+('Parcel 1 without DATSs'!G102*'Parcel 1 without DATSs'!G103*'General Information'!G112)+('Parcel 1 without DATSs'!G109*'Parcel 1 without DATSs'!G110*'General Information'!G113) -> 3 | F8: ((Amount of fertilisers 1 used *Number of fertilizer 1 applications *Fertilisers 1 price) + (Amount of fertilisers 2 used *Number of fertilizer 2 applications *Fertilisers 2 price) + (Amount of fertilisers 3 used *Number of fertilizer 3 applications *Fertilisers 3 price) | G8: =CONCATENATE("cost revenue no dats","_",$A$1,"_",A8,"_",B8) -> cost revenue no dats_COST ANALYSIS_FERTILISER_Cost of fertiliser | H8: E8
A9: FEED | B9: Cost of feed | C9: Without DATs | D9: =IFERROR(VLOOKUP('General Information'!$G$6, Convalide!$L$2:$M$8, 2,FALSE), "") -> €/l milk | E9: =('General Information'!G115*'Parcel 1 without DATSs'!G139+'General Information'!G116*'Parcel 1 without DATSs'!G141+'General Information'!G117*'Parcel 1 without DATSs'!G143)/(IF('General Information'!G6="crop",'Parcel 1 without DATSs'!E10,IF('General Information'!G6="milk",'Parcel 1 without DATSs'!G241,IF('General Information'!G6="meat",'Parcel 1 without DATSs'!G242,IF('General Information'!G6="animal",'Parcel 1 without DATSs'!G243,IF('General Information'!G6="oyster",'Parcel 1 without DATSs'!G244,IF('General Information'!G6="honey",'Parcel 1 without DATSs'!G245,'Parcel 1 without DATSs'!G246))))))) -> 3 | F9: (Amount of feed 1 * Feed 1 price) + (Amount of feed 2 * Feed 2 price) + … /animal | G9: =CONCATENATE("cost revenue no dats","_",$A$1,"_",A9,"_",B9) -> cost revenue no dats_COST ANALYSIS_FEED_Cost of feed | H9: E9
A10: DRUGS | B10: Cost of drugs | C10: Without DATs | D10: =IFERROR(VLOOKUP('General Information'!$G$6, Convalide!$L$2:$M$8, 2,FALSE), "") -> €/l milk | E10: =('General Information'!G119*'Parcel 1 without DATSs'!G162+'General Information'!G120*'Parcel 1 without DATSs'!G164+'General Information'!G121*'Parcel 1 without DATSs'!G166)/(IF('General Information'!G6="crop",'Parcel 1 without DATSs'!E10,IF('General Information'!G6="milk",'Parcel 1 without DATSs'!G241,IF('General Information'!G6="meat",'Parcel 1 without DATSs'!G242,IF('General Information'!G6="animal",'Parcel 1 without DATSs'!G243,IF('General Information'!G6="oyster",'Parcel 1 without DATSs'!G244,IF('General Information'!G6="honey",'Parcel 1 without DATSs'!G245,'Parcel 1 without DATSs'!G246))))))) -> 3 | F10: (Amount of drugs 1 * Feed 1 price) + (Amount of drugs 2 * Feed 2 price) + … /animal or beehives or pieces | G10: =CONCATENATE("cost revenue no dats","_",$A$1,"_",A10,"_",B10) -> cost revenue no dats_COST ANALYSIS_DRUGS _ Cost of drugs | H10: E10
A11: LABOUR | B11: Cost of labour for irrigation | C11: Without DATs | D11: =IFERROR(VLOOKUP('General Information'!$G$6, Convalide!$L$2:$M$8, 2,FALSE), "") -> €/l milk | E11: ='Parcel 1 without DATSs'!G184*'General Information'!G103/'Parcel 1 without DATSs'!E10 -> 1 | F11: number of hours for irrigation activities*Average salary /Parcel dimension | G11: =CONCATENATE("cost revenue no dats","_",$A$1,"_",A11,"_",B11) -> cost revenue no dats_COST ANALYSIS_LABOUR_Cost of labour for irrigation | H11: E11
A12: LABOUR | B12: Cost of labour for pesticide | C12: Without DATs | D12: =IFERROR(VLOOKUP('General Information'!$G$6, Convalide!$L$2:$M$8, 2,FALSE), "") -> €/l milk | E12: ='Parcel 1 without DATSs'!G185*'General Information'!G103/'Parcel 1 without DATSs'!E10 -> 1 | F12: number of hours for pesticide activities *Average salary /Parcel dimension | G12: =CONCATENATE("cost revenue no dats","_",$A$1,"_",A12,"_",B12) -> cost revenue no dats_COST ANALYSIS_LABOUR_Cost of labour for pesticide | H12: E12
A13: LABOUR | B13: Cost of labour for fertilisation | C13: Without DATs | D13: =IFERROR(VLOOKUP('General Information'!$G$6, Convalide!$L$2:$M$8, 2,FALSE), "") -> €/l milk | E13: ='Parcel 1 without DATSs'!G186*'General Information'!G103/'Parcel 1 without DATSs'!E10 -> 1 | F13: number of hours for fertilisation activities * Average salary /Parcel dimension | G13: =CONCATENATE("cost revenue no dats","_",$A$1,"_",A13,"_",B13) -> cost revenue no dats_COST ANALYSIS_LABOUR_Cost of labour for fertilisation | H13: E13
A14: LABOUR | B14: Cost of labour for sowing_planting | C14: Without DATs | D14: =IFERROR(VLOOKUP('General Information'!$G$6, Convalide!$L$2:$M$8, 2,FALSE), "") -> €/l milk | E14: ='Parcel 1 without DATSs'!G187*'General Information'!G103/'Parcel 1 without DATSs'!E10 -> 1 | F14: number of hours for sowing_planting activities * Average salary /Parcel dimension | G14: =CONCATENATE("cost revenue no dats","_",$A$1,"_",A14,"_",B14) -> cost revenue no dats_COST ANALYSIS_LABOUR_Cost of labour for sowing_planting | H14: E14
A15: LABOUR | B15: Cost of labour for pruning | C15: Without DATs | D15: =IFERROR(VLOOKUP('General Information'!$G$6, Convalide!$L$2:$M$8, 2,FALSE), "") -> €/l milk | E15: ='Parcel 1 without DATSs'!G188*'General Information'!G103/'Parcel 1 without DATSs'!E10 -> 1 | F15: number of hours for pruning activities *Average salary /Parcel dimension | G15: =CONCATENATE("cost revenue no dats","_",$A$1,"_",A15,"_",B15) -> cost revenue no dats_COST ANALYSIS_LABOUR_Cost of labour for pruning | H15: E15
A16: LABOUR | B16: Cost of labour for field visits | C16: Without DATs | D16: =IFERROR(VLOOKUP('General Information'!$G$6, Convalide!$L$2:$M$8, 2,FALSE), "") -> €/l milk | E16: ='Parcel 1 without DATSs'!G189*'General Information'!G103/'Parcel 1 without DATSs'!E10 -> 1 | F16: number of hours for field visits activities * Average professional salary /Parcel dimension | G16: =CONCATENATE("cost revenue no dats","_",$A$1,"_",A16,"_",B16) -> cost revenue no dats_COST ANALYSIS_LABOUR_Cost of labour for field visits | H16: E16
A17: LABOUR | B17: Cost of labour for greenhouse management | C17: Without DATs | D17: =IFERROR(VLOOKUP('General Information'!$G$6, Convalide!$L$2:$M$8, 2,FALSE), "") -> €/l milk | E17: ='Parcel 1 without DATSs'!G190*'General Information'!G103/'Parcel 1 without DATSs'!E10 -> 1 | F17: number of hours for greenhouse management *Average salary /Parcel dimension | G17: =CONCATENATE("cost revenue no dats","_",$A$1,"_",A17,"_",B17) -> cost revenue no dats_COST ANALYSIS_LABOUR_Cost of labour for greenhouse management | H17: E17
A18: LABOUR | B18: Cost of labour for tracking the quantity of grain available in the silo | C18: Without DATs | D18: =IFERROR(VLOOKUP('General Information'!$G$6, Convalide!$L$2:$M$8, 2,FALSE), "") -> €/l milk | E18: ='Parcel 1 without DATSs'!G191*'General Information'!G103/'Parcel 1 without DATSs'!E10 -> 1 | F18: number of hours for tracking the quantity of grain available in the silo *Average salary | G18: =CONCATENATE("cost revenue no dats","_",$A$1,"_",A18,"_",B18) -> cost revenue no dats_COST ANALYSIS_LABOUR_Cost of labour for tracking the quantity of grain available in the silo | H18: E18
A19: LABOUR | B19: Cost of labour for assessing product quality | C19: Without DATs | D19: =IFERROR(VLOOKUP('General Information'!$G$6, Convalide!$L$2:$M$8, 2,FALSE), "") -> €/l milk | E19: ='Parcel 1 without DATSs'!G192*'General Information'!G103/(IF('General Information'!G6="crop",'Parcel 1 without DATSs'!E10,IF('General Information'!G6="milk",'Parcel 1 without DATSs'!G241,IF('General Information'!G6="meat",'Parcel 1 without DATSs'!G242,IF('General Information'!G6="animal",'Parcel 1 without DATSs'!G243,IF('General Information'!G6="oyster",'Parcel 1 without DATSs'!G244,IF('General Information'!G6="honey",'Parcel 1 without DATSs'!G245,'Parcel 1 without DATSs'!G246))))))) -> 1 | F19: number of hours for assessing grain quality *Average salary | G19: =CONCATENATE("cost revenue no dats","_",$A$1,"_",A19,"_",B19) -> cost revenue no dats_COST ANALYSIS_LABOUR_Cost of labour for assessing product quality | H19: E19
A20: LABOUR | B20: Cost of labour for controlling purchase and sale prices and quantities | C20: Without DATs | D20: =IFERROR(VLOOKUP('General Information'!$G$6, Convalide!$L$2:$M$8, 2,FALSE), "") -> €/l milk | E20: ='Parcel 1 without DATSs'!G193*'General Information'!G103/(IF('General Information'!G6="crop",'Parcel 1 without DATSs'!E10,IF('General Information'!G6="milk",'Parcel 1 without DATSs'!G241,IF('General Information'!G6="meat",'Parcel 1 without DATSs'!G242,IF('General Information'!G6="animal",'Parcel 1 without DATSs'!G243,IF('General Information'!G6="oyster",'Parcel 1 without DATSs'!G244,IF('General Information'!G6="honey",'Parcel 1 without DATSs'!G245,'Parcel 1 without DATSs'!G246))))))) -> 1 | F20: number of hours for controlling purchase and sale prices and quantities *Average salary | G20: =CONCATENATE("cost revenue no dats","_",$A$1,"_",A20,"_",B20) -> cost revenue no dats_COST ANALYSIS_LABOUR_Cost of labour for controlling purchase and sale prices and quantities | H20: E20
A21: LABOUR | B21: Cost of labour for organising logistics | C21: Without DATs | D21: =IFERROR(VLOOKUP('General Information'!$G$6, Convalide!$L$2:$M$8, 2,FALSE), "") -> €/l milk | E21: ='Parcel 1 without DATSs'!G194*'General Information'!G103/(IF('General Information'!G6="crop",'Parcel 1 without DATSs'!E10,IF('General Information'!G6="milk",'Parcel 1 without DATSs'!G241,IF('General Information'!G6="meat",'Parcel 1 without DATSs'!G242,IF('General Information'!G6="animal",'Parcel 1 without DATSs'!G243,IF('General Information'!G6="oyster",'Parcel 1 without DATSs'!G244,IF('General Information'!G6="honey",'Parcel 1 without DATSs'!G245,'Parcel 1 without DATSs'!G246))))))) -> 1 | F21: number of hours for organise logistics *Average salary | G21: =CONCATENATE("cost revenue no dats","_",$A$1,"_",A21,"_",B21) -> cost revenue no dats_COST ANALYSIS_LABOUR_Cost of labour for organising logistics | H21: E21
A22: LABOUR | B22: Cost of labour for cleaning | C22: Without DATs | D22: =IFERROR(VLOOKUP('General Information'!$G$6, Convalide!$L$2:$M$8, 2,FALSE), "") -> €/l milk | E22: ='Parcel 1 without DATSs'!G195*'General Information'!G103/(IF('General Information'!G6="crop",'Parcel 1 without DATSs'!E10,IF('General Information'!G6="milk",'Parcel 1 without DATSs'!G241,IF('General Information'!G6="meat",'Parcel 1 without DATSs'!G242,IF('General Information'!G6="animal",'Parcel 1 without DATSs'!G243,IF('General Information'!G6="oyster",'Parcel 1 without DATSs'!G244,IF('General Information'!G6="honey",'Parcel 1 without DATSs'!G245,'Parcel 1 without DATSs'!G246))))))) -> 1 | F22: number of hours for cleaning *Average salary /animal | G22: =CONCATENATE("cost revenue no dats","_",$A$1,"_",A22,"_",B22) -> cost revenue no dats_COST ANALYSIS_LABOUR_Cost of labour for cleaning | H22: E22
A23: LABOUR | B23: Cost of labour for stable visits | C23: Without DATs | D23: =IFERROR(VLOOKUP('General Information'!$G$6, Convalide!$L$2:$M$8, 2,FALSE), "") -> €/l milk | E23: ='Parcel 1 without DATSs'!G196*'General Information'!G103/(IF('General Information'!G6="crop",'Parcel 1 without DATSs'!E10,IF('General Information'!G6="milk",'Parcel 1 without DATSs'!G241,IF('General Information'!G6="meat",'Parcel 1 without DATSs'!G242,IF('General Information'!G6="animal",'Parcel 1 without DATSs'!G243,IF('General Information'!G6="oyster",'Parcel 1 without DATSs'!G244,IF('General Information'!G6="honey",'Parcel 1 without DATSs'!G245,'Parcel 1 without DATSs'!G246))))))) -> 1 | F23: number of hours for stable visits*Average professional salary /animal | G23: =CONCATENATE("cost revenue no dats","_",$A$1,"_",A23,"_",B23) -> cost revenue no dats_COST ANALYSIS_LABOUR_Cost of labour for stable visits | H23: E23
A24: LABOUR | B24: Cost of labour for heat detection | C24: Without DATs | D24: =IFERROR(VLOOKUP('General Information'!$G$6, Convalide!$L$2:$M$8, 2,FALSE), "") -> €/l milk | E24: ='Parcel 1 without DATSs'!G197*'General Information'!G103/(IF('General Information'!G6="crop",'Parcel 1 without DATSs'!E10,IF('General Information'!G6="milk",'Parcel 1 without DATSs'!G241,IF('General Information'!G6="meat",'Parcel 1 without DATSs'!G242,IF('General Information'!G6="animal",'Parcel 1 without DATSs'!G243,IF('General Information'!G6="oyster",'Parcel 1 without DATSs'!G244,IF('General Information'!G6="honey",'Parcel 1 without DATSs'!G245,'Parcel 1 without DATSs'!G246))))))) -> 1 | F24: number of hours for heat detection *Average salary /animal | G24: =CONCATENATE("cost revenue no dats","_",$A$1,"_",A24,"_",B24) -> cost revenue no dats_COST ANALYSIS_LABOUR_Cost of labour for heat detection | H24: E24
A25: LABOUR | B25: Cost of labour for calving detection | C25: Without DATs | D25: =IFERROR(VLOOKUP('General Information'!$G$6, Convalide!$L$2:$M$8, 2,FALSE), "") -> €/l milk | E25: ='Parcel 1 without DATSs'!G198*'General Information'!G103/(IF('General Information'!G6="crop",'Parcel 1 without DATSs'!E10,IF('General Information'!G6="milk",'Parcel 1 without DATSs'!G241,IF('General Information'!G6="meat",'Parcel 1 without DATSs'!G242,IF('General Information'!G6="animal",'Parcel 1 without DATSs'!G243,IF('General Information'!G6="oyster",'Parcel 1 without DATSs'!G244,IF('General Information'!G6="honey",'Parcel 1 without DATSs'!G245,'Parcel 1 without DATSs'!G246))))))) -> 1 | F25: number of hours for calving detection *Average salary /animal | G25: =CONCATENATE("cost revenue no dats","_",$A$1,"_",A25,"_",B25) -> cost revenue no dats_COST ANALYSIS_LABOUR_Cost of labour for calving detection | H25: E25
A26: LABOUR | B26: Cost of labour for pigsty management | C26: Without DATs | D26: =IFERROR(VLOOKUP('General Information'!$G$6, Convalide!$L$2:$M$8, 2,FALSE), "") -> €/l milk | E26: ='Parcel 1 without DATSs'!G199*'General Information'!G103/(IF('General Information'!G6="crop",'Parcel 1 without DATSs'!E10,IF('General Information'!G6="milk",'Parcel 1 without DATSs'!G241,IF('General Information'!G6="meat",'Parcel 1 without DATSs'!G242,IF('General Information'!G6="animal",'Parcel 1 without DATSs'!G243,IF('General Information'!G6="oyster",'Parcel 1 without DATSs'!G244,IF('General Information'!G6="honey",'Parcel 1 without DATSs'!G245,'Parcel 1 without DATSs'!G246))))))) -> 1 | F26: number of hours for pigsty management*Average salary /animal | G26: =CONCATENATE("cost revenue no dats","_",$A$1,"_",A26,"_",B26) -> cost revenue no dats_COST ANALYSIS_LABOUR_Cost of labour for pigsty management | H26: E26
A27: LABOUR | B27: Cost of milking | C27: Without DATs | D27: =IFERROR(VLOOKUP('General Information'!$G$6, Convalide!$L$2:$M$8, 2,FALSE), "") -> €/l milk | E27: ='Parcel 1 without DATSs'!G200*'General Information'!G103/(IF('General Information'!G6="crop",'Parcel 1 without DATSs'!E10,IF('General Information'!G6="milk",'Parcel 1 without DATSs'!G241,IF('General Information'!G6="meat",'Parcel 1 without DATSs'!G242,IF('General Information'!G6="animal",'Parcel 1 without DATSs'!G243,IF('General Information'!G6="oyster",'Parcel 1 without DATSs'!G244,IF('General Information'!G6="honey",'Parcel 1 without DATSs'!G245,'Parcel 1 without DATSs'!G246))))))) -> 1 | F27: number of hours for milking *Average salary /animal | G27: =CONCATENATE("cost revenue no dats","_",$A$1,"_",A27,"_",B27) -> cost revenue no dats_COST ANALYSIS_LABOUR_Cost of milking | H27: E27
A28: LABOUR | B28: Cost of labour for (milk) quality assessment | C28: Without DATs | D28: =IFERROR(VLOOKUP('General Information'!$G$6, Convalide!$L$2:$M$8, 2,FALSE), "") -> €/l milk | E28: ='Parcel 1 without DATSs'!G201*'General Information'!G103/(IF('General Information'!G6="crop",'Parcel 1 without DATSs'!E10,IF('General Information'!G6="milk",'Parcel 1 without DATSs'!G241,IF('General Information'!G6="meat",'Parcel 1 without DATSs'!G242,IF('General Information'!G6="animal",'Parcel 1 without DATSs'!G243,IF('General Information'!G6="oyster",'Parcel 1 without DATSs'!G244,IF('General Information'!G6="honey",'Parcel 1 without DATSs'!G245,'Parcel 1 without DATSs'!G246))))))) -> 1 | F28: number of hours for (milk) quality assessment*Average salary /animal | G28: =CONCATENATE("cost revenue no dats","_",$A$1,"_",A28,"_",B28) -> cost revenue no dats_COST ANALYSIS_LABOUR_Cost of labour for (milk) quality assessment | H28: E28
A29: LABOUR | B29: Cost of labour for feeding | C29: Without DATs | D29: =IFERROR(VLOOKUP('General Information'!$G$6, Convalide!$L$2:$M$8, 2,FALSE), "") -> €/l milk | E29: ='Parcel 1 without DATSs'!G202*'General Information'!G103/(IF('General Information'!G6="crop",'Parcel 1 without DATSs'!E10,IF('General Information'!G6="milk",'Parcel 1 without DATSs'!G241,IF('General Information'!G6="meat",'Parcel 1 without DATSs'!G242,IF('General Information'!G6="animal",'Parcel 1 without DATSs'!G243,IF('General Information'!G6="oyster",'Parcel 1 without DATSs'!G244,IF('General Information'!G6="honey",'Parcel 1 without DATSs'!G245,'Parcel 1 without DATSs'!G246))))))) -> 1 | F29: number of hours for feeding *Average salary /animal | G29: =CONCATENATE("cost revenue no dats","_",$A$1,"_",A29,"_",B29) -> cost revenue no dats_COST ANALYSIS_LABOUR_Cost of labour for feeding | H29: E29
A30: LABOUR | B30: Cost of labour for beehives visits | C30: Without DATs | D30: =IFERROR(VLOOKUP('General Information'!$G$6, Convalide!$L$2:$M$8, 2,FALSE), "") -> €/l milk | E30: ='Parcel 1 without DATSs'!G203*'General Information'!G103/'Parcel 1 without DATSs'!E19 -> 1 | F30: number of hours for beehives visits *Average salary / beehive | G30: =CONCATENATE("cost revenue no dats","_",$A$1,"_",A30,"_",B30) -> cost revenue no dats_COST ANALYSIS_LABOUR_Cost of labour for beehives visits | H30: E30
A31: LABOUR | B31: Cost of labour for sampling of oysters | C31: Without DATs | D31: =IFERROR(VLOOKUP('General Information'!$G$6, Convalide!$L$2:$M$8, 2,FALSE), "") -> €/l milk | E31: ='Parcel 1 without DATSs'!G204*'General Information'!G103/'Parcel 1 without DATSs'!G244 -> 1 | F31: number of hours for sampling of oysters* Average salary /piece | G31: =CONCATENATE("cost revenue no dats","_",$A$1,"_",A31,"_",B31) -> cost revenue no dats_COST ANALYSIS_LABOUR_Cost of labour for sampling of oysters | H31: E31
A32: LABOUR | B32: Cost of labour for transporting oysters to the laboratory | C32: Without DATs | D32: =IFERROR(VLOOKUP('General Information'!$G$6, Convalide!$L$2:$M$8, 2,FALSE), "") -> €/l milk | E32: ='Parcel 1 without DATSs'!G205*'General Information'!G103/'Parcel 1 without DATSs'!G244 -> 1 | F32: number of hours for transporting oysters to the laboratory*Average salary /piece | G32: =CONCATENATE("cost revenue no dats","_",$A$1,"_",A32,"_",B32) -> cost revenue no dats_COST ANALYSIS_LABOUR_Cost of labour for transporting oysters to the laboratory | H32: E32
A33: LABOUR | B33: Cost of labour for harvesting | C33: Without DATs | D33: =IFERROR(VLOOKUP('General Information'!$G$6, Convalide!$L$2:$M$8, 2,FALSE), "") -> €/l milk | E33: ='Parcel 1 without DATSs'!G206*'General Information'!G103/(IF('General Information'!G6="crop",'Parcel 1 without DATSs'!E10,IF('General Information'!G6="milk",'Parcel 1 without DATSs'!G241,IF('General Information'!G6="meat",'Parcel 1 without DATSs'!G242,IF('General Information'!G6="animal",'Parcel 1 without DATSs'!G243,IF('General Information'!G6="oyster",'Parcel 1 without DATSs'!G244,IF('General Information'!G6="honey",'Parcel 1 without DATSs'!G245,'Parcel 1 without DATSs'!G246))))))) -> 1 | F33: number of hours for harvesting oyster*Average salary /piece | G33: =CONCATENATE("cost revenue no dats","_",$A$1,"_",A33,"_",B33) -> cost revenue no dats_COST ANALYSIS_LABOUR_Cost of labour for harvesting | H33: E33
A34: LABOUR | B34: Cost of labour for storage | C34: Without DATs | D34: =IFERROR(VLOOKUP('General Information'!$G$6, Convalide!$L$2:$M$8, 2,FALSE), "") -> €/l milk | E34: ='Parcel 1 without DATSs'!G207*'General Information'!G103/(IF('General Information'!G6="crop",'Parcel 1 without DATSs'!E10,IF('General Information'!G6="milk",'Parcel 1 without DATSs'!G241,IF('General Information'!G6="meat",'Parcel 1 without DATSs'!G242,IF('General Information'!G6="animal",'Parcel 1 without DATSs'!G243,IF('General Information'!G6="oyster",'Parcel 1 without DATSs'!G244,IF('General Information'!G6="honey",'Parcel 1 without DATSs'!G245,'Parcel 1 without DATSs'!G246))))))) -> 1 | F34: number of hours for storage *Average salary /piece | G34: =CONCATENATE("cost revenue no dats","_",$A$1,"_",A34,"_",B34) -> cost revenue no dats_COST ANALYSIS_LABOUR_Cost of labour for storage | H34: E34
A35: LABOUR | B35: Cost of administrative activities, data collection, etc. | C35: Without DATs | D35: =IFERROR(VLOOKUP('General Information'!$G$6, Convalide!$L$2:$M$8, 2,FALSE), "") -> €/l milk | E35: ='Parcel 1 without DATSs'!G208*'General Information'!G103/(IF('General Information'!G6="crop",'Parcel 1 without DATSs'!E10,IF('General Information'!G6="milk",'Parcel 1 without DATSs'!G241,IF('General Information'!G6="meat",'Parcel 1 without DATSs'!G242,IF('General Information'!G6="animal",'Parcel 1 without DATSs'!G243,IF('General Information'!G6="oyster",'Parcel 1 without DATSs'!G244,IF('General Information'!G6="honey",'Parcel 1 without DATSs'!G245,'Parcel 1 without DATSs'!G246))))))) -> 1 | F35: number of hours foradministrative activities *Average salary /parcel dimension or animal or beehives or pieces | G35: =CONCATENATE("cost revenue no dats","_",$A$1,"_",A35,"_",B35) -> cost revenue no dats_COST ANALYSIS_LABOUR_Cost of administrative activities, data collection, etc. | H35: E35
A36: COST | B36: TOT Cost | C36: Without DATs | D36: =IFERROR(VLOOKUP('General Information'!$G$6, Convalide!$L$2:$M$8, 2,FALSE), "") -> €/l milk | E36: =SUMIF(E3:E35, "<>#RIF!") -> 43 | F36: Sum(Cost of labour for irrigation + Cost of labour for fertilisation + … /parcel dimension or animal or beehives or pieces | G36: =CONCATENATE("cost revenue no dats","_",$A$1,"_",A36,"_",B36) -> cost revenue no dats_COST ANALYSIS_COST_TOT Cost | H36: E36
A37: DAT | B37: Cost of DAT | C37: Without DATs | E37: 0 | G37: =CONCATENATE("cost revenue no dats","_",$A$1,"_",A37,"_",B37) -> cost revenue no dats_COST ANALYSIS_DAT_Cost of DAT | H37: E37
A38: DAT | B38: Cost of Training | C38: Without DATs | E38: 0 | G38: =CONCATENATE("cost revenue no dats","_",$A$1,"_",A38,"_",B38) -> cost revenue no dats_COST ANALYSIS_DAT_Cost of Training | H38: E38
G39: No Data | H39: E39
A40: REVENUES ANALYSIS | G40: No Data | H40: E40
A41: CATEGORY | B41: INDICATOR | C41: SCENARIO | D41: UoM | E41: TOTAL | F41: FORMULAS | G41: No Data | H41: E41
A42: OUTPUT | B42: Crop revenue | C42: Without DATs | D42: €/ha | E42: ='Parcel 1 without DATSs'!G240/'Parcel 1 without DATSs'!E10*'General Information'!G105 -> 1 | F42: Yield*Product market price | G42: =CONCATENATE("cost revenue no dats","_",$A$40,"_",A42,"_",B42) -> cost revenue no dats_REVENUES ANALYSIS_OUTPUT_Crop revenue | H42: E42
A43: OUTPUT | B43: Milk revenue | C43: Without DATs | D43: €/animal | E43: ='Parcel 1 without DATSs'!G241/'Parcel 1 without DATSs'!E17*'General Information'!G105 -> 1 | F43: Milk *Product market price | G43: =CONCATENATE("cost revenue no dats","_",$A$40,"_",A43,"_",B43) -> cost revenue no dats_REVENUES ANALYSIS_OUTPUT_Milk revenue | H43: E43
A44: OUTPUT | B44: Meat revenue | C44: Without DATs | D44: €/animal | E44: ='Parcel 1 without DATSs'!G242/'Parcel 1 without DATSs'!E17*'General Information'!G105 -> 1 | F44: Meat*Product market price | G44: =CONCATENATE("cost revenue no dats","_",$A$40,"_",A44,"_",B44) -> cost revenue no dats_REVENUES ANALYSIS_OUTPUT_Meat revenue | H44: E44
A45: OUTPUT | B45: Oyster revenue | C45: Without DATs | D45: €/m2 | E45: ='Parcel 1 without DATSs'!G244/'Parcel 1 without DATSs'!E20*'General Information'!G105 -> 1 | F45: Oyster*Product market price | G45: =CONCATENATE("cost revenue no dats","_",$A$40,"_",A45,"_",B45) -> cost revenue no dats_REVENUES ANALYSIS_OUTPUT_Oyster revenue | H45: E45
A46: OUTPUT | B46: Honey revenue | C46: Without DATs | D46: €/beehive | E46: ='Parcel 1 without DATSs'!G245/'Parcel 1 without DATSs'!E19*'General Information'!G105 -> 1 | F46: Honey*Product market price | G46: =CONCATENATE("cost revenue no dats","_",$A$40,"_",A46,"_",B46) -> cost revenue no dats_REVENUES ANALYSIS_OUTPUT_Honey revenue | H46: E46
A47: OUTPUT | B47: Grain (silos) revenue | C47: Without DATs | D47: €/t | E47: ='Parcel 1 without DATSs'!G246*'General Information'!G105 -> 1 | G47: =CONCATENATE("cost revenue no dats","_",$A$40,"_",A47,"_",B47) -> cost revenue no dats_REVENUES ANALYSIS_OUTPUT_Grain (silos) revenue | H47: E47
A48: ADDITIONAL REVENUES | B48: Additional revenues | C48: Without DATs | D48: =IFERROR(VLOOKUP('General Information'!$G$6, Convalide!$L$2:$M$8, 2,FALSE), "") -> €/l milk | E48: ='Parcel 1 without DATSs'!G215 -> 1 | F48: Additional revenues | G48: =CONCATENATE("cost revenue no dats","_",$A$40,"_",A48,"_",B48) -> cost revenue no dats_REVENUES ANALYSIS_ADDITIONAL REVENUES_Additional revenues | H48: E48

Sheet sust. impact KPIs DATS
A1: Economic PRODUCTIVITY
B2: INDICATOR | C2: SCENARIO | D2: UoM | E2: TOTAL | F2: FORMULAS
B3: Yield | C3: With DATs | D3: t / ha | E3: ='Parcel 1 with DATSs'!K240/'Parcel 1 with DATSs'!K10 -> 1 | F3: total production / parcel area | G3: =CONCATENATE("sust kpis dats","_",$A$1,"_",B3) -> sust kpis dats_Economic PRODUCTIVITY _Yield | H3: E3
B4: Labour productivity (arable and horticulture) | C4: With DATs | D4: t / h | E4: ='Parcel 1 with DATSs'!K240/SUM('Parcel 1 with DATSs'!K184:K208) -> 0.04 | F4: total production / hours of labour employed | G4: =CONCATENATE("sust kpis dats","_",$A$1,"_",B4) -> sust kpis dats_Economic PRODUCTIVITY _Labour productivity (arable and horticulture) | H4: E4
B5: Labour productivity (dairy livestock) | C5: With DATs | D5: l milk/h | E5: ='Parcel 1 with DATSs'!K241/SUM('Parcel 1 with DATSs'!K184:K208) -> 0.04 | F5: total production / hours of labour employed | G5: =CONCATENATE("sust kpis dats","_",$A$1,"_",B5) -> sust kpis dats_Economic PRODUCTIVITY _Labour productivity (dairy livestock) | H5: E5
B6: Labour productivity (meat livestock) | C6: With DATs | D6: kg meat/h | E6: ='Parcel 1 with DATSs'!K242/SUM('Parcel 1 with DATSs'!K184:K208) -> 0.04 | F6: total production / hours of labour employed | G6: =CONCATENATE("sust kpis dats","_",$A$1,"_",B6) -> sust kpis dats_Economic PRODUCTIVITY _Labour productivity (meat livestock) | H6: E6
B7: Labour productivity (aquaculture) | C7: With DATs | D7: pieces/h | E7: ='Parcel 1 with DATSs'!K244/SUM('Parcel 1 with DATSs'!K184:K208) -> 0.04 | F7: total production / hours of labour employed | G7: =CONCATENATE("sust kpis dats","_",$A$1,"_",B7) -> sust kpis dats_Economic PRODUCTIVITY _Labour productivity (aquaculture) | H7: E7
B8: Labour productivity (apiculture) | C8: With DATs | D8: kg honey/h | E8: ='Parcel 1 with DATSs'!K245/SUM('Parcel 1 with DATSs'!K184:K208) -> 0.04 | F8: total production / hours of labour employed | G8: =CONCATENATE("sust kpis dats","_",$A$1,"_",B8) -> sust kpis dats_Economic PRODUCTIVITY _Labour productivity (apiculture) | H8: E8
B9: Labour productivity (silos) | C9: With DATs | D9: t/h | E9: ='Parcel 1 with DATSs'!K246/SUM('Parcel 1 with DATSs'!K184:K208) -> 0.04 | G9: =CONCATENATE("sust kpis dats","_",$A$1,"_",B9) -> sust kpis dats_Economic PRODUCTIVITY _Labour productivity (silos) | H9: E9
B10: Milk productivity | C10: With DATs | D10: l milk/cow/day | E10: ='Parcel 1 with DATSs'!K241/'Parcel 1 with DATSs'!K17/(('General Information'!G10-'General Information'!G9)+1) -> 1 | F10: total milk production / total number of cows | G10: =CONCATENATE("sust kpis dats","_",$A$1,"_",B10) -> sust kpis dats_Economic PRODUCTIVITY _Milk productivity | H10: E10
B11: Meat productivity | C11: With DATs | D11: kg meat/animal/day | E11: ='Parcel 1 with DATSs'!K242/'Parcel 1 with DATSs'!K17/(('General Information'!G10-'General Information'!G9)+1) -> 1 | F11: total production / animals | G11: =CONCATENATE("sust kpis dats","_",$A$1,"_",B11) -> sust kpis dats_Economic PRODUCTIVITY _Meat productivity | H11: E11
B12: Bees productivity | C12: With DATs | D12: kg honey/beehive | E12: ='Parcel 1 with DATSs'!K245/'Parcel 1 with DATSs'!K19 -> 1 | F12: total production / beehives | G12: =CONCATENATE("sust kpis dats","_",$A$1,"_",B12) -> sust kpis dats_Economic PRODUCTIVITY _Bees productivity | H12: E12
B13: Oyster productivity | C13: With DATs | D13: number of oysters/m2 | E13: ='Parcel 1 with DATSs'!K244/'Parcel 1 with DATSs'!K20 -> 1 | F13: production / area used | G13: =CONCATENATE("sust kpis dats","_",$A$1,"_",B13) -> sust kpis dats_Economic PRODUCTIVITY _Oyster productivity | H13: E13
H14: E14
A15: Economic EFFICIENCY | H15: E15
B16: INDICATOR | C16: SCENARIO | D16: UoM | E16: TOTAL | F16: FORMULAS | H16: E16
B17: Rate of time for quality analysis | C17: With DATs | D17: % | E17: =('Parcel 1 with DATSs'!K192/SUM('Parcel 1 with DATSs'!K191:K194))*100 -> 25 | F17: (hours spent for quality analysis / total number of working hours) *100 | G17: =CONCATENATE("sust kpis dats","_",$A$15,"_",B17) -> sust kpis dats_Economic EFFICIENCY _Rate of time for quality analysis | H17: E17
B18: Rate of on-time fulfilled orders | C18: With DATs | D18: % | E18: =('Parcel 1 with DATSs'!K212/'Parcel 1 with DATSs'!K213)*100 -> 100 | F18: (number of on-time fulfilled orders / number of orders received) * 100 | G18: =CONCATENATE("sust kpis dats","_",$A$15,"_",B18) -> sust kpis dats_Economic EFFICIENCY _Rate of on-time fulfilled orders | H18: E18
B19: Number of wrong orders | C19: With DATs | D19: n | E19: ='Parcel 1 with DATSs'!K214 -> 1 | F19: Number of wrong orders | G19: =CONCATENATE("sust kpis dats","_",$A$15,"_",B19) -> sust kpis dats_Economic EFFICIENCY _Number of wrong orders | H19: E19
H20: E20
A21: PRODUCT QUALITY | H21: E21
A22: INPUT | B22: INDICATOR | C22: SCENARIO | D22: UoM | E22: TOTAL | F22: FORMULAS | H22: E22
B23: Intrinsic product quality | C23: With DATs | G23: =CONCATENATE("sust kpis dats","_",$A$21,"_",B23) -> sust kpis dats_PRODUCT QUALITY _Intrinsic product quality | H23: E23
B24: Protein % DRY MATTER | C24: With DATs | D24: % | E24: ='Parcel 1 with DATSs'!K216 -> 1 | G24: =CONCATENATE("sust kpis dats","_",$A$21,"_",B24) -> sust kpis dats_PRODUCT QUALITY _Protein % DRY MATTER | H24: E24
B25: Humidity | C25: With DATs | D25: % | E25: ='Parcel 1 with DATSs'!K217 -> 1 | G25: =CONCATENATE("sust kpis dats","_",$A$21,"_",B25) -> sust kpis dats_PRODUCT QUALITY _Humidity | H25: E25
B26: Test Weight | C26: With DATs | D26: kg/hl | E26: ='Parcel 1 with DATSs'!K218 -> 1 | G26: =CONCATENATE("sust kpis dats","_",$A$21,"_",B26) -> sust kpis dats_PRODUCT QUALITY _Test Weight | H26: E26
H27: E27
A28: ENVIRONMENTAL KPIs | H28: E28
A29: INPUT | B29: INDICATOR | C29: SCENARIO | D29: UoM | E29: TOTAL | F29: Formula | H29: E29
A30: FERTILISER | B30: Nitrogen applied | C30: With DATs | D30: kg/ha | E30: ='Parcel 1 with DATSs'!K95*'Parcel 1 with DATSs'!K96*('Parcel 1 with DATSs'!K97/100)+'Parcel 1 with DATSs'!K102*'Parcel 1 with DATSs'!K103*('Parcel 1 with DATSs'!K104/100)+'Parcel 1 with DATSs'!K109*'Parcel 1 with DATSs'!K110*('Parcel 1 with DATSs'!K111/100) -> 0.03 | F30: Amount of N fertilizer used/total area | G30: =CONCATENATE("sust kpis dats","_",$A$28,"_",B30) -> sust kpis dats_ENVIRONMENTAL KPIs_Nitrogen applied | H30: E30
A31: FERTILISER | B31: Nitrogen use efficiency | C31: With DATs | D31: % | E31: =((('Parcel 1 with DATSs'!K240*1000/'Parcel 1 with DATSs'!K10)*C101)/(E30)*100) -> 2333.3333 | F31: (yield *Average N content (%))/(Amount of N fertilizer applied/ha)*100 | G31: =CONCATENATE("sust kpis dats","_",$A$28,"_",B31) -> sust kpis dats_ENVIRONMENTAL KPIs_Nitrogen use efficiency | H31: E31
A32: FERTILISER | B32: Phosphorus applied | C32: With DATs | D32: kg/ha | E32: ='Parcel 1 with DATSs'!K95*'Parcel 1 with DATSs'!K96*('Parcel 1 with DATSs'!K98/100)+'Parcel 1 with DATSs'!K102*'Parcel 1 with DATSs'!K103*('Parcel 1 with DATSs'!K105/100)+'Parcel 1 with DATSs'!K109*'Parcel 1 with DATSs'!K110*('Parcel 1 with DATSs'!K112/100) -> 0.03 | F32: Amount of P fertilizer used/total area | G32: =CONCATENATE("sust kpis dats","_",$A$28,"_",B32) -> sust kpis dats_ENVIRONMENTAL KPIs_Phosphorus applied | H32: E32
A33: FERTILISER | B33: Phosphorus use efficiency | C33: With DATs | D33: % | E33: =((('Parcel 1 with DATSs'!K240*1000/'Parcel 1 with DATSs'!K10)*C102)/E32*100) -> 733.33333 | F33: (yield*Average P content (%))/(Amount of P fertilizer used/ha)*100 | G33: =CONCATENATE("sust kpis dats","_",$A$28,"_",B33) -> sust kpis dats_ENVIRONMENTAL KPIs_Phosphorus use efficiency | H33: E33
A34: FERTILISER | B34: Potassium applied | C34: With DATs | D34: % | E34: ='Parcel 1 with DATSs'!K95*'Parcel 1 with DATSs'!K96*('Parcel 1 with DATSs'!K99/100)+'Parcel 1 with DATSs'!K102*'Parcel 1 with DATSs'!K103*('Parcel 1 with DATSs'!K106/100)+'Parcel 1 with DATSs'!K109*'Parcel 1 with DATSs'!K110*('Parcel 1 with DATSs'!K113/100) -> 0.03 | F34: Amount of K fertilizer used/total area | G34: =CONCATENATE("sust kpis dats","_",$A$28,"_",B34) -> sust kpis dats_ENVIRONMENTAL KPIs_ Potassium applied | H34: E34
A35: FERTILISER | B35: Potassium use efficiency | C35: With DATs | D35: % | E35: =(((('Parcel 1 with DATSs'!K240*1000)/'Parcel 1 with DATSs'!K10)*'sust. impact KPIs DATS'!C103)/E34*100) -> 6000 | F35: (yield*Average K content (%))/(Amount of K fertilizer used/ha)*100 | G35: =CONCATENATE("sust kpis dats","_",$A$28,"_",B35) -> sust kpis dats_ENVIRONMENTAL KPIs_Potassium use efficiency | H35: E35
A36: PESTICIDE | B36: pesticides, herbicides and fungicides use | C36: With DATs | D36: kg/ha | E36: =('Parcel 1 with DATSs'!K82*'Parcel 1 with DATSs'!K83)+('Parcel 1 with DATSs'!K85*'Parcel 1 with DATSs'!K86)+('Parcel 1 with DATSs'!K88*'Parcel 1 with DATSs'!K89) -> 3 | F36: Amount of pesticides, herbicides and fungicide used/total area | G36: =CONCATENATE("sust kpis dats","_",$A$28,"_",B36) -> sust kpis dats_ENVIRONMENTAL KPIs_pesticides, herbicides and fungicides use | H36: E36
A37: WATER | B37: Arable and horticulture water consumption | C37: With DATs | D37: m3/ha | E37: ='Parcel 1 with DATSs'!K29/'Parcel 1 with DATSs'!K10 -> 1 | F37: Amount of water used/total area | G37: =CONCATENATE("sust kpis dats","_",$A$28,"_",B37) -> sust kpis dats_ENVIRONMENTAL KPIs_Arable and horticulture water consumption | H37: E37
A38: WATER | B38: Aquaculture water productivity | C38: With DATs | D38: l/pieces | E38: ='Parcel 1 without DATSs'!#REF!/'Parcel 1 without DATSs'!#REF! -> #REF! | F38: Amount of water used/production | G38: =CONCATENATE("sust kpis dats","_",$A$28,"_",B38) -> sust kpis dats_ENVIRONMENTAL KPIs_Aquaculture water productivity | H38: E38
A39: WATER | B39: Irrigation water productivity | C39: With DATs | D39: kg/m3 | E39: =(('Parcel 1 with DATSs'!K240)*1000)/(IF(('Parcel 1 with DATSs'!K24+'Parcel 1 with DATSs'!K25)>0,('Parcel 1 with DATSs'!K24+'Parcel 1 with DATSs'!K25),'Parcel 1 with DATSs'!K29)) -> 500 | F39: Yield/Amount of water used for irrigation | G39: =CONCATENATE("sust kpis dats","_",$A$28,"_",B39) -> sust kpis dats_ENVIRONMENTAL KPIs_Irrigation water productivity | H39: E39
A40: ELECTRICITY | B40: Electricity consumption | C40: With DATs | D40: =IFERROR(VLOOKUP('General Information'!$G$6, Convalide!$V$2:$W$8, 2,FALSE), "") -> kWh/kg meat | E40: ='Parcel 1 with DATSs'!K68/(IF('General Information'!G6="crop",'Parcel 1 with DATSs'!K10,IF('General Information'!G6="milk",'Parcel 1 with DATSs'!K241,IF('General Information'!G6="meat",'Parcel 1 with DATSs'!K242,IF('General Information'!G6="animal",'Parcel 1 with DATSs'!K243,IF('General Information'!G6="oyster",'Parcel 1 with DATSs'!K244,IF('General Information'!G6="honey",'Parcel 1 with DATSs'!K245,'Parcel 1 with DATSs'!K246))))))) -> 1 | F40: Tot. amount of electricity used/tot area or m2 or animal | G40: =CONCATENATE("sust kpis dats","_",$A$28,"_",B40) -> sust kpis dats_ENVIRONMENTAL KPIs_Electricity consumption | H40: E40
A41: ANIMAL | B41: Ease of movement | C41: With DATs | D41: d/y | E41: ='Parcel 1 with DATSs'!K225/'Parcel 1 with DATSs'!K226 -> 1 | F41: number of days per year with access to pasture and outdoor loafing area | G41: =CONCATENATE("sust kpis dats","_",$A$28,"_",B41) -> sust kpis dats_ENVIRONMENTAL KPIs_Ease of movement | H41: E41
A42: ANIMAL | B42: Mortality rate (livestock) | C42: With DATs | D42: % | E42: ='Parcel 1 with DATSs'!K222/'Parcel 1 with DATSs'!K17*100 -> 100 | F42: (Number of deaths in a year/Average herd size) | G42: =CONCATENATE("sust kpis dats","_",$A$28,"_",B42) -> sust kpis dats_ENVIRONMENTAL KPIs_Mortality rate (livestock) | H42: E42
A43: ANIMAL | B43: Mortality rate (aquaculture) | C43: With DATs | D43: Oysters/m2 | E43: ='Parcel 1 with DATSs'!K222/'Parcel 1 with DATSs'!K20 -> 1 | F43: (Number of deaths in a year/total animals) | G43: =CONCATENATE("sust kpis dats","_",$A$28,"_",B43) -> sust kpis dats_ENVIRONMENTAL KPIs_Mortality rate (aquaculture) | H43: E43
A44: ANIMAL | B44: Mortality rate (apiculture) | C44: With DATs | D44: % | E44: ='Parcel 1 with DATSs'!K222/'Parcel 1 with DATSs'!K19*100 -> 100 | F44: (Number of deaths in a year/total animals) | G44: =CONCATENATE("sust kpis dats","_",$A$28,"_",B44) -> sust kpis dats_ENVIRONMENTAL KPIs_Mortality rate (apiculture) | H44: E44
A45: ANIMAL | B45: Mortality rate at birth | C45: With DATs | D45: % | E45: ='Parcel 1 with DATSs'!K223/'Parcel 1 with DATSs'!K224 -> 1 | F45: (Calves died in the first 24 h / Total number of calves born) | G45: =CONCATENATE("sust kpis dats","_",$A$28,"_",B45) -> sust kpis dats_ENVIRONMENTAL KPIs_Mortality rate at birth | H45: E45
A46: ANIMAL | B46: Cows with high SCC | C46: With DATs | D46: % | E46: ='Parcel 1 with DATSs'!K227/'Parcel 1 with DATSs'!K17 -> 1 | F46: number of cows producing high SCC milk / Total number of cows * 100 | G46: =CONCATENATE("sust kpis dats","_",$A$28,"_",B46) -> sust kpis dats_ENVIRONMENTAL KPIs_Cows with high SCC | H46: E46
A47: DRUGS | B47: Drugs use in dairy livestock | C47: With DATs | D47: g/animal | E47: =('Parcel 1 with DATSs'!K174+'Parcel 1 with DATSs'!K176+'Parcel 1 with DATSs'!K178)/'Parcel 1 with DATSs'!K17 -> 3 | F47: Amount of drugs used/ output | G47: =CONCATENATE("sust kpis dats","_",$A$28,"_",B47) -> sust kpis dats_ENVIRONMENTAL KPIs_Drugs use in dairy livestock | H47: E47
A48: DRUGS | B48: Drugs use in meat livestock | C48: With DATs | D48: g/animal | E48: =('Parcel 1 with DATSs'!K174+'Parcel 1 with DATSs'!K176+'Parcel 1 with DATSs'!K178)/'Parcel 1 with DATSs'!K17 -> 3 | F48: Amount of drugs used/ output | G48: =CONCATENATE("sust kpis dats","_",$A$28,"_",B48) -> sust kpis dats_ENVIRONMENTAL KPIs_Drugs use in meat livestock | H48: E48
A49: DRUGS | B49: Drugs use in aquaculture | C49: With DATs | D49: g/m2 | E49: =('Parcel 1 with DATSs'!K175+'Parcel 1 with DATSs'!K177+'Parcel 1 with DATSs'!#REF!)/'Parcel 1 with DATSs'!E20 -> #REF! | F49: Amount of drugs used/ output | G49: =CONCATENATE("sust kpis dats","_",$A$28,"_",B49) -> sust kpis dats_ENVIRONMENTAL KPIs_Drugs use in aquaculture | H49: E49
A50: DRUGS | B50: Drugs use in apiculture | C50: With DATs | D50: g/beehive | E50: =('Parcel 1 with DATSs'!K175+'Parcel 1 with DATSs'!K177+'Parcel 1 with DATSs'!#REF!)/'Parcel 1 with DATSs'!E19 -> #REF! | F50: Amount of drugs used/ output | G50: =CONCATENATE("sust kpis dats","_",$A$28,"_",B50) -> sust kpis dats_ENVIRONMENTAL KPIs_Drugs use in apiculture | H50: E50
A51: FUEL | B51: Fuel GHG emission | C51: With DATs | D51: kg Co2e/ha | E51: =('Parcel 1 with DATSs'!K43*'sust. impact KPIs DATS'!C97*'sust. impact KPIs DATS'!C98)/'Parcel 1 with DATSs'!K10 -> 2.66019 | F51: Tot. amount of fuel used *Lower heating value*Emission factor | G51: =CONCATENATE("sust kpis dats","_",$A$28,"_",B51) -> sust kpis dats_ENVIRONMENTAL KPIs_Fuel GHG emission | H51: E51
A52: FUEL | B52: Arable and horticulture fuel consumption | C52: With DATs | D52: l/ha | E52: ='Parcel 1 with DATSs'!K43/'Parcel 1 with DATSs'!K10 -> 1 | F52: Tot. amount of fuel used/tot area | G52: =CONCATENATE("sust kpis dats","_",$A$28,"_",B52) -> sust kpis dats_ENVIRONMENTAL KPIs_Arable and horticulture fuel consumption | H52: E52
A53: FUEL | B53: Livestock fuel consumption | C53: With DATs | D53: l/animal | E53: ='Parcel 1 with DATSs'!K43/'Parcel 1 with DATSs'!K17 -> 1 | F53: Tot. amount of fuel used/LSU | G53: =CONCATENATE("sust kpis dats","_",$A$28,"_",B53) -> sust kpis dats_ENVIRONMENTAL KPIs_Livestock fuel consumption | H53: E53
A54: FUEL | B54: Aquaculture fuel consumption | C54: With DATs | D54: l/m2 | E54: ='Parcel 1 with DATSs'!K43/'Parcel 1 with DATSs'!K20 -> 1 | F54: Tot. amount of fuel used/ area under aquaculture | G54: =CONCATENATE("sust kpis dats","_",$A$28,"_",B54) -> sust kpis dats_ENVIRONMENTAL KPIs_Aquaculture fuel consumption | H54: E54
A55: FUEL | B55: Apiculture fuel consumption | C55: With DATs | D55: l/beehive | E55: ='Parcel 1 with DATSs'!K43/'Parcel 1 with DATSs'!K19 -> 1 | F55: Tot. amount of fuel used/Number of beehives | G55: =CONCATENATE("sust kpis dats","_",$A$28,"_",B55) -> sust kpis dats_ENVIRONMENTAL KPIs_Apiculture fuel consumption | H55: E55
B56: direct | D56: direct | E56: =E30*C80 -> 0.0003 | F56: Amount of N fertilizer used (kg-N) * Emission factor 1 | G56: =CONCATENATE("sust kpis dats","_",$A$28,"_",B56) -> sust kpis dats_ENVIRONMENTAL KPIs_direct | H56: E56
B57: indirect volatilisation | D57: indirect volatilisation | E57: =((((IF('Parcel 1 with DATSs'!G100="Mineral",'Parcel 1 with DATSs'!G101*'Parcel 1 with DATSs'!G102*'Parcel 1 with DATSs'!G103/100,0))+ (IF('Parcel 1 with DATSs'!G107="Mineral",'Parcel 1 with DATSs'!G108*'Parcel 1 with DATSs'!G109*'Parcel 1 with DATSs'!G110/100,0))+ (IF('Parcel 1 with DATSs'!G114="Mineral",'Parcel 1 with DATSs'!G115*'Parcel 1 with DATSs'!G116*'Parcel 1 with DATSs'!G117/100,0))+ (IF('Parcel 1 with DATSs'!G121="Mineral",'Parcel 1 with DATSs'!G122*'Parcel 1 with DATSs'!G123*'Parcel 1 with DATSs'!G124/100,0))+ (IF('Parcel 1 with DATSs'!G128="Mineral",'Parcel 1 with DATSs'!G129*'Parcel 1 with DATSs'!G130*'Parcel 1 with DATSs'!G131/100,0))+ (IF('Parcel 1 with DATSs'!G135="Mineral",'Parcel 1 with DATSs'!G136*'Parcel 1 with DATSs'!G137*'Parcel 1 with DATSs'!G138/100,0))+ (IF('Parcel 1 with DATSs'!G142="Mineral",'Parcel 1 with DATSs'!G143*'Parcel 1 with DATSs'!G144*'Parcel 1 with DATSs'!G145/100,0))+ (IF('Parcel 1 with DATSs'!G149="Mineral",'Parcel 1 with DATSs'!G150*'Parcel 1 with DATSs'!G151*'Parcel 1 with DATSs'!G152/100,0))+ (IF('Parcel 1 with DATSs'!G156="Mineral",'Parcel 1 with DATSs'!G157*'Parcel 1 with DATSs'!G158*'Parcel 1 with DATSs'!G159/100,0))+ (IF('Parcel 1 with DATSs'!G163="Mineral",'Parcel 1 with DATSs'!G164*'Parcel 1 with DATSs'!G165*'Parcel 1 with DATSs'!G166/100,0))) *'sust. impact KPIs DATS'!C88) + (((IF('Parcel 1 with DATSs'!G100="Organic",'Parcel 1 with DATSs'!G101*'Parcel 1 with DATSs'!G102*'Parcel 1 with DATSs'!G103/100,0))+ (IF('Parcel 1 with DATSs'!G107="Organic",'Parcel 1 with DATSs'!G108*'Parcel 1 with DATSs'!G109*'Parcel 1 with DATSs'!G110/100,0))+ (IF('Parcel 1 with DATSs'!G114="Organic",'Parcel 1 with DATSs'!G115*'Parcel 1 with DATSs'!G116*'Parcel 1 with DATSs'!G117/100,0))+ (IF('Parcel 1 with DATSs'!G121="Organic",'Parcel 1 with DATSs'!G122*'Parcel 1 with DATSs'!G123*'Parcel 1 with DATSs'!G124/100,0))+ (IF('Parcel 1 with DATSs'!G128="Organic",'Parcel 1 with DATSs'!G129*'Parcel 1 with DATSs'!G130*'Parcel 1 with DATSs'!G131/100,0))+ (IF('Parcel 1 with DATSs'!G135="Organic",'Parcel 1 with DATSs'!G136*'Parcel 1 with DATSs'!G137*'Parcel 1 with DATSs'!G138/100,0))+ (IF('Parcel 1 with DATSs'!G142="Organic",'Parcel 1 with DATSs'!G143*'Parcel 1 with DATSs'!G144*'Parcel 1 with DATSs'!G145/100,0))+ (IF('Parcel 1 with DATSs'!G149="Organic",'Parcel 1 with DATSs'!G150*'Parcel 1 with DATSs'!G151*'Parcel 1 with DATSs'!G152/100,0))+ (IF('Parcel 1 with DATSs'!G156="Organic",'Parcel 1 with DATSs'!G157*'Parcel 1 with DATSs'!G158*'Parcel 1 with DATSs'!G159/100,0))+ (IF('Parcel 1 with DATSs'!G163="Organic",'Parcel 1 with DATSs'!G164*'Parcel 1 with DATSs'!G165*'Parcel 1 with DATSs'!G166/100,0))) *'sust. impact KPIs DATS'!C89)) *'sust. impact KPIs DATS'!C85 -> 0 | F57: [(Amount of synthetic N fertilizer used (kg-N) * fraction volatilized) + (Amount of organic N fertilizer used (kg-N) *fraction volatilized)] * Emission factor 4 | G57: =CONCATENATE("sust kpis dats","_",$A$28,"_",B57) -> sust kpis dats_ENVIRONMENTAL KPIs_indirect volatilisation | H57: E57
B58: indirect leaching/runoff | D58: indirect leaching/runoff | E58: =E30*C90*C92 -> 7.92e-05 | F58: Amount of N fertilizer used (kg-N) * fraction of leaching or runoff * emission factor 5 | G58: =CONCATENATE("sust kpis dats","_",$A$28,"_",B58) -> sust kpis dats_ENVIRONMENTAL KPIs_indirect leaching/runoff | H58: E58
A59: FERTILISER | B59: N2O GHG emission | C59: With DATs | D59: kg Co2e/ha | E59: =(E56+E57+E58)*C93*C94 -> 0.1626768 | F59: direct + indirect N2O emissions | G59: =CONCATENATE("sust kpis dats","_",$A$28,"_",B59) -> sust kpis dats_ENVIRONMENTAL KPIs_N2O GHG emission | H59: E59
B60: Total | E60: =E59+E51 -> 2.8228668 | G60: =CONCATENATE("sust kpis dats","_",$A$28,"_",B60) -> sust kpis dats_ENVIRONMENTAL KPIs_Total | H60: E60
H61: E61
A62: SOCIAL KPIs | H62: E62
B63: INDICATOR | C63: SCENARIO | D63: UoM | E63: TOTAL | F63: Formula | H63: E63
B64: Training hours (for the use of DATs) | C64: With DATs | D64: h/employee | E64: ='General Information'!G25/'General Information'!G14 -> 1 | F64: Time spent for training hours for all the employee/number of employees | G64: =CONCATENATE("sust kpis dats","_",$A$62,"_",B64) -> sust kpis dats_SOCIAL KPIs_Training hours (for the use of DATs) | H64: E64
B65: Working time | C65: With DATs | D65: h/week | E65: ='Parcel 1 with DATSs'!K233/'Parcel 1 with DATSs'!K234 -> 1 | F65: Hours worked /Number of working weeks in a year | G65: =CONCATENATE("sust kpis dats","_",$A$62,"_",B65) -> sust kpis dats_SOCIAL KPIs_Working time | H65: E65
B66: Frequency rate of occupational injuries | C66: With DATs | D66: n./hours | E66: ='Parcel 1 with DATSs'!K231/'Parcel 1 with DATSs'!K233 -> 1 | F66: Number of new injury cases/Total number of working hours | G66: =CONCATENATE("sust kpis dats","_",$A$62,"_",B66) -> sust kpis dats_SOCIAL KPIs_Frequency rate of occupational injuries | H66: E66
B67: Incidence of occupational injuries | C67: With DATs | D67: % | E67: ='Parcel 1 with DATSs'!K232/'Parcel 1 with DATSs'!K233 -> 1 | F67: Total number of lost working hours due to occupational injuries/Total number of working hours | G67: =CONCATENATE("sust kpis dats","_",$A$62,"_",B67) -> sust kpis dats_SOCIAL KPIs_Incidence of occupational injuries | H67: E67
B68: Contribution to local employment | C68: With DATs | D68: % | E68: ='Parcel 1 with DATSs'!K235/'Parcel 1 with DATSs'!K236 -> 1 | F68: Number of new local employees/Total new employees hired | G68: =CONCATENATE("sust kpis dats","_",$A$62,"_",B68) -> sust kpis dats_SOCIAL KPIs_Contribution to local employment | H68: E68
B77: IPCC 2006 methodology (2019 refinement) - Tier 1 | D77: (Fixed values)
A78: N2O EMISSIONS | B78: UoM | C78: value | D78: description
A79: direct emissions
A80: EF1 | B80: (Kg N2O-N)/(kg N input) | C80: 0.01 | D80: Emission Factor default value for direct emissions
A81: EF1 SW | B81: (Kg N2O-N)/(kg N input) | C81: 0.016 | D81: Emission Factor for Synthetic fertilizers in Wet climates (optional)
A82: EF1 OW | B82: (Kg N2O-N)/(kg N input) | C82: 0.006 | D82: Other N inputs in Wet climates (optional)
A83: EF1 AD | B83: (Kg N2O-N)/(kg N input) | C83: 0.006 | D83: All N inputs in Dry climates (optional)
A84: indirect emissions
A85: EF4 | B85: (Kg N2O-N)/(kg N volatilised) | C85: 0.01 | D85: Emission Factor default value for volatilization of N
A86: EF4 W | B86: (Kg N2O-N)/(kg N volatilised) | C86: 0.014 | D86: Emission Factor default value for volatilization of N in wet cliamtes
A87: EF4 D | B87: (Kg N2O-N)/(kg N volatilised) | C87: 0.005 | D87: Emission Factor default value for volatilization of N in dry climates
A88: Frac GASF | B88: (kg N volatilised)/(Kg of N input) | C88: 0.11 | D88: Fraction of synthetic fertiliser N that volatilises
A89: Frac GASM | B89: (kg N volatilised)/(Kg of N input) | C89: 0.21 | D89: Fraction of organic fertiliser N that volatilies
A90: FracLEACH | B90: (kg Nleaching&runoff)/(Kg N input) | C90: 0.24 | D90: For all N inputs
A91: FracLEACH D | B91: (kg Nleaching&runoff)/(Kg N input) | C91: 0 | D91: 0 if leaching & runoff process assumed to be absent or in dry climates
A92: EF5 | B92: (kg N2O–N)/(kg N leached and runoff) | C92: 0.011 | D92: Emission factor for N2O emissions from N leaching and runoff
A93: CF1 | B93: Kg/kg | C93: =44/28 -> 1.5714286 | D93: Coversion factor from N to N2O
A94: GWP-N2O | C94: 273 | D94: Global Warming Potential of N2O compared to CO2 (IPCC AR6)
A96: CO2 EMISSIONS FUEL
A97: Lower Heating Value Diesel | B97: Mj/l | C97: 35.9 | D97: Castoldi & Bechini, 2006
A98: EF diesel agri | B98: kg Co2e/Mj | C98: 0.0741 | D98: IPCC 2006
A100: Average nutrient content kg/kg
A101: ='General Information'!G7 -> Apple | B101: Average N content | C101: =IFERROR(VLOOKUP('General Information'!$G$7, Convalide!$O$2:$P$18, 2,FALSE), "") -> 0.0007
A102: ='General Information'!G7 -> Apple | B102: Average P content | C102: =IFERROR(VLOOKUP('General Information'!$G$7, Convalide!$Q$2:$R$18, 2,FALSE), "") -> 0.00022
A103: ='General Information'!G7 -> Apple | B103: Average K content | C103: =IFERROR(VLOOKUP('General Information'!$G$7, Convalide!$S$2:$T$18, 2,FALSE), "") -> 0.0018

Sheet sust. impact KPIs NO DATS
A1: Economic PRODUCTIVITY
A2: INPUT | B2: INDICATOR | C2: SCENARIO | D2: UoM | E2: TOTAL | F2: FORMULAS
B3: Land Productivity | C3: Without DATs | D3: t / ha | E3: ='Parcel 1 without DATSs'!G240/'Parcel 1 without DATSs'!E10 -> 1 | F3: total production / parcel area | G3: =CONCATENATE("sust kpis no dats","_",$A$1,"_",B3) -> sust kpis no dats_Economic PRODUCTIVITY _Land Productivity | H3: E3
B4: Labour productivity (arable and horticulture) | C4: Without DATs | D4: t / h | E4: ='Parcel 1 without DATSs'!G240/SUM('Parcel 1 without DATSs'!G184:G208) -> 0.04 | F4: total production / hours of labour employed | G4: =CONCATENATE("sust kpis no dats","_",$A$1,"_",B4) -> sust kpis no dats_Economic PRODUCTIVITY _Labour productivity (arable and horticulture) | H4: E4
B5: Labour productivity (dairy livestock) | C5: Without DATs | D5: l/h | E5: ='Parcel 1 without DATSs'!G241/SUM('Parcel 1 without DATSs'!G184:G208) -> 0.04 | F5: total production / hours of labour employed | G5: =CONCATENATE("sust kpis no dats","_",$A$1,"_",B5) -> sust kpis no dats_Economic PRODUCTIVITY _Labour productivity (dairy livestock) | H5: E5
B6: Labour productivity (meat livestock) | C6: Without DATs | D6: kg/h | E6: ='Parcel 1 without DATSs'!G242/SUM('Parcel 1 without DATSs'!G184:G208) -> 0.04 | F6: total production / hours of labour employed | G6: =CONCATENATE("sust kpis no dats","_",$A$1,"_",B6) -> sust kpis no dats_Economic PRODUCTIVITY _Labour productivity (meat livestock) | H6: E6
B7: Labour productivity (aquaculture) | C7: Without DATs | D7: piece/h | E7: ='Parcel 1 without DATSs'!G244/SUM('Parcel 1 without DATSs'!G184:G208) -> 0.04 | F7: total production / hours of labour employed | G7: =CONCATENATE("sust kpis no dats","_",$A$1,"_",B7) -> sust kpis no dats_Economic PRODUCTIVITY _Labour productivity (aquaculture) | H7: E7
B8: Labour productivity (apiculture) | C8: Without DATs | D8: kg/h | E8: ='Parcel 1 without DATSs'!G245/SUM('Parcel 1 without DATSs'!G184:G208) -> 0.04 | F8: total production / hours of labour employed | G8: =CONCATENATE("sust kpis no dats","_",$A$1,"_",B8) -> sust kpis no dats_Economic PRODUCTIVITY _Labour productivity (apiculture) | H8: E8
B9: Labour productivity (silos) | C9: Without DATs | D9: t/h | E9: ='Parcel 1 without DATSs'!G246/SUM('Parcel 1 without DATSs'!G184:G208) -> 0.04 | G9: =CONCATENATE("sust kpis no dats","_",$A$1,"_",B9) -> sust kpis no dats_Economic PRODUCTIVITY _Labour productivity (silos) | H9: E9
B10: Milk productivity | C10: Without DATs | D10: l milk/cow/day | E10: ='Parcel 1 without DATSs'!G241/'Parcel 1 without DATSs'!E17/(('General Information'!G10-'General Information'!G9)+1) -> 1 | F10: total milk production / total number of cows | G10: =CONCATENATE("sust kpis no dats","_",$A$1,"_",B10) -> sust kpis no dats_Economic PRODUCTIVITY _Milk productivity | H10: E10
B11: Meat productivity | C11: Without DATs | D11: kg / animals / day | E11: ='Parcel 1 without DATSs'!G242/'Parcel 1 without DATSs'!E17/('General Information'!G10-'General Information'!G9+1) -> 1 | F11: total production / animals | G11: =CONCATENATE("sust kpis no dats","_",$A$1,"_",B11) -> sust kpis no dats_Economic PRODUCTIVITY _Meat productivity | H11: E11
B12: Bees productivity | C12: Without DATs | D12: kg / beehives | E12: ='Parcel 1 without DATSs'!G245/'Parcel 1 without DATSs'!E19 -> 1 | F12: total production / beehives | G12: =CONCATENATE("sust kpis no dats","_",$A$1,"_",B12) -> sust kpis no dats_Economic PRODUCTIVITY _Bees productivity | H12: E12
B13: Oyster productivity | C13: Without DATs | D13: kg/m2 | E13: ='Parcel 1 without DATSs'!G244/'Parcel 1 without DATSs'!E20 -> 1 | F13: production / area used | G13: =CONCATENATE("sust kpis no dats","_",$A$1,"_",B13) -> sust kpis no dats_Economic PRODUCTIVITY _Oyster productivity | H13: E13
H14: E14
A15: Economic EFFICIENCY | H15: E15
A16: INPUT | B16: INDICATOR | C16: SCENARIO | D16: UoM | E16: TOTAL | F16: FORMULAS | H16: E16
B17: Rate of time for quality analysis | C17: Without DATs | D17: % | E17: =('Parcel 1 without DATSs'!G192/SUM('Parcel 1 without DATSs'!G191:G194))*100 -> 25 | F17: (hours assessing grain quality / total number of working hours) *100 | G17: =CONCATENATE("sust kpis no dats","_",$A$15,"_",B17) -> sust kpis no dats_Economic EFFICIENCY _Rate of time for quality analysis | H17: E17
B18: Rate of on-time fulfilled orders | C18: Without DATs | D18: % | E18: =('Parcel 1 without DATSs'!G212/'Parcel 1 without DATSs'!G213)*100 -> 100 | F18: (number of on-time fulfilled orders / number of orders received) * 100 | G18: =CONCATENATE("sust kpis no dats","_",$A$15,"_",B18) -> sust kpis no dats_Economic EFFICIENCY _Rate of on-time fulfilled orders | H18: E18
B19: Number of wrong orders | C19: Without DATs | D19: n | E19: ='Parcel 1 without DATSs'!G214 -> 1 | F19: Number of wrong orders | G19: =CONCATENATE("sust kpis no dats","_",$A$15,"_",B19) -> sust kpis no dats_Economic EFFICIENCY _Number of wrong orders | H19: E19
H20: E20
A21: PRODUCT QUALITY | H21: E21
A22: INPUT | B22: INDICATOR | C22: SCENARIO | D22: UoM | E22: TOTAL | F22: FORMULAS | H22: E22
B23: Intrinsic product quality | C23: Without DATs | G23: =CONCATENATE("sust kpis no dats","_",$A$21,"_",B23) -> sust kpis no dats_PRODUCT QUALITY _Intrinsic product quality | H23: E23
B24: Protein % DRY MATTER | C24: Without DATs | D24: % | E24: ='Parcel 1 without DATSs'!G216 -> 1 | G24: =CONCATENATE("sust kpis no dats","_",$A$21,"_",B24) -> sust kpis no dats_PRODUCT QUALITY _Protein % DRY MATTER | H24: E24
B25: Humidity | C25: Without DATs | D25: % | E25: ='Parcel 1 without DATSs'!#REF! -> #REF! | G25: =CONCATENATE("sust kpis no dats","_",$A$21,"_",B25) -> sust kpis no dats_PRODUCT QUALITY _Humidity | H25: E25
B26: Test Weight | C26: Without DATs | D26: kg/hl | E26: ='Parcel 1 without DATSs'!#REF! -> #REF! | G26: =CONCATENATE("sust kpis no dats","_",$A$21,"_",B26) -> sust kpis no dats_PRODUCT QUALITY _Test Weight | H26: E26
H27: E27
A28: ENVIRONMENTAL KPIs | H28: E28
A29: INPUT | B29: INDICATOR | C29: SCENARIO | D29: UoM | E29: TOTAL | F29: Formula | H29: E29
A30: FERTILISER | B30: Nitrogen applied | C30: Without DATs | D30: kg/ha | E30: ='Parcel 1 without DATSs'!G95*'Parcel 1 without DATSs'!G96*('Parcel 1 without DATSs'!G97/100)+'Parcel 1 without DATSs'!G102*'Parcel 1 without DATSs'!G103*('Parcel 1 without DATSs'!G104/100)+'Parcel 1 without DATSs'!G109*'Parcel 1 without DATSs'!G110*('Parcel 1 without DATSs'!G111/100) -> 0.03 | F30: Amount of N fertilizer used/total area | G30: =CONCATENATE("sust kpis no dats","_",$A$28,"_",B30) -> sust kpis no dats_ENVIRONMENTAL KPIs_Nitrogen applied | H30: E30
A31: FERTILISER | B31: Nitrogen use efficiency | C31: Without DATs | D31: % | E31: =(('Parcel 1 without DATSs'!G240*1000/'Parcel 1 without DATSs'!E10)*'sust. impact KPIs NO DATS'!C101)/E30*100 -> 2333.3333 | F31: (yield *Average N content (%))/(Amount of N fertilizer used /total area)*100 | G31: =CONCATENATE("sust kpis no dats","_",$A$28,"_",B31) -> sust kpis no dats_ENVIRONMENTAL KPIs_Nitrogen use efficiency | H31: E31
A32: FERTILISER | B32: Phosphorus applied | C32: Without DATs | D32: kg/ha | E32: ='Parcel 1 without DATSs'!G95*'Parcel 1 without DATSs'!G96*('Parcel 1 without DATSs'!G98/100)+'Parcel 1 without DATSs'!G102*'Parcel 1 without DATSs'!G103*('Parcel 1 without DATSs'!G105/100)+'Parcel 1 without DATSs'!G109*'Parcel 1 without DATSs'!G110*('Parcel 1 without DATSs'!G112/100) -> 0.03 | F32: Amount of P fertilizer used/total area | G32: =CONCATENATE("sust kpis no dats","_",$A$28,"_",B32) -> sust kpis no dats_ENVIRONMENTAL KPIs_Phosphorus applied | H32: E32
A33: FERTILISER | B33: Phosphorus use efficiency | C33: Without DATs | D33: % | E33: =(('Parcel 1 without DATSs'!G240*1000/'Parcel 1 without DATSs'!E10)*'sust. impact KPIs NO DATS'!C102)/E32*100 -> 733.33333 | F33: (yield*Average P content (%))/(Amount of P fertilizer used/total area)*100 | G33: =CONCATENATE("sust kpis no dats","_",$A$28,"_",B33) -> sust kpis no dats_ENVIRONMENTAL KPIs_Phosphorus use efficiency | H33: E33
A34: FERTILISER | B34: Potassium applied | C34: Without DATs | D34: % | E34: ='Parcel 1 without DATSs'!G95*'Parcel 1 without DATSs'!G96*('Parcel 1 without DATSs'!G99/100)+'Parcel 1 without DATSs'!G102*'Parcel 1 without DATSs'!G103*('Parcel 1 without DATSs'!G106/100)+'Parcel 1 without DATSs'!G109*'Parcel 1 without DATSs'!G110*('Parcel 1 without DATSs'!G113/100) -> 0.03 | F34: Amount of K fertilizer used/total area | G34: =CONCATENATE("sust kpis no dats","_",$A$28,"_",B34) -> sust kpis no dats_ENVIRONMENTAL KPIs_Potassium applied | H34: E34
A35: FERTILISER | B35: Potassium use efficiency | C35: Without DATs | D35: % | E35: =(('Parcel 1 without DATSs'!G240*1000/'Parcel 1 without DATSs'!E10)*'sust. impact KPIs NO DATS'!C103)/E34*100 -> 6000 | F35: (yield*Average K content (%))/(Amount of K fertilizer used/total area)*100 | G35: =CONCATENATE("sust kpis no dats","_",$A$28,"_",B35) -> sust kpis no dats_ENVIRONMENTAL KPIs_Potassium use efficiency | H35: E35
A36: PESTICIDE | B36: Pesticides, herbicides and fungicides use | C36: Without DATs | D36: kg/ha | E36: =('Parcel 1 without DATSs'!G73*'Parcel 1 without DATSs'!G74)+('Parcel 1 without DATSs'!G76*'Parcel 1 without DATSs'!G77)+('Parcel 1 without DATSs'!G79*'Parcel 1 without DATSs'!G80) -> 3 | F36: Amount of pesticides, herbicides and fungicides used/total area | G36: =CONCATENATE("sust kpis no dats","_",$A$28,"_",B36) -> sust kpis no dats_ENVIRONMENTAL KPIs_Pesticides, herbicides and fungicides use | H36: E36
A37: WATER | B37: Arable and horticulture water consumption | C37: Without DATs | D37: m3/ha | E37: ='Parcel 1 without DATSs'!G29/'Parcel 1 without DATSs'!E10 -> 1 | F37: Amount of water used/total area | G37: =CONCATENATE("sust kpis no dats","_",$A$28,"_",B37) -> sust kpis no dats_ENVIRONMENTAL KPIs_Arable and horticulture water consumption | H37: E37
A38: WATER | B38: Aquaculture water productivity | C38: Without DATs | D38: l/pieces | E38: ='Parcel 1 without DATSs'!#REF!/'Parcel 1 without DATSs'!#REF! -> #REF! | F38: Amount of water used/production | G38: =CONCATENATE("sust kpis no dats","_",$A$28,"_",B38) -> sust kpis no dats_ENVIRONMENTAL KPIs_Aquaculture water productivity | H38: E38
A39: WATER | B39: Irrigation water productivity | C39: Without DATs | D39: kg/m3 | E39: =(('Parcel 1 without DATSs'!G240)*1000)/(IF(('Parcel 1 without DATSs'!G24+'Parcel 1 without DATSs'!G25)>0,('Parcel 1 without DATSs'!G24+'Parcel 1 without DATSs'!G25),'Parcel 1 without DATSs'!G29)) -> 500 | F39: Yield/Amount of water used for irrigation | G39: =CONCATENATE("sust kpis no dats","_",$A$28,"_",B39) -> sust kpis no dats_ENVIRONMENTAL KPIs_Irrigation water productivity | H39: E39
A40: ELECTRICITY | B40: Electricity consumption | C40: Without DATs | D40: kWh/ha | E40: ='Parcel 1 without DATSs'!G68/(IF('General Information'!G6="crop",'Parcel 1 without DATSs'!E10,IF('General Information'!G6="milk",'Parcel 1 without DATSs'!G241,IF('General Information'!G6="meat",'Parcel 1 without DATSs'!G242,IF('General Information'!G6="animal",'Parcel 1 without DATSs'!G243,IF('General Information'!G6="oyster",'Parcel 1 without DATSs'!G244,IF('General Information'!G6="honey",'Parcel 1 without DATSs'!G245,'Parcel 1 without DATSs'!G246))))))) -> 1 | F40: Tot. amount of electricity used/tot area | G40: =CONCATENATE("sust kpis no dats","_",$A$28,"_",B40) -> sust kpis no dats_ENVIRONMENTAL KPIs_Electricity consumption | H40: E40
A41: ANIMAL | B41: Ease of movement | C41: Without DATs | D41: d/y | E41: ='Parcel 1 without DATSs'!G225/'Parcel 1 without DATSs'!G226 -> 1 | F41: number of days per year with access to pasture and outdoor loafing area | G41: =CONCATENATE("sust kpis no dats","_",$A$28,"_",B41) -> sust kpis no dats_ENVIRONMENTAL KPIs_Ease of movement | H41: E41
A42: ANIMAL | B42: Mortality rate (livestock) | C42: Without DATs | D42: % | E42: ='Parcel 1 without DATSs'!G222/'Parcel 1 without DATSs'!E17*100 -> 100 | F42: (Number of deaths in a year/Average herd size) | G42: =CONCATENATE("sust kpis no dats","_",$A$28,"_",B42) -> sust kpis no dats_ENVIRONMENTAL KPIs_Mortality rate (livestock) | H42: E42
A43: ANIMAL | B43: Mortality rate (aquaculture) | C43: Without DATs | D43: % | E43: ='Parcel 1 without DATSs'!G222/'Parcel 1 without DATSs'!E20 -> 1 | F43: (Number of deaths in a year/total animals) | G43: =CONCATENATE("sust kpis no dats","_",$A$28,"_",B43) -> sust kpis no dats_ENVIRONMENTAL KPIs_Mortality rate (aquaculture) | H43: E43
A44: ANIMAL | B44: Mortality rate (apiculture) | C44: Without DATs | D44: % | E44: ='Parcel 1 without DATSs'!G222/'Parcel 1 without DATSs'!E19*100 -> 100 | F44: (Number of deaths in a year/total animals) | G44: =CONCATENATE("sust kpis no dats","_",$A$28,"_",B44) -> sust kpis no dats_ENVIRONMENTAL KPIs_Mortality rate (apiculture) | H44: E44
A45: ANIMAL | B45: Mortality rate at birth | C45: Without DATs | D45: % | E45: ='Parcel 1 without DATSs'!G223/'Parcel 1 without DATSs'!G224 -> 1 | F45: (Calves died in the first 24 h / Total number of calves born) | G45: =CONCATENATE("sust kpis no dats","_",$A$28,"_",B45) -> sust kpis no dats_ENVIRONMENTAL KPIs_Mortality rate at birth | H45: E45
A46: ANIMAL | B46: Cows with high SCC | C46: Without DATs | D46: % | E46: ='Parcel 1 without DATSs'!G227/'Parcel 1 without DATSs'!E17 -> 1 | F46: number of cows producing high SCC milk / Total number of cows * 100 | G46: =CONCATENATE("sust kpis no dats","_",$A$28,"_",B46) -> sust kpis no dats_ENVIRONMENTAL KPIs_Cows with high SCC | H46: E46
A47: DRUGS | B47: Drugs use in dairy livestock | C47: Without DATs | D47: kg/l | E47: =('Parcel 1 without DATSs'!G162+'Parcel 1 without DATSs'!G164+'Parcel 1 without DATSs'!G166)/'Parcel 1 without DATSs'!E17 -> 3 | F47: Amount of drugs used/ output | G47: =CONCATENATE("sust kpis no dats","_",$A$28,"_",B47) -> sust kpis no dats_ENVIRONMENTAL KPIs_Drugs use in dairy livestock | H47: E47
A48: DRUGS | B48: Drugs use in meat livestock | C48: Without DATs | D48: kg/output | E48: =('Parcel 1 without DATSs'!G162+'Parcel 1 without DATSs'!G164+'Parcel 1 without DATSs'!G166)/'Parcel 1 without DATSs'!E17 -> 3 | F48: Amount of drugs used/ output | G48: =CONCATENATE("sust kpis no dats","_",$A$28,"_",B48) -> sust kpis no dats_ENVIRONMENTAL KPIs_Drugs use in meat livestock | H48: E48
A49: DRUGS | B49: Drugs use in aquaculture | C49: Without DATs | D49: kg/output | E49: =('Parcel 1 without DATSs'!G162+'Parcel 1 without DATSs'!G164+'Parcel 1 without DATSs'!G166)/'Parcel 1 without DATSs'!E20 -> 3 | F49: Amount of drugs used/ output | G49: =CONCATENATE("sust kpis no dats","_",$A$28,"_",B49) -> sust kpis no dats_ENVIRONMENTAL KPIs_Drugs use in aquaculture | H49: E49
A50: DRUGS | B50: Drugs use in apiculture | C50: Without DATs | D50: kg/output | E50: =('Parcel 1 without DATSs'!G162+'Parcel 1 without DATSs'!G164+'Parcel 1 without DATSs'!G166)/'Parcel 1 without DATSs'!E19 -> 3 | F50: Amount of drugs used/ output | G50: =CONCATENATE("sust kpis no dats","_",$A$28,"_",B50) -> sust kpis no dats_ENVIRONMENTAL KPIs_Drugs use in apiculture | H50: E50
A51: FUEL | B51: Fuel GHG emission | C51: Without DATs | D51: kg Co2e/ha | E51: =('Parcel 1 without DATSs'!G43*'sust. impact KPIs NO DATS'!C97*'sust. impact KPIs NO DATS'!C98)/'Parcel 1 without DATSs'!E10 -> 2.66019 | F51: Tot. amount of fuel used *Lower heating value*Emission factor | G51: =CONCATENATE("sust kpis no dats","_",$A$28,"_",B51) -> sust kpis no dats_ENVIRONMENTAL KPIs_Fuel GHG emission | H51: E51
A52: FUEL | B52: Arable and horticulture fuel consumption | C52: Without DATs | D52: l/ha | E52: ='Parcel 1 without DATSs'!G43/'Parcel 1 without DATSs'!E10 -> 1 | F52: Tot. amount of fuel used/tot area | G52: =CONCATENATE("sust kpis no dats","_",$A$28,"_",B52) -> sust kpis no dats_ENVIRONMENTAL KPIs_Arable and horticulture fuel consumption | H52: E52
A53: FUEL | B53: Livestock fuel consumption | C53: Without DATs | D53: l/animals | E53: ='Parcel 1 without DATSs'!G43/'Parcel 1 without DATSs'!E17 -> 1 | F53: Tot. amount of fuel used/number of animals | G53: =CONCATENATE("sust kpis no dats","_",$A$28,"_",B53) -> sust kpis no dats_ENVIRONMENTAL KPIs_Livestock fuel consumption | H53: E53
A54: FUEL | B54: Aquaculture fuel consumption | C54: Without DATs | D54: l/m2 | E54: ='Parcel 1 without DATSs'!G43/'Parcel 1 without DATSs'!E20 -> 1 | F54: Tot. amount of fuel used/ area under aquaculture | G54: =CONCATENATE("sust kpis no dats","_",$A$28,"_",B54) -> sust kpis no dats_ENVIRONMENTAL KPIs_Aquaculture fuel consumption | H54: E54
A55: FUEL | B55: Apiculture fuel consumption | C55: Without DATs | D55: kg/beehives | E55: ='Parcel 1 without DATSs'!G43/'Parcel 1 without DATSs'!E19 -> 1 | F55: Tot. amount of fuel used/Number of beehives | G55: =CONCATENATE("sust kpis no dats","_",$A$28,"_",B55) -> sust kpis no dats_ENVIRONMENTAL KPIs_Apiculture fuel consumption | H55: E55
B56: direct | D56: direct | E56: =E30*C80 -> 0.0003 | F56: Amount of N fertilizer used (kg-N) * Emission factor 1 | G56: =CONCATENATE("sust kpis no dats","_",$A$28,"_",B56) -> sust kpis no dats_ENVIRONMENTAL KPIs_direct | H56: E56
B57: indirect volatilisation | D57: indirect volatilisation | E57: =(((IF('Parcel 1 without DATSs'!G94="Mineral",'Parcel 1 without DATSs'!G95*'Parcel 1 without DATSs'!G96*'Parcel 1 without DATSs'!G97/100,0))+(IF('Parcel 1 without DATSs'!G101="Mineral",'Parcel 1 without DATSs'!G102*'Parcel 1 without DATSs'!G103*'Parcel 1 without DATSs'!G104/100,0))+(IF('Parcel 1 without DATSs'!G108="Mineral",'Parcel 1 without DATSs'!G109*'Parcel 1 without DATSs'!G110*'Parcel 1 without DATSs'!G111/100,0)))*'sust. impact KPIs DATS'!C88 + ((IF('Parcel 1 without DATSs'!G94="Organic",'Parcel 1 without DATSs'!G95*'Parcel 1 without DATSs'!G96*'Parcel 1 without DATSs'!G97/100,0))+(IF('Parcel 1 without DATSs'!G101="Organic",'Parcel 1 without DATSs'!G102*'Parcel 1 without DATSs'!G103*'Parcel 1 without DATSs'!G104/100,0))+(IF('Parcel 1 without DATSs'!G108="Organic",'Parcel 1 without DATSs'!G109*'Parcel 1 without DATSs'!G110*'Parcel 1 without DATSs'!G111/100,0)))*'sust. impact KPIs DATS'!C89)*'sust. impact KPIs DATS'!C85 -> 0 | F57: [(Amount of synthetic N fertilizer used (kg-N) * fraction volatilized) + (Amount of organic N fertilizer used (kg-N) *fraction volatilized)] * Emission factor 4 | G57: =CONCATENATE("sust kpis no dats","_",$A$28,"_",B57) -> sust kpis no dats_ENVIRONMENTAL KPIs_indirect volatilisation | H57: E57
B58: indirect leaching/runoff | D58: indirect leaching/runoff | E58: =E30*C90*C92 -> 7.92e-05 | F58: Amount of N fertilizer used (kg-N) * fraction of leaching or runoff * emission factor 5 | G58: =CONCATENATE("sust kpis no dats","_",$A$28,"_",B58) -> sust kpis no dats_ENVIRONMENTAL KPIs_indirect leaching/runoff | H58: E58
A59: FERTILISER | B59: N2O GHG emission | C59: Without DATs | D59: kg Co2e/ha | E59: =(E56+E57+E58)*C93*C94 -> 0.1626768 | F59: direct + indirect N2O emissions | G59: =CONCATENATE("sust kpis no dats","_",$A$28,"_",B59) -> sust kpis no dats_ENVIRONMENTAL KPIs_N2O GHG emission | H59: E59
B60: Total | E60: =((305-E59)/E59)*100 -> 187388.32 | G60: =CONCATENATE("sust kpis no dats","_",$A$28,"_",B60) -> sust kpis no dats_ENVIRONMENTAL KPIs_Total | H60: E60
H61: E61
A62: SOCIAL KPIs | H62: E62
B63: INDICATOR | C63: SCENARIO | D63: UoM | E63: TOTAL | F63: Formula | H63: E63
B64: Training hours (for the use of DATs) | C64: With DATs | D64: h/employee | E64: 0 | F64: Time spent for training hours for all the employee/number of employees | G64: =CONCATENATE("sust kpis dats","_",$A$62,"_",B64) -> sust kpis dats_SOCIAL KPIs_Training hours (for the use of DATs) | H64: E64
B65: Working time | C65: Without DATs | D65: h/week | E65: ='Parcel 1 without DATSs'!G233/'Parcel 1 without DATSs'!G234 -> 1 | F65: Hours worked per type of worker (e.g., hours of full time employees)/Number of working weeks in a year | G65: =CONCATENATE("sust kpis no dats","_",$A$62,"_",B65) -> sust kpis no dats_SOCIAL KPIs_Working time | H65: E65
B66: Frequency rate of occupational injuries | C66: Without DATs | D66: n./hours | E66: ='Parcel 1 without DATSs'!G231/'Parcel 1 without DATSs'!G233 -> 1 | F66: Number of new injury cases/Total number of working hours | G66: =CONCATENATE("sust kpis no dats","_",$A$62,"_",B66) -> sust kpis no dats_SOCIAL KPIs_Frequency rate of occupational injuries | H66: E66
B67: Incidence of occupational injuries | C67: Without DATs | D67: % | E67: ='Parcel 1 without DATSs'!G232/'Parcel 1 without DATSs'!G233 -> 1 | F67: Total number of lost working hours due to occupational injuries/Total number of working hours | G67: =CONCATENATE("sust kpis no dats","_",$A$62,"_",B67) -> sust kpis no dats_SOCIAL KPIs_Incidence of occupational injuries | H67: E67
B68: Contribution to local employment | C68: Without DATs | D68: % | E68: ='Parcel 1 without DATSs'!G235/'Parcel 1 without DATSs'!G236 -> 1 | F68: Number of new local employees/Total new employees hired | G68: =CONCATENATE("sust kpis no dats","_",$A$62,"_",B68) -> sust kpis no dats_SOCIAL KPIs_Contribution to local employment | H68: E68
B77: IPCC 2006 methodology (2019 refinement) - Tier 1 | D77: (Fixed values)
A78: N2O EMISSIONS | B78: UoM | C78: value | D78: description
A79: direct emissions
A80: EF1 | B80: (Kg N2O-N)/(kg N input) | C80: 0.01 | D80: Emission Factor default value for direct emissions
A81: EF1 SW | B81: (Kg N2O-N)/(kg N input) | C81: 0.016 | D81: Emission Factor for Synthetic fertilizers in Wet climates (optional)
A82: EF1 OW | B82: (Kg N2O-N)/(kg N input) | C82: 0.006 | D82: Other N inputs in Wet climates (optional)
A83: EF1 AD | B83: (Kg N2O-N)/(kg N input) | C83: 0.006 | D83: All N inputs in Dry climates (optional)
A84: indirect emissions
A85: EF4 | B85: (Kg N2O-N)/(kg N volatilised) | C85: 0.01 | D85: Emission Factor default value for volatilization of N
A86: EF4 W | B86: (Kg N2O-N)/(kg N volatilised) | C86: 0.014 | D86: Emission Factor default value for volatilization of N in wet cliamtes
A87: EF4 D | B87: (Kg N2O-N)/(kg N volatilised) | C87: 0.005 | D87: Emission Factor default value for volatilization of N in dry climates
A88: Frac GASF | B88: (kg N volatilised)/(Kg of N input) | C88: 0.11 | D88: Fraction of synthetic fertiliser N that volatilises
A89: Frac GASM | B89: (kg N volatilised)/(Kg of N input) | C89: 0.21 | D89: Fraction of organic fertiliser N that volatilies
A90: FracLEACH | B90: (kg Nleaching&runoff)/(Kg N input) | C90: 0.24 | D90: For all N inputs
A91: FracLEACH D | B91: (kg Nleaching&runoff)/(Kg N input) | C91: 0 | D91: 0 if leaching & runoff process assumed to be absent or in dry climates
A92: EF5 | B92: (kg N2O–N)/(kg N leached and runoff) | C92: 0.011 | D92: Emission factor for N2O emissions from N leaching and runoff
A93: CF1 | B93: Kg/kg | C93: =44/28 -> 1.5714286 | D93: Coversion factor from N to N2O
A94: GWP-N2O | C94: 273 | D94: Global Warming Potential of N2O compared to CO2 (IPCC AR6)
A96: CO2 EMISSIONS FUEL
A97: Lower Heating Value Diesel | B97: MJ/l | C97: 35.9 | D97: Castoldi & Bechini, 2006
A98: EF diesel agri | B98: kg Co2e/Mj | C98: 0.0741 | D98: IPCC 2006
A100: Average nutrient content kg/kg
A101: ='General Information'!G7 -> Apple | B101: Average N content | C101: =IFERROR(VLOOKUP('General Information'!$G$7, Convalide!$O$2:$P$18, 2,FALSE), "") -> 0.0007
A102: ='General Information'!G7 -> Apple | B102: Average P content | C102: =IFERROR(VLOOKUP('General Information'!$G$7, Convalide!$Q$2:$R$18, 2,FALSE), "") -> 0.00022
