Workbook

Sheet Instructions 
B2: Instructions to be followed to complete the Data Collection Template
B3: This form is intended to be filled out by each farmer involved in the Test Case (TC) and aims at collecting information that will be used for assessing the impacts of Digital agriculture technology solutions (DATSs). Please read carefully the following instructions. - We kindly ask you to be as accurate as possible in providing the data and monitor them periodically as these will be the input for performance assessment. - Please ensure you keep track of the data requested and regularly check its availability. It's crucial that these values align for both user and non-user parcels. If they differ, kindly notify us promptly via email at the provided contact details. - The data included in the template have been carefully chosen based on their link with the DATSs used in your TC and they were further customised following your feedback. If some of the data cannot be applicable/available to your TC, please enter ‘n.a.’ in the corresponding cell and provide a comment explaining why they are not applicable. Additionally, in case some of the data cannot be collected due to some problems you may encounter during the season, please inform us promptly by writing an e-mail to the contact details provided below. - In order to obtain the assessment of the impacts of DATS, it is necessary to provide data for the farm(s) using DATS and for the one without. According to the QuantiFarm project proposal, each parcel using DATSs is associated with a comparable non-DATs parcel (in terms of size, geographical area, production, etc.). - Recall that: - the term DATS refers to the combinations or set of technological solutions implemented within the TC; For any doubts or clarifications, please do not hesitate to contact us at the following email address: francesco.parigi@polimi.it and andrea.bianchi@polimi.it (cc: dmoniz@consulai.com) This form is intended to be filled out by each farmer involved in the Test Case (TC) and aims at collecting information that will be used for assessing the impacts of Digital agriculture technology solutions (DATSs).
B5: Table of abbreviations
B6: - | C6: number (1, 2, 3, …)
B7: € | C7: euro
C8: cubic centimetre
C9: cubic decimetre
B10: g | C10: grams
B11: h | C11: hour
B12: ha | C12: hectare
B13: K | C13: potassium
B14: k€ | C14: kiloeuro (€ 1,000)
B15: kg | C15: kilograms
B16: kWh | C16: kilowatt-hour
B17: l | C17: litre
B18: mg | C18: micrograms
B19: mo | C19: month
C20: square metre
C21: cubic metre
B22: N | C22: nitrogen
B23: P | C23: phosphorus
B24: ppm | C24: parts per million
B25: t | C25: tonnes
B26: w | C26: week
B27: y | C27: year

Sheet General Information
B2: Question | C2: Unit of measure | D2: Value
B3: TC Number | C3: n | D3: TC10
B4: TC Leader | C4: - | D4: Arable
B5: FARM DATA
B6: Type of output/product | C6: - | D6: Crop
B7: Crop | C7: - | D7: Wheat (T. aestivum)
B8: Animal
B9: Start of the growing/production season | C9: (gg/mm/yyyy) | D9: 45200
B10: End of the growing/production season | C10: (gg/mm/yyyy) | D10: 45474
B11: Biogeographical region | C11: -
B12: Total farm size | C12: ha
B13: Number of comparison(s) | C13: n
B14: Number of employees | C14: n | D14: 9
B15: Number of full-time employees | C15: n
B16: Number of seasonal employees | C16: n
B18: DATSs 1 DATA | F18: DATSs 2 DATA | J18: DATSs n DATA
B19: Question | C19: Unit of measure | D19: Value | F19: Question | G19: Unit of measure | H19: Value | J19: Question | K19: Unit of measure | L19: Value
B20: Initial investment for DATSs | C20: € | D20: 70396 | F20: Initial investment for DATSs | G20: € | J20: Initial investment for DATSs | K20: €
B21: Expected life span of each DATSs | C21: y | D21: 10 | F21: Expected life span of each DATSs | G21: y | J21: Expected life span of each DATSs | K21: y
B22: Time to install and make DATSs operational | C22: h | D22: 60 | F22: Time to install and make DATSs operational | G22: h | J22: Time to install and make DATSs operational | K22: h
B23: DATs maintenance costs | C23: €/y | D23: 500 | F23: DATs maintenance costs | G23: €/y | J23: DATs maintenance costs | K23: €/y
B24: DATS annual fees | C24: €/y | D24: 1100 | F24: DATS annual fees | G24: €/y | J24: DATS annual fees | K24: €/y
B25: Training hours for the use of the DATSs in a year | C25: h | D25: 40 | F25: Training hours for the use of the DATSs in a year | G25: h | J25: Training hours for the use of the DATSs in a year | K25: h
B26: Number of people involved in the training | C26: n | D26: 2 | F26: Number of people involved in the training | G26: n | J26: Number of people involved in the training | K26: n
B27: Cost of training service by external people (advisor, DATS providers, ...) | C27: €/y | D27: 1200 | F27: Cost of training service by external people (advisor, DATS providers, ...) | G27: €/y | J27: Cost of training service by external people (advisor, DATS providers, ...) | K27: €/y
B28: DATSs name | C28: - | F28: DATSs name | G28: - | J28: DATSs name | K28: -
B30: MARKET DATA FOR DATSs USER | F30: MARKET DATA FOR NON-DATSs USER
B31: Question | C31: Unit of measure | D31: Value | F31: Question | G31: Unit of measure | H31: Value
B32: Water price | D32: 0 | F32: Water price | H32: 0
B33: Fuel price | C33: €/l | D33: 1.15 | F33: Fuel price | G33: €/l | H33: 1.15
B34: Number of fuel for greehnouse temperature control price | C34: n | F34: Number of fuel for greehnouse temperature control price | G34: n
B35: Fuel 1 for greehnouse temperature control price | F35: Fuel 1 for greehnouse temperature control price
B36: Fuel 2 for greehnouse temperature control price | F36: Fuel 2 for greehnouse temperature control price
B37: Fuel 3 for greehnouse temperature control price | F37: Fuel 3 for greehnouse temperature control price
B38: Electricity price | C38: €/kWh | D38: 0.148 | F38: Electricity price | G38: €/kWh | H38: 0.148
B39: Average salary (farmer and emloyees) | C39: €/h | D39: 7.2 | F39: Average salary (farmer and emloyees) | G39: €/h | H39: 7.2
B40: Average professional salary (agronomist, veterinary, ...) | C40: €/h | D40: 8.6 | F40: Average professional salary (agronomist, veterinary, ...) | G40: €/h | H40: 8.6
B41: Sold product market price | C41: €/t | D41: 192 | F41: Sold product market price | G41: €/t | H41: 192
B42: Number of pesticide used (herbicides, fungicides, insecticides) | C42: n | D42: 4 | F42: Number of pesticide used (herbicides, fungicides, insecticides) | G42: n | H42: 6
B43: Pesticide 1 price | C43: €/kg | D43: 8 | F43: Pesticide 1 price | G43: €/kg | H43: 14.4
B44: Pesticide 2 price | C44: €/kg | D44: 66 | F44: Pesticide 2 price | G44: €/kg | H44: 28
B45: Pesticide 3 price | C45: €/kg | D45: 32 | F45: Pesticide 3 price | G45: €/kg | H45: 33.8
B46: Pesticide 4 price | C46: €/kg | D46: 18 | F46: Pesticide 4 price | G46: €/kg | H46: 21.2
B47: Pesticide 5 price | C47: €/kg | F47: Pesticide 5 price | G47: €/kg | H47: 85.4
B48: Pesticide 6 price | C48: €/kg | F48: Pesticide 6 price | G48: €/kg | H48: 12
B49: Pesticide 7 price | C49: €/kg | F49: Pesticide 7 price | G49: €/kg
B50: Pesticide 8 price | C50: €/kg | F50: Pesticide 8 price
B51: Pesticide 9 price | C51: €/kg | F51: Pesticide 9 price
B52: Pesticide 10 price | C52: €/kg | F52: Pesticide 10 price
B53: Number of fertilizers used | C53: n | D53: 2 | F53: Number of fertilizers used | G53: n | H53: 5
B54: Fertiliser 1 price | C54: €/kg | D54: 1.05 | F54: Fertiliser 1 price | G54: €/kg | H54: 0.3
B55: Fertiliser 2 price | C55: €/kg | D55: 0.8 | F55: Fertiliser 2 price | G55: €/kg | H55: 0.4
B56: Fertiliser 3 price | C56: €/kg | F56: Fertiliser 3 price | G56: €/kg | H56: 0.3
B57: Fertiliser 4 price | C57: €/kg | F57: Fertiliser 4 price | G57: €/kg | H57: 13.5
B58: Fertiliser 5 price | C58: €/kg | F58: Fertiliser 5 price | G58: €/kg | H58: 25
B59: Fertiliser 6 price | C59: €/kg | F59: Fertiliser 6 price | G59: €/kg
B60: Fertiliser 7 price | F60: Fertiliser 7 price
B61: Fertiliser 8 price | F61: Fertiliser 8 price
B62: Fertiliser 9 price | F62: Fertiliser 9 price
B63: Fertiliser 10 price | F63: Fertiliser 10 price
B64: Number of feed used | C64: n | F64: Number of feed used | G64: n
B65: Feed 1 price | C65: €/t | F65: Feed 1 price | G65: €/t
B66: Feed 2 price | C66: €/t | F66: Feed 2 price | G66: €/t
B67: Feed 3 price | F67: Feed 3 price
B68: Feed 4 price | F68: Feed 4 price
B69: Feed 5 price | C69: €/t | F69: Feed 5 price | G69: €/t
B70: Number of drugs used | C70: n | F70: Number of drugs used | G70: n
B71: Drug 1 price | C71: €/g | F71: Drug 1 price | G71: €/g
B72: Drug 2 price | C72: €/g | F72: Drug 2 price | G72: €/g
B73: Drug 3 price | C73: €/g | F73: Drug 3 price | G73: €/g

Sheet Parcel 1 with DATSs
BF1: yes
G2: PARCEL WITH DATSs | BF2: no
C4: Identification | D4: Parcel Name
B8: Information about the TC
B9: # | C9: data | D9: u.m. | E9: value | G9: Notes
B10: 1 | C10: Parcel dimension | D10: ha | E10: 898
B11: 2 | C11: Number of plants/trees | D11: n
B12: 3 | C12: Sand content in the soil | D12: % | E12: 7.2
B13: 4 | C13: Clay content in the soil | D13: % | E13: 22.2
B14: 5 | C14: Silt content in the soil | D14: % | E14: 63.7
B15: 6 | C15: Soil Bulk Density | E15: 1.2
B16: 7 | C16: Soil Organic Carbon | D16: % | E16: 3.24
B17: 8 | C17: Number of animals | D17: n
B18: 9 | C18: Livestock units per hectare | D18: LSU/ha
B19: 10 | C19: Number of beehives | D19: n
B20: 11 | C20: Area under aquaculture
B22: WATER | G22: Year 1 | J22: Year 2 | M22: Year 3
B23: # | C23: data | D23: u.m. | G23: With DATSs | H23: Notes | J23: With DATSs | K23: Notes | M23: With DATSs | N23: Notes
B24: 12 | C24: Irrigation | G24: 360
B25: 13 | C25: Fertigation
B26: 14 | C26: Pest dilution
B27: 15 | C27: Cleaning
B28: 16 | C28: Drinking
B29: 17 | C29: Total water used | G29: 360
B31: FUEL | G31: Year 1 | J31: Year 2 | M31: Year 3
B32: # | C32: data | D32: u.m. | G32: With DATSs | H32: Notes | J32: With DATSs | K32: Notes | M32: With DATSs | N32: Notes
B33: 18 | C33: Fertilisation | D33: l | G33: 3560
B34: 19 | C34: Pesticides | D34: l | G34: 4450
B35: 20 | C35: Irrigation | D35: l
B36: 21 | C36: Sowing / Planting | D36: l | G36: 9345
B37: 22 | C37: Temperature and Humidity Control | D37: l
B38: 23 | C38: Pruning | D38: l | G38: 4005
B39: 24 | C39: Beehives visits | D39: l
B40: 25 | C40: Transporting oysters to the laboratory | D40: l
B41: 26 | C41: Milking | D41: l
B42: 27 | C42: Feeding | D42: l
B43: 28 | C43: Total fuel used | D43: l | G43: 44500
B45: FUEL FOR GREENHOUSE TEMPERATURE CONTROL | G45: Year 1 | J45: Year 2 | M45: Year 3
B46: # | C46: data | E46: u.m. | G46: With DATSs | H46: Notes | J46: With DATSs | K46: Notes | M46: With DATSs | N46: Notes
B47: 29 | C47: Fuel 1 | D47: Name fuel 1
B48: 30 | C48: Fuel 1 | D48: Quantity
B49: 31 | C49: Fuel 2 | D49: Name fuel 2
B50: 32 | C50: Fuel 2 | D50: Quantity
B51: 33 | C51: Fuel n | D51: Name fuel n
B52: 34 | C52: Fuel n | D52: Quantity
B54: ELECTRICITY | G54: Year 1 | J54: Year 2 | M54: Year 3
B55: # | C55: data | D55: u.m. | G55: With DATSs | H55: Notes | J55: With DATSs | K55: Notes | M55: With DATSs | N55: Notes
B56: 35 | C56: Temperature and Humidity Control | D56: kWh
B57: 36 | C57: Irrigation | D57: kWh
B58: 37 | C58: Milking | D58: kWh
B59: 38 | C59: Heat detection | D59: kWh
B60: 39 | C60: Calving detection | D60: kWh
B61: 40 | C61: Feeding | D61: kWh
B62: 41 | C62: Total electricity used | D62: kWh | G62: 2776
B64: PESTICIDES (HERBICIDES, FUNGICIDES, INSECTICIDES) | G64: Year 1 | J64: Year 2 | M64: Year 3
B65: # | C65: data | E65: u.m. | G65: With DATSs | H65: Notes | J65: With DATSs | K65: Notes | M65: With DATSs | N65: Notes
B66: 42 | C66: Product 1 | D66: Name product 1 | G66: Dicopur D (Herbicide)
B67: 43 | C67: Product 1 | D67: N. of treatements | E67: n | G67: 1
B68: 44 | C68: Product 1 | D68: Average quantity per application | E68: =IF('General Information'!C43="€/kg","kg/ha","l/ha") -> kg/ha | G68: 0.8
B69: 45 | C69: Product 2 | D69: Name product 2 | G69: Secator Progress (Herbicide)
B70: 46 | C70: Product 2 | D70: N. of treatements | E70: n | G70: 1
B71: 47 | C71: Product 2 | D71: Average quantity per application | E71: =IF('General Information'!C44="€/kg","kg/ha","l/ha") -> kg/ha | G71: 0.15
B72: 48 | C72: Product 3 | D72: Name product n | G72: LS Prothio-Tebuc (Fungicide)
B73: 49 | C73: Product 3 | D73: N. of treatements | E73: n | G73: 1
B74: 50 | C74: Product 3 | D74: Average quantity per application | E74: =IF('General Information'!C45="€/kg","kg/ha","l/ha") -> kg/ha | G74: 0.75
B75: 51 | C75: Product 4 | D75: Name product n | G75: STARPRO 430SC (Fungicide)
B76: 52 | C76: Product 4 | D76: N. of treatements | E76: n | G76: 1
B77: 53 | C77: Product 4 | D77: Average quantity per application | E77: =IF('General Information'!C46="€/kg","kg/ha","l/ha") -> kg/ha | G77: 0.6
B78: 54 | C78: Product 4 | D78: Name product n
B79: 55 | C79: Product 5 | D79: N. of treatements | E79: n
B80: 56 | C80: Product 5 | D80: Average quantity per application | E80: =IF('General Information'!C47="€/kg","kg/ha","l/ha") -> kg/ha
B81: 57 | C81: Product 6 | D81: Name product n
B82: 58 | C82: Product 6 | D82: N. of treatements | E82: n
B83: 59 | C83: Product 6 | D83: Average quantity per application | E83: =IF('General Information'!C48="€/kg","kg/ha","l/ha") -> kg/ha
B84: 60 | C84: Product 7 | D84: Name product n
B85: 61 | C85: Product 7 | D85: N. of treatements | E85: n
B86: 62 | C86: Product 7 | D86: Average quantity per application | E86: =IF('General Information'!C49="€/kg","kg/ha","l/ha") -> kg/ha
B87: 63 | C87: Product 8 | D87: Name product n
B88: 64 | C88: Product 8 | D88: N. of treatements | E88: n
B89: 65 | C89: Product 8 | D89: Average quantity per application | E89: =IF('General Information'!C52="€/kg","kg/ha","l/ha") -> kg/ha
B90: 66 | C90: Product 9 | D90: Name product n
B91: 67 | C91: Product 9 | D91: N. of treatements | E91: n
B92: 68 | C92: Product 9 | D92: Average quantity per application | E92: =IF('General Information'!C55="€/kg","kg/ha","l/ha") -> kg/ha
B93: 69 | C93: Product 10 | D93: Name product n
B94: 70 | C94: Product 10 | D94: N. of treatements | E94: n
B95: 71 | C95: Product 10 | D95: Average quantity per application | E95: =IF('General Information'!C58="€/kg","kg/ha","l/ha") -> kg/ha
B97: FERTILISER | G97: Year 1 | J97: Year 2 | M97: Year 3
B98: # | C98: data | E98: u.m. | G98: With DATSs | H98: Notes | J98: With DATSs | K98: Notes | M98: With DATSs | N98: Notes
B99: 72 | C99: Fertilizer 1 | D99: Name fertiliser 1 | G99: MAP (11-52-0)
B100: 73 | C100: Fertilizer 1 | D100: Mineral/Organic | G100: Mineral
B101: 74 | C101: Fertilizer 1 | D101: N. of treatements | E101: n | G101: 1
B102: 75 | C102: Fertilizer 1 | D102: Average quantity per application | E102: =IF('General Information'!C54="€/t","t/ha","kg/ha") -> kg/ha | G102: 60
B103: 76 | C103: Fertilizer 1 | D103: N concentration | E103: % | G103: 11
B104: 77 | C104: Fertilizer 1 | D104: P concentration | E104: % | G104: 52
B105: 78 | C105: Fertilizer 1 | D105: K concentration | E105: % | G105: 0
B106: 79 | C106: Fertilizer 2 | D106: Name fertiliser 2 | G106: Ammonium Nitrate
B107: 80 | C107: Fertilizer 2 | D107: Mineral/Organic | G107: Mineral
B108: 81 | C108: Fertilizer 2 | D108: N. of treatements | E108: n | G108: 1
B109: 82 | C109: Fertilizer 2 | D109: Average quantity per application | E109: =IF('General Information'!C55="€/t","t/ha","kg/ha") -> kg/ha | G109: 300
B110: 83 | C110: Fertilizer 2 | D110: N concentration | E110: % | G110: 34.5
...

Sheet Parcel 1 without DATSs
BG1: yes
G2: PARCEL WITHOUT DATSs | BG2: no
C4: Identification | D4: Parcel Name
B8: Information about the TC
B9: # | C9: data | D9: u.m. | E9: value | G9: Notes
B10: 1 | C10: Parcel dimension | D10: ha | E10: 208
B11: 2 | C11: Number of plants/trees | D11: n
B12: 3 | C12: Sand content in the soil | D12: % | E12: 6.4
B13: 4 | C13: Clay content in the soil | D13: % | E13: 27.8
B14: 5 | C14: Silt content in the soil | D14: % | E14: 59.9
B15: 6 | C15: Soil Bulk Density | E15: 1.22
B16: 7 | C16: Soil Organic Carbon | D16: % | E16: 3.6
B17: 8 | C17: Number of animals | D17: n
B18: 9 | C18: Livestock units per hectare | D18: LSU/ha
B19: 10 | C19: Number of beehives | D19: n
B20: 11 | C20: Area under aquaculture
B22: WATER | G22: Year 1 | J22: Year 2 | M22: Year 3
B23: # | C23: data | D23: u.m. | G23: Without DATSs | H23: Notes | J23: Without DATSs | K23: Notes | M23: Without DATSs | N23: Without DAT
B24: 12 | C24: Irrigation | G24: 166
B25: 13 | C25: Fertigation
B26: 14 | C26: Pest dilution
B27: 15 | C27: Cleaning
B28: 16 | C28: Drinking
B29: 17 | C29: or Total water used | G29: 166
B31: FUEL | G31: Year 1 | J31: Year 2 | M31: Year 3
B32: # | C32: data | D32: u.m. | G32: Without DATSs | H32: Notes | J32: Without DATSs | K32: Notes | M32: Without DATSs | N32: Without DAT
B33: 18 | C33: Fertilisation | D33: l | G33: 784
B34: 19 | C34: Pesticides | D34: l | G34: 1004
B35: 20 | C35: Irrigation | D35: l | G35: 0
B36: 21 | C36: Sowing / Planting | D36: l | G36: 3568
B37: 22 | C37: Temperature and Humidity Control | D37: l
B38: 23 | C38: Pruning | D38: l
B39: 24 | C39: Beehives visits | D39: l
B40: 25 | C40: Transporting oysters to the laboratory | D40: l
B41: 26 | C41: Milking | D41: l
B42: 27 | C42: Feeding | D42: l
B43: 28 | C43: or Total fuel used | D43: l | G43: 11150
B45: FUEL FOR GREENHOUSE TEMPERATURE CONTROL | G45: Year 1 | J45: Year 2 | M45: Year 3
B46: # | C46: data | E46: u.m. | G46: Without DATSs | H46: Notes | J46: Without DATSs | K46: Notes | M46: Without DATSs | N46: Without DAT
B47: 29 | C47: Fuel 1 | D47: Name fuel 1
B48: 30 | C48: Fuel 1 | D48: Quantity
B49: 31 | C49: Fuel 2 | D49: Name fuel 2
B50: 32 | C50: Fuel 2 | D50: Quantity
B51: 33 | C51: Fuel n | D51: Name fuel 2
B52: 34 | C52: Fuel n | D52: Quantity
B54: ELECTRICITY | G54: Year 1 | J54: Year 2 | M54: Year 3
B55: # | C55: data | D55: u.m. | G55: Without DATSs | H55: Notes | J55: Without DATSs | K55: Notes | M55: Without DATSs | N55: Without DAT
B56: 35 | C56: Temperature and Humidity Control | D56: kWh
B57: 36 | C57: Irrigation | D57: kWh
B58: 37 | C58: Milking | D58: kWh
B59: 38 | C59: Heat detection | D59: kWh
B60: 39 | C60: Calving detection | D60: kWh
B61: 40 | C61: Feeding | D61: kWh
B62: 41 | C62: or Total electricity used | D62: kWh | G62: 1077
B64: PESTICIDES (HERBICIDES, FUNGICIDES, INSECTICIDES) | G64: Year 1 | J64: Year 2 | M64: Year 3
B65: # | C65: data | E65: u.m. | G65: Without DATSs | H65: Notes | J65: Without DATSs | K65: Notes | M65: Without DATSs | N65: Without DAT
B66: 42 | C66: Product 1 | D66: Name product 1 | G66: Trinity (Herbicide)
B67: 43 | C67: Product 1 | D67: N. of treatements | E67: n | G67: 1
B68: 44 | C68: Product 1 | D68: Average quantity per application | E68: =IF('General Information'!C43="€/kg","kg/ha","l/ha") -> kg/ha | G68: 2
B69: 45 | C69: Product 2 | D69: Name product 2 | G69: Tomigan XL (Herbicide)
B70: 46 | C70: Product 2 | D70: N. of treatements | E70: n | G70: 1
B71: 47 | C71: Product 2 | D71: Average quantity per application | E71: =IF('General Information'!C44="€/kg","kg/ha","l/ha") -> kg/ha | G71: 1
B72: 48 | C72: Product 3 | D72: Name product n | G72: Custodia (Fungicide)
B73: 49 | C73: Product 3 | D73: N. of treatements | E73: n | G73: 1
B74: 50 | C74: Product 3 | D74: Average quantity per application | E74: =IF('General Information'!C45="€/kg","kg/ha","l/ha") -> kg/ha | G74: 1
B75: 51 | C75: Product 4 | D75: Name product n | G75: Lamdex (Insecticide)
B76: 52 | C76: Product 4 | D76: N. of treatements | E76: n | G76: 1
B77: 53 | C77: Product 4 | D77: Average quantity per application | E77: =IF('General Information'!C46="€/kg","kg/ha","l/ha") -> kg/ha | G77: 0.3
B78: 54 | C78: Product 4 | D78: Name product n | G78: Vandex (Insecticide)
B79: 55 | C79: Product 5 | D79: N. of treatements | E79: n | G79: 1
B80: 56 | C80: Product 5 | D80: Average quantity per application | E80: =IF('General Information'!C47="€/kg","kg/ha","l/ha") -> kg/ha | G80: 0.08
B81: 57 | C81: Product 6 | D81: Name product n | G81: Kinto Plus / Picus (Seed treatment)
B82: 58 | C82: Product 6 | D82: N. of treatements | E82: n | G82: 1
B83: 59 | C83: Product 6 | D83: Average quantity per application | E83: =IF('General Information'!C48="€/kg","kg/ha","l/ha") -> kg/ha | G83: 1
B84: 60 | C84: Product 7 | D84: Name product n
B85: 61 | C85: Product 7 | D85: N. of treatements | E85: n
B86: 62 | C86: Product 7 | D86: Average quantity per application | E86: =IF('General Information'!C49="€/kg","kg/ha","l/ha") -> kg/ha
B87: 63 | C87: Product 8 | D87: Name product n
B88: 64 | C88: Product 8 | D88: N. of treatements | E88: n
B89: 65 | C89: Product 8 | D89: Average quantity per application | E89: =IF('General Information'!C52="€/kg","kg/ha","l/ha") -> kg/ha
B90: 66 | C90: Product 9 | D90: Name product n
B91: 67 | C91: Product 9 | D91: N. of treatements | E91: n
B92: 68 | C92: Product 9 | D92: Average quantity per application | E92: =IF('General Information'!C55="€/kg","kg/ha","l/ha") -> kg/ha
B93: 69 | C93: Product 10 | D93: Name product n
B94: 70 | C94: Product 10 | D94: N. of treatements | E94: n
B95: 71 | C95: Product 10 | D95: Average quantity per application | E95: =IF('General Information'!C58="€/kg","kg/ha","l/ha") -> kg/ha
B97: FERTILISER | G97: Year 1 | J97: Year 2 | M97: Year 3
B98: # | C98: data | E98: u.m. | G98: Without DATSs | H98: Notes | J98: Without DATSs | K98: Notes | M98: Without DATSs | N98: Without DAT
B99: 72 | C99: Fertilizer 1 | D99: Name fertiliser 1 | G99: Ammonium Sulphate
B100: 73 | C100: Fertilizer 1 | D100: Mineral/Organic | G100: Mineral
B101: 74 | C101: Fertilizer 1 | D101: N. of treatements | E101: n | G101: 1
B102: 75 | C102: Fertilizer 1 | D102: Average quantity per application | E102: =IF('General Information'!C54="€/t","t/ha","kg/ha") -> kg/ha | G102: 180
B103: 76 | C103: Fertilizer 1 | D103: N concentration | E103: % | G103: 21
B104: 77 | C104: Fertilizer 1 | D104: P concentration | E104: % | G104: 0
B105: 78 | C105: Fertilizer 1 | D105: K concentration | E105: % | G105: 0
B106: 79 | C106: Fertilizer 2 | D106: Name fertiliser 2 | G106: NPK (15-25-0)
B107: 80 | C107: Fertilizer 2 | D107: Mineral/Organic | G107: Mineral
B108: 81 | C108: Fertilizer 2 | D108: N. of treatements | E108: n | G108: 1
B109: 82 | C109: Fertilizer 2 | D109: Average quantity per application | E109: =IF('General Information'!C55="€/t","t/ha","kg/ha") -> kg/ha | G109: 190
B110: 83 | C110: Fertilizer 2 | D110: N concentration | E110: % | G110: 15
...

Sheet Cost-revenue DATS
A1: COST ANALYSIS
A2: INPUT | B2: INDICATOR | C2: SCENARIO | D2: UoM | E2: TOTAL | F2: FORMULAS
A3: WATER | B3: Cost of water | C3: With DATs | D3: =IFERROR(VLOOKUP('General Information'!$D$6, Validations!$L$2:$M$8, 2,FALSE), "") -> €/ha | E3: =('Parcel 1 with DATSs'!G29*'General Information'!D32)/(IF('General Information'!D6="crop",'Parcel 1 with DATSs'!E10,IF('General Information'!D6="milk",'Parcel 1 with DATSs'!G251,IF('General Information'!D6="meat",'Parcel 1 with DATSs'!G252,IF('General Information'!D6="animal",'Parcel 1 with DATSs'!G253,IF('General Information'!D6="oyster",'Parcel 1 with DATSs'!G254,IF('General Information'!D6="honey",'Parcel 1 with DATSs'!G255,'Parcel 1 with DATSs'!G256))))))) -> 0 | F3: IF(Total water used>0; (Total water used * water price)/Parcel dimension; Sum(water Irrigation+ water Fertigation + water Pest dilution + …) * water price)
A4: FUEL | B4: Cost of fuel | C4: With DATs | D4: =IFERROR(VLOOKUP('General Information'!$D$6, Validations!$L$2:$M$8, 2,FALSE), "") -> €/ha | E4: ='Parcel 1 with DATSs'!G43*'General Information'!D33/(IF('General Information'!D6="crop",'Parcel 1 with DATSs'!E10,IF('General Information'!D6="milk",'Parcel 1 with DATSs'!G251,IF('General Information'!D6="meat",'Parcel 1 with DATSs'!G252,IF('General Information'!D6="animal",'Parcel 1 with DATSs'!G253,IF('General Information'!D6="oyster",'Parcel 1 with DATSs'!G254,IF('General Information'!D6="honey",'Parcel 1 with DATSs'!G255,'Parcel 1 with DATSs'!G256))))))) -> 56.987751 | F4: IF(Total fuel used>0; (Total fuel used*fuel price)/Parcel dimension; sum(Fertilisation+Pesticides +Irrigation+Sowing_Planting+Pruning+…) * fuel price)
A5: ELECTRICITY | B5: Cost of electricity | C5: With DATs | D5: =IFERROR(VLOOKUP('General Information'!$D$6, Validations!$L$2:$M$8, 2,FALSE), "") -> €/ha | E5: ='Parcel 1 with DATSs'!G62*'General Information'!D38/(IF('General Information'!D6="crop",'Parcel 1 with DATSs'!E10,IF('General Information'!D6="milk",'Parcel 1 with DATSs'!G251,IF('General Information'!D6="meat",'Parcel 1 with DATSs'!G252,IF('General Information'!D6="animal",'Parcel 1 with DATSs'!G253,IF('General Information'!D6="oyster",'Parcel 1 with DATSs'!G254,IF('General Information'!D6="honey",'Parcel 1 with DATSs'!G255,'Parcel 1 with DATSs'!G256))))))) -> 0.45751448 | F5: IF(Total electricity used > 0; (Total electricity used* electricity price)/Parcel dimension; Sum(irrigation,…) *electricity price)
A6: PESTICIDE | B6: Cost for pesticide | C6: With DATs | D6: =IFERROR(VLOOKUP('General Information'!$D$6, Validations!$L$2:$M$8, 2,FALSE), "") -> €/ha | E6: =('Parcel 1 with DATSs'!G67*'Parcel 1 with DATSs'!G68*'General Information'!D43)+ ('Parcel 1 with DATSs'!G70*'Parcel 1 with DATSs'!G71*'General Information'!D44)+ ('Parcel 1 with DATSs'!G73*'Parcel 1 with DATSs'!G74*'General Information'!D45)+ ('Parcel 1 with DATSs'!G76*'Parcel 1 with DATSs'!G77*'General Information'!D46)+ ('Parcel 1 with DATSs'!G79*'Parcel 1 with DATSs'!G80*'General Information'!D47)+ ('Parcel 1 with DATSs'!G82*'Parcel 1 with DATSs'!G83*'General Information'!D48)+ ('Parcel 1 with DATSs'!G85*'Parcel 1 with DATSs'!G86*'General Information'!D49)+ ('Parcel 1 with DATSs'!G88*'Parcel 1 with DATSs'!G89*'General Information'!D50)+ ('Parcel 1 with DATSs'!G91*'Parcel 1 with DATSs'!G92*'General Information'!D51)+ ('Parcel 1 with DATSs'!G94*'Parcel 1 with DATSs'!G95*'General Information'!D52) -> 51.1 | F6: [(N. of treatements of pesticide 1*Amount of pesticide 1*pesticide 1 price)+(N. of treatements of pesticide 2 *Amount of pesticide 2 used *pesticide 2 price) + (N. of treatements of pesticide 3 *Amount of pesticide 3 used *pesticide 3 price (€/kg)]
A7: FERTILISER | B7: Cost of fertiliser | C7: With DATs | D7: =IFERROR(VLOOKUP('General Information'!$D$6, Validations!$L$2:$M$8, 2,FALSE), "") -> €/ha | E7: =('Parcel 1 with DATSs'!G101*'Parcel 1 with DATSs'!G102*'General Information'!D54)+ ('Parcel 1 with DATSs'!G108*'Parcel 1 with DATSs'!G109*'General Information'!D55)+ ('Parcel 1 with DATSs'!G115*'Parcel 1 with DATSs'!G116*'General Information'!D56)+ ('Parcel 1 with DATSs'!G122*'Parcel 1 with DATSs'!G123*'General Information'!D57)+ ('Parcel 1 with DATSs'!G129*'Parcel 1 with DATSs'!G130*'General Information'!D58)+ ('Parcel 1 with DATSs'!G136*'Parcel 1 with DATSs'!G137*'General Information'!D59)+ ('Parcel 1 with DATSs'!G143*'Parcel 1 with DATSs'!G144*'General Information'!D60)+ ('Parcel 1 with DATSs'!G150*'Parcel 1 with DATSs'!G151*'General Information'!D61)+ ('Parcel 1 with DATSs'!G157*'Parcel 1 with DATSs'!G158*'General Information'!D62)+ ('Parcel 1 with DATSs'!G164*'Parcel 1 with DATSs'!G165*'General Information'!D63) -> 303 | F7: ((Amount of fertilisers 1 used *Number of fertilizer 1 applications *Fertilisers 1 price) + (Amount of fertilisers 2 used *Number of fertilizer 2 applications *Fertilisers 2 price) + (Amount of fertilisers 3 used *Number of fertilizer 3 applications *Fertilisers 3 price)
A8: FEED | B8: Cost of feed | C8: With DATs | D8: =IFERROR(VLOOKUP('General Information'!$D$6, Validations!$L$2:$M$8, 2,FALSE), "") -> €/ha | E8: =(('General Information'!D65*'Parcel 1 with DATSs'!G173)+('General Information'!D66*'Parcel 1 with DATSs'!G175)+('General Information'!D69*'Parcel 1 with DATSs'!G177))/(IF('General Information'!D6="crop",'Parcel 1 with DATSs'!E10,IF('General Information'!D6="milk",'Parcel 1 with DATSs'!G251,IF('General Information'!D6="meat",'Parcel 1 with DATSs'!G252,IF('General Information'!D6="animal",'Parcel 1 with DATSs'!G253,IF('General Information'!D6="oyster",'Parcel 1 with DATSs'!G254,IF('General Information'!D6="honey",'Parcel 1 with DATSs'!G255,'Parcel 1 with DATSs'!G256))))))) -> 0 | F8: (Amount of feed 1 * Feed 1 price) + (Amount of feed 2 * Feed 2 price) + … /animal
A9: DRUGS | B9: Cost of drugs | C9: With DATs | D9: =IFERROR(VLOOKUP('General Information'!$D$6, Validations!$L$2:$M$8, 2,FALSE), "") -> €/ha | E9: =(('General Information'!D71*'Parcel 1 with DATSs'!G186)+('General Information'!D72*'Parcel 1 with DATSs'!G188)+('General Information'!D73*'Parcel 1 with DATSs'!G190))/(IF('General Information'!D6="crop",'Parcel 1 with DATSs'!E10,IF('General Information'!D6="milk",'Parcel 1 with DATSs'!G251,IF('General Information'!D6="meat",'Parcel 1 with DATSs'!G252,IF('General Information'!D6="animal",'Parcel 1 with DATSs'!G253,IF('General Information'!D6="oyster",'Parcel 1 with DATSs'!G254,IF('General Information'!D6="honey",'Parcel 1 with DATSs'!G255,'Parcel 1 with DATSs'!G256))))))) -> 0 | F9: (Amount of drugs 1 * Feed 1 price) + (Amount of drugs 2 * Feed 2 price) + … /animal or beehives or pieces
A10: LABOUR | B10: Cost of labour for irrigation | C10: With DATs | D10: =IFERROR(VLOOKUP('General Information'!$D$6, Validations!$L$2:$M$8, 2,FALSE), "") -> €/ha | E10: ='Parcel 1 with DATSs'!G194*'General Information'!D39/'Parcel 1 with DATSs'!E10 -> 0 | F10: number of hours for irrigation activities*Average salary /Parcel dimension
A11: LABOUR | B11: Cost of labour for pesticide application | C11: With DATs | D11: =IFERROR(VLOOKUP('General Information'!$D$6, Validations!$L$2:$M$8, 2,FALSE), "") -> €/ha | E11: ='Parcel 1 with DATSs'!G195*'General Information'!D39/'Parcel 1 with DATSs'!E10 -> 19.699777 | F11: number of hours for pesticide activities *Average salary /Parcel dimension
A12: LABOUR | B12: Cost of labour for fertilisation | C12: With DATs | D12: =IFERROR(VLOOKUP('General Information'!$D$6, Validations!$L$2:$M$8, 2,FALSE), "") -> €/ha | E12: ='Parcel 1 with DATSs'!G196*'General Information'!D39/'Parcel 1 with DATSs'!E10 -> 9.8538976 | F12: number of hours for fertilisation activities * Average salary /Parcel dimension
A13: LABOUR | B13: Cost of labour for sowing_planting | C13: With DATs | D13: =IFERROR(VLOOKUP('General Information'!$D$6, Validations!$L$2:$M$8, 2,FALSE), "") -> €/ha | E13: ='Parcel 1 with DATSs'!G197*'General Information'!D39/'Parcel 1 with DATSs'!E10 -> 9.8538976 | F13: number of hours for sowing_planting activities * Average salary /Parcel dimension
A14: LABOUR | B14: Cost of labour for pruning | C14: With DATs | D14: =IFERROR(VLOOKUP('General Information'!$D$6, Validations!$L$2:$M$8, 2,FALSE), "") -> €/ha | E14: ='Parcel 1 with DATSs'!G198*'General Information'!D39/'Parcel 1 with DATSs'!E10 -> 4.9229399 | F14: number of hours for pruning activities *Average salary /Parcel dimension
A15: LABOUR | B15: Cost of labour for field visits | C15: With DATs | D15: =IFERROR(VLOOKUP('General Information'!$D$6, Validations!$L$2:$M$8, 2,FALSE), "") -> €/ha | E15: ='Parcel 1 with DATSs'!G199*'General Information'!D39/'Parcel 1 with DATSs'!E10 -> 8.4427617 | F15: number of hours for field visits activities * Average professional salary /Parcel dimension
A16: LABOUR | B16: Cost of labour for greenhouse maintenance | C16: With DATs | D16: =IFERROR(VLOOKUP('General Information'!$D$6, Validations!$L$2:$M$8, 2,FALSE), "") -> €/ha | E16: ='Parcel 1 with DATSs'!G200*'General Information'!D39/'Parcel 1 with DATSs'!E10 -> 0 | F16: number of hours for greenhouse management *Average salary /Parcel dimension
A17: LABOUR | B17: Cost of labour for tracking the quantity of grain available in the silo | C17: With DATs | D17: =IFERROR(VLOOKUP('General Information'!$D$6, Validations!$L$2:$M$8, 2,FALSE), "") -> €/ha | E17: ='Parcel 1 with DATSs'!G201*'General Information'!D39/'Parcel 1 with DATSs'!G256 -> #DIV/0! | F17: number of hours for tracking the quantity of grain available in the silo *Average salary
A18: LABOUR | B18: Cost of labour for assessing product quality | C18: With DATs | D18: =IFERROR(VLOOKUP('General Information'!$D$6, Validations!$L$2:$M$8, 2,FALSE), "") -> €/ha | E18: ='Parcel 1 with DATSs'!G202*'General Information'!D39/(IF('General Information'!D6="crop",'Parcel 1 with DATSs'!E10,IF('General Information'!D6="milk",'Parcel 1 with DATSs'!G251,IF('General Information'!D6="meat",'Parcel 1 with DATSs'!G252,IF('General Information'!D6="animal",'Parcel 1 with DATSs'!G253,IF('General Information'!D6="oyster",'Parcel 1 with DATSs'!G254,IF('General Information'!D6="honey",'Parcel 1 with DATSs'!G255,'Parcel 1 with DATSs'!G256))))))) -> 0 | F18: number of hours for assessing grain quality *Average salary
A19: LABOUR | B19: Cost of labour for controlling purchase and sale prices and quantities | C19: With DATs | D19: =IFERROR(VLOOKUP('General Information'!$D$6, Validations!$L$2:$M$8, 2,FALSE), "") -> €/ha | E19: ='Parcel 1 with DATSs'!G203*'General Information'!D39/(IF('General Information'!D6="crop",'Parcel 1 with DATSs'!E10,IF('General Information'!D6="milk",'Parcel 1 with DATSs'!G251,IF('General Information'!D6="meat",'Parcel 1 with DATSs'!G252,IF('General Information'!D6="animal",'Parcel 1 with DATSs'!G253, IF('General Information'!D6="oyster",'Parcel 1 with DATSs'!G254,IF('General Information'!D6="honey",'Parcel 1 with DATSs'!G255,'Parcel 1 with DATSs'!G256))))))) -> 0 | F19: number of hours for controlling purchase and sale prices and quantities *Average salary
A20: LABOUR | B20: Cost of labour for organise logistics | C20: With DATs | D20: =IFERROR(VLOOKUP('General Information'!$D$6, Validations!$L$2:$M$8, 2,FALSE), "") -> €/ha | E20: ='Parcel 1 with DATSs'!G204*'General Information'!D39/(IF('General Information'!D6="crop",'Parcel 1 with DATSs'!E10,IF('General Information'!D6="milk",'Parcel 1 with DATSs'!G251,IF('General Information'!D6="meat",'Parcel 1 with DATSs'!G252,IF('General Information'!D6="animal",'Parcel 1 with DATSs'!G253, IF('General Information'!D6="oyster",'Parcel 1 with DATSs'!G254,IF('General Information'!D6="honey",'Parcel 1 with DATSs'!G255,'Parcel 1 with DATSs'!G256))))))) -> 0 | F20: number of hours for organise logistics *Average salary
A21: LABOUR | B21: Cost of labour for cleaning | C21: With DATs | D21: =IFERROR(VLOOKUP('General Information'!$D$6, Validations!$L$2:$M$8, 2,FALSE), "") -> €/ha | E21: ='Parcel 1 with DATSs'!G205*'General Information'!D39/(IF('General Information'!D6="crop",'Parcel 1 with DATSs'!E10,IF('General Information'!D6="milk",'Parcel 1 with DATSs'!G251,IF('General Information'!D6="meat",'Parcel 1 with DATSs'!G252,IF('General Information'!D6="animal",'Parcel 1 with DATSs'!G253, IF('General Information'!D6="oyster",'Parcel 1 with DATSs'!G254,IF('General Information'!D6="honey",'Parcel 1 with DATSs'!G255,'Parcel 1 with DATSs'!G256))))))) -> 0 | F21: number of hours for cleaning *Average salary /animal
A22: LABOUR | B22: Cost of labour for stable visits | C22: With DATs | D22: =IFERROR(VLOOKUP('General Information'!$D$6, Validations!$L$2:$M$8, 2,FALSE), "") -> €/ha | E22: ='Parcel 1 with DATSs'!G206*'General Information'!D39/(IF('General Information'!D6="crop",'Parcel 1 with DATSs'!E10,IF('General Information'!D6="milk",'Parcel 1 with DATSs'!G251,IF('General Information'!D6="meat",'Parcel 1 with DATSs'!G252,IF('General Information'!D6="animal",'Parcel 1 with DATSs'!G253, IF('General Information'!D6="oyster",'Parcel 1 with DATSs'!G254,IF('General Information'!D6="honey",'Parcel 1 with DATSs'!G255,'Parcel 1 with DATSs'!G256))))))) -> 0 | F22: number of hours for stable visits*Average professional salary /animal
A23: LABOUR | B23: Cost of labour for heat detection | C23: With DATs | D23: =IFERROR(VLOOKUP('General Information'!$D$6, Validations!$L$2:$M$8, 2,FALSE), "") -> €/ha | E23: ='Parcel 1 with DATSs'!G207*'General Information'!D39/(IF('General Information'!D6="crop",'Parcel 1 with DATSs'!E10,IF('General Information'!D6="milk",'Parcel 1 with DATSs'!G251,IF('General Information'!D6="meat",'Parcel 1 with DATSs'!G252,IF('General Information'!D6="animal",'Parcel 1 with DATSs'!G253, IF('General Information'!D6="oyster",'Parcel 1 with DATSs'!G254,IF('General Information'!D6="honey",'Parcel 1 with DATSs'!G255,'Parcel 1 with DATSs'!G256))))))) -> 0 | F23: number of hours for heat detection *Average salary /animal
A24: LABOUR | B24: Cost of labour for calving detection | C24: With DATs | D24: =IFERROR(VLOOKUP('General Information'!$D$6, Validations!$L$2:$M$8, 2,FALSE), "") -> €/ha | E24: ='Parcel 1 with DATSs'!G208*'General Information'!D39/(IF('General Information'!D6="crop",'Parcel 1 with DATSs'!E10,IF('General Information'!D6="milk",'Parcel 1 with DATSs'!G251,IF('General Information'!D6="meat",'Parcel 1 with DATSs'!G252,IF('General Information'!D6="animal",'Parcel 1 with DATSs'!G253, IF('General Information'!D6="oyster",'Parcel 1 with DATSs'!G254,IF('General Information'!D6="honey",'Parcel 1 with DATSs'!G255,'Parcel 1 with DATSs'!G256))))))) -> 0 | F24: number of hours for calving detection *Average salary /animal
A25: LABOUR | B25: Cost of labour for pigsty management | C25: With DATs | D25: =IFERROR(VLOOKUP('General Information'!$D$6, Validations!$L$2:$M$8, 2,FALSE), "") -> €/ha | E25: ='Parcel 1 with DATSs'!G209*'General Information'!D39/(IF('General Information'!D6="crop",'Parcel 1 with DATSs'!E10,IF('General Information'!D6="milk",'Parcel 1 with DATSs'!G251,IF('General Information'!D6="meat",'Parcel 1 with DATSs'!G252,IF('General Information'!D6="animal",'Parcel 1 with DATSs'!G253, IF('General Information'!D6="oyster",'Parcel 1 with DATSs'!G254,IF('General Information'!D6="honey",'Parcel 1 with DATSs'!G255,'Parcel 1 with DATSs'!G256))))))) -> 0 | F25: number of hours for pigsty management*Average salary /animal
A26: LABOUR | B26: Cost of milking | C26: With DATs | D26: =IFERROR(VLOOKUP('General Information'!$D$6, Validations!$L$2:$M$8, 2,FALSE), "") -> €/ha | E26: ='Parcel 1 with DATSs'!G210*'General Information'!D39/(IF('General Information'!D6="crop",'Parcel 1 with DATSs'!E10,IF('General Information'!D6="milk",'Parcel 1 with DATSs'!G251,IF('General Information'!D6="meat",'Parcel 1 with DATSs'!G252,IF('General Information'!D6="animal",'Parcel 1 with DATSs'!G253, IF('General Information'!D6="oyster",'Parcel 1 with DATSs'!G254,IF('General Information'!D6="honey",'Parcel 1 with DATSs'!G255,'Parcel 1 with DATSs'!G256))))))) -> 0 | F26: number of hours for milking *Average salary /animal
A27: LABOUR | B27: Cost of labour for (milk) quality assessment | C27: With DATs | D27: =IFERROR(VLOOKUP('General Information'!$D$6, Validations!$L$2:$M$8, 2,FALSE), "") -> €/ha | E27: ='Parcel 1 with DATSs'!G211*'General Information'!D39/(IF('General Information'!D6="crop",'Parcel 1 with DATSs'!E10,IF('General Information'!D6="milk",'Parcel 1 with DATSs'!G251,IF('General Information'!D6="meat",'Parcel 1 with DATSs'!G252,IF('General Information'!D6="animal",'Parcel 1 with DATSs'!G253, IF('General Information'!D6="oyster",'Parcel 1 with DATSs'!G254,IF('General Information'!D6="honey",'Parcel 1 with DATSs'!G255,'Parcel 1 with DATSs'!G256))))))) -> 0 | F27: number of hours for (milk) quality assessment*Average salary /animal
A28: LABOUR | B28: Cost of labour for feeding | C28: With DATs | D28: =IFERROR(VLOOKUP('General Information'!$D$6, Validations!$L$2:$M$8, 2,FALSE), "") -> €/ha | E28: ='Parcel 1 with DATSs'!G212*'General Information'!D39/(IF('General Information'!D6="crop",'Parcel 1 with DATSs'!E10,IF('General Information'!D6="milk",'Parcel 1 with DATSs'!G251,IF('General Information'!D6="meat",'Parcel 1 with DATSs'!G252,IF('General Information'!D6="animal",'Parcel 1 with DATSs'!G253, IF('General Information'!D6="oyster",'Parcel 1 with DATSs'!G254,IF('General Information'!D6="honey",'Parcel 1 with DATSs'!G255,'Parcel 1 with DATSs'!G256))))))) -> 0 | F28: number of hours for feeding *Average salary /animal
A29: LABOUR | B29: Cost of labour for beehives visits | C29: With DATs | D29: =IFERROR(VLOOKUP('General Information'!$D$6, Validations!$L$2:$M$8, 2,FALSE), "") -> €/ha | E29: ='Parcel 1 with DATSs'!G213*'General Information'!D39/'Parcel 1 with DATSs'!G255 -> #DIV/0! | F29: number of hours for beehives visits *Average salary / beehive
A30: LABOUR | B30: Cost of labour for sampling of oysters | C30: With DATs | D30: =IFERROR(VLOOKUP('General Information'!$D$6, Validations!$L$2:$M$8, 2,FALSE), "") -> €/ha | E30: ='Parcel 1 with DATSs'!G214*'General Information'!D39/'Parcel 1 with DATSs'!G254 -> #DIV/0! | F30: number of hours for sampling of oysters* Average salary /piece
A31: LABOUR | B31: Cost of labour for transporting oysters to the laboratory | C31: With DATs | D31: =IFERROR(VLOOKUP('General Information'!$D$6, Validations!$L$2:$M$8, 2,FALSE), "") -> €/ha | E31: ='Parcel 1 with DATSs'!G215*'General Information'!D39/'Parcel 1 with DATSs'!G254 -> #DIV/0! | F31: number of hours for transporting oysters to the laboratory*Average salary /piece
A32: LABOUR | B32: Cost of labour for harvesting | C32: With DATs | D32: =IFERROR(VLOOKUP('General Information'!$D$6, Validations!$L$2:$M$8, 2,FALSE), "") -> €/ha | E32: ='Parcel 1 with DATSs'!G216*'General Information'!$D$39/(IF('General Information'!D6="crop",'Parcel 1 with DATSs'!E10,IF('General Information'!D6="milk",'Parcel 1 with DATSs'!G251,IF('General Information'!D6="meat",'Parcel 1 with DATSs'!G252,IF('General Information'!D6="animal",'Parcel 1 with DATSs'!G253, IF('General Information'!D6="oyster",'Parcel 1 with DATSs'!G254,IF('General Information'!D6="honey",'Parcel 1 with DATSs'!G255,'Parcel 1 with DATSs'!G256))))))) -> 14.776837 | F32: number of hours for harvesting oyster*Average salary /piece
A33: LABOUR | B33: Cost of labour for storage | C33: With DATs | D33: =IFERROR(VLOOKUP('General Information'!$D$6, Validations!$L$2:$M$8, 2,FALSE), "") -> €/ha | E33: ='Parcel 1 with DATSs'!G217*'General Information'!D39/(IF('General Information'!D6="crop",'Parcel 1 with DATSs'!E10,IF('General Information'!D6="milk",'Parcel 1 with DATSs'!G251,IF('General Information'!D6="meat",'Parcel 1 with DATSs'!G252,IF('General Information'!D6="animal",'Parcel 1 with DATSs'!G253, IF('General Information'!D6="oyster",'Parcel 1 with DATSs'!G254,IF('General Information'!D6="honey",'Parcel 1 with DATSs'!G255,'Parcel 1 with DATSs'!G256))))))) -> 0 | F33: number of hours for storage *Average salary /piece
A34: LABOUR | B34: Cost of administrative activities, data collection, etc. | C34: With DATs | D34: =IFERROR(VLOOKUP('General Information'!$D$6, Validations!$L$2:$M$8, 2,FALSE), "") -> €/ha | E34: ='Parcel 1 with DATSs'!G218*'General Information'!$D$39/(IF('General Information'!D6="crop",'Parcel 1 with DATSs'!E10,IF('General Information'!D6="milk",'Parcel 1 with DATSs'!G251,IF('General Information'!D6="meat",'Parcel 1 with DATSs'!G252,IF('General Information'!D6="animal",'Parcel 1 with DATSs'!G253, IF('General Information'!D6="oyster",'Parcel 1 with DATSs'!G254,IF('General Information'!D6="honey",'Parcel 1 with DATSs'!G255,'Parcel 1 with DATSs'!G256))))))) -> 8.4427617 | F34: number of hours foradministrative activities *Average salary /parcel dimension or animal or beehives or pieces
A35: COST | B35: TOT Cost | C35: With DATs | D35: =IFERROR(VLOOKUP('General Information'!$D$6, Validations!$L$2:$M$8, 2,FALSE), "") -> €/ha | E35: =_xlfn.AGGREGATE(9,6,E3:E34) -> 487.53814 | F35: Sum(Cost of labour for irrigation + Cost of labour for fertilisation + … /parcel dimension or animal or beehives or pieces
A36: DATSs | B36: Cost of DATSs | C36: With DATs | D36: =IFERROR(VLOOKUP('General Information'!$D$6, Validations!$L$2:$M$8, 2,FALSE), "") -> €/ha | E36: =(('General Information'!D23+'General Information'!D24)+('General Information'!H23+'General Information'!H24)+('General Information'!L23+'General Information'!L24))/(IF('General Information'!D6="crop",'Parcel 1 with DATSs'!E10,IF('General Information'!D6="milk",'Parcel 1 with DATSs'!G251,IF('General Information'!D6="meat",'Parcel 1 with DATSs'!G252,IF('General Information'!D6="animal",'Parcel 1 with DATSs'!G253, IF('General Information'!D6="oyster",'Parcel 1 with DATSs'!G254,IF('General Information'!D6="honey",'Parcel 1 with DATSs'!G255,'Parcel 1 with DATSs'!G256))))))) -> 1.7817372 | F36: DAT maintenance + (Training hours*salary) /parcel dimension or animal or beehives or pieces
A37: DATSs | B37: Cost of Training | C37: With DATs | D37: =IFERROR(VLOOKUP('General Information'!$D$6, Validations!$L$2:$M$8, 2,FALSE), "") -> €/ha | E37: ='General Information'!D27/(IF('General Information'!D6="crop",'Parcel 1 with DATSs'!E10,IF('General Information'!D6="milk",'Parcel 1 with DATSs'!G251,IF('General Information'!D6="meat",'Parcel 1 with DATSs'!G252,IF('General Information'!D6="animal",'Parcel 1 with DATSs'!G253, IF('General Information'!D6="oyster",'Parcel 1 with DATSs'!G254,IF('General Information'!D6="honey",'Parcel 1 with DATSs'!G255,'Parcel 1 with DATSs'!G256))))))) -> 1.3363029 | F37: Costs of external persons being paid to train employees on the use of DAT /parcel dimension or animal or beehives or pieces
A39: REVENUES ANALYSIS
A40: CATEGORY | B40: INDICATOR | C40: SCENARIO | D40: UoM | E40: TOTAL | F40: FORMULAS
A41: OUTPUT | B41: Crop revenue | C41: With DATs | D41: €/ha | E41: ='Parcel 1 with DATSs'!G250/'Parcel 1 with DATSs'!E10*'General Information'!$D$41 -> 1217.4254 | F41: Yield*Product market price
A42: OUTPUT | B42: Milk revenue | C42: With DATs | D42: =IFERROR(VLOOKUP('General Information'!$D$6, Validations!$L$2:$M$8, 2,FALSE), "") -> €/ha | E42: =('Parcel 1 with DATSs'!G251*'General Information'!$D$41/(IF('General Information'!D6="crop",'Parcel 1 with DATSs'!E10,IF('General Information'!D6="milk",'Parcel 1 with DATSs'!G251,IF('General Information'!D6="meat",'Parcel 1 with DATSs'!G252,IF('General Information'!D6="animal",'Parcel 1 with DATSs'!G253,IF('General Information'!D6="oyster",'Parcel 1 with DATSs'!G254,IF('General Information'!D6="honey",'Parcel 1 with DATSs'!G255,'Parcel 1 with DATSs'!G256))))))))*1000 -> 0 | F42: Milk *Product market price
A43: OUTPUT | B43: Meat revenue | C43: With DATs | D43: =IFERROR(VLOOKUP('General Information'!$D$6, Validations!$L$2:$M$8, 2,FALSE), "") -> €/ha | E43: =('Parcel 1 with DATSs'!G252*'General Information'!D41/(IF('General Information'!D6="crop",'Parcel 1 with DATSs'!E10,IF('General Information'!D6="milk",'Parcel 1 with DATSs'!G251,IF('General Information'!D6="meat",'Parcel 1 with DATSs'!G252,IF('General Information'!D6="animal",'Parcel 1 with DATSs'!G253,IF('General Information'!D6="oyster",'Parcel 1 with DATSs'!G254,IF('General Information'!D6="honey",'Parcel 1 with DATSs'!G255,'Parcel 1 with DATSs'!G256))))))))/10 -> 0 | F43: Meat*Product market price
A44: OUTPUT | B44: Oyster revenue | C44: With DATs | D44: €/m2 | E44: ='Parcel 1 with DATSs'!G254*'General Information'!$H$41/'Parcel 1 with DATSs'!E20 -> #DIV/0! | F44: Oyster*Product market price
A45: OUTPUT | B45: Honey revenue | C45: With DATs | D45: €/beehive | E45: ='Parcel 1 with DATSs'!G255*'General Information'!$H$41/'Parcel 1 with DATSs'!E19 -> #DIV/0! | F45: Honey*Product market price
A46: OUTPUT | B46: Grain (silos) revenue | C46: With DATs | D46: €/t | E46: ='Parcel 1 with DATSs'!G256*'General Information'!D41 -> 0
A47: ADDITIONAL REVENUES | B47: Additional revenues | C47: With DATs | D47: =IFERROR(VLOOKUP('General Information'!$D$6, Validations!$L$2:$M$8, 2,FALSE), "") -> €/ha | E47: ='Parcel 1 with DATSs'!G225 -> 0 | F47: Additional revenues

Sheet Cost-revenue NO DATS
A1: COST ANALYSIS
A2: INPUT | B2: INDICATOR | C2: SCENARIO | D2: UoM | E2: TOTAL | F2: FORMULAS
A3: WATER | B3: Cost of water | C3: Without DATs | D3: =IFERROR(VLOOKUP('General Information'!$D$6, Validations!$L$2:$M$8, 2,FALSE), "") -> €/ha | E3: =('Parcel 1 without DATSs'!G29*'General Information'!H32)/(IF('General Information'!D6="crop",'Parcel 1 without DATSs'!E10,IF('General Information'!D6="milk",'Parcel 1 without DATSs'!G251,IF('General Information'!D6="meat",'Parcel 1 without DATSs'!G252,IF('General Information'!D6="animal",'Parcel 1 without DATSs'!G253,IF('General Information'!D6="oyster",'Parcel 1 without DATSs'!G254,IF('General Information'!D6="honey",'Parcel 1 without DATSs'!G255,'Parcel 1 without DATSs'!G256))))))) -> 0 | F3: IF(Total water used>0; (Total water used * water price)/Parcel dimension; Sum(water Irrigation+ water Fertigation + water Pest dilution + …) * water price)
A4: FUEL | B4: Cost of fuel | C4: Without DATs | D4: =IFERROR(VLOOKUP('General Information'!$D$6, Validations!$L$2:$M$8, 2,FALSE), "") -> €/ha | E4: ='Parcel 1 without DATSs'!G43*'General Information'!H33/(IF('General Information'!D6="crop",'Parcel 1 without DATSs'!E10,IF('General Information'!D6="milk",'Parcel 1 without DATSs'!G251,IF('General Information'!D6="meat",'Parcel 1 without DATSs'!G252,IF('General Information'!D6="animal",'Parcel 1 without DATSs'!G253,IF('General Information'!D6="oyster",'Parcel 1 without DATSs'!G254,IF('General Information'!D6="honey",'Parcel 1 without DATSs'!G255,'Parcel 1 without DATSs'!G256))))))) -> 61.646635 | F4: IF(Total fuel used>0; (Total fuel used*fuel price)/Parcel dimension; sum(Fertilisation+Pesticides +Irrigation+Sowing_Planting+Pruning+…) * fuel price)
A5: ELECTRICITY | B5: Cost of electricity | C5: Without DATs | D5: =IFERROR(VLOOKUP('General Information'!$D$6, Validations!$L$2:$M$8, 2,FALSE), "") -> €/ha | E5: ='Parcel 1 without DATSs'!G62*'General Information'!H38/(IF('General Information'!D6="crop",'Parcel 1 without DATSs'!E10,IF('General Information'!D6="milk",'Parcel 1 without DATSs'!G251,IF('General Information'!D6="meat",'Parcel 1 without DATSs'!G252,IF('General Information'!D6="animal",'Parcel 1 without DATSs'!G253,IF('General Information'!D6="oyster",'Parcel 1 without DATSs'!G254,IF('General Information'!D6="honey",'Parcel 1 without DATSs'!G255,'Parcel 1 without DATSs'!G256))))))) -> 0.76632692 | F5: IF(Total electricity used > 0; (Total electricity used* electricity price)/Parcel dimension; Sum(irrigation,…) *electricity price)
A6: PESTICIDE | B6: Cost for pesticide | C6: Without DATs | D6: =IFERROR(VLOOKUP('General Information'!$D$6, Validations!$L$2:$M$8, 2,FALSE), "") -> €/ha | E6: =('Parcel 1 without DATSs'!G67*'Parcel 1 without DATSs'!G68*'General Information'!H43)+ ('Parcel 1 without DATSs'!G70*'Parcel 1 without DATSs'!G71*'General Information'!H44)+ ('Parcel 1 without DATSs'!G73*'Parcel 1 without DATSs'!G74*'General Information'!H45)+ ('Parcel 1 without DATSs'!G76*'Parcel 1 without DATSs'!G77*'General Information'!H46)+ ('Parcel 1 without DATSs'!G79*'Parcel 1 without DATSs'!G80*'General Information'!H47)+ ('Parcel 1 without DATSs'!G82*'Parcel 1 without DATSs'!G83*'General Information'!H48)+ ('Parcel 1 without DATSs'!G85*'Parcel 1 without DATSs'!G86*'General Information'!H49)+ ('Parcel 1 without DATSs'!G88*'Parcel 1 without DATSs'!G89*'General Information'!H50)+ ('Parcel 1 without DATSs'!G91*'Parcel 1 without DATSs'!G92*'General Information'!H51)+ ('Parcel 1 without DATSs'!G94*'Parcel 1 without DATSs'!G95*'General Information'!H52) -> 115.792 | F6: [(N. of treatements of pesticide 1*Amount of pesticide 1*pesticide 1 price)+(N. of treatements of pesticide 2 *Amount of pesticide 2 used *pesticide 2 price) + (N. of treatements of pesticide 3 *Amount of pesticide 3 used *pesticide 3 price (€/kg)]
A7: FERTILISER | B7: Cost of fertiliser | C7: Without DATs | D7: =IFERROR(VLOOKUP('General Information'!$D$6, Validations!$L$2:$M$8, 2,FALSE), "") -> €/ha | E7: =('Parcel 1 without DATSs'!G101*'Parcel 1 without DATSs'!G102*'General Information'!H54)+ ('Parcel 1 without DATSs'!G108*'Parcel 1 without DATSs'!G109*'General Information'!H55)+ ('Parcel 1 without DATSs'!G115*'Parcel 1 without DATSs'!G116*'General Information'!H56)+ ('Parcel 1 without DATSs'!G122*'Parcel 1 without DATSs'!G123*'General Information'!H57)+ ('Parcel 1 without DATSs'!G129*'Parcel 1 without DATSs'!G130*'General Information'!H58)+ ('Parcel 1 without DATSs'!G136*'Parcel 1 without DATSs'!G137*'General Information'!H59)+ ('Parcel 1 without DATSs'!G143*'Parcel 1 without DATSs'!G144*'General Information'!H60)+ ('Parcel 1 without DATSs'!G150*'Parcel 1 without DATSs'!G151*'General Information'!H61)+ ('Parcel 1 without DATSs'!G157*'Parcel 1 without DATSs'!G158*'General Information'!H62)+ ('Parcel 1 without DATSs'!G164*'Parcel 1 without DATSs'!G165*'General Information'!H63) -> 247.545 | F7: ((Amount of fertilisers 1 used *Number of fertilizer 1 applications *Fertilisers 1 price) + (Amount of fertilisers 2 used *Number of fertilizer 2 applications *Fertilisers 2 price) + (Amount of fertilisers 3 used *Number of fertilizer 3 applications *Fertilisers 3 price)
A8: FEED | B8: Cost of feed | C8: Without DATs | D8: =IFERROR(VLOOKUP('General Information'!$D$6, Validations!$L$2:$M$8, 2,FALSE), "") -> €/ha | E8: =('General Information'!H65*'Parcel 1 without DATSs'!G173+'General Information'!H66*'Parcel 1 without DATSs'!G175+'General Information'!H69*'Parcel 1 without DATSs'!G177)/(IF('General Information'!D6="crop",'Parcel 1 without DATSs'!E10,IF('General Information'!D6="milk",'Parcel 1 without DATSs'!G251,IF('General Information'!D6="meat",'Parcel 1 without DATSs'!G252,IF('General Information'!D6="animal",'Parcel 1 without DATSs'!G253,IF('General Information'!D6="oyster",'Parcel 1 without DATSs'!G254,IF('General Information'!D6="honey",'Parcel 1 without DATSs'!G255,'Parcel 1 without DATSs'!G256))))))) -> 0 | F8: (Amount of feed 1 * Feed 1 price) + (Amount of feed 2 * Feed 2 price) + … /animal
A9: DRUGS | B9: Cost of drugs | C9: Without DATs | D9: =IFERROR(VLOOKUP('General Information'!$D$6, Validations!$L$2:$M$8, 2,FALSE), "") -> €/ha | E9: =('General Information'!H71*'Parcel 1 without DATSs'!G186+'General Information'!H72*'Parcel 1 without DATSs'!G188+'General Information'!H73*'Parcel 1 without DATSs'!G190)/(IF('General Information'!D6="crop",'Parcel 1 without DATSs'!E10,IF('General Information'!D6="milk",'Parcel 1 without DATSs'!G251,IF('General Information'!D6="meat",'Parcel 1 without DATSs'!G252,IF('General Information'!D6="animal",'Parcel 1 without DATSs'!G253,IF('General Information'!D6="oyster",'Parcel 1 without DATSs'!G254,IF('General Information'!D6="honey",'Parcel 1 without DATSs'!G255,'Parcel 1 without DATSs'!G256))))))) -> 0 | F9: (Amount of drugs 1 * Feed 1 price) + (Amount of drugs 2 * Feed 2 price) + … /animal or beehives or pieces
A10: LABOUR | B10: Cost of labour for irrigation | C10: Without DATs | D10: =IFERROR(VLOOKUP('General Information'!$D$6, Validations!$L$2:$M$8, 2,FALSE), "") -> €/ha | E10: ='Parcel 1 without DATSs'!G194*'General Information'!H39/'Parcel 1 without DATSs'!E10 -> 0 | F10: number of hours for irrigation activities*Average salary /Parcel dimension
A11: LABOUR | B11: Cost of labour for pesticide | C11: Without DATs | D11: =IFERROR(VLOOKUP('General Information'!$D$6, Validations!$L$2:$M$8, 2,FALSE), "") -> €/ha | E11: ='Parcel 1 without DATSs'!G195*'General Information'!H39/'Parcel 1 without DATSs'!E10 -> 22.707692 | F11: number of hours for pesticide activities *Average salary /Parcel dimension
A12: LABOUR | B12: Cost of labour for fertilisation | C12: Without DATs | D12: =IFERROR(VLOOKUP('General Information'!$D$6, Validations!$L$2:$M$8, 2,FALSE), "") -> €/ha | E12: ='Parcel 1 without DATSs'!G196*'General Information'!H39/'Parcel 1 without DATSs'!E10 -> 13.430769 | F12: number of hours for fertilisation activities * Average salary /Parcel dimension
A13: LABOUR | B13: Cost of labour for sowing_planting | C13: Without DATs | D13: =IFERROR(VLOOKUP('General Information'!$D$6, Validations!$L$2:$M$8, 2,FALSE), "") -> €/ha | E13: ='Parcel 1 without DATSs'!G197*'General Information'!H39/'Parcel 1 without DATSs'!E10 -> 20.665385 | F13: number of hours for sowing_planting activities * Average salary /Parcel dimension
A14: LABOUR | B14: Cost of labour for pruning | C14: Without DATs | D14: =IFERROR(VLOOKUP('General Information'!$D$6, Validations!$L$2:$M$8, 2,FALSE), "") -> €/ha | E14: ='Parcel 1 without DATSs'!G198*'General Information'!H39/'Parcel 1 without DATSs'!E10 -> 5.1576923 | F14: number of hours for pruning activities *Average salary /Parcel dimension
A15: LABOUR | B15: Cost of labour for field visits | C15: Without DATs | D15: =IFERROR(VLOOKUP('General Information'!$D$6, Validations!$L$2:$M$8, 2,FALSE), "") -> €/ha | E15: ='Parcel 1 without DATSs'!G199*'General Information'!H39/'Parcel 1 without DATSs'!E10 -> 13.673077 | F15: number of hours for field visits activities * Average professional salary /Parcel dimension
A16: LABOUR | B16: Cost of labour for greenhouse management | C16: Without DATs | D16: =IFERROR(VLOOKUP('General Information'!$D$6, Validations!$L$2:$M$8, 2,FALSE), "") -> €/ha | E16: ='Parcel 1 without DATSs'!G200*'General Information'!H39/'Parcel 1 without DATSs'!E10 -> 0 | F16: number of hours for greenhouse management *Average salary /Parcel dimension
A17: LABOUR | B17: Cost of labour for tracking the quantity of grain available in the silo | C17: Without DATs | D17: =IFERROR(VLOOKUP('General Information'!$D$6, Validations!$L$2:$M$8, 2,FALSE), "") -> €/ha | E17: ='Parcel 1 without DATSs'!G201*'General Information'!H39/'Parcel 1 without DATSs'!E10 -> 0 | F17: number of hours for tracking the quantity of grain available in the silo *Average salary
A18: LABOUR | B18: Cost of labour for assessing product quality | C18: Without DATs | D18: =IFERROR(VLOOKUP('General Information'!$D$6, Validations!$L$2:$M$8, 2,FALSE), "") -> €/ha | E18: ='Parcel 1 without DATSs'!G202*'General Information'!H39/(IF('General Information'!D6="crop",'Parcel 1 without DATSs'!E10,IF('General Information'!D6="milk",'Parcel 1 without DATSs'!G251,IF('General Information'!D6="meat",'Parcel 1 without DATSs'!G252,IF('General Information'!D6="animal",'Parcel 1 without DATSs'!G253,IF('General Information'!D6="oyster",'Parcel 1 without DATSs'!G254,IF('General Information'!D6="honey",'Parcel 1 without DATSs'!G255,'Parcel 1 without DATSs'!G256))))))) -> 0 | F18: number of hours for assessing grain quality *Average salary
A19: LABOUR | B19: Cost of labour for controlling purchase and sale prices and quantities | C19: Without DATs | D19: =IFERROR(VLOOKUP('General Information'!$D$6, Validations!$L$2:$M$8, 2,FALSE), "") -> €/ha | E19: ='Parcel 1 without DATSs'!G203*'General Information'!H39/(IF('General Information'!D6="crop",'Parcel 1 without DATSs'!E10,IF('General Information'!D6="milk",'Parcel 1 without DATSs'!G251,IF('General Information'!D6="meat",'Parcel 1 without DATSs'!G252,IF('General Information'!D6="animal",'Parcel 1 without DATSs'!G253,IF('General Information'!D6="oyster",'Parcel 1 without DATSs'!G254,IF('General Information'!D6="honey",'Parcel 1 without DATSs'!G255,'Parcel 1 without DATSs'!G256))))))) -> 0 | F19: number of hours for controlling purchase and sale prices and quantities *Average salary
A20: LABOUR | B20: Cost of labour for organising logistics | C20: Without DATs | D20: =IFERROR(VLOOKUP('General Information'!$D$6, Validations!$L$2:$M$8, 2,FALSE), "") -> €/ha | E20: ='Parcel 1 without DATSs'!G204*'General Information'!H39/(IF('General Information'!D6="crop",'Parcel 1 without DATSs'!E10,IF('General Information'!D6="milk",'Parcel 1 without DATSs'!G251,IF('General Information'!D6="meat",'Parcel 1 without DATSs'!G252,IF('General Information'!D6="animal",'Parcel 1 without DATSs'!G253,IF('General Information'!D6="oyster",'Parcel 1 without DATSs'!G254,IF('General Information'!D6="honey",'Parcel 1 without DATSs'!G255,'Parcel 1 without DATSs'!G256))))))) -> 0 | F20: number of hours for organise logistics *Average salary
A21: LABOUR | B21: Cost of labour for cleaning | C21: Without DATs | D21: =IFERROR(VLOOKUP('General Information'!$D$6, Validations!$L$2:$M$8, 2,FALSE), "") -> €/ha | E21: ='Parcel 1 without DATSs'!G205*'General Information'!H39/(IF('General Information'!D6="crop",'Parcel 1 without DATSs'!E10,IF('General Information'!D6="milk",'Parcel 1 without DATSs'!G251,IF('General Information'!D6="meat",'Parcel 1 without DATSs'!G252,IF('General Information'!D6="animal",'Parcel 1 without DATSs'!G253,IF('General Information'!D6="oyster",'Parcel 1 without DATSs'!G254,IF('General Information'!D6="honey",'Parcel 1 without DATSs'!G255,'Parcel 1 without DATSs'!G256))))))) -> 0 | F21: number of hours for cleaning *Average salary /animal
A22: LABOUR | B22: Cost of labour for stable visits | C22: Without DATs | D22: =IFERROR(VLOOKUP('General Information'!$D$6, Validations!$L$2:$M$8, 2,FALSE), "") -> €/ha | E22: ='Parcel 1 without DATSs'!G206*'General Information'!H39/(IF('General Information'!D6="crop",'Parcel 1 without DATSs'!E10,IF('General Information'!D6="milk",'Parcel 1 without DATSs'!G251,IF('General Information'!D6="meat",'Parcel 1 without DATSs'!G252,IF('General Information'!D6="animal",'Parcel 1 without DATSs'!G253,IF('General Information'!D6="oyster",'Parcel 1 without DATSs'!G254,IF('General Information'!D6="honey",'Parcel 1 without DATSs'!G255,'Parcel 1 without DATSs'!G256))))))) -> 0 | F22: number of hours for stable visits*Average professional salary /animal
A23: LABOUR | B23: Cost of labour for heat detection | C23: Without DATs | D23: =IFERROR(VLOOKUP('General Information'!$D$6, Validations!$L$2:$M$8, 2,FALSE), "") -> €/ha | E23: ='Parcel 1 without DATSs'!G207*'General Information'!H39/(IF('General Information'!D6="crop",'Parcel 1 without DATSs'!E10,IF('General Information'!D6="milk",'Parcel 1 without DATSs'!G251,IF('General Information'!D6="meat",'Parcel 1 without DATSs'!G252,IF('General Information'!D6="animal",'Parcel 1 without DATSs'!G253,IF('General Information'!D6="oyster",'Parcel 1 without DATSs'!G254,IF('General Information'!D6="honey",'Parcel 1 without DATSs'!G255,'Parcel 1 without DATSs'!G256))))))) -> 0 | F23: number of hours for heat detection *Average salary /animal
A24: LABOUR | B24: Cost of labour for calving detection | C24: Without DATs | D24: =IFERROR(VLOOKUP('General Information'!$D$6, Validations!$L$2:$M$8, 2,FALSE), "") -> €/ha | E24: ='Parcel 1 without DATSs'!G208*'General Information'!H39/(IF('General Information'!D6="crop",'Parcel 1 without DATSs'!E10,IF('General Information'!D6="milk",'Parcel 1 without DATSs'!G251,IF('General Information'!D6="meat",'Parcel 1 without DATSs'!G252,IF('General Information'!D6="animal",'Parcel 1 without DATSs'!G253,IF('General Information'!D6="oyster",'Parcel 1 without DATSs'!G254,IF('General Information'!D6="honey",'Parcel 1 without DATSs'!G255,'Parcel 1 without DATSs'!G256))))))) -> 0 | F24: number of hours for calving detection *Average salary /animal
A25: LABOUR | B25: Cost of labour for pigsty management | C25: Without DATs | D25: =IFERROR(VLOOKUP('General Information'!$D$6, Validations!$L$2:$M$8, 2,FALSE), "") -> €/ha | E25: ='Parcel 1 without DATSs'!G209*'General Information'!H39/(IF('General Information'!D6="crop",'Parcel 1 without DATSs'!E10,IF('General Information'!D6="milk",'Parcel 1 without DATSs'!G251,IF('General Information'!D6="meat",'Parcel 1 without DATSs'!G252,IF('General Information'!D6="animal",'Parcel 1 without DATSs'!G253,IF('General Information'!D6="oyster",'Parcel 1 without DATSs'!G254,IF('General Information'!D6="honey",'Parcel 1 without DATSs'!G255,'Parcel 1 without DATSs'!G256))))))) -> 0 | F25: number of hours for pigsty management*Average salary /animal
A26: LABOUR | B26: Cost of milking | C26: Without DATs | D26: =IFERROR(VLOOKUP('General Information'!$D$6, Validations!$L$2:$M$8, 2,FALSE), "") -> €/ha | E26: ='Parcel 1 without DATSs'!G210*'General Information'!H39/(IF('General Information'!D6="crop",'Parcel 1 without DATSs'!E10,IF('General Information'!D6="milk",'Parcel 1 without DATSs'!G251,IF('General Information'!D6="meat",'Parcel 1 without DATSs'!G252,IF('General Information'!D6="animal",'Parcel 1 without DATSs'!G253,IF('General Information'!D6="oyster",'Parcel 1 without DATSs'!G254,IF('General Information'!D6="honey",'Parcel 1 without DATSs'!G255,'Parcel 1 without DATSs'!G256))))))) -> 0 | F26: number of hours for milking *Average salary /animal
A27: LABOUR | B27: Cost of labour for (milk) quality assessment | C27: Without DATs | D27: =IFERROR(VLOOKUP('General Information'!$D$6, Validations!$L$2:$M$8, 2,FALSE), "") -> €/ha | E27: ='Parcel 1 without DATSs'!G211*'General Information'!H39/(IF('General Information'!D6="crop",'Parcel 1 without DATSs'!E10,IF('General Information'!D6="milk",'Parcel 1 without DATSs'!G251,IF('General Information'!D6="meat",'Parcel 1 without DATSs'!G252,IF('General Information'!D6="animal",'Parcel 1 without DATSs'!G253,IF('General Information'!D6="oyster",'Parcel 1 without DATSs'!G254,IF('General Information'!D6="honey",'Parcel 1 without DATSs'!G255,'Parcel 1 without DATSs'!G256))))))) -> 0 | F27: number of hours for (milk) quality assessment*Average salary /animal
A28: LABOUR | B28: Cost of labour for feeding | C28: Without DATs | D28: =IFERROR(VLOOKUP('General Information'!$D$6, Validations!$L$2:$M$8, 2,FALSE), "") -> €/ha | E28: ='Parcel 1 without DATSs'!G212*'General Information'!H39/(IF('General Information'!D6="crop",'Parcel 1 without DATSs'!E10,IF('General Information'!D6="milk",'Parcel 1 without DATSs'!G251,IF('General Information'!D6="meat",'Parcel 1 without DATSs'!G252,IF('General Information'!D6="animal",'Parcel 1 without DATSs'!G253,IF('General Information'!D6="oyster",'Parcel 1 without DATSs'!G254,IF('General Information'!D6="honey",'Parcel 1 without DATSs'!G255,'Parcel 1 without DATSs'!G256))))))) -> 0 | F28: number of hours for feeding *Average salary /animal
A29: LABOUR | B29: Cost of labour for beehives visits | C29: Without DATs | D29: =IFERROR(VLOOKUP('General Information'!$D$6, Validations!$L$2:$M$8, 2,FALSE), "") -> €/ha | E29: ='Parcel 1 without DATSs'!G213*'General Information'!H39/'Parcel 1 without DATSs'!E19 -> #DIV/0! | F29: number of hours for beehives visits *Average salary / beehive
A30: LABOUR | B30: Cost of labour for sampling of oysters | C30: Without DATs | D30: =IFERROR(VLOOKUP('General Information'!$D$6, Validations!$L$2:$M$8, 2,FALSE), "") -> €/ha | E30: ='Parcel 1 without DATSs'!G214*'General Information'!H39/'Parcel 1 without DATSs'!G254 -> #DIV/0! | F30: number of hours for sampling of oysters* Average salary /piece
A31: LABOUR | B31: Cost of labour for transporting oysters to the laboratory | C31: Without DATs | D31: =IFERROR(VLOOKUP('General Information'!$D$6, Validations!$L$2:$M$8, 2,FALSE), "") -> €/ha | E31: ='Parcel 1 without DATSs'!G215*'General Information'!H39/'Parcel 1 without DATSs'!G254 -> #DIV/0! | F31: number of hours for transporting oysters to the laboratory*Average salary /piece
A32: LABOUR | B32: Cost of labour for harvesting | C32: Without DATs | D32: =IFERROR(VLOOKUP('General Information'!$D$6, Validations!$L$2:$M$8, 2,FALSE), "") -> €/ha | E32: ='Parcel 1 without DATSs'!G216*'General Information'!H39/(IF('General Information'!D6="crop",'Parcel 1 without DATSs'!E10,IF('General Information'!D6="milk",'Parcel 1 without DATSs'!G251,IF('General Information'!D6="meat",'Parcel 1 without DATSs'!G252,IF('General Information'!D6="animal",'Parcel 1 without DATSs'!G253,IF('General Information'!D6="oyster",'Parcel 1 without DATSs'!G254,IF('General Information'!D6="honey",'Parcel 1 without DATSs'!G255,'Parcel 1 without DATSs'!G256))))))) -> 30.980769 | F32: number of hours for harvesting oyster*Average salary /piece
A33: LABOUR | B33: Cost of labour for storage | C33: Without DATs | D33: =IFERROR(VLOOKUP('General Information'!$D$6, Validations!$L$2:$M$8, 2,FALSE), "") -> €/ha | E33: ='Parcel 1 without DATSs'!G217*'General Information'!H39/(IF('General Information'!D6="crop",'Parcel 1 without DATSs'!E10,IF('General Information'!D6="milk",'Parcel 1 without DATSs'!G251,IF('General Information'!D6="meat",'Parcel 1 without DATSs'!G252,IF('General Information'!D6="animal",'Parcel 1 without DATSs'!G253,IF('General Information'!D6="oyster",'Parcel 1 without DATSs'!G254,IF('General Information'!D6="honey",'Parcel 1 without DATSs'!G255,'Parcel 1 without DATSs'!G256))))))) -> 0 | F33: number of hours for storage *Average salary /piece
A34: LABOUR | B34: Cost of administrative activities, data collection, etc. | C34: Without DATs | D34: =IFERROR(VLOOKUP('General Information'!$D$6, Validations!$L$2:$M$8, 2,FALSE), "") -> €/ha | E34: ='Parcel 1 without DATSs'!G218*'General Information'!H39/(IF('General Information'!D6="crop",'Parcel 1 without DATSs'!E10,IF('General Information'!D6="milk",'Parcel 1 without DATSs'!G251,IF('General Information'!D6="meat",'Parcel 1 without DATSs'!G252,IF('General Information'!D6="animal",'Parcel 1 without DATSs'!G253,IF('General Information'!D6="oyster",'Parcel 1 without DATSs'!G254,IF('General Information'!D6="honey",'Parcel 1 without DATSs'!G255,'Parcel 1 without DATSs'!G256))))))) -> 13.673077 | F34: number of hours foradministrative activities *Average salary /parcel dimension or animal or beehives or pieces
A35: COST | B35: TOT Cost | C35: Without DATs | D35: =IFERROR(VLOOKUP('General Information'!$D$6, Validations!$L$2:$M$8, 2,FALSE), "") -> €/ha | E35: =_xlfn.AGGREGATE(9,6,E3:E34) -> 546.03842 | F35: Sum(Cost of labour for irrigation + Cost of labour for fertilisation + … /parcel dimension or animal or beehives or pieces
A36: DAT | B36: Cost of DAT | C36: Without DATs | E36: 0
A37: DAT | B37: Cost of Training | C37: Without DATs | E37: 0
A39: REVENUES ANALYSIS
A40: CATEGORY | B40: INDICATOR | C40: SCENARIO | D40: UoM | E40: TOTAL | F40: FORMULAS
A41: OUTPUT | B41: Crop revenue | C41: Without DATs | D41: €/ha | E41: ='Parcel 1 without DATSs'!G250/'Parcel 1 without DATSs'!E10*'General Information'!H41 -> 1070.7692 | F41: Yield*Product market price
A42: OUTPUT | B42: Milk revenue | C42: Without DATs | D42: =IFERROR(VLOOKUP('General Information'!$D$6, Validations!$L$2:$M$8, 2,FALSE), "") -> €/ha | E42: =('Parcel 1 without DATSs'!G251*'General Information'!H41/(IF('General Information'!D6="crop",'Parcel 1 without DATSs'!E10,IF('General Information'!D6="milk",'Parcel 1 without DATSs'!G251,IF('General Information'!D6="meat",'Parcel 1 without DATSs'!G252,IF('General Information'!D6="animal",'Parcel 1 without DATSs'!G253,IF('General Information'!D6="oyster",'Parcel 1 without DATSs'!G254,IF('General Information'!D6="honey",'Parcel 1 without DATSs'!G255,'Parcel 1 without DATSs'!G256))))))))*1000 -> 0 | F42: Milk *Product market price
A43: OUTPUT | B43: Meat revenue | C43: Without DATs | D43: =IFERROR(VLOOKUP('General Information'!$D$6, Validations!$L$2:$M$8, 2,FALSE), "") -> €/ha | E43: =('Parcel 1 without DATSs'!G252*'General Information'!H41/(IF('General Information'!D6="crop",'Parcel 1 without DATSs'!E10,IF('General Information'!D6="milk",'Parcel 1 without DATSs'!G251,IF('General Information'!D6="meat",'Parcel 1 without DATSs'!G252,IF('General Information'!D6="animal",'Parcel 1 without DATSs'!G253,IF('General Information'!D6="oyster",'Parcel 1 without DATSs'!G254,IF('General Information'!D6="honey",'Parcel 1 without DATSs'!G255,'Parcel 1 without DATSs'!G256))))))))/10 -> 0 | F43: Meat*Product market price
A44: OUTPUT | B44: Oyster revenue | C44: Without DATs | D44: €/m2 | E44: ='Parcel 1 without DATSs'!G254*'General Information'!H41/'Parcel 1 without DATSs'!E20 -> #DIV/0! | F44: Oyster*Product market price
A45: OUTPUT | B45: Honey revenue | C45: Without DATs | D45: €/beehive | E45: ='Parcel 1 without DATSs'!G255/'Parcel 1 without DATSs'!E19*'General Information'!H41 -> #DIV/0! | F45: Honey*Product market price
A46: OUTPUT | B46: Grain (silos) revenue | C46: Without DATs | D46: €/t | E46: ='Parcel 1 without DATSs'!G256*'General Information'!H41 -> 0
A47: ADDITIONAL REVENUES | B47: Additional revenues | C47: Without DATs | D47: =IFERROR(VLOOKUP('General Information'!$D$6, Validations!$L$2:$M$8, 2,FALSE), "") -> €/ha | E47: ='Parcel 1 without DATSs'!G225 -> 0 | F47: Additional revenues

Sheet sust. impact KPIs DATS
A1: Economic - PRODUCTIVITY
B2: INDICATOR | C2: SCENARIO | D2: UoM | E2: TOTAL | F2: FORMULAS
B3: Yield | C3: With DATs | D3: t / ha | E3: ='Parcel 1 with DATSs'!G250/'Parcel 1 with DATSs'!E10 -> 6.3407572 | F3: total production / parcel area
B4: Labour productivity (arable and horticulture) | C4: With DATs | D4: t / h | E4: ='Parcel 1 with DATSs'!G250/SUM('Parcel 1 with DATSs'!G194:G218) -> 0.60075965 | F4: total production / hours of labour employed
B5: Labour productivity (dairy livestock) | C5: With DATs | D5: l milk/h | E5: ='Parcel 1 with DATSs'!G251/SUM('Parcel 1 with DATSs'!G194:G218) -> 0 | F5: total production / hours of labour employed
B6: Labour productivity (meat livestock) | C6: With DATs | D6: kg meat/h | E6: ='Parcel 1 with DATSs'!G252/SUM('Parcel 1 with DATSs'!G194:G218) -> 0 | F6: total production / hours of labour employed
B7: Labour productivity (aquaculture) | C7: With DATs | D7: pieces/h | E7: ='Parcel 1 with DATSs'!G254/SUM('Parcel 1 with DATSs'!G194:G218) -> 0 | F7: total production / hours of labour employed
B8: Labour productivity (apiculture) | C8: With DATs | D8: kg honey/h | E8: ='Parcel 1 with DATSs'!G255/SUM('Parcel 1 with DATSs'!G194:G218) -> 0 | F8: total production / hours of labour employed
B9: Labour productivity (silos) | C9: With DATs | D9: t/h | E9: ='Parcel 1 with DATSs'!G256/SUM('Parcel 1 with DATSs'!G194:G218) -> 0
B10: Milk productivity | C10: With DATs | D10: l milk/cow/day | E10: ='Parcel 1 with DATSs'!G251/'Parcel 1 with DATSs'!E17/365 -> #DIV/0! | F10: total milk production / total number of cows
B11: Meat productivity | C11: With DATs | D11: kg meat/animal/day | E11: ='Parcel 1 with DATSs'!G252/'Parcel 1 with DATSs'!E17/365 -> #DIV/0! | F11: total production / animals
B12: Bees productivity | C12: With DATs | D12: kg honey/beehive | E12: ='Parcel 1 with DATSs'!G255/'Parcel 1 with DATSs'!E19 -> #DIV/0! | F12: total production / beehives
B13: Oyster productivity | C13: With DATs | D13: number of oysters/m2 | E13: ='Parcel 1 with DATSs'!G254/'Parcel 1 with DATSs'!E20 -> #DIV/0! | F13: production / area used
A15: Economic - EFFICIENCY
B16: INDICATOR | C16: SCENARIO | D16: UoM | E16: TOTAL | F16: FORMULAS
B17: Rate of time for quality analysis | C17: With DATs | D17: % | E17: =('Parcel 1 with DATSs'!G202/SUM('Parcel 1 with DATSs'!G201:G204))*100 -> #DIV/0! | F17: (hours spent for quality analysis / total number of working hours) *100
B18: Rate of on-time fulfilled orders | C18: With DATs | D18: % | E18: =('Parcel 1 with DATSs'!G222/'Parcel 1 with DATSs'!G223)*100 -> #DIV/0! | F18: (number of on-time fulfilled orders / number of orders received) * 100
B19: Number of wrong orders | C19: With DATs | D19: n | E19: ='Parcel 1 with DATSs'!G224 -> 0 | F19: Number of wrong orders
A21: PRODUCT QUALITY
A22: INPUT | B22: INDICATOR | C22: SCENARIO | D22: UoM | E22: TOTAL | F22: FORMULAS
B23: Intrinsic product quality | C23: With DATs
B24: Protein % DRY MATTER | C24: With DATs | D24: % | E24: ='Parcel 1 with DATSs'!G226 -> 12.5
B25: Humidity | C25: With DATs | D25: % | E25: ='Parcel 1 with DATSs'!G227 -> 14.1
B26: Test Weight | C26: With DATs | D26: kg/hl | E26: ='Parcel 1 with DATSs'!G228 -> 76.6
A28: ENVIRONMENTAL KPIs
A29: INPUT | B29: INDICATOR | C29: SCENARIO | D29: UoM | E29: TOTAL | F29: Formula
A30: FERTILISER | B30: Nitrogen applied | C30: With DATs | D30: kg/ha | E30: =('Parcel 1 with DATSs'!G101*'Parcel 1 with DATSs'!G102*('Parcel 1 with DATSs'!G103/100))+ ('Parcel 1 with DATSs'!G108*'Parcel 1 with DATSs'!G109*('Parcel 1 with DATSs'!G110/100))+ ('Parcel 1 with DATSs'!G115*'Parcel 1 with DATSs'!G116*('Parcel 1 with DATSs'!G117/100))+ ('Parcel 1 with DATSs'!G122*'Parcel 1 with DATSs'!G123*('Parcel 1 with DATSs'!G124/100))+ ('Parcel 1 with DATSs'!G129*'Parcel 1 with DATSs'!G130*('Parcel 1 with DATSs'!G131/100))+ ('Parcel 1 with DATSs'!G136*'Parcel 1 with DATSs'!G137*('Parcel 1 with DATSs'!G138/100))+ ('Parcel 1 with DATSs'!G143*'Parcel 1 with DATSs'!G144*('Parcel 1 with DATSs'!G145/100))+ ('Parcel 1 with DATSs'!G150*'Parcel 1 with DATSs'!G151*('Parcel 1 with DATSs'!G152/100))+ ('Parcel 1 with DATSs'!G157*'Parcel 1 with DATSs'!G158*('Parcel 1 with DATSs'!G159/100))+ ('Parcel 1 with DATSs'!G164*'Parcel 1 with DATSs'!G165*('Parcel 1 with DATSs'!G166/100)) -> 110.1 | F30: Amount of N fertilizer used/total area
A31: FERTILISER | B31: Nitrogen use efficiency | C31: With DATs | D31: % | E31: =((('Parcel 1 with DATSs'!G250*1000/'Parcel 1 with DATSs'!E10)*C98)/(E30)*100) -> 116.3336 | F31: (yield *Average N content (%))/(Amount of N fertilizer applied/ha)*100
A32: FERTILISER | B32: Phosphorus applied | C32: With DATs | D32: kg/ha | E32: =('Parcel 1 with DATSs'!G101*'Parcel 1 with DATSs'!G102*('Parcel 1 with DATSs'!G104/100))+ ('Parcel 1 with DATSs'!G108*'Parcel 1 with DATSs'!G109*('Parcel 1 with DATSs'!G111/100))+ ('Parcel 1 with DATSs'!G115*'Parcel 1 with DATSs'!G116*('Parcel 1 with DATSs'!G118/100))+ ('Parcel 1 with DATSs'!G122*'Parcel 1 with DATSs'!G123*('Parcel 1 with DATSs'!G125/100))+ ('Parcel 1 with DATSs'!G129*'Parcel 1 with DATSs'!G130*('Parcel 1 with DATSs'!G132/100))+ ('Parcel 1 with DATSs'!G136*'Parcel 1 with DATSs'!G137*('Parcel 1 with DATSs'!G139/100))+ ('Parcel 1 with DATSs'!G143*'Parcel 1 with DATSs'!G144*('Parcel 1 with DATSs'!G146/100))+ ('Parcel 1 with DATSs'!G150*'Parcel 1 with DATSs'!G151*('Parcel 1 with DATSs'!G153/100))+ ('Parcel 1 with DATSs'!G157*'Parcel 1 with DATSs'!G158*('Parcel 1 with DATSs'!G160/100))+ ('Parcel 1 with DATSs'!G164*'Parcel 1 with DATSs'!G165*('Parcel 1 with DATSs'!G167/100)) -> 31.2 | F32: Amount of P fertilizer used/total area
A33: FERTILISER | B33: Phosphorus use efficiency | C33: With DATs | D33: % | E33: =((('Parcel 1 with DATSs'!G250*1000/'Parcel 1 with DATSs'!E10)*C99)/E32*100) -> 166.64811 | F33: (yield*Average P content (%))/(Amount of P fertilizer used/ha)*100
A34: FERTILISER | B34: Potassium applied | C34: With DATs | D34: % | E34: =('Parcel 1 with DATSs'!G101*'Parcel 1 with DATSs'!G102*('Parcel 1 with DATSs'!G105/100))+ ('Parcel 1 with DATSs'!G108*'Parcel 1 with DATSs'!G109*('Parcel 1 with DATSs'!G112/100))+ ('Parcel 1 with DATSs'!G115*'Parcel 1 with DATSs'!G116*('Parcel 1 with DATSs'!G119/100))+ ('Parcel 1 with DATSs'!G122*'Parcel 1 with DATSs'!G123*('Parcel 1 with DATSs'!G126/100))+ ('Parcel 1 with DATSs'!G129*'Parcel 1 with DATSs'!G130*('Parcel 1 with DATSs'!G133/100))+ ('Parcel 1 with DATSs'!G136*'Parcel 1 with DATSs'!G137*('Parcel 1 with DATSs'!G140/100))+ ('Parcel 1 with DATSs'!G143*'Parcel 1 with DATSs'!G144*('Parcel 1 with DATSs'!G147/100))+ ('Parcel 1 with DATSs'!G150*'Parcel 1 with DATSs'!G151*('Parcel 1 with DATSs'!G154/100))+ ('Parcel 1 with DATSs'!G157*'Parcel 1 with DATSs'!G158*('Parcel 1 with DATSs'!G161/100))+ ('Parcel 1 with DATSs'!G164*'Parcel 1 with DATSs'!G165*('Parcel 1 with DATSs'!G168/100)) -> 0 | F34: Amount of K fertilizer used/total area
A35: FERTILISER | B35: Potassium use efficiency | C35: With DATs | D35: % | E35: =(((('Parcel 1 with DATSs'!G250*1000)/'Parcel 1 with DATSs'!E10)*'sust. impact KPIs DATS'!C100)/E34*100) -> #DIV/0! | F35: (yield*Average K content (%))/(Amount of K fertilizer used/ha)*100
A36: PESTICIDE | B36: pesticides, herbicides and fungicides use | C36: With DATs | D36: kg/ha | E36: =('Parcel 1 with DATSs'!G67*'Parcel 1 with DATSs'!G68)+ ('Parcel 1 with DATSs'!G70*'Parcel 1 with DATSs'!G71)+ ('Parcel 1 with DATSs'!G73*'Parcel 1 with DATSs'!G74)+ ('Parcel 1 with DATSs'!G76*'Parcel 1 with DATSs'!G77)+ ('Parcel 1 with DATSs'!G79*'Parcel 1 with DATSs'!G80)+ ('Parcel 1 with DATSs'!G82*'Parcel 1 with DATSs'!G83)+ ('Parcel 1 with DATSs'!G85*'Parcel 1 with DATSs'!G86)+ ('Parcel 1 with DATSs'!G88*'Parcel 1 with DATSs'!G89)+ ('Parcel 1 with DATSs'!G91*'Parcel 1 with DATSs'!G92)+ ('Parcel 1 with DATSs'!G94*'Parcel 1 with DATSs'!G95) -> 2.3 | F36: Amount of pesticides, herbicides and fungicide used/total area
A37: WATER | B37: Water consumption | C37: With DATs | D37: =IFERROR(VLOOKUP('General Information'!$D$6, Validations!$J$2:$K$8, 2,FALSE), "") | E37: ='Parcel 1 with DATSs'!G29/(IF('General Information'!D6="crop",'Parcel 1 with DATSs'!E10,IF('General Information'!D6="milk",'Parcel 1 with DATSs'!G251,IF('General Information'!D6="meat",'Parcel 1 with DATSs'!G252,IF('General Information'!D6="animal",'Parcel 1 with DATSs'!G253,IF('General Information'!D6="oyster",'Parcel 1 with DATSs'!G254,IF('General Information'!D6="honey",'Parcel 1 with DATSs'!G255,'Parcel 1 with DATSs'!G256))))))) -> 0.40089087 | F37: Amount of water used/total area
A38: WATER | B38: Aquaculture water productivity | C38: With DATs | D38: l/pieces | F38: Amount of water used/production
A39: WATER | B39: Irrigation water productivity | C39: With DATs | D39: kg/m3 | E39: =(('Parcel 1 with DATSs'!G250)*1000)/(IF(('Parcel 1 with DATSs'!G24+'Parcel 1 with DATSs'!G25)>0,('Parcel 1 with DATSs'!G24+'Parcel 1 with DATSs'!G25),'Parcel 1 with DATSs'!G29)) -> 15816.667 | F39: Yield/Amount of water used for irrigation
A40: ELECTRICITY | B40: Electricity consumption | C40: With DATs | D40: =IFERROR(VLOOKUP('General Information'!$D$6, Validations!$W$2:$X$8, 2,FALSE), "") -> kWh/ha | E40: ='Parcel 1 with DATSs'!G62/(IF('General Information'!D6="crop",'Parcel 1 with DATSs'!E10,IF('General Information'!D6="milk",'Parcel 1 with DATSs'!G251,IF('General Information'!D6="meat",'Parcel 1 with DATSs'!G252,IF('General Information'!D6="animal",'Parcel 1 with DATSs'!G253,IF('General Information'!D6="oyster",'Parcel 1 with DATSs'!G254,IF('General Information'!D6="honey",'Parcel 1 with DATSs'!G255,'Parcel 1 with DATSs'!G256))))))) -> 3.091314 | F40: Tot. amount of electricity used/tot area or m2 or animal
A41: ANIMAL | B41: Ease of movement | C41: With DATs | D41: d/y | E41: ='Parcel 1 with DATSs'!G235/'Parcel 1 with DATSs'!G236 -> #DIV/0! | F41: number of days per year with access to pasture and outdoor loafing area
A42: ANIMAL | B42: Mortality rate (livestock) | C42: With DATs | D42: % | E42: ='Parcel 1 with DATSs'!G232/'Parcel 1 with DATSs'!E17*100 -> #DIV/0! | F42: (Number of deaths in a year/Average herd size) | H42: =5/200*100 -> 2.5
A43: ANIMAL | B43: Mortality rate (aquaculture) | C43: With DATs | E43: ='Parcel 1 with DATSs'!G232/'Parcel 1 with DATSs'!E20 -> #DIV/0! | F43: (Number of deaths in a year/total animals)
A44: ANIMAL | B44: Mortality rate (apiculture) | C44: With DATs | D44: % | E44: ='Parcel 1 with DATSs'!G232/'Parcel 1 with DATSs'!E19*100 -> #DIV/0! | F44: (Number of deaths in a year/total animals)
A45: ANIMAL | B45: Mortality rate at birth | C45: With DATs | D45: % | E45: ='Parcel 1 with DATSs'!G233/'Parcel 1 with DATSs'!G234 -> #DIV/0! | F45: (Calves died in the first 24 h / Total number of calves born)
A46: ANIMAL | B46: Cows with high SCC | C46: With DATs | D46: % | E46: ='Parcel 1 with DATSs'!G237/'Parcel 1 with DATSs'!E17 -> #DIV/0! | F46: number of cows producing high SCC milk / Total number of cows * 100
A47: DRUGS | B47: Drugs use in dairy livestock | C47: With DATs | D47: =IFERROR(VLOOKUP('General Information'!$D$6, Validations!$AA$2:$AB$8, 2,FALSE), "") -> 0 | E47: =('Parcel 1 with DATSs'!G186+'Parcel 1 with DATSs'!G188+'Parcel 1 with DATSs'!G190)/(IF('General Information'!D6="crop",'Parcel 1 with DATSs'!E10,IF('General Information'!D6="milk",'Parcel 1 with DATSs'!G251,IF('General Information'!D6="meat",'Parcel 1 with DATSs'!G252,IF('General Information'!D6="animal",'Parcel 1 with DATSs'!G253,IF('General Information'!D6="oyster",'Parcel 1 with DATSs'!G254,IF('General Information'!D6="honey",'Parcel 1 with DATSs'!G255,'Parcel 1 with DATSs'!G256))))))) -> 0 | F47: Amount of drugs used/ output
A48: DRUGS | B48: Drugs use in meat livestock | C48: With DATs | D48: =IFERROR(VLOOKUP('General Information'!$D$6, Validations!$AA$2:$AB$8, 2,FALSE), "") -> 0 | E48: =('Parcel 1 with DATSs'!G186+'Parcel 1 with DATSs'!G188+'Parcel 1 with DATSs'!G190)/(IF('General Information'!D6="crop",'Parcel 1 with DATSs'!E10,IF('General Information'!D6="milk",'Parcel 1 with DATSs'!G251,IF('General Information'!D6="meat",'Parcel 1 with DATSs'!G252,IF('General Information'!D6="animal",'Parcel 1 with DATSs'!G253,IF('General Information'!D6="oyster",'Parcel 1 with DATSs'!G254,IF('General Information'!D6="honey",'Parcel 1 with DATSs'!G255,'Parcel 1 with DATSs'!G256))))))) -> 0 | F48: Amount of drugs used/ output
A49: DRUGS | B49: Drugs use in aquaculture | C49: With DATs | D49: g/m2 | E49: =('Parcel 1 with DATSs'!G187+'Parcel 1 with DATSs'!G189+'Parcel 1 with DATSs'!#REF!)/'Parcel 1 with DATSs'!E20 -> #REF! | F49: Amount of drugs used/ output
A50: DRUGS | B50: Drugs use in apiculture | C50: With DATs | D50: g/beehive | E50: =('Parcel 1 with DATSs'!G187+'Parcel 1 with DATSs'!G189+'Parcel 1 with DATSs'!#REF!)/'Parcel 1 with DATSs'!E19 -> #REF! | F50: Amount of drugs used/ output
A51: FUEL | B51: Fuel GHG emission | C51: With DATs | D51: =IFERROR(VLOOKUP('General Information'!$D$6, Validations!$AA$2:$AC$8, 3,FALSE), "") -> kg CO2 eq/ha | E51: =('Parcel 1 with DATSs'!G43*'sust. impact KPIs DATS'!C94*'sust. impact KPIs DATS'!C95)/(IF('General Information'!D6="crop",'Parcel 1 with DATSs'!E10,IF('General Information'!D6="milk",'Parcel 1 with DATSs'!G251,IF('General Information'!D6="meat",'Parcel 1 with DATSs'!G252,IF('General Information'!D6="animal",'Parcel 1 with DATSs'!G253,IF('General Information'!D6="oyster",'Parcel 1 with DATSs'!G254,IF('General Information'!D6="honey",'Parcel 1 with DATSs'!G255,'Parcel 1 with DATSs'!G256))))))) -> 131.82456 | F51: Tot. amount of fuel used *Lower heating value*Emission factor
A52: FUEL | B52: Arable and horticulture fuel consumption | C52: With DATs | D52: l/ha | E52: ='Parcel 1 with DATSs'!G43/'Parcel 1 with DATSs'!E10 -> 49.554566 | F52: Tot. amount of fuel used/tot area
A53: FUEL | B53: Livestock fuel consumption | C53: With DATs | D53: =IFERROR(VLOOKUP('General Information'!$D$6, Validations!$AA$2:$AD$8, 4,FALSE), "") -> l/ha | E53: ='Parcel 1 with DATSs'!G43/'Parcel 1 with DATSs'!E17 -> #DIV/0! | F53: Tot. amount of fuel used/LSU
A54: FUEL | B54: Aquaculture fuel consumption | C54: With DATs | D54: l/m2 | E54: ='Parcel 1 with DATSs'!G43/'Parcel 1 with DATSs'!E20 -> #DIV/0! | F54: Tot. amount of fuel used/ area under aquaculture
A55: FUEL | B55: Apiculture fuel consumption | C55: With DATs | D55: l/beehive | E55: ='Parcel 1 with DATSs'!G43/'Parcel 1 with DATSs'!E19 -> #DIV/0! | F55: Tot. amount of fuel used/Number of beehives
F56: tot | H56: direct | J56: indirect volatilisation | L56: indirect leaching/runoff
A57: FERTILISER | B57: N2O GHG emission | C57: With DATs | D57: kg Co2e/ha | E57: =(G57+I57+K57)*C90*C91 -> 648.98005 | F57: direct + indirect N2O emissions | G57: =E30*C77 -> 1.101 | H57: Amount of N fertilizer used (kg-N) * Emission factor 1 | I57: =((((IF('Parcel 1 with DATSs'!G100="Mineral",'Parcel 1 with DATSs'!G101*'Parcel 1 with DATSs'!G102*'Parcel 1 with DATSs'!G103/100,0))+ (IF('Parcel 1 with DATSs'!G107="Mineral",'Parcel 1 with DATSs'!G108*'Parcel 1 with DATSs'!G109*'Parcel 1 with DATSs'!G110/100,0))+ (IF('Parcel 1 with DATSs'!G114="Mineral",'Parcel 1 with DATSs'!G115*'Parcel 1 with DATSs'!G116*'Parcel 1 with DATSs'!G117/100,0))+ (IF('Parcel 1 with DATSs'!G121="Mineral",'Parcel 1 with DATSs'!G122*'Parcel 1 with DATSs'!G123*'Parcel 1 with DATSs'!G124/100,0))+ (IF('Parcel 1 with DATSs'!G128="Mineral",'Parcel 1 with DATSs'!G129*'Parcel 1 with DATSs'!G130*'Parcel 1 with DATSs'!G131/100,0))+ (IF('Parcel 1 with DATSs'!G135="Mineral",'Parcel 1 with DATSs'!G136*'Parcel 1 with DATSs'!G137*'Parcel 1 with DATSs'!G138/100,0))+ (IF('Parcel 1 with DATSs'!G142="Mineral",'Parcel 1 with DATSs'!G143*'Parcel 1 with DATSs'!G144*'Parcel 1 with DATSs'!G145/100,0))+ (IF('Parcel 1 with DATSs'!G149="Mineral",'Parcel 1 with DATSs'!G150*'Parcel 1 with DATSs'!G151*'Parcel 1 with DATSs'!G152/100,0))+ (IF('Parcel 1 with DATSs'!G156="Mineral",'Parcel 1 with DATSs'!G157*'Parcel 1 with DATSs'!G158*'Parcel 1 with DATSs'!G159/100,0))+ (IF('Parcel 1 with DATSs'!G163="Mineral",'Parcel 1 with DATSs'!G164*'Parcel 1 with DATSs'!G165*'Parcel 1 with DATSs'!G166/100,0))) *'sust. impact KPIs DATS'!C85) + (((IF('Parcel 1 with DATSs'!G100="Organic",'Parcel 1 with DATSs'!G101*'Parcel 1 with DATSs'!G102*'Parcel 1 with DATSs'!G103/100,0))+ (IF('Parcel 1 with DATSs'!G107="Organic",'Parcel 1 with DATSs'!G108*'Parcel 1 with DATSs'!G109*'Parcel 1 with DATSs'!G110/100,0))+ (IF('Parcel 1 with DATSs'!G114="Organic",'Parcel 1 with DATSs'!G115*'Parcel 1 with DATSs'!G116*'Parcel 1 with DATSs'!G117/100,0))+ (IF('Parcel 1 with DATSs'!G121="Organic",'Parcel 1 with DATSs'!G122*'Parcel 1 with DATSs'!G123*'Parcel 1 with DATSs'!G124/100,0))+ (IF('Parcel 1 with DATSs'!G128="Organic",'Parcel 1 with DATSs'!G129*'Parcel 1 with DATSs'!G130*'Parcel 1 with DATSs'!G131/100,0))+ (IF('Parcel 1 with DATSs'!G135="Organic",'Parcel 1 with DATSs'!G136*'Parcel 1 with DATSs'!G137*'Parcel 1 with DATSs'!G138/100,0))+ (IF('Parcel 1 with DATSs'!G142="Organic",'Parcel 1 with DATSs'!G143*'Parcel 1 with DATSs'!G144*'Parcel 1 with DATSs'!G145/100,0))+ (IF('Parcel 1 with DATSs'!G149="Organic",'Parcel 1 with DATSs'!G150*'Parcel 1 with DATSs'!G151*'Parcel 1 with DATSs'!G152/100,0))+ (IF('Parcel 1 with DATSs'!G156="Organic",'Parcel 1 with DATSs'!G157*'Parcel 1 with DATSs'!G158*'Parcel 1 with DATSs'!G159/100,0))+ (IF('Parcel 1 with DATSs'!G163="Organic",'Parcel 1 with DATSs'!G164*'Parcel 1 with DATSs'!G165*'Parcel 1 with DATSs'!G166/100,0))) *'sust. impact KPIs DATS'!C86)) *'sust. impact KPIs DATS'!C82 -> 0.12111 | J57: [(Amount of synthetic N fertilizer used (kg-N) * fraction volatilized) + (Amount of organic N fertilizer used (kg-N) *fraction volatilized)] * Emission factor 4 | K57: =E30*C87*C89 -> 0.290664 | L57: Amount of N fertilizer used (kg-N) * fraction of leaching or runoff * emission factor 5
A58: GHG | B58: total ghg emissions | C58: With DATs | D58: =D51 -> kg CO2 eq/ha | E58: =E57+E51 -> 780.80461 | I58: =IF(ISERR((((('Parcel 1 with DATSs'!G101*'Parcel 1 with DATSs'!G102*100/'Parcel 1 with DATSs'!G103)+('Parcel 1 with DATSs'!G108*'Parcel 1 with DATSs'!G109*100/'Parcel 1 with DATSs'!G110))*'sust. impact KPIs DATS'!C85)+(('Parcel 1 with DATSs'!G115*'Parcel 1 with DATSs'!G116*100/'Parcel 1 with DATSs'!G117)*'sust. impact KPIs DATS'!C86))*C82),0,(((('Parcel 1 with DATSs'!G101*'Parcel 1 with DATSs'!G102*100/'Parcel 1 with DATSs'!G103)+('Parcel 1 with DATSs'!G108*'Parcel 1 with DATSs'!G109*100/'Parcel 1 with DATSs'!G110))*'sust. impact KPIs DATS'!C85)+(('Parcel 1 with DATSs'!G115*'Parcel 1 with DATSs'!G116*100/'Parcel 1 with DATSs'!G117)*'sust. impact KPIs DATS'!C86))*C82) -> 0
A59: SOCIAL KPIs
B60: INDICATOR | C60: SCENARIO | D60: UoM | E60: TOTAL | F60: Formula
B61: Training hours (for the use of DATs) | C61: With DATs | D61: h/employee | E61: ='General Information'!D25/'General Information'!D14 -> 4.4444444 | F61: Time spent for training hours for all the employee/number of employees
B62: Working time | C62: With DATs | D62: =IFERROR(VLOOKUP('General Information'!$D$6, Validations!$L$2:$N$8, 3,FALSE), "") -> h/ha | E62: {=(SUM(SUMIFS('Parcel 1 with DATSs'!G194:G218,'Parcel 1 with DATSs'!C194:C218,'Analysis DATS vs. NO DATS'!C12:C36,'Analysis DATS vs. NO DATS'!I12:I36,1)))/(IF('General Information'!D6="crop",'Parcel 1 with DATSs'!E10,IF('General Information'!D6="milk",'Parcel 1 with DATSs'!G251,IF('General Information'!D6="meat",'Parcel 1 with DATSs'!G252,IF('General Information'!D6="animal",'Parcel 1 with DATSs'!G253,IF('General Information'!D6="oyster",'Parcel 1 with DATSs'!G254,IF('General Information'!D6="honey",'Parcel 1 with DATSs'!G255,'Parcel 1 with DATSs'!G256)))))))} -> 7.8184855 | F62: Hours worked for the specific activities impacted by DATSs
B63: Frequency rate of occupational injuries | C63: With DATs | D63: n./hours | E63: ='Parcel 1 with DATSs'!G241/'Parcel 1 with DATSs'!G243 -> 0 | F63: Number of new injury cases/Total number of working hours
B64: Incidence of occupational injuries | C64: With DATs | D64: % | E64: ='Parcel 1 with DATSs'!G242/'Parcel 1 with DATSs'!G243 -> 0 | F64: Total number of lost working hours due to occupational injuries/Total number of working hours
B65: Contribution to local employment | C65: With DATs | D65: % | E65: ='Parcel 1 with DATSs'!G245/'Parcel 1 with DATSs'!G246 -> 0.66666667 | F65: Number of new local employees/Total new employees hired
E67: {=SUM(SUMIFS('Parcel 1 with DATSs'!G194:G218,'Parcel 1 with DATSs'!C194:C218,'Analysis DATS vs. NO DATS'!C12:C36,'Analysis DATS vs. NO DATS'!I12:I36,1))} -> 7021
B74: IPCC 2006 methodology (2019 refinement) - Tier 1 | D74: (Fixed values)
A75: N2O EMISSIONS | B75: UoM | C75: value | D75: description
A76: direct emissions
A77: EF1 | B77: (Kg N2O-N)/(kg N input) | C77: 0.01 | D77: Emission Factor default value for direct emissions
A78: EF1 SW | B78: (Kg N2O-N)/(kg N input) | C78: 0.016 | D78: Emission Factor for Synthetic fertilizers in Wet climates (optional)
A79: EF1 OW | B79: (Kg N2O-N)/(kg N input) | C79: 0.006 | D79: Other N inputs in Wet climates (optional)
A80: EF1 AD | B80: (Kg N2O-N)/(kg N input) | C80: 0.006 | D80: All N inputs in Dry climates (optional)
A81: indirect emissions
A82: EF4 | B82: (Kg N2O-N)/(kg N volatilised) | C82: 0.01 | D82: Emission Factor default value for volatilization of N
A83: EF4 W | B83: (Kg N2O-N)/(kg N volatilised) | C83: 0.014 | D83: Emission Factor default value for volatilization of N in wet cliamtes
A84: EF4 D | B84: (Kg N2O-N)/(kg N volatilised) | C84: 0.005 | D84: Emission Factor default value for volatilization of N in dry climates
A85: Frac GASF | B85: (kg N volatilised)/(Kg of N input) | C85: 0.11 | D85: Fraction of synthetic fertiliser N that volatilises
A86: Frac GASM | B86: (kg N volatilised)/(Kg of N input) | C86: 0.21 | D86: Fraction of organic fertiliser N that volatilies
A87: FracLEACH | B87: (kg Nleaching&runoff)/(Kg N input) | C87: 0.24 | D87: For all N inputs
A88: FracLEACH D | B88: (kg Nleaching&runoff)/(Kg N input) | C88: 0 | D88: 0 if leaching & runoff process assumed to be absent or in dry climates
A89: EF5 | B89: (kg N2O–N)/(kg N leached and runoff) | C89: 0.011 | D89: Emission factor for N2O emissions from N leaching and runoff
A90: CF1 | B90: Kg/kg | C90: =44/28 -> 1.5714286 | D90: Coversion factor from N to N2O
A91: GWP-N2O | C91: 273 | D91: Global Warming Potential of N2O compared to CO2 (IPCC AR6)
A93: CO2 EMISSIONS FUEL
A94: Lower Heating Value Diesel | B94: Mj/l | C94: 35.9 | D94: Castoldi & Bechini, 2006
A95: EF diesel agri | B95: kg Co2e/Mj | C95: 0.0741 | D95: IPCC 2006
A97: Average nutrient content kg/kg
A98: ='General Information'!D7 -> Wheat (T. aestivum) | B98: Average N content | C98: =IFERROR(VLOOKUP('General Information'!$D$7, Validations!$P$2:$Q$18, 2,FALSE), "") -> 0.0202
A99: ='General Information'!D7 -> Wheat (T. aestivum) | B99: Average P content | C99: =IFERROR(VLOOKUP('General Information'!$D$7, Validations!$R$2:$S$18, 2,FALSE), "") -> 0.0082
A100: ='General Information'!D7 -> Wheat (T. aestivum) | B100: Average K content | C100: =IFERROR(VLOOKUP('General Information'!$D$7, Validations!$T$2:$U$18, 2,FALSE), "") -> 0.0052

Sheet sust. impact KPIs NO DATS
A1: PRODUCTIVITY
A2: INPUT | B2: INDICATOR | C2: SCENARIO | D2: UoM | E2: TOTAL | F2: FORMULAS
B3: Land Productivity | C3: Without DATs | D3: t/ha | E3: ='Parcel 1 without DATSs'!G250/'Parcel 1 without DATSs'!E10 -> 5.5769231 | F3: total production / parcel area
B4: Labour productivity (arable and horticulture) | C4: Without DATs | D4: t/h | E4: ='Parcel 1 without DATSs'!G250/SUM('Parcel 1 without DATSs'!G194:G218) -> 0.33381295 | F4: total production / hours of labour employed
B5: Labour productivity (dairy livestock) | C5: Without DATs | D5: l/h | E5: ='Parcel 1 without DATSs'!G251/SUM('Parcel 1 without DATSs'!G194:G218) -> 0 | F5: total production / hours of labour employed
B6: Labour productivity (meat livestock) | C6: Without DATs | D6: kg/h | E6: ='Parcel 1 without DATSs'!G252/SUM('Parcel 1 without DATSs'!G194:G218) -> 0 | F6: total production / hours of labour employed
B7: Labour productivity (aquaculture) | C7: Without DATs | D7: pieces/h | E7: ='Parcel 1 without DATSs'!G254/SUM('Parcel 1 without DATSs'!G194:G218) -> 0 | F7: total production / hours of labour employed
B8: Labour productivity (apiculture) | C8: Without DATs | D8: kg/h | E8: ='Parcel 1 without DATSs'!G255/SUM('Parcel 1 without DATSs'!G194:G218) -> 0 | F8: total production / hours of labour employed
B9: Labour productivity (silos) | C9: Without DATs | D9: t/h | E9: ='Parcel 1 without DATSs'!G256/SUM('Parcel 1 without DATSs'!G194:G218) -> 0
B10: Milk productivity | C10: Without DATs | D10: l milk/cow/day | E10: ='Parcel 1 without DATSs'!G251/'Parcel 1 without DATSs'!E17/365 -> #DIV/0! | F10: total milk production / total number of cows
B11: Meat productivity | C11: Without DATs | D11: kg / animals / day | E11: ='Parcel 1 without DATSs'!G252/'Parcel 1 without DATSs'!E17/365 -> #DIV/0! | F11: total production / animals
B12: Bees productivity | C12: Without DATs | D12: kg / beehives | E12: ='Parcel 1 without DATSs'!G255/'Parcel 1 without DATSs'!E19 -> #DIV/0! | F12: total production / beehives
B13: Oyster productivity | C13: Without DATs | D13: number of oysters/m2 | E13: ='Parcel 1 without DATSs'!G254/'Parcel 1 without DATSs'!E20 -> #DIV/0! | F13: production / area used
A15: EFFICIENCY
A16: INPUT | B16: INDICATOR | C16: SCENARIO | D16: UoM | E16: TOTAL | F16: FORMULAS
B17: Rate of time for quality analysis | C17: Without DATs | D17: % | E17: =('Parcel 1 without DATSs'!G202/SUM('Parcel 1 without DATSs'!G201:G204))*100 -> #DIV/0! | F17: (hours assessing grain quality / total number of working hours) *100
B18: Rate of on-time fulfilled orders | C18: Without DATs | D18: % | E18: =('Parcel 1 without DATSs'!G222/'Parcel 1 without DATSs'!G223)*100 -> #DIV/0! | F18: (number of on-time fulfilled orders / number of orders received) * 100
B19: Number of wrong orders | C19: Without DATs | D19: n | E19: ='Parcel 1 without DATSs'!G224 -> 0 | F19: Number of wrong orders
A21: PRODUCT QUALITY
A22: INPUT | B22: INDICATOR | C22: SCENARIO | D22: UoM | E22: TOTAL | F22: FORMULAS
B23: Intrinsic product quality | C23: Without DATs
B24: Protein % DRY MATTER | C24: Without DATs | D24: % | E24: ='Parcel 1 without DATSs'!G226 -> 12
B25: Humidity | C25: Without DATs | D25: % | E25: ='Parcel 1 without DATSs'!G227 -> 13.5
B26: Test Weight | C26: Without DATs | D26: kg/hl | E26: ='Parcel 1 without DATSs'!G228 -> 71.5
A28: ENVIRONMENTAL ANALYSIS
A29: INPUT | B29: INDICATOR | C29: SCENARIO | D29: UoM | E29: TOTAL | F29: Formula
A30: FERTILISER | B30: Nitrogen applied | C30: Without DATs | D30: kg/ha | E30: =('Parcel 1 without DATSs'!G101*'Parcel 1 without DATSs'!G102*('Parcel 1 without DATSs'!G103/100))+ ('Parcel 1 without DATSs'!G108*'Parcel 1 without DATSs'!G109*('Parcel 1 without DATSs'!G110/100))+ ('Parcel 1 without DATSs'!G115*'Parcel 1 without DATSs'!G116*('Parcel 1 without DATSs'!G117/100))+ ('Parcel 1 without DATSs'!G122*'Parcel 1 without DATSs'!G123*('Parcel 1 without DATSs'!G124/100))+ ('Parcel 1 without DATSs'!G129*'Parcel 1 without DATSs'!G130*('Parcel 1 without DATSs'!G131/100))+ ('Parcel 1 without DATSs'!G136*'Parcel 1 without DATSs'!G137*('Parcel 1 without DATSs'!G138/100))+ ('Parcel 1 without DATSs'!G143*'Parcel 1 without DATSs'!G144*('Parcel 1 without DATSs'!G145/100))+ ('Parcel 1 without DATSs'!G150*'Parcel 1 without DATSs'!G151*('Parcel 1 without DATSs'!G152/100))+ ('Parcel 1 without DATSs'!G157*'Parcel 1 without DATSs'!G158*('Parcel 1 without DATSs'!G159/100))+ ('Parcel 1 without DATSs'!G164*'Parcel 1 without DATSs'!G165*('Parcel 1 without DATSs'!G166/100)) -> 67.8135 | F30: Amount of N fertilizer used/total area
A31: FERTILISER | B31: Nitrogen use efficiency | C31: Without DATs | D31: % | E31: =(('Parcel 1 without DATSs'!G250*1000/'Parcel 1 without DATSs'!E10)*'sust. impact KPIs NO DATS'!C98)/E30*100 -> 166.12304 | F31: (yield *Average N content (%))/(Amount of N fertilizer used /total area)*100
A32: FERTILISER | B32: Phosphorus applied | C32: Without DATs | D32: kg/ha | E32: =('Parcel 1 without DATSs'!G101*'Parcel 1 without DATSs'!G102*('Parcel 1 without DATSs'!G104/100))+ ('Parcel 1 without DATSs'!G108*'Parcel 1 without DATSs'!G109*('Parcel 1 without DATSs'!G111/100))+ ('Parcel 1 without DATSs'!G115*'Parcel 1 without DATSs'!G116*('Parcel 1 without DATSs'!G118/100))+ ('Parcel 1 without DATSs'!G122*'Parcel 1 without DATSs'!G123*('Parcel 1 without DATSs'!G125/100))+ ('Parcel 1 without DATSs'!G129*'Parcel 1 without DATSs'!G130*('Parcel 1 without DATSs'!G132/100))+ ('Parcel 1 without DATSs'!G136*'Parcel 1 without DATSs'!G137*('Parcel 1 without DATSs'!G139/100))+ ('Parcel 1 without DATSs'!G143*'Parcel 1 without DATSs'!G144*('Parcel 1 without DATSs'!G146/100))+ ('Parcel 1 without DATSs'!G150*'Parcel 1 without DATSs'!G151*('Parcel 1 without DATSs'!G153/100))+ ('Parcel 1 without DATSs'!G157*'Parcel 1 without DATSs'!G158*('Parcel 1 without DATSs'!G160/100))+ ('Parcel 1 without DATSs'!G164*'Parcel 1 without DATSs'!G165*('Parcel 1 without DATSs'!G167/100)) -> 47.5 | F32: Amount of P fertilizer used/total area
A33: FERTILISER | B33: Phosphorus use efficiency | C33: Without DATs | D33: % | E33: =(('Parcel 1 without DATSs'!G250*1000/'Parcel 1 without DATSs'!E10)*'sust. impact KPIs NO DATS'!C99)/E32*100 -> 96.275304 | F33: (yield*Average P content (%))/(Amount of P fertilizer used/total area)*100
A34: FERTILISER | B34: Potassium applied | C34: Without DATs | D34: kg/ha | E34: =('Parcel 1 without DATSs'!G101*'Parcel 1 without DATSs'!G102*('Parcel 1 without DATSs'!G105/100))+ ('Parcel 1 without DATSs'!G108*'Parcel 1 without DATSs'!G109*('Parcel 1 without DATSs'!G112/100))+ ('Parcel 1 without DATSs'!G115*'Parcel 1 without DATSs'!G116*('Parcel 1 without DATSs'!G119/100))+ ('Parcel 1 without DATSs'!G122*'Parcel 1 without DATSs'!G123*('Parcel 1 without DATSs'!G126/100))+ ('Parcel 1 without DATSs'!G129*'Parcel 1 without DATSs'!G130*('Parcel 1 without DATSs'!G133/100))+ ('Parcel 1 without DATSs'!G136*'Parcel 1 without DATSs'!G137*('Parcel 1 without DATSs'!G140/100))+ ('Parcel 1 without DATSs'!G143*'Parcel 1 without DATSs'!G144*('Parcel 1 without DATSs'!G147/100))+ ('Parcel 1 without DATSs'!G150*'Parcel 1 without DATSs'!G151*('Parcel 1 without DATSs'!G154/100))+ ('Parcel 1 without DATSs'!G157*'Parcel 1 without DATSs'!G158*('Parcel 1 without DATSs'!G161/100))+ ('Parcel 1 without DATSs'!G164*'Parcel 1 without DATSs'!G165*('Parcel 1 without DATSs'!G168/100)) -> 0.062 | F34: Amount of K fertilizer used/total area
A35: FERTILISER | B35: Potassium use efficiency | C35: Without DATs | D35: % | E35: =(('Parcel 1 without DATSs'!G250*1000/'Parcel 1 without DATSs'!E10)*'sust. impact KPIs NO DATS'!C100)/E34*100 -> 46774.194 | F35: (yield*Average K content (%))/(Amount of K fertilizer used/total area)*100
A36: PESTICIDE | B36: Pesticides, herbicides and fungicides use | C36: Without DATs | D36: kg/ha | E36: =('Parcel 1 without DATSs'!G67*'Parcel 1 without DATSs'!G68)+ ('Parcel 1 without DATSs'!G70*'Parcel 1 without DATSs'!G71)+ ('Parcel 1 without DATSs'!G73*'Parcel 1 without DATSs'!G74)+ ('Parcel 1 without DATSs'!G76*'Parcel 1 without DATSs'!G77)+ ('Parcel 1 without DATSs'!G79*'Parcel 1 without DATSs'!G80)+ ('Parcel 1 without DATSs'!G82*'Parcel 1 without DATSs'!G83)+ ('Parcel 1 without DATSs'!G85*'Parcel 1 without DATSs'!G86)+ ('Parcel 1 without DATSs'!G88*'Parcel 1 without DATSs'!G89)+ ('Parcel 1 without DATSs'!G91*'Parcel 1 without DATSs'!G92)+ ('Parcel 1 without DATSs'!G94*'Parcel 1 without DATSs'!G95) -> 5.38 | F36: Amount of pesticides, herbicides and fungicides used/total area
A37: WATER | B37: Water consumption | C37: Without DATs | D37: =IFERROR(VLOOKUP('General Information'!$D$6, Validations!$J$2:$K$8, 2,FALSE), "") | E37: ='Parcel 1 without DATSs'!G29/(IF('General Information'!D6="crop",'Parcel 1 without DATSs'!E10,IF('General Information'!D6="milk",'Parcel 1 without DATSs'!G251,IF('General Information'!D6="meat",'Parcel 1 without DATSs'!G252,IF('General Information'!D6="animal",'Parcel 1 without DATSs'!G253,IF('General Information'!D6="oyster",'Parcel 1 without DATSs'!G254,IF('General Information'!D6="honey",'Parcel 1 without DATSs'!G255,'Parcel 1 without DATSs'!G256))))))) -> 0.79807692 | F37: Amount of water used/total area
A38: WATER | B38: Aquaculture water productivity | C38: Without DATs | D38: l/pieces | F38: Amount of water used/production
A39: WATER | B39: Irrigation water productivity | C39: Without DATs | D39: kg/m3 | E39: =(('Parcel 1 without DATSs'!G250)*1000)/(IF(('Parcel 1 without DATSs'!G24+'Parcel 1 without DATSs'!G25)>0,('Parcel 1 without DATSs'!G24+'Parcel 1 without DATSs'!G25),'Parcel 1 without DATSs'!G29)) -> 6987.9518 | F39: Yield/Amount of water used for irrigation
A40: ELECTRICITY | B40: Electricity consumption | C40: Without DATs | D40: =IFERROR(VLOOKUP('General Information'!$D$6, Validations!$W$2:$X$8, 2,FALSE), "") -> kWh/ha | E40: ='Parcel 1 without DATSs'!G62/(IF('General Information'!D6="crop",'Parcel 1 without DATSs'!E10,IF('General Information'!D6="milk",'Parcel 1 without DATSs'!G251,IF('General Information'!D6="meat",'Parcel 1 without DATSs'!G252,IF('General Information'!D6="animal",'Parcel 1 without DATSs'!G253,IF('General Information'!D6="oyster",'Parcel 1 without DATSs'!G254,IF('General Information'!D6="honey",'Parcel 1 without DATSs'!G255,'Parcel 1 without DATSs'!G256))))))) -> 5.1778846 | F40: Tot. amount of electricity used/tot area
A41: ANIMAL | B41: Ease of movement | C41: Without DATs | D41: d/y | E41: ='Parcel 1 without DATSs'!G235/'Parcel 1 without DATSs'!G236 -> #DIV/0! | F41: number of days per year with access to pasture and outdoor loafing area
A42: ANIMAL | B42: Mortality rate (livestock) | C42: Without DATs | D42: % | E42: ='Parcel 1 without DATSs'!G232/'Parcel 1 without DATSs'!E17*100 -> #DIV/0! | F42: (Number of deaths in a year/Average herd size)
A43: ANIMAL | B43: Mortality rate (aquaculture) | C43: Without DATs | D43: % | E43: ='Parcel 1 without DATSs'!G232/'Parcel 1 without DATSs'!E20 -> #DIV/0! | F43: (Number of deaths in a year/total animals)
A44: ANIMAL | B44: Mortality rate (apiculture) | C44: Without DATs | D44: % | E44: ='Parcel 1 without DATSs'!G232/'Parcel 1 without DATSs'!E19*100 -> #DIV/0! | F44: (Number of deaths in a year/total animals)
A45: ANIMAL | B45: Mortality rate at birth | C45: Without DATs | D45: % | E45: ='Parcel 1 without DATSs'!G233/'Parcel 1 without DATSs'!G234 -> #DIV/0! | F45: (Calves died in the first 24 h / Total number of calves born)
A46: ANIMAL | B46: Cows with high SCC | C46: Without DATs | D46: % | E46: ='Parcel 1 without DATSs'!G237/'Parcel 1 without DATSs'!E17 -> #DIV/0! | F46: number of cows producing high SCC milk / Total number of cows * 100
A47: DRUGS | B47: Drugs use in dairy livestock | C47: Without DATs | D47: =IFERROR(VLOOKUP('General Information'!$D$6, Validations!$AA$2:$AB$8, 2,FALSE), "") -> 0 | E47: =('Parcel 1 without DATSs'!G186+'Parcel 1 without DATSs'!G188+'Parcel 1 without DATSs'!G190)/(IF('General Information'!D6="crop",'Parcel 1 without DATSs'!E10,IF('General Information'!D6="milk",'Parcel 1 without DATSs'!G251,IF('General Information'!D6="meat",'Parcel 1 without DATSs'!G252,IF('General Information'!D6="animal",'Parcel 1 without DATSs'!G253,IF('General Information'!D6="oyster",'Parcel 1 without DATSs'!G254,IF('General Information'!D6="honey",'Parcel 1 without DATSs'!G255,'Parcel 1 without DATSs'!G256))))))) -> 0 | F47: Amount of drugs used/ output
A48: DRUGS | B48: Drugs use in meat livestock | C48: Without DATs | D48: =IFERROR(VLOOKUP('General Information'!$D$6, Validations!$AA$2:$AB$8, 2,FALSE), "") -> 0 | E48: =('Parcel 1 without DATSs'!G186+'Parcel 1 without DATSs'!G188+'Parcel 1 without DATSs'!G190)/(IF('General Information'!D6="crop",'Parcel 1 without DATSs'!E10,IF('General Information'!D6="milk",'Parcel 1 without DATSs'!G251,IF('General Information'!D6="meat",'Parcel 1 without DATSs'!G252,IF('General Information'!D6="animal",'Parcel 1 without DATSs'!G253,IF('General Information'!D6="oyster",'Parcel 1 without DATSs'!G254,IF('General Information'!D6="honey",'Parcel 1 without DATSs'!G255,'Parcel 1 without DATSs'!G256))))))) -> 0 | F48: Amount of drugs used/ output
A49: DRUGS | B49: Drugs use in aquaculture | C49: Without DATs | D49: g/m2 | E49: =('Parcel 1 without DATSs'!G186+'Parcel 1 without DATSs'!G188+'Parcel 1 without DATSs'!G190)/'Parcel 1 without DATSs'!E20 -> #DIV/0! | F49: Amount of drugs used/ output
A50: DRUGS | B50: Drugs use in apiculture | C50: Without DATs | D50: g/beehive | E50: =('Parcel 1 without DATSs'!G186+'Parcel 1 without DATSs'!G188+'Parcel 1 without DATSs'!G190)/'Parcel 1 without DATSs'!E19 -> #DIV/0! | F50: Amount of drugs used/ output
A51: FUEL | B51: Fuel GHG emission | C51: Without DATs | D51: =IFERROR(VLOOKUP('General Information'!$D$6, Validations!$AA$2:$AC$8, 3,FALSE), "") -> kg CO2 eq/ha | E51: =('Parcel 1 without DATSs'!G43*'sust. impact KPIs NO DATS'!C94*'sust. impact KPIs NO DATS'!C95)/(IF('General Information'!D6="crop",'Parcel 1 without DATSs'!E10,IF('General Information'!D6="milk",'Parcel 1 without DATSs'!G251,IF('General Information'!D6="meat",'Parcel 1 without DATSs'!G252,IF('General Information'!D6="animal",'Parcel 1 without DATSs'!G253,IF('General Information'!D6="oyster",'Parcel 1 without DATSs'!G254,IF('General Information'!D6="honey",'Parcel 1 without DATSs'!G255,'Parcel 1 without DATSs'!G256))))))) -> 142.60153 | F51: Tot. amount of fuel used *Lower heating value*Emission factor | H51: =6.2*100/31 -> 20
A52: FUEL | B52: Arable and horticulture fuel consumption | C52: Without DATs | D52: l/ha | E52: ='Parcel 1 without DATSs'!G43/'Parcel 1 without DATSs'!E10 -> 53.605769 | F52: Tot. amount of fuel used/tot area
A53: FUEL | B53: Livestock fuel consumption | C53: Without DATs | D53: =IFERROR(VLOOKUP('General Information'!$D$6, Validations!$AA$2:$AD$8, 4,FALSE), "") -> l/ha | E53: ='Parcel 1 without DATSs'!G43/'Parcel 1 without DATSs'!E17 -> #DIV/0! | F53: Tot. amount of fuel used/number of animals
A54: FUEL | B54: Aquaculture fuel consumption | C54: Without DATs | D54: l/m2 | E54: ='Parcel 1 without DATSs'!G43/'Parcel 1 without DATSs'!E20 -> #DIV/0! | F54: Tot. amount of fuel used/ area under aquaculture
A55: FUEL | B55: Apiculture fuel consumption | C55: Without DATs | D55: kg/beehives | E55: ='Parcel 1 without DATSs'!G43/'Parcel 1 without DATSs'!E19 -> #DIV/0! | F55: Tot. amount of fuel used/Number of beehives
F56: tot | H56: direct | J56: indirect volatilisation
A57: FERTILISER | B57: N2O GHG emission | C57: Without DATs | D57: kg Co2e/ha | E57: =(G57+I57+K57)*C90*C91 -> 399.72396 | F57: direct + indirect N2O emissions | G57: =E30*C77 -> 0.678135 | H57: Amount of N fertilizer used (kg-N) * Emission factor 1 | I57: =((((IF('Parcel 1 without DATSs'!G100="Mineral",'Parcel 1 without DATSs'!G101*'Parcel 1 without DATSs'!G102*'Parcel 1 without DATSs'!G103/100,0)) + (IF('Parcel 1 without DATSs'!G107="Mineral",'Parcel 1 without DATSs'!G108*'Parcel 1 without DATSs'!G109*'Parcel 1 without DATSs'!G110/100,0)) + (IF('Parcel 1 without DATSs'!G114="Mineral",'Parcel 1 without DATSs'!G115*'Parcel 1 without DATSs'!G116*'Parcel 1 without DATSs'!G117/100,0)) + (IF('Parcel 1 without DATSs'!G121="Mineral",'Parcel 1 without DATSs'!G122*'Parcel 1 without DATSs'!G123*'Parcel 1 without DATSs'!G124/100,0)) + (IF('Parcel 1 without DATSs'!G128="Mineral",'Parcel 1 without DATSs'!G129*'Parcel 1 without DATSs'!G130*'Parcel 1 without DATSs'!G131/100,0)) + (IF('Parcel 1 without DATSs'!G135="Mineral",'Parcel 1 without DATSs'!G136*'Parcel 1 without DATSs'!G137*'Parcel 1 without DATSs'!G138/100,0)) + (IF('Parcel 1 without DATSs'!G142="Mineral",'Parcel 1 without DATSs'!G143*'Parcel 1 without DATSs'!G144*'Parcel 1 without DATSs'!G145/100,0)) + (IF('Parcel 1 without DATSs'!G149="Mineral",'Parcel 1 without DATSs'!G150*'Parcel 1 without DATSs'!G151*'Parcel 1 without DATSs'!G152/100,0)) + (IF('Parcel 1 without DATSs'!G156="Mineral",'Parcel 1 without DATSs'!G157*'Parcel 1 without DATSs'!G158*'Parcel 1 without DATSs'!G159/100,0)) + (IF('Parcel 1 without DATSs'!G163="Mineral",'Parcel 1 without DATSs'!G164*'Parcel 1 without DATSs'!G165*'Parcel 1 without DATSs'!G166/100,0)))*'sust. impact KPIs DATS'!C85) + (((IF('Parcel 1 without DATSs'!G100="Organic",'Parcel 1 without DATSs'!G101*'Parcel 1 without DATSs'!G102*'Parcel 1 without DATSs'!G103/100,0)) + (IF('Parcel 1 without DATSs'!G107="Organic",'Parcel 1 without DATSs'!G108*'Parcel 1 without DATSs'!G109*'Parcel 1 without DATSs'!G110/100,0)) + (IF('Parcel 1 without DATSs'!G114="Organic",'Parcel 1 without DATSs'!G115*'Parcel 1 without DATSs'!G116*'Parcel 1 without DATSs'!G117/100,0)) + (IF('Parcel 1 without DATSs'!G121="Organic",'Parcel 1 without DATSs'!G122*'Parcel 1 without DATSs'!G123*'Parcel 1 without DATSs'!G124/100,0)) + (IF('Parcel 1 without DATSs'!G128="Organic",'Parcel 1 without DATSs'!G129*'Parcel 1 without DATSs'!G130*'Parcel 1 without DATSs'!G131/100,0)) + (IF('Parcel 1 without DATSs'!G135="Organic",'Parcel 1 without DATSs'!G136*'Parcel 1 without DATSs'!G137*'Parcel 1 without DATSs'!G138/100,0)) + (IF('Parcel 1 without DATSs'!G142="Organic",'Parcel 1 without DATSs'!G143*'Parcel 1 without DATSs'!G144*'Parcel 1 without DATSs'!G145/100,0)) + (IF('Parcel 1 without DATSs'!G149="Organic",'Parcel 1 without DATSs'!G150*'Parcel 1 without DATSs'!G151*'Parcel 1 without DATSs'!G152/100,0)) + (IF('Parcel 1 without DATSs'!G156="Organic",'Parcel 1 without DATSs'!G157*'Parcel 1 without DATSs'!G158*'Parcel 1 without DATSs'!G159/100,0)) + (IF('Parcel 1 without DATSs'!G163="Organic",'Parcel 1 without DATSs'!G164*'Parcel 1 without DATSs'!G165*'Parcel 1 without DATSs'!G166/100,0)))*'sust. impact KPIs DATS'!C86)) *'sust. impact KPIs DATS'!C82 -> 0.07459485 | J57: [(Amount of synthetic N fertilizer used (kg-N) * fraction volatilized) + (Amount of organic N fertilizer used (kg-N) *fraction volatilized)] * Emission factor 4 | K57: =E30*C87*C89 -> 0.17902764 | L57: Amount of N fertilizer used (kg-N) * fraction of leaching or runoff * emission factor 5
A58: GHG | B58: total ghg emissions | C58: Without DATs | D58: =D51 -> kg CO2 eq/ha | E58: =E57+E51 -> 542.32549
A59: SOCIAL ANALYSIS
B60: INDICATOR | C60: SCENARIO | D60: UoM | E60: TOTAL | F60: Formula
B62: Working time | C62: Without DATs | D62: =IFERROR(VLOOKUP('General Information'!$D$6, Validations!$L$2:$N$8, 3,FALSE), "") -> h/ha | E62: {=(SUM(SUMIFS('Parcel 1 without DATSs'!G194:G218,'Parcel 1 without DATSs'!C194:C218,'Analysis DATS vs. NO DATS'!C12:C36,'Analysis DATS vs. NO DATS'!I12:I36,1)))/(IF('General Information'!D6="crop",'Parcel 1 without DATSs'!E10,IF('General Information'!D6="milk",'Parcel 1 without DATSs'!G251,IF('General Information'!D6="meat",'Parcel 1 without DATSs'!G252,IF('General Information'!D6="animal",'Parcel 1 without DATSs'!G253,IF('General Information'!D6="oyster",'Parcel 1 without DATSs'!G254,IF('General Information'!D6="honey",'Parcel 1 without DATSs'!G255,'Parcel 1 without DATSs'!G256)))))))} -> 11.6875 | F62: Hours worked for the specific activities that could be impacted by DATSs | G62: =(SUM('Parcel 1 without DATSs'!G194:G218))/(IF('General Information'!D6="crop",'Parcel 1 without DATSs'!E10,IF('General Information'!D6="milk",'Parcel 1 without DATSs'!G251,IF('General Information'!D6="meat",'Parcel 1 without DATSs'!G252,IF('General Information'!D6="animal",'Parcel 1 without DATSs'!G253,IF('General Information'!D6="oyster",'Parcel 1 without DATSs'!G254,IF('General Information'!D6="honey",'Parcel 1 without DATSs'!G255,'Parcel 1 without DATSs'!G256))))))) -> 16.706731
B63: Frequency rate of occupational injuries | C63: Without DATs | D63: n./hours | E63: ='Parcel 1 without DATSs'!G241/'Parcel 1 without DATSs'!G243 -> 0 | F63: Number of new injury cases/Total number of working hours
B64: Incidence of occupational injuries | C64: Without DATs | D64: % | E64: ='Parcel 1 without DATSs'!G242/'Parcel 1 without DATSs'!G243 -> 0 | F64: Total number of lost working hours due to occupational injuries/Total number of working hours
B65: Contribution to local employment | C65: Without DATs | D65: % | E65: ='Parcel 1 without DATSs'!G245/'Parcel 1 without DATSs'!G246 -> #DIV/0! | F65: Number of new local employees/Total new employees hired
B74: IPCC 2006 methodology (2019 refinement) - Tier 1 | D74: (Fixed values)
A75: N2O EMISSIONS | B75: UoM | C75: value | D75: description
A76: direct emissions
A77: EF1 | B77: (Kg N2O-N)/(kg N input) | C77: 0.01 | D77: Emission Factor default value for direct emissions
A78: EF1 SW | B78: (Kg N2O-N)/(kg N input) | C78: 0.016 | D78: Emission Factor for Synthetic fertilizers in Wet climates (optional)
A79: EF1 OW | B79: (Kg N2O-N)/(kg N input) | C79: 0.006 | D79: Other N inputs in Wet climates (optional)
A80: EF1 AD | B80: (Kg N2O-N)/(kg N input) | C80: 0.006 | D80: All N inputs in Dry climates (optional)
A81: indirect emissions
A82: EF4 | B82: (Kg N2O-N)/(kg N volatilised) | C82: 0.01 | D82: Emission Factor default value for volatilization of N
A83: EF4 W | B83: (Kg N2O-N)/(kg N volatilised) | C83: 0.014 | D83: Emission Factor default value for volatilization of N in wet cliamtes
A84: EF4 D | B84: (Kg N2O-N)/(kg N volatilised) | C84: 0.005 | D84: Emission Factor default value for volatilization of N in dry climates
A85: Frac GASF | B85: (kg N volatilised)/(Kg of N input) | C85: 0.11 | D85: Fraction of synthetic fertiliser N that volatilises
A86: Frac GASM | B86: (kg N volatilised)/(Kg of N input) | C86: 0.21 | D86: Fraction of organic fertiliser N that volatilies
A87: FracLEACH | B87: (kg Nleaching&runoff)/(Kg N input) | C87: 0.24 | D87: For all N inputs
A88: FracLEACH D | B88: (kg Nleaching&runoff)/(Kg N input) | C88: 0 | D88: 0 if leaching & runoff process assumed to be absent or in dry climates
A89: EF5 | B89: (kg N2O–N)/(kg N leached and runoff) | C89: 0.011 | D89: Emission factor for N2O emissions from N leaching and runoff
A90: CF1 | B90: Kg/kg | C90: =44/28 -> 1.5714286 | D90: Coversion factor from N to N2O
A91: GWP-N2O | C91: 273 | D91: Global Warming Potential of N2O compared to CO2 (IPCC AR6)
A93: CO2 EMISSIONS FUEL
A94: Lower Heating Value Diesel | B94: MJ/l | C94: 35.9 | D94: Castoldi & Bechini, 2006
A95: EF diesel agri | B95: kg Co2e/Mj | C95: 0.0741 | D95: IPCC 2006
A97: Average nutrient content kg/kg
A98: ='General Information'!D7 -> Wheat (T. aestivum) | B98: Average N content | C98: =IFERROR(VLOOKUP('General Information'!$D$7, Validations!$P$2:$Q$18, 2,FALSE), "") -> 0.0202
A99: ='General Information'!D7 -> Wheat (T. aestivum) | B99: Average P content | C99: =IFERROR(VLOOKUP('General Information'!$D$7, Validations!$R$2:$S$18, 2,FALSE), "") -> 0.0082
A100: ='General Information'!D7 -> Wheat (T. aestivum) | B100: Average K content | C100: =IFERROR(VLOOKUP('General Information'!$D$7, Validations!$T$2:$U$18, 2,FALSE), "") -> 0.0052

Sheet Analysis DATS vs. NO DATS
S1: IMPACT CATEGORY AGGREGATION | X1: SUSTAINABILITY CATEGORY AGGREGATION
A2: Sustainability category | B2: Impact category | C2: KPI | D2: UNIT | E2: Abs. Value | F2: % | G2: % Adjusted (+/-) for aggregation | H2: if > is good = 1 | I2: Impacted KPIs | J2: Main Impacts | K2: Monetary Impacts | L2: Aggregated Impacts | M2: Title (for column J) | N2: Subtitle (for column J) | O2: Short description (for column K) | P2: Icon | Q2: Colour | S2: KPI category | T2: % aggregated | U2: % aggregated (max range) | V2: Icon | W2: Colour | X2: Sustainability category | Y2: Sustainability category | Z2: overall score (%) | AB2: code | AC2: meaning | AD2: colour
A3: Economic | B3: DATSs COSTS | C3: Cost of DATSs (maintenance + annual fees) | D3: ='Cost-revenue DATS'!D35 -> €/ha | E3: =('Cost-revenue DATS'!E36-'Cost-revenue NO DATS'!E36) -> 1.7817372 | K3: 1 | O3: Cost of DATSs (maintenance + annual fees) | P3: 1 | Q3: 3 | S3: COSTS | T3: =IFERROR((VLOOKUP("Sum of costs",C5:G38,5,FALSE)),0) -> 7.6464927 | U3: =MIN(MAX(T3,-100),100) -> 7.6464927 | V3: 10 | W3: =IF(T3>0,1,IF(T3=0,2,0)) -> 1 | X3: Economic | AB3: 1 | AC3: POSITIVE IMPACT | AD3: green
A4: Economic | B4: DATSs COSTS | C4: Initial investment for the DATSs | D4: ='Cost-revenue DATS'!$D$3 -> €/ha | E4: =('General Information'!D20+'General Information'!H20+'General Information'!L20)/(IF('General Information'!D6="crop",'Parcel 1 with DATSs'!E10,IF('General Information'!D6="milk",'Parcel 1 with DATSs'!G251,IF('General Information'!D6="meat",'Parcel 1 with DATSs'!G252,IF('General Information'!D6="animal",'Parcel 1 with DATSs'!G253,IF('General Information'!D6="oyster",'Parcel 1 with DATSs'!G254,IF('General Information'!D6="honey",'Parcel 1 with DATSs'!G255,'Parcel 1 with DATSs'!G256))))))) -> 78.391982 | K4: 1 | O4: Initial investment for the DATSs | P4: 1 | Q4: 3 | S4: PRODUCTIVITY | T4: =IFERROR(AVERAGEIFS(G$5:G$99,B$5:B$99,S4,L$5:L$99,1),0) -> 26.241205 | U4: =MIN(MAX(T4,-100),100) -> 26.241205 | V4: 12 | W4: =IF(T4>0,1,IF(T4=0,2,0)) -> 1 | X4: Economic | Y4: Economic | Z4: =AVERAGEIF(X3:X9,Y4,T3:T9) -> 16.943849 | AB4: 0 | AC4: NEGATIVE IMPACT | AD4: red
A5: Economic | B5: COSTS | C5: Cost of water | D5: ='Cost-revenue DATS'!$D$3 -> €/ha | E5: ='Cost-revenue DATS'!E3-'Cost-revenue NO DATS'!E3 -> 0 | F5: =E5*100/'Cost-revenue NO DATS'!E3 -> #DIV/0! | G5: =IF(H5=1,F5,F5*(-1)) -> #DIV/0! | H5: 0 | P5: 2 | Q5: =IFERROR(IF(IF(H5=1,E5,-E5)>0,1,IF(IF(H5=1,E5,-E5)<0,0,2)),"") -> 2 | S5: WATER | T5: =IFERROR(AVERAGEIFS(G$5:G$99,B$5:B$99,S5,L$5:L$99,1),0) -> 0 | U5: =MIN(MAX(T5,-100),100) -> 0 | V5: 2 | W5: =IF(T5>0,1,IF(T5=0,2,0)) -> 2 | X5: Environmental | AB5: 2 | AC5: NEUTRAL | AD5: grey
A6: Economic | B6: COSTS | C6: Cost of fuel | D6: ='Cost-revenue DATS'!$D$3 -> €/ha | E6: ='Cost-revenue DATS'!E4-'Cost-revenue NO DATS'!E4 -> -4.6588841 | F6: =E6*100/'Cost-revenue NO DATS'!E4 -> -7.5574021 | G6: =IF(H6=1,F6,F6*(-1)) -> 7.5574021 | H6: 0 | I6: 1 | K6: 1 | L6: 1 | O6: Cost of fuel: Most of the fuel is used for soil preparation and sowing, but also for fertilization and other agronomic practices impacted by the DATSs | P6: 3 | Q6: =IFERROR(IF(IF(H6=1,E6,-E6)>0,1,IF(IF(H6=1,E6,-E6)<0,0,2)),"") -> 1 | S6: INPUTS | T6: =IFERROR(AVERAGEIFS(G$5:G$99,B$5:B$99,S6,L$5:L$99,1),0) -> 3.2147664 | U6: =MIN(MAX(T6,-100),100) -> 3.2147664 | V6: 6 | W6: =IF(T6>0,1,IF(T6=0,2,0)) -> 1 | X6: Environmental | Y6: Environmental | Z6: =AVERAGEIF(X3:X9,Y6,T3:T9) -> -4.2077724 | AB6: 3 | AC6: DATS | AD6: blu
A7: Economic | B7: COSTS | C7: Cost of electricity | D7: ='Cost-revenue DATS'!$D$3 -> €/ha | E7: ='Cost-revenue DATS'!E5-'Cost-revenue NO DATS'!E5 -> -0.30881245 | F7: =E7*100/'Cost-revenue NO DATS'!E5 -> -40.297742 | G7: =IF(H7=1,F7,F7*(-1)) -> 40.297742 | H7: 0 | P7: 4 | Q7: =IFERROR(IF(IF(H7=1,E7,-E7)>0,1,IF(IF(H7=1,E7,-E7)<0,0,2)),"") -> 1 | S7: ENERGY | T7: =IFERROR(AVERAGEIFS(G$5:G$99,B$5:B$99,S7,L$5:L$99,1),0) -> 23.927572 | U7: =MIN(MAX(T7,-100),100) -> 23.927572 | V7: 4 | W7: =IF(T7>0,1,IF(T7=0,2,0)) -> 1 | X7: Environmental
A8: Economic | B8: COSTS | C8: Cost of pesticide | D8: ='Cost-revenue DATS'!$D$3 -> €/ha | E8: ='Cost-revenue DATS'!E6-'Cost-revenue NO DATS'!E6 -> -64.692 | F8: =E8*100/'Cost-revenue NO DATS'!E6 -> -55.869145 | G8: =IF(H8=1,F8,F8*(-1)) -> 55.869145 | H8: 0 | I8: 1 | J8: 1 | K8: 1 | L8: 1 | M8: DECREASED PESTICIDE CONSUMPTION | N8: due to the use of data from sensors, satellite and agro-meteorological stations | O8: Cost of pesticides: The DSS, also thanks to the data from sensors, satellite and agrometeorological stations, enables a better management of phytosanitary treatments | P8: 5 | Q8: =IFERROR(IF(IF(H8=1,E8,-E8)>0,1,IF(IF(H8=1,E8,-E8)<0,0,2)),"") -> 1 | S8: GHG EMISSIONS | T8: =IFERROR(AVERAGEIFS(G$5:G$99,B$5:B$99,S8,L$5:L$99,1),0) -> -43.973428 | U8: =MIN(MAX(T8,-100),100) -> -43.973428 | V8: 13 | W8: =IF(T8>0,1,IF(T8=0,2,0)) -> 0 | X8: Environmental | Y8: Social | Z8: =AVERAGEIF(X3:X9,Y8,T3:T9) -> 33.103867
A9: Economic | B9: COSTS | C9: Cost of fertiliser | D9: ='Cost-revenue DATS'!$D$3 -> €/ha | E9: ='Cost-revenue DATS'!E7-'Cost-revenue NO DATS'!E7 -> 55.455 | F9: =E9*100/'Cost-revenue NO DATS'!E7 -> 22.401988 | G9: =IF(H9=1,F9,F9*(-1)) -> -22.401988 | H9: 0 | I9: 1 | K9: 1 | L9: 1 | O9: Cost of fertilizers: An increase in fertilizer costs is observed, not due to an increase in the quantity distributed, but due to the different types and costs of the fertilizers used | P9: 6 | Q9: =IFERROR(IF(IF(H9=1,E9,-E9)>0,1,IF(IF(H9=1,E9,-E9)<0,0,2)),"") -> 0 | S9: LABOUR | T9: =IFERROR(AVERAGEIFS(G$5:G$99,B$5:B$99,S9,L$5:L$99,1),0) -> 33.103867 | U9: =MIN(MAX(T9,-100),100) -> 33.103867 | V9: 9 | W9: =IF(T9>0,1,IF(T9=0,2,0)) -> 1 | X9: Social
A10: Economic | B10: COSTS | C10: Cost of feed | D10: ='Cost-revenue DATS'!$D$3 -> €/ha | E10: ='Cost-revenue DATS'!E8-'Cost-revenue NO DATS'!E8 -> 0 | F10: =E10*100/'Cost-revenue NO DATS'!E8 -> #DIV/0! | G10: =IF(H10=1,F10,F10*(-1)) -> #DIV/0! | H10: 0 | P10: 7 | Q10: =IFERROR(IF(IF(H10=1,E10,-E10)>0,1,IF(IF(H10=1,E10,-E10)<0,0,2)),"") -> 2
A11: Economic | B11: COSTS | C11: Cost of drugs | D11: ='Cost-revenue DATS'!$D$3 -> €/ha | E11: ='Cost-revenue DATS'!E9-'Cost-revenue NO DATS'!E9 -> 0 | F11: =E11*100/'Cost-revenue NO DATS'!E9 -> #DIV/0! | G11: =IF(H11=1,F11,F11*(-1)) -> #DIV/0! | H11: 0 | P11: 8 | Q11: =IFERROR(IF(IF(H11=1,E11,-E11)>0,1,IF(IF(H11=1,E11,-E11)<0,0,2)),"") -> 2
A12: Economic | B12: COSTS | C12: Labour for irrigation | D12: ='Cost-revenue DATS'!$D$3 -> €/ha | E12: ='Cost-revenue DATS'!E10-'Cost-revenue NO DATS'!E10 -> 0 | F12: =E12*100/'Cost-revenue NO DATS'!E10 -> #DIV/0! | G12: =IF(H12=1,F12,F12*(-1)) -> #DIV/0! | H12: 0 | P12: 9 | Q12: =IFERROR(IF(IF(H12=1,E12,-E12)>0,1,IF(IF(H12=1,E12,-E12)<0,0,2)),"") -> 2
A13: Economic | B13: COSTS | C13: Labour for pesticide | D13: ='Cost-revenue DATS'!$D$3 -> €/ha | E13: ='Cost-revenue DATS'!E11-'Cost-revenue NO DATS'!E11 -> -3.007915 | F13: =E13*100/'Cost-revenue NO DATS'!E11 -> -13.246238 | G13: =IF(H13=1,F13,F13*(-1)) -> 13.246238 | H13: 0 | I13: 1 | K13: 1 | L13: 1 | O13: Cost of labour for pesticides application: A decrease in the number of plant protection products and field interventions has reduced the work associated with this activity | P13: 9 | Q13: =IFERROR(IF(IF(H13=1,E13,-E13)>0,1,IF(IF(H13=1,E13,-E13)<0,0,2)),"") -> 1
A14: Economic | B14: COSTS | C14: Labour for fertilisation | D14: ='Cost-revenue DATS'!$D$3 -> €/ha | E14: ='Cost-revenue DATS'!E12-'Cost-revenue NO DATS'!E12 -> -3.5768717 | F14: =E14*100/'Cost-revenue NO DATS'!E12 -> -26.63192 | G14: =IF(H14=1,F14,F14*(-1)) -> 26.63192 | H14: 0 | I14: 1 | K14: 1 | L14: 1 | O14: Cost of labour for fertilization: A decrease in the number of fertilizations and fertilizers applied has reduced the work associated with this activity | P14: 9 | Q14: =IFERROR(IF(IF(H14=1,E14,-E14)>0,1,IF(IF(H14=1,E14,-E14)<0,0,2)),"") -> 1
A15: Economic | B15: COSTS | C15: Labour for sowing_planting | D15: ='Cost-revenue DATS'!$D$3 -> €/ha | E15: ='Cost-revenue DATS'!E13-'Cost-revenue NO DATS'!E13 -> -10.811487 | F15: =E15*100/'Cost-revenue NO DATS'!E13 -> -52.316893 | G15: =IF(H15=1,F15,F15*(-1)) -> 52.316893 | H15: 0 | I15: 1 | K15: 1 | L15: 1 | O15: Cost of labour for soil preparation and sowing: The DATS can help optimize field operations and, therefore, also save on energy inputs | P15: 9 | Q15: =IFERROR(IF(IF(H15=1,E15,-E15)>0,1,IF(IF(H15=1,E15,-E15)<0,0,2)),"") -> 1
A16: Economic | B16: COSTS | C16: Labour for pruning | D16: ='Cost-revenue DATS'!$D$3 -> €/ha | E16: ='Cost-revenue DATS'!E14-'Cost-revenue NO DATS'!E14 -> -0.23475244 | F16: =E16*100/'Cost-revenue NO DATS'!E14 -> -4.5515015 | G16: =IF(H16=1,F16,F16*(-1)) -> 4.5515015 | H16: 0 | P16: 9 | Q16: =IFERROR(IF(IF(H16=1,E16,-E16)>0,1,IF(IF(H16=1,E16,-E16)<0,0,2)),"") -> 1
A17: Economic | B17: COSTS | C17: Labour for field visits | D17: ='Cost-revenue DATS'!$D$3 -> €/ha | E17: ='Cost-revenue DATS'!E15-'Cost-revenue NO DATS'!E15 -> -5.2303152 | F17: =E17*100/'Cost-revenue NO DATS'!E15 -> -38.252657 | G17: =IF(H17=1,F17,F17*(-1)) -> 38.252657 | H17: 0 | I17: 1 | K17: 1 | L17: 1 | O17: Cost of labour for field visits: Thanks to the ability to monitor and manage the farm remotely, the DATS allows for more efficient field visits | P17: 9 | Q17: =IFERROR(IF(IF(H17=1,E17,-E17)>0,1,IF(IF(H17=1,E17,-E17)<0,0,2)),"") -> 1
A18: Economic | B18: COSTS | C18: Labour for greenhouse management | D18: ='Cost-revenue DATS'!$D$3 -> €/ha | E18: ='Cost-revenue DATS'!E16-'Cost-revenue NO DATS'!E16 -> 0 | F18: =E18*100/'Cost-revenue NO DATS'!E16 -> #DIV/0! | G18: =IF(H18=1,F18,F18*(-1)) -> #DIV/0! | H18: 0 | P18: 9 | Q18: =IFERROR(IF(IF(H18=1,E18,-E18)>0,1,IF(IF(H18=1,E18,-E18)<0,0,2)),"") -> 2
A19: Economic | B19: COSTS | C19: Labour for tracking the quantity of grain available in the silo | D19: ='Cost-revenue DATS'!$D$3 -> €/ha | E19: ='Cost-revenue DATS'!E17-'Cost-revenue NO DATS'!E17 -> #DIV/0! | F19: =E19*100/'Cost-revenue NO DATS'!E17 -> #DIV/0! | G19: =IF(H19=1,F19,F19*(-1)) -> #DIV/0! | H19: 0 | P19: 9 | Q19: =IFERROR(IF(IF(H19=1,E19,-E19)>0,1,IF(IF(H19=1,E19,-E19)<0,0,2)),"")
A20: Economic | B20: COSTS | C20: Labour for assessing grain quality | D20: ='Cost-revenue DATS'!$D$3 -> €/ha | E20: ='Cost-revenue DATS'!E18-'Cost-revenue NO DATS'!E18 -> 0 | F20: =E20*100/'Cost-revenue NO DATS'!E18 -> #DIV/0! | G20: =IF(H20=1,F20,F20*(-1)) -> #DIV/0! | H20: 0 | P20: 9 | Q20: =IFERROR(IF(IF(H20=1,E20,-E20)>0,1,IF(IF(H20=1,E20,-E20)<0,0,2)),"") -> 2
A21: Economic | B21: COSTS | C21: Labour for controlling purchase and sale prices and quantities | D21: ='Cost-revenue DATS'!$D$3 -> €/ha | E21: ='Cost-revenue DATS'!E19-'Cost-revenue NO DATS'!E19 -> 0 | F21: =E21*100/'Cost-revenue NO DATS'!E19 -> #DIV/0! | G21: =IF(H21=1,F21,F21*(-1)) -> #DIV/0! | H21: 0 | P21: 9 | Q21: =IFERROR(IF(IF(H21=1,E21,-E21)>0,1,IF(IF(H21=1,E21,-E21)<0,0,2)),"") -> 2
A22: Economic | B22: COSTS | C22: Labour for organise logistics | D22: ='Cost-revenue DATS'!$D$3 -> €/ha | E22: ='Cost-revenue DATS'!E20-'Cost-revenue NO DATS'!E20 -> 0 | F22: =E22*100/'Cost-revenue NO DATS'!E20 -> #DIV/0! | G22: =IF(H22=1,F22,F22*(-1)) -> #DIV/0! | H22: 0 | P22: 9 | Q22: =IFERROR(IF(IF(H22=1,E22,-E22)>0,1,IF(IF(H22=1,E22,-E22)<0,0,2)),"") -> 2
A23: Economic | B23: COSTS | C23: Labour for cleaning | D23: ='Cost-revenue DATS'!$D$3 -> €/ha | E23: ='Cost-revenue DATS'!E21-'Cost-revenue NO DATS'!E21 -> 0 | F23: =E23*100/'Cost-revenue NO DATS'!E21 -> #DIV/0! | G23: =IF(H23=1,F23,F23*(-1)) -> #DIV/0! | H23: 0 | P23: 9 | Q23: =IFERROR(IF(IF(H23=1,E23,-E23)>0,1,IF(IF(H23=1,E23,-E23)<0,0,2)),"") -> 2
A24: Economic | B24: COSTS | C24: Labour for stable visits | D24: ='Cost-revenue DATS'!$D$3 -> €/ha | E24: ='Cost-revenue DATS'!E22-'Cost-revenue NO DATS'!E22 -> 0 | F24: =E24*100/'Cost-revenue NO DATS'!E22 -> #DIV/0! | G24: =IF(H24=1,F24,F24*(-1)) -> #DIV/0! | H24: 0 | P24: 9 | Q24: =IFERROR(IF(IF(H24=1,E24,-E24)>0,1,IF(IF(H24=1,E24,-E24)<0,0,2)),"") -> 2
A25: Economic | B25: COSTS | C25: Labour for heat detection | D25: ='Cost-revenue DATS'!$D$3 -> €/ha | E25: ='Cost-revenue DATS'!E23-'Cost-revenue NO DATS'!E23 -> 0 | F25: =E25*100/'Cost-revenue NO DATS'!E23 -> #DIV/0! | G25: =IF(H25=1,F25,F25*(-1)) -> #DIV/0! | H25: 0 | P25: 9 | Q25: =IFERROR(IF(IF(H25=1,E25,-E25)>0,1,IF(IF(H25=1,E25,-E25)<0,0,2)),"") -> 2
A26: Economic | B26: COSTS | C26: Labour for calving detection | D26: ='Cost-revenue DATS'!$D$3 -> €/ha | E26: ='Cost-revenue DATS'!E24-'Cost-revenue NO DATS'!E24 -> 0 | F26: =E26*100/'Cost-revenue NO DATS'!E24 -> #DIV/0! | G26: =IF(H26=1,F26,F26*(-1)) -> #DIV/0! | H26: 0 | P26: 9 | Q26: =IFERROR(IF(IF(H26=1,E26,-E26)>0,1,IF(IF(H26=1,E26,-E26)<0,0,2)),"") -> 2
A27: Economic | B27: COSTS | C27: Labour for pigsty management | D27: ='Cost-revenue DATS'!$D$3 -> €/ha | E27: ='Cost-revenue DATS'!E25-'Cost-revenue NO DATS'!E25 -> 0 | F27: =E27*100/'Cost-revenue NO DATS'!E25 -> #DIV/0! | G27: =IF(H27=1,F27,F27*(-1)) -> #DIV/0! | H27: 0 | P27: 9 | Q27: =IFERROR(IF(IF(H27=1,E27,-E27)>0,1,IF(IF(H27=1,E27,-E27)<0,0,2)),"") -> 2
A28: Economic | B28: COSTS | C28: Labour for milking | D28: ='Cost-revenue DATS'!$D$3 -> €/ha | E28: ='Cost-revenue DATS'!E26-'Cost-revenue NO DATS'!E26 -> 0 | F28: =E28*100/'Cost-revenue NO DATS'!E26 -> #DIV/0! | G28: =IF(H28=1,F28,F28*(-1)) -> #DIV/0! | H28: 0 | P28: 9 | Q28: =IFERROR(IF(IF(H28=1,E28,-E28)>0,1,IF(IF(H28=1,E28,-E28)<0,0,2)),"") -> 2
A29: Economic | B29: COSTS | C29: Labour for (milk) quality assessment | D29: ='Cost-revenue DATS'!$D$3 -> €/ha | E29: ='Cost-revenue DATS'!E27-'Cost-revenue NO DATS'!E27 -> 0 | F29: =E29*100/'Cost-revenue NO DATS'!E27 -> #DIV/0! | G29: =IF(H29=1,F29,F29*(-1)) -> #DIV/0! | H29: 0 | P29: 9 | Q29: =IFERROR(IF(IF(H29=1,E29,-E29)>0,1,IF(IF(H29=1,E29,-E29)<0,0,2)),"") -> 2
A30: Economic | B30: COSTS | C30: Labour for feeding | D30: ='Cost-revenue DATS'!$D$3 -> €/ha | E30: ='Cost-revenue DATS'!E28-'Cost-revenue NO DATS'!E28 -> 0 | F30: =E30*100/'Cost-revenue NO DATS'!E28 -> #DIV/0! | G30: =IF(H30=1,F30,F30*(-1)) -> #DIV/0! | H30: 0 | P30: 9 | Q30: =IFERROR(IF(IF(H30=1,E30,-E30)>0,1,IF(IF(H30=1,E30,-E30)<0,0,2)),"") -> 2
A31: Economic | B31: COSTS | C31: Labour for beehives visits | D31: €/beehive | E31: ='Cost-revenue DATS'!E29-'Cost-revenue NO DATS'!E29 -> #DIV/0! | F31: =E31*100/'Cost-revenue NO DATS'!E29 -> #DIV/0! | G31: =IF(H31=1,F31,F31*(-1)) -> #DIV/0! | H31: 0 | P31: 9 | Q31: =IFERROR(IF(IF(H31=1,E31,-E31)>0,1,IF(IF(H31=1,E31,-E31)<0,0,2)),"")
A32: Economic | B32: COSTS | C32: Labour for sampling of oysters | D32: €/piece | E32: ='Cost-revenue DATS'!E30-'Cost-revenue NO DATS'!E30 -> #DIV/0! | F32: =E32*100/'Cost-revenue NO DATS'!E30 -> #DIV/0! | G32: =IF(H32=1,F32,F32*(-1)) -> #DIV/0! | H32: 0 | P32: 9 | Q32: =IFERROR(IF(IF(H32=1,E32,-E32)>0,1,IF(IF(H32=1,E32,-E32)<0,0,2)),"")
A33: Economic | B33: COSTS | C33: Labour for transporting oysters to the laboratory | D33: €/piece | E33: ='Cost-revenue DATS'!E31-'Cost-revenue NO DATS'!E31 -> #DIV/0! | F33: =E33*100/'Cost-revenue NO DATS'!E31 -> #DIV/0! | G33: =IF(H33=1,F33,F33*(-1)) -> #DIV/0! | H33: 0 | P33: 9 | Q33: =IFERROR(IF(IF(H33=1,E33,-E33)>0,1,IF(IF(H33=1,E33,-E33)<0,0,2)),"")
A34: Economic | B34: COSTS | C34: Labour for harvesting | D34: ='Cost-revenue DATS'!$D$3 -> €/ha | E34: ='Cost-revenue DATS'!E32-'Cost-revenue NO DATS'!E32 -> -16.203932 | F34: =E34*100/'Cost-revenue NO DATS'!E32 -> -52.303194 | G34: =IF(H34=1,F34,F34*(-1)) -> 52.303194 | H34: 0 | P34: 9 | Q34: =IFERROR(IF(IF(H34=1,E34,-E34)>0,1,IF(IF(H34=1,E34,-E34)<0,0,2)),"") -> 1
A35: Economic | B35: COSTS | C35: Labour for storage | D35: ='Cost-revenue DATS'!$D$3 -> €/ha | E35: ='Cost-revenue DATS'!E33-'Cost-revenue NO DATS'!E33 -> 0 | F35: =E35*100/'Cost-revenue NO DATS'!E33 -> #DIV/0! | G35: =IF(H35=1,F35,F35*(-1)) -> #DIV/0! | H35: 0 | P35: 9 | Q35: =IFERROR(IF(IF(H35=1,E35,-E35)>0,1,IF(IF(H35=1,E35,-E35)<0,0,2)),"") -> 2
A36: Economic | B36: COSTS | C36: Labour for administrative activities, data collection, etc. | D36: ='Cost-revenue DATS'!$D$3 -> €/ha | E36: ='Cost-revenue DATS'!E34-'Cost-revenue NO DATS'!E34 -> -5.2303152 | F36: =E36*100/'Cost-revenue NO DATS'!E34 -> -38.252657 | G36: =IF(H36=1,F36,F36*(-1)) -> 38.252657 | H36: 0 | I36: 1 | K36: 1 | L36: 1 | O36: Cost of labour for administrative activities and data management: The DATSs also assist with administrative tasks and the management of data and information flows | P36: 9 | Q36: =IFERROR(IF(IF(H36=1,E36,-E36)>0,1,IF(IF(H36=1,E36,-E36)<0,0,2)),"") -> 1
A37: Economic | B37: COSTS | C37: Sum of costs of labour | D37: ='Cost-revenue DATS'!D35 -> €/ha | E37: =SUMIF(I12:I36,1,E12:E36) -> -27.856904 | F37: =E37*100/'Cost-revenue NO DATS'!E35 -> -5.1016381 | G37: =IF(H37=1,F37,F37*(-1)) -> 5.1016381 | H37: 0 | I37: 1 | L37: 1 | Q37: =IFERROR(IF(IF(H37=1,E37,-E37)>0,1,IF(IF(H37=1,E37,-E37)<0,0,2)),"") -> 1
A38: Economic | B38: COSTS | C38: Sum of costs | D38: ='Cost-revenue DATS'!D36 -> €/ha | E38: =SUMIF(I5:I36,1,E5:E36) -> -41.752788 | F38: =E38*100/'Cost-revenue NO DATS'!E35 -> -7.6464927 | G38: =IF(H38=1,F38,F38*(-1)) -> 7.6464927 | H38: 0 | I38: 1 | J38: 1 | L38: 1 | M38: SAVED COSTS | N38: due to both better management of phytosanitary treatments and more efficient management of field activities. | P38: 10 | Q38: =IFERROR(IF(IF(H38=1,E38,-E38)>0,1,IF(IF(H38=1,E38,-E38)<0,0,2)),"") -> 1
A39: Economic | B39: OUTPUT | C39: Crop revenue | D39: ='Cost-revenue DATS'!$D$3 -> €/ha | E39: ='Cost-revenue DATS'!E41-'Cost-revenue NO DATS'!E41 -> 146.65616 | F39: =E39*100/'Cost-revenue NO DATS'!E41 -> 13.696337 | G39: =IF(H39=1,F39,F39*(-1)) -> 13.696337 | H39: 1 | I39: 1 | J39: 1 | K39: 1 | L39: 1 | M39: INCREASED REVENUES | N39: due to the higher yield observed | O39: Revenues: The increase in revenue is due to an higher yield observed in the farm using DATSs | P39: 10 | Q39: =IFERROR(IF(IF(H39=1,E39,-E39)>0,1,IF(IF(H39=1,E39,-E39)<0,0,2)),"") -> 1
A40: Economic | B40: OUTPUT | C40: Milk revenue | D40: ='Cost-revenue DATS'!$D$3 -> €/ha | E40: ='Cost-revenue DATS'!E42-'Cost-revenue NO DATS'!E42 -> 0 | F40: =E40*100/'Cost-revenue NO DATS'!E42 -> #DIV/0! | G40: =IF(H40=1,F40,F40*(-1)) -> #DIV/0! | H40: 1 | P40: 10 | Q40: =IFERROR(IF(IF(H40=1,E40,-E40)>0,1,IF(IF(H40=1,E40,-E40)<0,0,2)),"") -> 2
A41: Economic | B41: OUTPUT | C41: Meat revenue | D41: ='Cost-revenue DATS'!$D$3 -> €/ha | E41: ='Cost-revenue DATS'!E43-'Cost-revenue NO DATS'!E43 -> 0 | F41: =E41*100/'Cost-revenue NO DATS'!E43 -> #DIV/0! | G41: =IF(H41=1,F41,F41*(-1)) -> #DIV/0! | H41: 1 | P41: 10 | Q41: =IFERROR(IF(IF(H41=1,E41,-E41)>0,1,IF(IF(H41=1,E41,-E41)<0,0,2)),"") -> 2
A42: Economic | B42: OUTPUT | C42: Oyster revenue | D42: ='Cost-revenue DATS'!$D$3 -> €/ha | E42: ='Cost-revenue DATS'!E44-'Cost-revenue NO DATS'!E44 -> #DIV/0! | F42: =E42*100/'Cost-revenue NO DATS'!E44 -> #DIV/0! | G42: =IF(H42=1,F42,F42*(-1)) -> #DIV/0! | H42: 1 | P42: 10 | Q42: =IFERROR(IF(IF(H42=1,E42,-E42)>0,1,IF(IF(H42=1,E42,-E42)<0,0,2)),"")
A43: Economic | B43: OUTPUT | C43: Honey revenue | D43: ='Cost-revenue DATS'!$D$3 -> €/ha | E43: ='Cost-revenue DATS'!E45-'Cost-revenue NO DATS'!E45 -> #DIV/0! | F43: =E43*100/'Cost-revenue NO DATS'!E45 -> #DIV/0! | G43: =IF(H43=1,F43,F43*(-1)) -> #DIV/0! | H43: 1 | P43: 10 | Q43: =IFERROR(IF(IF(H43=1,E43,-E43)>0,1,IF(IF(H43=1,E43,-E43)<0,0,2)),"")
A44: Economic | B44: OUTPUT | C44: Silos revenue | D44: ='Cost-revenue DATS'!$D$3 -> €/ha | E44: ='Cost-revenue DATS'!E46-'Cost-revenue NO DATS'!E46 -> 0 | F44: =E44*100/'Cost-revenue NO DATS'!E46 -> #DIV/0! | G44: =IF(H44=1,F44,F44*(-1)) -> #DIV/0! | H44: 1 | P44: 10 | Q44: =IFERROR(IF(IF(H44=1,E44,-E44)>0,1,IF(IF(H44=1,E44,-E44)<0,0,2)),"") -> 2
A45: Economic | B45: CBA | C45: BENEFIT | D45: =D38 -> €/ha | E45: =IF(I39=1,E39-E38,-E38) -> 188.40895 | H45: 1 | Q45: =IFERROR(IF(IF(H45=1,E45,-E45)>0,1,IF(IF(H45=1,E45,-E45)<0,0,2)),"") -> 1
A46: Economic | B46: CBA | C46: NET BENEFIT | D46: =D45 -> €/ha | E46: =E45-E3 -> 186.62721 | H46: 1 | I46: 1 | J46: 1 | K46: 1 | L46: 1 | M46: NET BENEFIT | N46: due to an increase in yields and a general decrease in costs | O46: Net Benefit: Despite the savings in terms of NPK thanks to the DSS, considering the lower yields in the plots with DATSs, the balance is negative. | P46: 10 | Q46: =IFERROR(IF(IF(H46=1,E46,-E46)>0,1,IF(IF(H46=1,E46,-E46)<0,0,2)),"") -> 1 | R46: 1
A47: Economic | B47: CBA | C47: PAYBACK PERIOD | D47: years | E47: =E4/E46 -> 0.42004583 | J47: 1 | M47: PAYBACK PERIOD | N47: is less than 1 year | P47: 11 | Q47: 1
A48: Economic | B48: CBA | C48: NPV | D48: =D46 -> €/ha | Q48: 2
A49: Economic | B49: CBA | C49: ROI | D49: =D48 -> €/ha | Q49: 2
A50: Economic | B50: PRODUCTIVITY | C50: Land Productivity | D50: t / ha | E50: ='sust. impact KPIs DATS'!E3-'sust. impact KPIs NO DATS'!E3 -> 0.76383416 | F50: =E50*100/'sust. impact KPIs NO DATS'!E3 -> 13.696337 | G50: =IF(H50=1,F50,F50*(-1)) -> 13.696337 | H50: 1 | I50: 1 | L50: 1 | Q50: =IFERROR(IF(IF(H50=1,E50,-E50)>0,1,IF(IF(H50=1,E50,-E50)<0,0,2)),"") -> 1
A51: Economic | B51: PRODUCTIVITY | C51: Labour productivity (arable and horticulture) | D51: ='sust. impact KPIs DATS'!D4 -> t / h | E51: ='sust. impact KPIs DATS'!E4-'sust. impact KPIs NO DATS'!E4 -> 0.2669467 | F51: =E51*100/'sust. impact KPIs NO DATS'!E4 -> 79.968948 | G51: =IF(H51=1,F51,F51*(-1)) -> 79.968948 | H51: 1 | I51: 1 | L51: 1 | Q51: =IFERROR(IF(IF(H51=1,E51,-E51)>0,1,IF(IF(H51=1,E51,-E51)<0,0,2)),"") -> 1
A52: Economic | B52: PRODUCTIVITY | C52: Labour productivity (dairy livestock) | D52: ='sust. impact KPIs DATS'!D5 -> l milk/h | E52: ='sust. impact KPIs DATS'!E5-'sust. impact KPIs NO DATS'!E5 -> 0 | F52: =E52*100/'sust. impact KPIs NO DATS'!E5 -> #DIV/0! | G52: =IF(H52=1,F52,F52*(-1)) -> #DIV/0! | H52: 1 | Q52: =IFERROR(IF(IF(H52=1,E52,-E52)>0,1,IF(IF(H52=1,E52,-E52)<0,0,2)),"") -> 2
A53: Economic | B53: PRODUCTIVITY | C53: Labour productivity (meat livestock) | D53: ='sust. impact KPIs DATS'!D6 -> kg meat/h | E53: ='sust. impact KPIs DATS'!E6-'sust. impact KPIs NO DATS'!E6 -> 0 | F53: =E53*100/'sust. impact KPIs NO DATS'!E6 -> #DIV/0! | G53: =IF(H53=1,F53,F53*(-1)) -> #DIV/0! | H53: 1 | Q53: =IFERROR(IF(IF(H53=1,E53,-E53)>0,1,IF(IF(H53=1,E53,-E53)<0,0,2)),"") -> 2
A54: Economic | B54: PRODUCTIVITY | C54: Labour productivity (aquaculture) | D54: ='sust. impact KPIs DATS'!D7 -> pieces/h | E54: ='sust. impact KPIs DATS'!E7-'sust. impact KPIs NO DATS'!E7 -> 0 | F54: =E54*100/'sust. impact KPIs NO DATS'!E7 -> #DIV/0! | G54: =IF(H54=1,F54,F54*(-1)) -> #DIV/0! | H54: 1 | Q54: =IFERROR(IF(IF(H54=1,E54,-E54)>0,1,IF(IF(H54=1,E54,-E54)<0,0,2)),"") -> 2
A55: Economic | B55: PRODUCTIVITY | C55: Labour productivity (apiculture) | D55: ='sust. impact KPIs DATS'!D8 -> kg honey/h | E55: ='sust. impact KPIs DATS'!E8-'sust. impact KPIs NO DATS'!E8 -> 0 | F55: =E55*100/'sust. impact KPIs NO DATS'!E8 -> #DIV/0! | G55: =IF(H55=1,F55,F55*(-1)) -> #DIV/0! | H55: 1 | Q55: =IFERROR(IF(IF(H55=1,E55,-E55)>0,1,IF(IF(H55=1,E55,-E55)<0,0,2)),"") -> 2
A56: Economic | B56: PRODUCTIVITY | C56: Milk productivity | D56: l/cow/day | E56: ='sust. impact KPIs DATS'!E10-'sust. impact KPIs NO DATS'!E10 -> #DIV/0! | F56: =E56*100/'sust. impact KPIs NO DATS'!E10 -> #DIV/0! | G56: =IF(H56=1,F56,F56*(-1)) -> #DIV/0! | H56: 1 | Q56: =IFERROR(IF(IF(H56=1,E56,-E56)>0,1,IF(IF(H56=1,E56,-E56)<0,0,2)),"")
A57: Economic | B57: PRODUCTIVITY | C57: Meat productivity | D57: kg/cow/day | E57: ='sust. impact KPIs DATS'!E11-'sust. impact KPIs NO DATS'!E11 -> #DIV/0! | F57: =E57*100/'sust. impact KPIs NO DATS'!E11 -> #DIV/0! | G57: =IF(H57=1,F57,F57*(-1)) -> #DIV/0! | H57: 1 | Q57: =IFERROR(IF(IF(H57=1,E57,-E57)>0,1,IF(IF(H57=1,E57,-E57)<0,0,2)),"")
A58: Economic | B58: PRODUCTIVITY | C58: Bees productivity | D58: kg/beehives | E58: ='sust. impact KPIs DATS'!E12-'sust. impact KPIs NO DATS'!E12 -> #DIV/0! | F58: =E58*100/'sust. impact KPIs NO DATS'!E12 -> #DIV/0! | G58: =IF(H58=1,F58,F58*(-1)) -> #DIV/0! | H58: 1 | Q58: =IFERROR(IF(IF(H58=1,E58,-E58)>0,1,IF(IF(H58=1,E58,-E58)<0,0,2)),"")
A59: Economic | B59: PRODUCTIVITY | C59: Oyster productivity | D59: number of oysters/m2 | E59: ='sust. impact KPIs DATS'!E13-'sust. impact KPIs NO DATS'!E13 -> #DIV/0! | F59: =E59*100/'sust. impact KPIs NO DATS'!E13 -> #DIV/0! | G59: =IF(H59=1,F59,F59*(-1)) -> #DIV/0! | H59: 1 | Q59: =IFERROR(IF(IF(H59=1,E59,-E59)>0,1,IF(IF(H59=1,E59,-E59)<0,0,2)),"")
B60: PRODUCTIVITY | C60: Rate of time for quality analysis | D60: % | E60: ='sust. impact KPIs DATS'!E17-'sust. impact KPIs NO DATS'!E17 -> #DIV/0! | F60: =E60*100/'sust. impact KPIs NO DATS'!E17 -> #DIV/0! | G60: =IF(H60=1,F60,F60*(-1)) -> #DIV/0! | H60: 0 | Q60: =IFERROR(IF(IF(H60=1,E60,-E60)>0,1,IF(IF(H60=1,E60,-E60)<0,0,2)),"")
A61: Economic | B61: PRODUCTIVITY | C61: Rate of on-time fulfilled orders | D61: % | E61: ='sust. impact KPIs DATS'!E18-'sust. impact KPIs NO DATS'!E18 -> #DIV/0! | F61: =E61*100/'sust. impact KPIs NO DATS'!E18 -> #DIV/0! | G61: =IF(H61=1,F61,F61*(-1)) -> #DIV/0! | H61: 1 | Q61: =IFERROR(IF(IF(H61=1,E61,-E61)>0,1,IF(IF(H61=1,E61,-E61)<0,0,2)),"")
A62: Economic | B62: PRODUCTIVITY | C62: Number of wrong orders | D62: n | E62: ='sust. impact KPIs DATS'!E19-'sust. impact KPIs NO DATS'!E19 -> 0 | F62: =E62*100/'sust. impact KPIs NO DATS'!E19 -> #DIV/0! | G62: =IF(H62=1,F62,F62*(-1)) -> #DIV/0! | H62: 0 | Q62: =IFERROR(IF(IF(H62=1,E62,-E62)>0,1,IF(IF(H62=1,E62,-E62)<0,0,2)),"") -> 2
B63: PRODUCTIVITY | C63: Intrinsic product quality | E63: ='sust. impact KPIs DATS'!E23-'sust. impact KPIs NO DATS'!E23 -> 0 | F63: =E63*100/'sust. impact KPIs NO DATS'!E23 -> #DIV/0! | G63: =IF(H63=1,F63,F63*(-1)) -> #DIV/0! | H63: 1 | Q63: =IFERROR(IF(IF(H63=1,E63,-E63)>0,1,IF(IF(H63=1,E63,-E63)<0,0,2)),"") -> 2
A64: Economic | B64: PRODUCTIVITY | C64: Protein % DRY MATTER | D64: % | E64: ='sust. impact KPIs DATS'!E24-'sust. impact KPIs NO DATS'!E24 -> 0.5 | F64: =E64*100/'sust. impact KPIs NO DATS'!E24 -> 4.1666667 | G64: =IF(H64=1,F64,F64*(-1)) -> 4.1666667 | H64: 1 | I64: 1 | L64: 1 | Q64: =IFERROR(IF(IF(H64=1,E64,-E64)>0,1,IF(IF(H64=1,E64,-E64)<0,0,2)),"") -> 1
A65: Economic | B65: PRODUCTIVITY | C65: Humidity | D65: % | E65: ='sust. impact KPIs DATS'!E25-'sust. impact KPIs NO DATS'!E25 -> 0.6 | F65: =E65*100/'sust. impact KPIs NO DATS'!E25 -> 4.4444444 | G65: =IF(H65=1,F65,F65*(-1)) -> -4.4444444 | H65: 0 | Q65: =IFERROR(IF(IF(H65=1,E65,-E65)>0,1,IF(IF(H65=1,E65,-E65)<0,0,2)),"") -> 0
A66: Economic | B66: PRODUCTIVITY | C66: Test Weight | D66: kg/hl | E66: ='sust. impact KPIs DATS'!E26-'sust. impact KPIs NO DATS'!E26 -> 5.1 | F66: =E66*100/'sust. impact KPIs NO DATS'!E26 -> 7.1328671 | G66: =IF(H66=1,F66,F66*(-1)) -> 7.1328671 | H66: 1 | I66: 1 | L66: 1 | Q66: =IFERROR(IF(IF(H66=1,E66,-E66)>0,1,IF(IF(H66=1,E66,-E66)<0,0,2)),"") -> 1
A67: Environmental | B67: INPUTS | C67: Nitrogen applied | D67: kg/ha | E67: ='sust. impact KPIs DATS'!E30-'sust. impact KPIs NO DATS'!E30 -> 42.2865 | F67: =E67*100/'sust. impact KPIs NO DATS'!E30 -> 62.357053 | G67: =IF(H67=1,F67,F67*(-1)) -> -62.357053 | H67: 0 | I67: 1 | L67: 1 | Q67: =IFERROR(IF(IF(H67=1,E67,-E67)>0,1,IF(IF(H67=1,E67,-E67)<0,0,2)),"") -> 0
A68: Environmental | B68: INPUTS | C68: Nitrogen use efficiency | D68: % | E68: =ABS('sust. impact KPIs NO DATS'!E31-100)-ABS('sust. impact KPIs DATS'!E31-100) -> 49.789435 | G68: =IF(H68=1,E68,E68*(-1)) -> 49.789435 | H68: 1 | I68: 1 | L68: 1 | Q68: =IFERROR(IF(IF(H68=1,E68,-E68)>0,1,IF(IF(H68=1,E68,-E68)<0,0,2)),"") -> 1
A69: Environmental | B69: INPUTS | C69: Phosphorus applied | D69: kg/ha | E69: ='sust. impact KPIs DATS'!E32-'sust. impact KPIs NO DATS'!E32 -> -16.3 | F69: =E69*100/'sust. impact KPIs NO DATS'!E32 -> -34.315789 | G69: =IF(H69=1,F69,F69*(-1)) -> 34.315789 | H69: 0 | I69: 1 | L69: 1 | Q69: =IFERROR(IF(IF(H69=1,E69,-E69)>0,1,IF(IF(H69=1,E69,-E69)<0,0,2)),"") -> 1
A70: Environmental | B70: INPUTS | C70: Phosphorus use efficiency | D70: % | E70: =ABS('sust. impact KPIs NO DATS'!E33-100)-ABS('sust. impact KPIs DATS'!E33-100) -> -62.923411 | G70: =IF(H70=1,E70,E70*(-1)) -> -62.923411 | H70: 1 | I70: 1 | L70: 1 | Q70: =IFERROR(IF(IF(H70=1,E70,-E70)>0,1,IF(IF(H70=1,E70,-E70)<0,0,2)),"") -> 0
A71: Environmental | B71: INPUTS | C71: Potassium applied | D71: kg/ha | E71: ='sust. impact KPIs DATS'!E34-'sust. impact KPIs NO DATS'!E34 -> -0.062 | F71: =E71*100/'sust. impact KPIs NO DATS'!E34 -> -100 | G71: =IF(H71=1,F71,F71*(-1)) -> 100 | H71: 0 | Q71: =IFERROR(IF(IF(H71=1,E71,-E71)>0,1,IF(IF(H71=1,E71,-E71)<0,0,2)),"") -> 1
A72: Environmental | B72: INPUTS | C72: Potassium use efficiency | D72: % | E72: =ABS('sust. impact KPIs NO DATS'!E35-100)-ABS('sust. impact KPIs DATS'!E35-100) -> #DIV/0! | G72: =IF(H72=1,E72,E72*(-1)) -> #DIV/0! | H72: 1 | Q72: =IFERROR(IF(IF(H72=1,E72,-E72)>0,1,IF(IF(H72=1,E72,-E72)<0,0,2)),"")
A73: Environmental | B73: INPUTS | C73: pesticides, herbicides and fungicides use | D73: kg/ha | E73: ='sust. impact KPIs DATS'!E36-'sust. impact KPIs NO DATS'!E36 -> -3.08 | F73: =E73*100/'sust. impact KPIs NO DATS'!E36 -> -57.249071 | G73: =IF(H73=1,F73,F73*(-1)) -> 57.249071 | H73: 0 | I73: 1 | L73: 1 | Q73: =IFERROR(IF(IF(H73=1,E73,-E73)>0,1,IF(IF(H73=1,E73,-E73)<0,0,2)),"") -> 1
A74: Environmental | B74: WATER | C74: Water consumption | D74: ='sust. impact KPIs NO DATS'!D37 | E74: ='sust. impact KPIs DATS'!E37-'sust. impact KPIs NO DATS'!E37 -> -0.39718605 | F74: =E74*100/'sust. impact KPIs NO DATS'!E37 -> -49.767891 | G74: =IF(H74=1,F74,F74*(-1)) -> 49.767891 | H74: 0 | Q74: =IFERROR(IF(IF(H74=1,E74,-E74)>0,1,IF(IF(H74=1,E74,-E74)<0,0,2)),"") -> 1
A75: Environmental | B75: WATER | C75: Aquaculture water productivity | D75: t/m2 | E75: ='sust. impact KPIs DATS'!E38-'sust. impact KPIs NO DATS'!E38 -> 0 | F75: =E75*100/'sust. impact KPIs NO DATS'!E38 -> #DIV/0! | G75: =IF(H75=1,F75,F75*(-1)) -> #DIV/0! | H75: 0 | Q75: =IFERROR(IF(IF(H75=1,E75,-E75)>0,1,IF(IF(H75=1,E75,-E75)<0,0,2)),"") -> 2
A76: Environmental | B76: WATER | C76: Irrigation water productivity | D76: kg/m3 | E76: ='sust. impact KPIs DATS'!E39-'sust. impact KPIs NO DATS'!E39 -> 8828.7149 | F76: =E76*100/'sust. impact KPIs NO DATS'!E39 -> 126.34195 | G76: =IF(H76=1,F76,F76*(-1)) -> 126.34195 | H76: 1 | Q76: =IFERROR(IF(IF(H76=1,E76,-E76)>0,1,IF(IF(H76=1,E76,-E76)<0,0,2)),"") -> 1
A77: Environmental | B77: ENERGY | C77: Electricity consumption | D77: ='sust. impact KPIs NO DATS'!D40 -> kWh/ha | E77: ='sust. impact KPIs DATS'!E40-'sust. impact KPIs NO DATS'!E40 -> -2.0865706 | F77: =E77*100/'sust. impact KPIs NO DATS'!E40 -> -40.297742 | G77: =IF(H77=1,F77,F77*(-1)) -> 40.297742 | H77: 0 | I77: 1 | L77: 1 | Q77: =IFERROR(IF(IF(H77=1,E77,-E77)>0,1,IF(IF(H77=1,E77,-E77)<0,0,2)),"") -> 1
A78: Social | B78: ANIMAL | C78: Ease of movement | D78: d/y | E78: ='sust. impact KPIs DATS'!E41-'sust. impact KPIs NO DATS'!E41 -> #DIV/0! | F78: =E78*100/'sust. impact KPIs NO DATS'!E41 -> #DIV/0! | G78: =IF(H78=1,F78,F78*(-1)) -> #DIV/0! | H78: 1 | Q78: =IFERROR(IF(IF(H78=1,E78,-E78)>0,1,IF(IF(H78=1,E78,-E78)<0,0,2)),"")
A79: Social | B79: ANIMAL | C79: Mortality rate (livestock) | D79: % | E79: ='sust. impact KPIs DATS'!E42-'sust. impact KPIs NO DATS'!E42 -> #DIV/0! | F79: =E79*100/'sust. impact KPIs NO DATS'!E42 -> #DIV/0! | G79: =IF(H79=1,F79,F79*(-1)) -> #DIV/0! | H79: 0 | Q79: =IFERROR(IF(IF(H79=1,E79,-E79)>0,1,IF(IF(H79=1,E79,-E79)<0,0,2)),"")
A80: Social | B80: ANIMAL | C80: Mortality rate (aquaculture) | D80: % | E80: ='sust. impact KPIs DATS'!E43-'sust. impact KPIs NO DATS'!E43 -> #DIV/0! | F80: =E80*100/'sust. impact KPIs NO DATS'!E43 -> #DIV/0! | G80: =IF(H80=1,F80,F80*(-1)) -> #DIV/0! | H80: 0 | Q80: =IFERROR(IF(IF(H80=1,E80,-E80)>0,1,IF(IF(H80=1,E80,-E80)<0,0,2)),"")
A81: Social | B81: ANIMAL | C81: Mortality rate (apiculture) | D81: % | E81: ='sust. impact KPIs DATS'!E44-'sust. impact KPIs NO DATS'!E44 -> #DIV/0! | F81: =E81*100/'sust. impact KPIs NO DATS'!E44 -> #DIV/0! | G81: =IF(H81=1,F81,F81*(-1)) -> #DIV/0! | H81: 0 | Q81: =IFERROR(IF(IF(H81=1,E81,-E81)>0,1,IF(IF(H81=1,E81,-E81)<0,0,2)),"")
A82: Social | B82: ANIMAL | C82: Mortality rate at birth | D82: % | E82: ='sust. impact KPIs DATS'!E45-'sust. impact KPIs NO DATS'!E45 -> #DIV/0! | F82: =E82*100/'sust. impact KPIs NO DATS'!E45 -> #DIV/0! | G82: =IF(H82=1,F82,F82*(-1)) -> #DIV/0! | H82: 0 | Q82: =IFERROR(IF(IF(H82=1,E82,-E82)>0,1,IF(IF(H82=1,E82,-E82)<0,0,2)),"")
A83: Social | B83: ANIMAL | C83: Cows with high SCC | D83: % | E83: ='sust. impact KPIs DATS'!E46-'sust. impact KPIs NO DATS'!E46 -> #DIV/0! | F83: =E83*100/'sust. impact KPIs NO DATS'!E46 -> #DIV/0! | G83: =IF(H83=1,F83,F83*(-1)) -> #DIV/0! | H83: 0 | Q83: =IFERROR(IF(IF(H83=1,E83,-E83)>0,1,IF(IF(H83=1,E83,-E83)<0,0,2)),"")
A84: Environmental | B84: INPUTS | C84: Drugs use in dairy livestock | D84: ='sust. impact KPIs NO DATS'!D47 -> 0 | E84: ='sust. impact KPIs DATS'!E47-'sust. impact KPIs NO DATS'!E47 -> 0 | F84: =E84*100/'sust. impact KPIs NO DATS'!E47 -> #DIV/0! | G84: =IF(H84=1,F84,F84*(-1)) -> #DIV/0! | H84: 0 | Q84: =IFERROR(IF(IF(H84=1,E84,-E84)>0,1,IF(IF(H84=1,E84,-E84)<0,0,2)),"") -> 2
A85: Environmental | B85: INPUTS | C85: Drugs use in meat livestock | D85: ='sust. impact KPIs NO DATS'!D48 -> 0 | E85: ='sust. impact KPIs DATS'!E48-'sust. impact KPIs NO DATS'!E48 -> 0 | F85: =E85*100/'sust. impact KPIs NO DATS'!E48 -> #DIV/0! | G85: =IF(H85=1,F85,F85*(-1)) -> #DIV/0! | H85: 0 | Q85: =IFERROR(IF(IF(H85=1,E85,-E85)>0,1,IF(IF(H85=1,E85,-E85)<0,0,2)),"") -> 2
A86: Environmental | B86: INPUTS | C86: Drugs use in aquaculture | D86: ='sust. impact KPIs NO DATS'!D49 -> g/m2 | E86: ='sust. impact KPIs DATS'!E49-'sust. impact KPIs NO DATS'!E49 -> #REF! | F86: =E86*100/'sust. impact KPIs NO DATS'!E49 -> #REF! | G86: =IF(H86=1,F86,F86*(-1)) -> #REF! | H86: 0 | Q86: =IFERROR(IF(IF(H86=1,E86,-E86)>0,1,IF(IF(H86=1,E86,-E86)<0,0,2)),"")
A87: Environmental | B87: INPUTS | C87: Drugs use in apiculture | D87: ='sust. impact KPIs NO DATS'!D50 -> g/beehive | E87: ='sust. impact KPIs DATS'!E50-'sust. impact KPIs NO DATS'!E50 -> #REF! | F87: =E87*100/'sust. impact KPIs NO DATS'!E50 -> #REF! | G87: =IF(H87=1,F87,F87*(-1)) -> #REF! | H87: 0 | Q87: =IFERROR(IF(IF(H87=1,E87,-E87)>0,1,IF(IF(H87=1,E87,-E87)<0,0,2)),"")
A88: Environmental | B88: GHG EMISSIONS | C88: Fuel GHG emission | D88: ='sust. impact KPIs NO DATS'!D51 -> kg CO2 eq/ha | E88: ='sust. impact KPIs DATS'!E51-'sust. impact KPIs NO DATS'!E51 -> -10.776971 | F88: =E88*100/'sust. impact KPIs NO DATS'!E51 -> -7.5574021 | G88: =IF(H88=1,F88,F88*(-1)) -> 7.5574021 | H88: 0 | I88: 1 | Q88: =IFERROR(IF(IF(H88=1,E88,-E88)>0,1,IF(IF(H88=1,E88,-E88)<0,0,2)),"") -> 1
A89: Environmental | B89: ENERGY | C89: Arable and horticulture fuel consumption | D89: l/ha | E89: ='sust. impact KPIs DATS'!E52-'sust. impact KPIs NO DATS'!E52 -> -4.0512035 | F89: =E89*100/'sust. impact KPIs NO DATS'!E52 -> -7.5574021 | G89: =IF(H89=1,F89,F89*(-1)) -> 7.5574021 | H89: 0 | I89: 1 | L89: 1 | Q89: =IFERROR(IF(IF(H89=1,E89,-E89)>0,1,IF(IF(H89=1,E89,-E89)<0,0,2)),"") -> 1
A90: Environmental | B90: ENERGY | C90: Livestock fuel consumption | D90: ='sust. impact KPIs NO DATS'!D53 -> l/ha | E90: ='sust. impact KPIs DATS'!E53-'sust. impact KPIs NO DATS'!E53 -> #DIV/0! | F90: =E90*100/'sust. impact KPIs NO DATS'!E53 -> #DIV/0! | G90: =IF(H90=1,F90,F90*(-1)) -> #DIV/0! | H90: 0 | Q90: =IFERROR(IF(IF(H90=1,E90,-E90)>0,1,IF(IF(H90=1,E90,-E90)<0,0,2)),"")
A91: Environmental | B91: ENERGY | C91: Aquaculture fuel consumption | D91: l/m2 | E91: ='sust. impact KPIs DATS'!E54-'sust. impact KPIs NO DATS'!E54 -> #DIV/0! | F91: =E91*100/'sust. impact KPIs NO DATS'!E54 -> #DIV/0! | G91: =IF(H91=1,F91,F91*(-1)) -> #DIV/0! | H91: 0 | Q91: =IFERROR(IF(IF(H91=1,E91,-E91)>0,1,IF(IF(H91=1,E91,-E91)<0,0,2)),"")
A92: Environmental | B92: ENERGY | C92: Apiculture fuel consumption | D92: l/beehives | E92: ='sust. impact KPIs DATS'!E55-'sust. impact KPIs NO DATS'!E55 -> #DIV/0! | F92: =E92*100/'sust. impact KPIs NO DATS'!E55 -> #DIV/0! | G92: =IF(H92=1,F92,F92*(-1)) -> #DIV/0! | H92: 0 | Q92: =IFERROR(IF(IF(H92=1,E92,-E92)>0,1,IF(IF(H92=1,E92,-E92)<0,0,2)),"")
A93: Environmental | B93: GHG EMISSIONS | C93: N2O GHG emission | D93: kg Co2e/ha | E93: ='sust. impact KPIs DATS'!E57-'sust. impact KPIs NO DATS'!E57 -> 249.25608 | G93: =IF(H93=1,F93,F93*(-1)) -> 0 | H93: 0 | I93: 1 | Q93: =IFERROR(IF(IF(H93=1,E93,-E93)>0,1,IF(IF(H93=1,E93,-E93)<0,0,2)),"") -> 0
A94: Environmental | B94: GHG EMISSIONS | C94: GHG emissions | D94: ='sust. impact KPIs NO DATS'!D58 -> kg CO2 eq/ha | E94: ='sust. impact KPIs DATS'!E58-'sust. impact KPIs NO DATS'!E58 -> 238.47911 | F94: =E94*100/'sust. impact KPIs NO DATS'!E58 -> 43.973428 | G94: =IF(H94=1,F94,F94*(-1)) -> -43.973428 | H94: 0 | I94: 1 | L94: 1 | Q94: =IFERROR(IF(IF(H94=1,E94,-E94)>0,1,IF(IF(H94=1,E94,-E94)<0,0,2)),"") -> 0
A95: Social | B95: LABOUR | C95: Training hours (for the use of DATs) | D95: h/employee | E95: ='sust. impact KPIs DATS'!E61 -> 4.4444444 | F95: =E95*100/'sust. impact KPIs NO DATS'!E61 -> #DIV/0! | G95: =IF(H95=1,F95,F95*(-1)) -> #DIV/0! | H95: 1 | Q95: =IFERROR(IF(IF(H95=1,E95,-E95)>0,1,IF(IF(H95=1,E95,-E95)<0,0,2)),"") -> 1
A96: Social | B96: LABOUR | C96: Working time | D96: % | E96: ='sust. impact KPIs DATS'!E62-'sust. impact KPIs NO DATS'!E62 -> -3.8690145 | F96: =E96*100/'sust. impact KPIs NO DATS'!E62 -> -33.103867 | G96: =IF(H96=1,F96,F96*(-1)) -> 33.103867 | H96: 0 | I96: 1 | J96: 1 | L96: 1 | M96: DECREASED WORKING TIME | N96: due to an improvment in agronomic management and thanks to the support of the DATS in monitoring the crop remotely | Q96: =IFERROR(IF(IF(H96=1,E96,-E96)>0,1,IF(IF(H96=1,E96,-E96)<0,0,2)),"") -> 1
A97: Social | B97: LABOUR | C97: Frequency rate of occupational injuries | D97: n./hours | E97: ='sust. impact KPIs DATS'!E63-'sust. impact KPIs NO DATS'!E63 -> 0 | G97: =IF(H97=1,F97,F97*(-1)) -> 0 | H97: 0 | Q97: =IFERROR(IF(IF(H97=1,E97,-E97)>0,1,IF(IF(H97=1,E97,-E97)<0,0,2)),"") -> 2
A98: Social | B98: LABOUR | C98: Incidence of occupational injuries | D98: % | E98: ='sust. impact KPIs DATS'!E64-'sust. impact KPIs NO DATS'!E64 -> 0 | G98: =IF(H98=1,F98,F98*(-1)) -> 0 | H98: 0 | Q98: =IFERROR(IF(IF(H98=1,E98,-E98)>0,1,IF(IF(H98=1,E98,-E98)<0,0,2)),"") -> 2
A99: Social | B99: LABOUR | C99: Contribution to local employment | D99: % | E99: ='sust. impact KPIs DATS'!E65-'sust. impact KPIs NO DATS'!E65 -> #DIV/0! | G99: =IF(H99=1,F99,F99*(-1)) -> 0 | H99: 1 | Q99: =IFERROR(IF(IF(H99=1,E99,-E99)>0,1,IF(IF(H99=1,E99,-E99)<0,0,2)),"")
Q100: =IFERROR(IF(IF(H100=1,E100,-E100)>0,1,IF(IF(H100=1,E100,-E100)<0,0,2)),"") -> 2
...

Sheet Icons
A1: Icon number | B1: Icon
A2: 1 | B2: #VALUE!
A3: 2 | B3: #VALUE!
A4: 3 | B4: #VALUE!
A5: 4 | B5: #VALUE!
A6: 5 | B6: #VALUE!
A7: 6 | B7: #VALUE!
A8: 7 | B8: #VALUE!
A9: 8 | B9: #VALUE!
A10: 9 | B10: #VALUE!
A11: 10 | B11: #VALUE!
A12: 11 | B12: #VALUE!
A13: 12 | B13: #VALUE!
A14: 13 | B14: #VALUE!

Sheet Validations
A1: MARKET DATA | B1: WATER | C1: FUEL | D1: ELECTRICITY | E1: PESTICIDES | F1: FERTILIZERS | G1: FERTILIZER TYPE | H1: FEED | J1: Production type | K1: water | L1: Production type | M1: costs | N1: working time | P1: crop | Q1: N content (avg.) | S1: P content (avg.) | U1: K content (avg.) | W1: Production type | X1: Electricity consumption | Y1: Animal | AA1: Production type | AB1: DRUGS | AC1: GHG emissions | AD1: FUEL
A2: €/t | C2: l/ha | D2: kWh/ha | E2: kg/ha | F2: kg/ha | G2: Mineral | H2: kg/100 kg meat | J2: Crop | L2: crop | M2: €/ha | N2: h/ha | P2: Apple | Q2: 0.0007 | R2: Apple | S2: 0.00022 | T2: Apple | U2: 0.0018 | W2: crop | X2: kWh/ha | Y2: Cow | AA2: Crop | AC2: kg CO2 eq/ha | AD2: l/ha
A3: €/kg | C3: l/100 kg meat | D3: kWh/100 kg meat | E3: l/ha | F3: t/ha | G3: Organic | H3: kg/animal | J3: Milk | L3: milk | M3: €/1000 l milk | N3: h/1000 l milk | P3: Bananas | Q3: 0.00166 | R3: Bananas | S3: 0.00036 | T3: Bananas | U3: 0.0043 | W3: greenhouse | X3: kWh/ha | Y3: Pig | AA3: Milk | AB3: g/1000 l milk | AC3: kg CO2 eq/1000 l milk | AD3: l/1000 l milk
A4: €/l | C4: l/animal | D4: kWh/animal | H4: kg/1000 l milk | J4: Meat | L4: meat | M4: €/100 kg meat | N4: h/100 kg meat | P4: Barley | Q4: 0.02 | R4: Barley | S4: 0.0083 | T4: Barley | U4: 0.0066 | W4: milk | X4: kWh/1000 l milk | Y4: Poultry | AA4: Meat | AB4: g/100 kg meat | AC4: kg CO2 eq/100 kg meat | AD4: l/100 kg meat
A5: €/piece | C5: l/1000 l milk | D5: kWh/1000 l milk | J5: Animal | L5: animal | M5: €/animal | N5: h/animal | P5: Blueberries | Q5: 0.0047 | R5: Blueberries | S5: 0.0011 | T5: Blueberries | U5: 0.0048 | W5: meat | X5: kWh/100 kg meat | AA5: Animal | AB5: g/animal | AC5: kg CO2 eq/animal | AD5: l/animal
B6: l/m2 | C6: l/beehive | D6: kWh/beehive | J6: Oyster | L6: oyster | M6: €/piece | N6: h/piece | P6: Corn | Q6: 0.0147 | R6: Corn | S6: 0.0065 | T6: Corn | U6: 0.0042 | W6: animal | X6: kWh/animal | AA6: Oyster | AB6: g/piece | AC6: kg CO2 eq/piece | AD6: l/piece
C7: l/piece | D7: kWh/piece | J7: Honey | L7: honey | M7: €/kg honey | N7: h/kg honey | P7: Corn (silage) | Q7: 0.0043 | R7: Corn (silage) | S7: 0.0014 | T7: Corn (silage) | U7: 0.0033 | W7: oyster | X7: kWh/piece | AA7: Honey | AB7: g/beehive | AC7: kg CO2 eq/kg honey | AD7: l/beehive
J8: Grain (silos) | L8: grain (silos) | M8: €/t | N8: h/t | P8: Cotton | Q8: 0.065 | R8: Cotton | S8: 0.029 | T8: Cotton | U8: 0.039 | W8: honey | X8: kWh/kg honey | AA8: Grain (silos) | AC8: kg CO2 eq/t | AD8: l/t
P9: Grape | Q9: =1.32/1000 -> 0.00132 | R9: Grape | S9: 0.00025 | T9: Grape | U9: 0.00224 | W9: grain (silos) | X9: kWh/t
P10: Olives | Q10: 0.00287 | R10: Olives | S10: 0.00049 | T10: Olives | U10: 0.00442
P11: Onion | Q11: 0.003 | R11: Onion | S11: 0.0012 | T11: Onion | U11: 0.004
P12: Potatoes | Q12: =3.5/1000 -> 0.0035 | R12: Potatoes | S12: =1.3/1000 -> 0.0013 | T12: Potatoes | U12: =5.8/1000 -> 0.0058
P13: Rapeseed | Q13: 0.031 | R13: Rapeseed | S13: 0.02 | T13: Rapeseed | U13: 0.021
P14: Rye | Q14: 0.025 | R14: Rye | S14: 0.0082 | T14: Rye | U14: 0.0055
P15: Strawberries | Q15: 0.0058 | R15: Strawberries | S15: 0.0011 | T15: Strawberries | U15: 0.0081
P16: Tomato | Q16: 0.0032 | R16: Tomato | S16: 0.001 | T16: Tomato | U16: 0.0068
P17: Wheat (T. aestivum) | Q17: 0.0202 | R17: Wheat (T. aestivum) | S17: 0.0082 | T17: Wheat (T. aestivum) | U17: 0.0052
P18: Wheat (T. durum) | Q18: 0.0203 | R18: Wheat (T. durum) | S18: 0.0084 | T18: Wheat (T. durum) | U18: 0.0051
